Workbook

Sheet 說明_ReadMe
A1: VMH-EcoMap-24 交付與收款儀表板｜使用說明
A2: P3 執行交付工具・案件自 20 號漏斗簽約後轉入・付款計畫沿用 21 號
B4: ■ 這個工具在回答什麼
B5: 簽約只是開始。這張表回答執行期最重要的四個問題：進度落後了嗎？成本超支了嗎？錢收到了沒？墊資墊到多深？ 用的是實獲值管理（EVM）的簡化版——工程與政府專案的國際標準方法，但只保留三個數字，非 PM 背景也看得懂。
B7: ■ EVM 三個數字的白話翻譯
B8: PV 計畫值＝到今天為止「照計畫應該做完多少錢的活」。 EV 實獲值＝實際做完的活，換算成錢。 AC 實際成本＝實際花掉的錢。 SPI＝EV÷PV：小於 1＝進度落後。CPI＝EV÷AC：小於 1＝每花一塊錢只做出不到一塊錢的活。 EAC 預測完工成本＝總預算÷CPI：照目前效率做完全案會花多少——這是最早的超支預警。
B10: ■ 每月月底 20 分鐘例行
B11: ① 里程碑頁：把本月完成的里程碑填上實際完成日。 ② EVM 月報：填「實際完成累計%」（誠實估，寧可保守）與「實際成本累計」。 ③ 收款頁：把收到的款填實收日與金額。 ④ 看儀表板：SPI、CPI 連續兩個月低於 0.9 就要開檢討會，不要等到驗收才發現。
B13: ■ 與其他工具的銜接
B14: 案件在 20 號漏斗簽約後轉入這裡；付款計畫直接沿用 21 號投標試算的付款條件頁。 結案後把「實際總成本」回填 21 號的假設來源頁——這是下一案報價最珍貴的校正資料。

Sheet 00_儀表板_Dashboard
A1: 儀表板｜Dashboard（全自動）
A2: ❓一眼看：進度、成本、現金三件事健不健康。
B5: SPI 進度績效 | C5: =IFERROR(INDEX(03_EVM月報_Monthly!$I$5:$I$28,COUNT(03_EVM月報_Monthly!$I$5:$I$28)),"") -> 0.87 | D5: <1＝進度落後。0.9 以下連兩個月要開檢討會
B6: CPI 成本績效 | C6: =IFERROR(INDEX(03_EVM月報_Monthly!$J$5:$J$28,COUNT(03_EVM月報_Monthly!$J$5:$J$28)),"") -> 0.92 | D6: <1＝花錢的效率不夠
B7: EAC 預測完工成本 | C7: =IFERROR(INDEX(03_EVM月報_Monthly!$K$5:$K$28,COUNT(03_EVM月報_Monthly!$K$5:$K$28)),"") -> 810 | D7: 千USD。照目前效率做完全案會花多少
B8: 預算 BAC | C8: =01_專案設定_Setup!$C$8 -> 745 | D8: 千USD
B9: 預測超支 | C9: =IFERROR(INDEX(03_EVM月報_Monthly!$K$5:$K$28,COUNT(03_EVM月報_Monthly!$K$5:$K$28))-01_專案設定_Setup!$C$8,"") -> 65 | D9: 千USD。正數＝會超支，現在就要處理
B10: 里程碑達成 | C10: =COUNTIF(02_里程碑_Milestones!$F$5:$F$12,"*達成*")&" / "&COUNTA(02_里程碑_Milestones!$A$5:$A$12) -> 4 / 8
B11: 已收款 | C11: =SUM(04_收款_Receivables!$G$5:$G$10) -> 138 | D11: 千USD
B12: 收款達成率 | C12: =IFERROR(SUM(04_收款_Receivables!$G$5:$G$10)/SUMIF(04_收款_Receivables!$E$5:$E$10,"<>",04_收款_Receivables!$C$5:$C$10),"") -> 0.375 | D12: 已收 ÷ 已到期應收
B13: 逾期未收 | C13: =SUMIFS(04_收款_Receivables!$C$5:$C$10,04_收款_Receivables!$I$5:$I$10,"🔴 逾期") -> 0 | D13: 千USD ★ 這是最該追的數字
B15: SPI/CPI 曲線與現金流階梯圖請開 HTML 版（tools/delivery.html）。結案後：把最後的 AC 實際成本回填 21 號「假設來源」頁，讓下一案的估價踩在真實數字上。

Sheet 01_專案設定_Setup
A1: 專案設定｜Setup
A2: ❓這一案的合約金額、預算、時程基準。
A3: 圖例： | B3: 要填 | C3: 自動 | D3: （範例為虛構案件，參考後換成真實資料）
B5: 案件ID（自 20 號漏斗） | C5: P-002
B6: 案件名稱 | C6: （虛構範例）峴港綜合醫院 UPS 與不斷電系統
B7: 合約金額（千USD） | C7: 920
B8: 總成本預算 BAC（千USD） | C8: 745 | D8: 來自 21 號投標試算的總成本——EVM 的分母
B9: 開工日 | C9: 2026-04-01
B10: 合約工期（月） | C10: 8
B11: 資料基準日 | C11: 2026-08-18 | D11: 本次更新的月份

Sheet 02_里程碑_Milestones
A1: 里程碑｜Milestones
A2: ❓這頁在回答：關鍵節點有沒有準時過？
A3: 圖例： | B3: 要填 | C3: 自動 | D3: （範例為虛構案件，參考後換成真實資料）
A4: 里程碑 | B4: 權重% | C4: 計畫完成日 | D4: 實際完成日 | E4: 延誤天數 | F4: 狀態 | G4: 備註
A5: 合約生效與預付款 | B5: 0.05 | C5: 2026-04-01 | D5: 2026-04-01 | E5: =IF($D5="","",DATEVALUE($D5)-DATEVALUE($C5)) -> 0 | F5: =IF($D5<>"",IF($E5>7,"⚠ 延誤達成","✓ 達成"),IF(DATEVALUE($C5)<DATEVALUE(01_專案設定_Setup!$C$11),"🔴 逾期未完","進行中")) -> ✓ 達成
A6: 設備下單與工廠排產 | B6: 0.1 | C6: 2026-04-20 | D6: 2026-04-25 | E6: =IF($D6="","",DATEVALUE($D6)-DATEVALUE($C6)) -> 5 | F6: =IF($D6<>"",IF($E6>7,"⚠ 延誤達成","✓ 達成"),IF(DATEVALUE($C6)<DATEVALUE(01_專案設定_Setup!$C$11),"🔴 逾期未完","進行中")) -> ✓ 達成
A7: 設備出廠驗收 FAT | B7: 0.2 | C7: 2026-06-15 | D7: 2026-06-28 | E7: =IF($D7="","",DATEVALUE($D7)-DATEVALUE($C7)) -> 13 | F7: =IF($D7<>"",IF($E7>7,"⚠ 延誤達成","✓ 達成"),IF(DATEVALUE($C7)<DATEVALUE(01_專案設定_Setup!$C$11),"🔴 逾期未完","進行中")) -> ⚠ 延誤達成
A8: 到港清關 | B8: 0.1 | C8: 2026-07-10 | D8: 2026-07-25 | E8: =IF($D8="","",DATEVALUE($D8)-DATEVALUE($C8)) -> 15 | F8: =IF($D8<>"",IF($E8>7,"⚠ 延誤達成","✓ 達成"),IF(DATEVALUE($C8)<DATEVALUE(01_專案設定_Setup!$C$11),"🔴 逾期未完","進行中")) -> ⚠ 延誤達成
A9: 進場安裝 50% | B9: 0.15 | C9: 2026-08-10 | E9: =IF($D9="","",$D9-DATEVALUE($C9)) | F9: =IF($D9<>"",IF($E9>7,"⚠ 延誤達成","✓ 達成"),IF(DATEVALUE($C9)<DATEVALUE(01_專案設定_Setup!$C$11),"🔴 逾期未完","進行中")) -> 🔴 逾期未完
A10: 安裝完成 | B10: 0.15 | C10: 2026-09-05 | E10: =IF($D10="","",$D10-DATEVALUE($C10)) | F10: =IF($D10<>"",IF($E10>7,"⚠ 延誤達成","✓ 達成"),IF(DATEVALUE($C10)<DATEVALUE(01_專案設定_Setup!$C$11),"🔴 逾期未完","進行中")) -> 進行中
A11: 測試與試運轉 SAT | B11: 0.15 | C11: 2026-10-05 | E11: =IF($D11="","",$D11-DATEVALUE($C11)) | F11: =IF($D11<>"",IF($E11>7,"⚠ 延誤達成","✓ 達成"),IF(DATEVALUE($C11)<DATEVALUE(01_專案設定_Setup!$C$11),"🔴 逾期未完","進行中")) -> 進行中
A12: 正式驗收移交 | B12: 0.1 | C12: 2026-11-15 | E12: =IF($D12="","",$D12-DATEVALUE($C12)) | F12: =IF($D12<>"",IF($E12>7,"⚠ 延誤達成","✓ 達成"),IF(DATEVALUE($C12)<DATEVALUE(01_專案設定_Setup!$C$11),"🔴 逾期未完","進行中")) -> 進行中

Sheet 03_EVM月報_Monthly
A1: EVM 月報｜每月月底填一列
A2: ❓這頁在回答：進度與成本的健康趨勢。★ 「實際完成累計%」要誠實估，寧可保守
A3: 圖例： | B3: 要填 | C3: 自動 | D3: （範例為虛構案件，參考後換成真實資料）
A4: 月份 | B4: 月序 | C4: 計畫完成累計% | D4: 實際完成累計% | E4: 實際成本累計(千USD) | F4: PV 計畫值 | G4: EV 實獲值 | H4: AC 實際成本 | I4: SPI 進度 | J4: CPI 成本 | K4: EAC 預測完工
A5: 2026-04 | B5: 1 | C5: 0.08 | D5: 0.07 | E5: 55 | F5: =IF($C5="","",$C5*01_專案設定_Setup!$C$8) -> 59.6 | G5: =IF($D5="","",$D5*01_專案設定_Setup!$C$8) -> 52.15 | H5: =IF($E5="","",$E5) -> 55 | I5: =IF(OR($F5="",$G5="",$F5=0),"",ROUND($G5/$F5,2)) -> 0.88 | J5: =IF(OR($G5="",$H5="",$H5=0),"",ROUND($G5/$H5,2)) -> 0.95 | K5: =IF($J5="","",ROUND(01_專案設定_Setup!$C$8/$J5,0)) -> 784
A6: 2026-05 | B6: 2 | C6: 0.2 | D6: 0.17 | E6: 140 | F6: =IF($C6="","",$C6*01_專案設定_Setup!$C$8) -> 149 | G6: =IF($D6="","",$D6*01_專案設定_Setup!$C$8) -> 126.65 | H6: =IF($E6="","",$E6) -> 140 | I6: =IF(OR($F6="",$G6="",$F6=0),"",ROUND($G6/$F6,2)) -> 0.85 | J6: =IF(OR($G6="",$H6="",$H6=0),"",ROUND($G6/$H6,2)) -> 0.9 | K6: =IF($J6="","",ROUND(01_專案設定_Setup!$C$8/$J6,0)) -> 828
A7: 2026-06 | B7: 3 | C7: 0.35 | D7: 0.3 | E7: 255 | F7: =IF($C7="","",$C7*01_專案設定_Setup!$C$8) -> 260.75 | G7: =IF($D7="","",$D7*01_專案設定_Setup!$C$8) -> 223.5 | H7: =IF($E7="","",$E7) -> 255 | I7: =IF(OR($F7="",$G7="",$F7=0),"",ROUND($G7/$F7,2)) -> 0.86 | J7: =IF(OR($G7="",$H7="",$H7=0),"",ROUND($G7/$H7,2)) -> 0.88 | K7: =IF($J7="","",ROUND(01_專案設定_Setup!$C$8/$J7,0)) -> 847
A8: 2026-07 | B8: 4 | C8: 0.48 | D8: 0.41 | E8: 340 | F8: =IF($C8="","",$C8*01_專案設定_Setup!$C$8) -> 357.6 | G8: =IF($D8="","",$D8*01_專案設定_Setup!$C$8) -> 305.45 | H8: =IF($E8="","",$E8) -> 340 | I8: =IF(OR($F8="",$G8="",$F8=0),"",ROUND($G8/$F8,2)) -> 0.85 | J8: =IF(OR($G8="",$H8="",$H8=0),"",ROUND($G8/$H8,2)) -> 0.9 | K8: =IF($J8="","",ROUND(01_專案設定_Setup!$C$8/$J8,0)) -> 828
A9: 2026-08 | B9: 5 | C9: 0.6 | D9: 0.52 | E9: 420 | F9: =IF($C9="","",$C9*01_專案設定_Setup!$C$8) -> 447 | G9: =IF($D9="","",$D9*01_專案設定_Setup!$C$8) -> 387.4 | H9: =IF($E9="","",$E9) -> 420 | I9: =IF(OR($F9="",$G9="",$F9=0),"",ROUND($G9/$F9,2)) -> 0.87 | J9: =IF(OR($G9="",$H9="",$H9=0),"",ROUND($G9/$H9,2)) -> 0.92 | K9: =IF($J9="","",ROUND(01_專案設定_Setup!$C$8/$J9,0)) -> 810
F10: =IF($C10="","",$C10*01_專案設定_Setup!$C$8) | G10: =IF($D10="","",$D10*01_專案設定_Setup!$C$8) | H10: =IF($E10="","",$E10) | I10: =IF(OR($F10="",$G10="",$F10=0),"",ROUND($G10/$F10,2)) | J10: =IF(OR($G10="",$H10="",$H10=0),"",ROUND($G10/$H10,2)) | K10: =IF($J10="","",ROUND(01_專案設定_Setup!$C$8/$J10,0))
F11: =IF($C11="","",$C11*01_專案設定_Setup!$C$8) | G11: =IF($D11="","",$D11*01_專案設定_Setup!$C$8) | H11: =IF($E11="","",$E11) | I11: =IF(OR($F11="",$G11="",$F11=0),"",ROUND($G11/$F11,2)) | J11: =IF(OR($G11="",$H11="",$H11=0),"",ROUND($G11/$H11,2)) | K11: =IF($J11="","",ROUND(01_專案設定_Setup!$C$8/$J11,0))
F12: =IF($C12="","",$C12*01_專案設定_Setup!$C$8) | G12: =IF($D12="","",$D12*01_專案設定_Setup!$C$8) | H12: =IF($E12="","",$E12) | I12: =IF(OR($F12="",$G12="",$F12=0),"",ROUND($G12/$F12,2)) | J12: =IF(OR($G12="",$H12="",$H12=0),"",ROUND($G12/$H12,2)) | K12: =IF($J12="","",ROUND(01_專案設定_Setup!$C$8/$J12,0))
F13: =IF($C13="","",$C13*01_專案設定_Setup!$C$8) | G13: =IF($D13="","",$D13*01_專案設定_Setup!$C$8) | H13: =IF($E13="","",$E13) | I13: =IF(OR($F13="",$G13="",$F13=0),"",ROUND($G13/$F13,2)) | J13: =IF(OR($G13="",$H13="",$H13=0),"",ROUND($G13/$H13,2)) | K13: =IF($J13="","",ROUND(01_專案設定_Setup!$C$8/$J13,0))
F14: =IF($C14="","",$C14*01_專案設定_Setup!$C$8) | G14: =IF($D14="","",$D14*01_專案設定_Setup!$C$8) | H14: =IF($E14="","",$E14) | I14: =IF(OR($F14="",$G14="",$F14=0),"",ROUND($G14/$F14,2)) | J14: =IF(OR($G14="",$H14="",$H14=0),"",ROUND($G14/$H14,2)) | K14: =IF($J14="","",ROUND(01_專案設定_Setup!$C$8/$J14,0))
F15: =IF($C15="","",$C15*01_專案設定_Setup!$C$8) | G15: =IF($D15="","",$D15*01_專案設定_Setup!$C$8) | H15: =IF($E15="","",$E15) | I15: =IF(OR($F15="",$G15="",$F15=0),"",ROUND($G15/$F15,2)) | J15: =IF(OR($G15="",$H15="",$H15=0),"",ROUND($G15/$H15,2)) | K15: =IF($J15="","",ROUND(01_專案設定_Setup!$C$8/$J15,0))
F16: =IF($C16="","",$C16*01_專案設定_Setup!$C$8) | G16: =IF($D16="","",$D16*01_專案設定_Setup!$C$8) | H16: =IF($E16="","",$E16) | I16: =IF(OR($F16="",$G16="",$F16=0),"",ROUND($G16/$F16,2)) | J16: =IF(OR($G16="",$H16="",$H16=0),"",ROUND($G16/$H16,2)) | K16: =IF($J16="","",ROUND(01_專案設定_Setup!$C$8/$J16,0))
F17: =IF($C17="","",$C17*01_專案設定_Setup!$C$8) | G17: =IF($D17="","",$D17*01_專案設定_Setup!$C$8) | H17: =IF($E17="","",$E17) | I17: =IF(OR($F17="",$G17="",$F17=0),"",ROUND($G17/$F17,2)) | J17: =IF(OR($G17="",$H17="",$H17=0),"",ROUND($G17/$H17,2)) | K17: =IF($J17="","",ROUND(01_專案設定_Setup!$C$8/$J17,0))
F18: =IF($C18="","",$C18*01_專案設定_Setup!$C$8) | G18: =IF($D18="","",$D18*01_專案設定_Setup!$C$8) | H18: =IF($E18="","",$E18) | I18: =IF(OR($F18="",$G18="",$F18=0),"",ROUND($G18/$F18,2)) | J18: =IF(OR($G18="",$H18="",$H18=0),"",ROUND($G18/$H18,2)) | K18: =IF($J18="","",ROUND(01_專案設定_Setup!$C$8/$J18,0))
F19: =IF($C19="","",$C19*01_專案設定_Setup!$C$8) | G19: =IF($D19="","",$D19*01_專案設定_Setup!$C$8) | H19: =IF($E19="","",$E19) | I19: =IF(OR($F19="",$G19="",$F19=0),"",ROUND($G19/$F19,2)) | J19: =IF(OR($G19="",$H19="",$H19=0),"",ROUND($G19/$H19,2)) | K19: =IF($J19="","",ROUND(01_專案設定_Setup!$C$8/$J19,0))
F20: =IF($C20="","",$C20*01_專案設定_Setup!$C$8) | G20: =IF($D20="","",$D20*01_專案設定_Setup!$C$8) | H20: =IF($E20="","",$E20) | I20: =IF(OR($F20="",$G20="",$F20=0),"",ROUND($G20/$F20,2)) | J20: =IF(OR($G20="",$H20="",$H20=0),"",ROUND($G20/$H20,2)) | K20: =IF($J20="","",ROUND(01_專案設定_Setup!$C$8/$J20,0))
F21: =IF($C21="","",$C21*01_專案設定_Setup!$C$8) | G21: =IF($D21="","",$D21*01_專案設定_Setup!$C$8) | H21: =IF($E21="","",$E21) | I21: =IF(OR($F21="",$G21="",$F21=0),"",ROUND($G21/$F21,2)) | J21: =IF(OR($G21="",$H21="",$H21=0),"",ROUND($G21/$H21,2)) | K21: =IF($J21="","",ROUND(01_專案設定_Setup!$C$8/$J21,0))
... F28: =IF($C28="","",$C28*01_專案設定_Setup!$C$8) | G28: =IF($D28="","",$D28*01_專案設定_Setup!$C$8) | H28: =IF($E28="","",$E28) | I28: =IF(OR($F28="",$G28="",$F28=0),"",ROUND($G28/$F28,2)) | J28: =IF(OR($G28="",$H28="",$H28=0),"",ROUND($G28/$H28,2)) | K28: =IF($J28="","",ROUND(01_專案設定_Setup!$C$8/$J28,0))

Sheet 04_收款_Receivables
A1: 收款｜Receivables（沿用 21 號付款條件的里程碑）
A2: ❓這頁在回答：錢收到了沒？逾期多久了？
A3: 圖例： | B3: 要填 | C3: 自動 | D3: （範例為虛構案件，參考後換成真實資料）
A4: 收款里程碑 | B4: 比例% | C4: 應收金額(千USD) | D4: 請款日 | E4: 付款到期日 | F4: 實收日 | G4: 實收金額(千USD) | H4: 逾期天數 | I4: 狀態
A5: 合約簽訂預付款 | B5: 0.15 | C5: =ROUND($B5*01_專案設定_Setup!$C$7,0) -> 138 | D5: 2026-04-01 | E5: 2026-05-01 | F5: 2026-05-06 | G5: 138 | H5: =IF($F5<>"","",IF($E5="","",MAX(0,DATEVALUE(01_專案設定_Setup!$C$11)-DATEVALUE($E5)))) | I5: =IF($F5<>"","✓ 已收",IF($E5="","未到請款",IF($H5>0,"🔴 逾期","等待中"))) -> ✓ 已收
A6: 設備到港 | B6: 0.25 | C6: =ROUND($B6*01_專案設定_Setup!$C$7,0) -> 230 | D6: 2026-07-25 | E6: 2026-08-25 | H6: =IF($F6<>"","",IF($E6="","",MAX(0,DATEVALUE(01_專案設定_Setup!$C$11)-DATEVALUE($E6)))) -> 0 | I6: =IF($F6<>"","✓ 已收",IF($E6="","未到請款",IF($H6>0,"🔴 逾期","等待中"))) -> 等待中
A7: 安裝進度 50% | B7: 0.2 | C7: =ROUND($B7*01_專案設定_Setup!$C$7,0) -> 184 | H7: =IF($F7<>"","",IF($E7="","",MAX(0,DATEVALUE(01_專案設定_Setup!$C$11)-DATEVALUE($E7)))) | I7: =IF($F7<>"","✓ 已收",IF($E7="","未到請款",IF($H7>0,"🔴 逾期","等待中"))) -> 未到請款
A8: 測試完成 | B8: 0.2 | C8: =ROUND($B8*01_專案設定_Setup!$C$7,0) -> 184 | H8: =IF($F8<>"","",IF($E8="","",MAX(0,DATEVALUE(01_專案設定_Setup!$C$11)-DATEVALUE($E8)))) | I8: =IF($F8<>"","✓ 已收",IF($E8="","未到請款",IF($H8>0,"🔴 逾期","等待中"))) -> 未到請款
A9: 正式驗收 | B9: 0.15 | C9: =ROUND($B9*01_專案設定_Setup!$C$7,0) -> 138 | H9: =IF($F9<>"","",IF($E9="","",MAX(0,DATEVALUE(01_專案設定_Setup!$C$11)-DATEVALUE($E9)))) | I9: =IF($F9<>"","✓ 已收",IF($E9="","未到請款",IF($H9>0,"🔴 逾期","等待中"))) -> 未到請款
A10: 保固期滿尾款 | B10: 0.05 | C10: =ROUND($B10*01_專案設定_Setup!$C$7,0) -> 46 | H10: =IF($F10<>"","",IF($E10="","",MAX(0,DATEVALUE(01_專案設定_Setup!$C$11)-DATEVALUE($E10)))) | I10: =IF($F10<>"","✓ 已收",IF($E10="","未到請款",IF($H10>0,"🔴 逾期","等待中"))) -> 未到請款

Sheet _選單_Lists
A1: 里程碑狀態
A2: ✓ 達成
A3: ⚠ 延誤達成
A4: 🔴 逾期未完
A5: 進行中
