Workbook

Sheet 說明_ReadMe
A1: VMH-EcoMap-14 醫院作戰檔案與資格審查｜使用說明
A2: P0 鎖定目標工具（①＋②）・2026-08-15・對應藍圖 VMH-EcoMap-13
B4: ■ 這個檔在解決什麼
B5: 「該把有限的時間花在哪家醫院、哪個案子」。市場層的答案在盤點工具（85門生意），這裡管的是案件層：具體的醫院、具體的人、具體的錢。
B7: ■ 三個分頁的關係
B8: 醫院名錄（填）→ 作戰檔案（自動長出一頁摘要，開會前看）→ 資格審查（一案一列打分，決定追不追）。只有「醫院名錄」和「資格審查」要填，作戰檔案是全自動的。
B10: ■ 每週動線
B11: ①新情報進來→更新醫院名錄該列 ②新案子出現→資格審查加一列打分 ③週會投影資格審查分頁，按「判定」欄排序，逐案過「下一步行動」。
B13: ■ 打分的紀律
B14: 照「審查標準」分頁的錨點打，不要憑感覺。兩人分別打分再對答案，差 2 分以上的題目就是情報不足的題目——那正是下一步要去查的東西。
B16: ■ 與其他工具的銜接
B17: 判定=積極爭取 → 開始準備 P1 拜訪包與現勘（藍圖④⑤）；案子若來自公開標案 → 到 VMH-EcoMap-15 標案雷達登錄，資格文件庫同步查備齊狀態；要算細帳 → 回 VMH-EcoMap-2 試算器。
B19: ■ 維護
B20: 下拉選單在「選單_Lists」分頁改；醫院超過 40 家再擴列（名錄第 45 列以後照格式往下加，作戰檔案與審查的下拉範圍要同步改）。

Sheet 醫院名錄_Registry
A1: 醫院名錄｜Registry（主資料——一列一家醫院，作戰檔案與資格審查都從這裡取值）
A2: ❓這頁在回答：我們盯上了哪些醫院、每一家的關鍵情報是什麼？ 填這裡→「作戰檔案」自動長出一頁摘要。
A3: 圖例： | B3: 要填 | C3: 自動 | D3: （範例）列請參考後刪除或保留當樣板
A4: 醫院ID | B4: 醫院名稱(中) | C4: 名稱(越/英) | D4: 省/市 | E4: 屬性 | F4: 技術層級 | G4: 床位 | H4: 日均門診 | I4: 財務自主(tự chủ) | J4: 簽約主體 | K4: 預算來源 | L4: 院長 | M4: 黨委書記 | N4: 主管副院長 | O4: IT/設備主管 | P4: 我方窗口 | Q4: 引薦人/關係路徑 | R4: 關係強度 | S4: HIS廠商 | T4: EMR狀態 | U4: 機房/IDC現況 | V4: 既有BMS/弱電品牌 | W4: 主要供應商與到期 | X4: 新建/改建計畫 | Y4: 痛點與觸發事件 | Z4: 目標商機(可多個) | AA4: EVN電費帳單 | AB4: 最後接觸日 | AC4: 下一步行動 | AD4: 負責人 | AE4: 期限 | AF4: 備註
A5: H-001 | B5: （範例）省級綜合醫院A | C5: Bệnh viện Đa khoa Tỉnh A | D5: 興安省 | E5: 公立-省級 | F5: 基本 Cơ bản | G5: 800 | H5: 2200 | I5: Nhóm 2 經常性支出自主 | J5: 院方(需衛生廳核備) | K5: 醫院發展基金＋省預算 | L5: Dr. Nguyễn Văn A | M5: Ông Trần B | N5: Dr. Lê C(主管基建) | O5: Ông Phạm D | P5: （待建立） | Q5: 台商協會X會長→院長 | R5: 中(有引薦路徑) | S5: Viettel | T5: 建置中 | U5: 自建小機房、無備援、UPS 10年未換 | V5: 無BMS、弱電雜牌 | W5: Viettel HIS 約2027到期 | X5: 新建二期大樓 300床(2027動工) | Y5: EMR達標壓力＋新大樓要智慧化 | Z5: OPP-24; OPP-26 | AA5: 索取中 | AB5: 2026-08-01 | AC5: 安排參訪台灣參考醫院 | AD5: NC | AE5: 2026-09-15 | AF5: 院長對節能有興趣
A6: H-002
A7: H-003
A8: H-004
A9: H-005
A10: H-006
A11: H-007
A12: H-008
A13: H-009
A14: H-010
A15: H-011
A16: H-012
A17: H-013
... A45: H-041

Sheet 作戰檔案_Card
B1: 醫院作戰檔案｜Account Dossier
B2: 選一家醫院，整頁自動更新。開會前十分鐘讀這一頁就夠。可直接列印 A4。
B4: 選擇醫院 → | C4: （範例）省級綜合醫院A
B6: 基本盤
B7: 越/英名稱 | C7: =IFERROR(INDEX(醫院名錄_Registry!$C$5:$C$45,MATCH($C$4,醫院名錄_Registry!$B$5:$B$45,0)),"") -> Bệnh viện Đa khoa Tỉnh A | E7: 省/市 | F7: =IFERROR(INDEX(醫院名錄_Registry!$D$5:$D$45,MATCH($C$4,醫院名錄_Registry!$B$5:$B$45,0)),"") -> 興安省
B8: 屬性 | C8: =IFERROR(INDEX(醫院名錄_Registry!$E$5:$E$45,MATCH($C$4,醫院名錄_Registry!$B$5:$B$45,0)),"") -> 公立-省級 | E8: 技術層級 | F8: =IFERROR(INDEX(醫院名錄_Registry!$F$5:$F$45,MATCH($C$4,醫院名錄_Registry!$B$5:$B$45,0)),"") -> 基本 Cơ bản
B9: 床位 | C9: =IFERROR(INDEX(醫院名錄_Registry!$G$5:$G$45,MATCH($C$4,醫院名錄_Registry!$B$5:$B$45,0)),"") -> 800 | E9: 日均門診 | F9: =IFERROR(INDEX(醫院名錄_Registry!$H$5:$H$45,MATCH($C$4,醫院名錄_Registry!$B$5:$B$45,0)),"") -> 2200
B11: 治理與金流（誰能簽、錢從哪來）
B12: 財務自主 | C12: =IFERROR(INDEX(醫院名錄_Registry!$I$5:$I$45,MATCH($C$4,醫院名錄_Registry!$B$5:$B$45,0)),"") -> Nhóm 2 經常性支出自主 | E12: 簽約主體 | F12: =IFERROR(INDEX(醫院名錄_Registry!$J$5:$J$45,MATCH($C$4,醫院名錄_Registry!$B$5:$B$45,0)),"") -> 院方(需衛生廳核備)
B13: 預算來源 | C13: =IFERROR(INDEX(醫院名錄_Registry!$K$5:$K$45,MATCH($C$4,醫院名錄_Registry!$B$5:$B$45,0)),"") -> 醫院發展基金＋省預算
B15: 決策鏈（找對人）
B16: 院長 | C16: =IFERROR(INDEX(醫院名錄_Registry!$L$5:$L$45,MATCH($C$4,醫院名錄_Registry!$B$5:$B$45,0)),"") -> Dr. Nguyễn Văn A | E16: 黨委書記 | F16: =IFERROR(INDEX(醫院名錄_Registry!$M$5:$M$45,MATCH($C$4,醫院名錄_Registry!$B$5:$B$45,0)),"") -> Ông Trần B
B17: 主管副院長 | C17: =IFERROR(INDEX(醫院名錄_Registry!$N$5:$N$45,MATCH($C$4,醫院名錄_Registry!$B$5:$B$45,0)),"") -> Dr. Lê C(主管基建) | E17: IT/設備主管 | F17: =IFERROR(INDEX(醫院名錄_Registry!$O$5:$O$45,MATCH($C$4,醫院名錄_Registry!$B$5:$B$45,0)),"") -> Ông Phạm D
B18: 我方窗口 | C18: =IFERROR(INDEX(醫院名錄_Registry!$P$5:$P$45,MATCH($C$4,醫院名錄_Registry!$B$5:$B$45,0)),"") -> （待建立） | E18: 引薦路徑 | F18: =IFERROR(INDEX(醫院名錄_Registry!$Q$5:$Q$45,MATCH($C$4,醫院名錄_Registry!$B$5:$B$45,0)),"") -> 台商協會X會長→院長
B19: 關係強度 | C19: =IFERROR(INDEX(醫院名錄_Registry!$R$5:$R$45,MATCH($C$4,醫院名錄_Registry!$B$5:$B$45,0)),"") -> 中(有引薦路徑)
B21: 現況系統（切入點）
B22: HIS廠商 | C22: =IFERROR(INDEX(醫院名錄_Registry!$S$5:$S$45,MATCH($C$4,醫院名錄_Registry!$B$5:$B$45,0)),"") -> Viettel | E22: EMR狀態 | F22: =IFERROR(INDEX(醫院名錄_Registry!$T$5:$T$45,MATCH($C$4,醫院名錄_Registry!$B$5:$B$45,0)),"") -> 建置中
B23: 機房現況 | C23: =IFERROR(INDEX(醫院名錄_Registry!$U$5:$U$45,MATCH($C$4,醫院名錄_Registry!$B$5:$B$45,0)),"") -> 自建小機房、無備援、UPS 10年未換 | E23: BMS/弱電 | F23: =IFERROR(INDEX(醫院名錄_Registry!$V$5:$V$45,MATCH($C$4,醫院名錄_Registry!$B$5:$B$45,0)),"") -> 無BMS、弱電雜牌
B24: 供應商到期 | C24: =IFERROR(INDEX(醫院名錄_Registry!$W$5:$W$45,MATCH($C$4,醫院名錄_Registry!$B$5:$B$45,0)),"") -> Viettel HIS 約2027到期
B26: 商機與行動
B27: 新建/改建 | C27: =IFERROR(INDEX(醫院名錄_Registry!$X$5:$X$45,MATCH($C$4,醫院名錄_Registry!$B$5:$B$45,0)),"") -> 新建二期大樓 300床(2027動工) | E27: 痛點/觸發 | F27: =IFERROR(INDEX(醫院名錄_Registry!$Y$5:$Y$45,MATCH($C$4,醫院名錄_Registry!$B$5:$B$45,0)),"") -> EMR達標壓力＋新大樓要智慧化
B28: 目標商機 | C28: =IFERROR(INDEX(醫院名錄_Registry!$Z$5:$Z$45,MATCH($C$4,醫院名錄_Registry!$B$5:$B$45,0)),"") -> OPP-24; OPP-26 | E28: EVN帳單 | F28: =IFERROR(INDEX(醫院名錄_Registry!$AA$5:$AA$45,MATCH($C$4,醫院名錄_Registry!$B$5:$B$45,0)),"") -> 索取中
B29: 最後接觸 | C29: =IFERROR(INDEX(醫院名錄_Registry!$AB$5:$AB$45,MATCH($C$4,醫院名錄_Registry!$B$5:$B$45,0)),"") -> 2026-08-01 | E29: 下一步 | F29: =IFERROR(INDEX(醫院名錄_Registry!$AC$5:$AC$45,MATCH($C$4,醫院名錄_Registry!$B$5:$B$45,0)),"") -> 安排參訪台灣參考醫院
B30: 負責人 | C30: =IFERROR(INDEX(醫院名錄_Registry!$AD$5:$AD$45,MATCH($C$4,醫院名錄_Registry!$B$5:$B$45,0)),"") -> NC | E30: 期限 | F30: =IFERROR(INDEX(醫院名錄_Registry!$AE$5:$AE$45,MATCH($C$4,醫院名錄_Registry!$B$5:$B$45,0)),"") -> 2026-09-15
B31: 備註 | C31: =IFERROR(INDEX(醫院名錄_Registry!$AF$5:$AF$45,MATCH($C$4,醫院名錄_Registry!$B$5:$B$45,0)),"") -> 院長對節能有興趣
B33: ★ 這一頁全部唯讀；要改內容回「醫院名錄」改，這裡自動更新。

Sheet 資格審查_Scorecard
A1: 機會資格審查｜Qualification Scorecard（一案一列，10 題 × 0/1/2 分，10 分鐘填完）
A2: ❓這頁在回答：這個案子值得投入嗎？ 規則：總分≥14 積極爭取｜10–13 觀察培養｜<10 暫停。★ Q1 預算或 Q6 付款風險為 0 → 無論總分一律暫停。評分錨點見「審查標準」分頁。
A3: 圖例： | B3: 要填 | C3: 自動 | D3: （範例）列請參考後刪除或保留當樣板
A4: 案件ID | B4: 醫院 | C4: 目標商機 | D4: 案件說明 | E4: Q1 預算 | F4: Q2 管道 | G4: Q3 觸發 | H4: Q4 匹配 | I4: Q5 競爭 | J4: Q6 付款 | K4: Q7 資源 | L4: Q8 在地 | M4: Q9 時程 | N4: Q10 戰略 | O4: 總分 | P4: 判定 | Q4: 下一步行動 | R4: 負責人 | S4: 期限 | T4: 狀態 | U4: 備註
A5: C-001 | B5: （範例）省級綜合醫院A | C5: OPP-26 智慧院區AIoT（BMS／RTLS／智慧病房） | D5: 二期新大樓智慧化整包 | E5: 2 | F5: 1 | G5: 2 | H5: 2 | I5: 2 | J5: 1 | K5: 2 | L5: 1 | M5: 2 | N5: 2 | O5: =IF(COUNT(E5:N5)=0,"",SUM(E5:N5)) -> 17 | P5: =IF(COUNT(E5:N5)=0,"",IF(OR(E5=0,J5=0),"暫停(關鍵題0分)",IF(O5>=14,"積極爭取",IF(O5>=10,"觀察培養","暫停")))) -> 積極爭取 | Q5: 現勘＋索取機電圖說 | R5: NC | S5: 2026-09-30 | T5: 進行中 | U5: 搭 QCVN 04-3 生效時程
A6: C-002 | O6: =IF(COUNT(E6:N6)=0,"",SUM(E6:N6)) | P6: =IF(COUNT(E6:N6)=0,"",IF(OR(E6=0,J6=0),"暫停(關鍵題0分)",IF(O6>=14,"積極爭取",IF(O6>=10,"觀察培養","暫停"))))
A7: C-003 | O7: =IF(COUNT(E7:N7)=0,"",SUM(E7:N7)) | P7: =IF(COUNT(E7:N7)=0,"",IF(OR(E7=0,J7=0),"暫停(關鍵題0分)",IF(O7>=14,"積極爭取",IF(O7>=10,"觀察培養","暫停"))))
A8: C-004 | O8: =IF(COUNT(E8:N8)=0,"",SUM(E8:N8)) | P8: =IF(COUNT(E8:N8)=0,"",IF(OR(E8=0,J8=0),"暫停(關鍵題0分)",IF(O8>=14,"積極爭取",IF(O8>=10,"觀察培養","暫停"))))
A9: C-005 | O9: =IF(COUNT(E9:N9)=0,"",SUM(E9:N9)) | P9: =IF(COUNT(E9:N9)=0,"",IF(OR(E9=0,J9=0),"暫停(關鍵題0分)",IF(O9>=14,"積極爭取",IF(O9>=10,"觀察培養","暫停"))))
A10: C-006 | O10: =IF(COUNT(E10:N10)=0,"",SUM(E10:N10)) | P10: =IF(COUNT(E10:N10)=0,"",IF(OR(E10=0,J10=0),"暫停(關鍵題0分)",IF(O10>=14,"積極爭取",IF(O10>=10,"觀察培養","暫停"))))
A11: C-007 | O11: =IF(COUNT(E11:N11)=0,"",SUM(E11:N11)) | P11: =IF(COUNT(E11:N11)=0,"",IF(OR(E11=0,J11=0),"暫停(關鍵題0分)",IF(O11>=14,"積極爭取",IF(O11>=10,"觀察培養","暫停"))))
A12: C-008 | O12: =IF(COUNT(E12:N12)=0,"",SUM(E12:N12)) | P12: =IF(COUNT(E12:N12)=0,"",IF(OR(E12=0,J12=0),"暫停(關鍵題0分)",IF(O12>=14,"積極爭取",IF(O12>=10,"觀察培養","暫停"))))
A13: C-009 | O13: =IF(COUNT(E13:N13)=0,"",SUM(E13:N13)) | P13: =IF(COUNT(E13:N13)=0,"",IF(OR(E13=0,J13=0),"暫停(關鍵題0分)",IF(O13>=14,"積極爭取",IF(O13>=10,"觀察培養","暫停"))))
A14: C-010 | O14: =IF(COUNT(E14:N14)=0,"",SUM(E14:N14)) | P14: =IF(COUNT(E14:N14)=0,"",IF(OR(E14=0,J14=0),"暫停(關鍵題0分)",IF(O14>=14,"積極爭取",IF(O14>=10,"觀察培養","暫停"))))
A15: C-011 | O15: =IF(COUNT(E15:N15)=0,"",SUM(E15:N15)) | P15: =IF(COUNT(E15:N15)=0,"",IF(OR(E15=0,J15=0),"暫停(關鍵題0分)",IF(O15>=14,"積極爭取",IF(O15>=10,"觀察培養","暫停"))))
A16: C-012 | O16: =IF(COUNT(E16:N16)=0,"",SUM(E16:N16)) | P16: =IF(COUNT(E16:N16)=0,"",IF(OR(E16=0,J16=0),"暫停(關鍵題0分)",IF(O16>=14,"積極爭取",IF(O16>=10,"觀察培養","暫停"))))
A17: C-013 | O17: =IF(COUNT(E17:N17)=0,"",SUM(E17:N17)) | P17: =IF(COUNT(E17:N17)=0,"",IF(OR(E17=0,J17=0),"暫停(關鍵題0分)",IF(O17>=14,"積極爭取",IF(O17>=10,"觀察培養","暫停"))))
... A35: C-031 | O35: =IF(COUNT(E35:N35)=0,"",SUM(E35:N35)) | P35: =IF(COUNT(E35:N35)=0,"",IF(OR(E35=0,J35=0),"暫停(關鍵題0分)",IF(O35>=14,"積極爭取",IF(O35>=10,"觀察培養","暫停"))))

Sheet 審查標準_Criteria
A1: 審查標準｜評分錨點（10 題，每題 0/1/2 分——照著錨點打，不同人打分才會一致）
A3: 題 | B3: 面向 | C3: 2 分 | D3: 1 分 | E3: 0 分
A4: Q1 | B4: 預算來源 | C4: 有文號或已核定計畫，金額量級明確 | D4: 拍板者口頭承諾，來源方向清楚 | E4: 沒有可指認的預算來源
A5: Q2 | B5: 決策管道 | C5: 可直達拍板者（院長/董事會） | D5: 經一層引薦可達 | E5: 只認識承辦或事務層
A6: Q3 | B6: 觸發事件 | C6: 法規期限或已核定的新建/汰換計畫 | D6: 明確痛點且院方主動提及 | E6: 只有我們認為他需要
A7: Q4 | B7: 能力匹配 | C7: L2 主場或聯盟缺口=0 的商機 | D7: 聯盟能力可補、需要組隊 | E7: 缺口大、要找新夥伴
A8: Q5 | B8: 競爭態勢 | C8: 無深耕競爭者 | D8: 有競爭者但我方有明確切入角 | E8: 已被特定廠商鎖定多年
A9: Q6 | B9: 付款風險 | C9: 私立或 Nhóm 1 全自主 | D9: Nhóm 2 或有專項撥款文號 | E9: 依賴尚未核定的公務撥款
A10: Q7 | B10: 資源負擔 | C10: 現有人力可承接追案 | D10: 需增援一人或一夥伴 | E10: 超出現階段負荷
A11: Q8 | B11: 在地支持 | C11: 有引薦人＋在地夥伴可動員 | D11: 兩者有其一 | E11: 兩者皆無
A12: Q9 | B12: 時程可行 | C12: 決策窗口 ≥ 我方準備時間×1.5 | D12: 窗口緊但來得及 | E12: 趕不上（例：標案剩<14天且資格文件未備）
A13: Q10 | B13: 戰略價值 | C13: 首案示範性＋可複製到其他醫院 | D13: 單案有利潤 | E13: 拿下也無後續價值
A15: 判定規則
A16: ・總分 ≥14：積極爭取——進入 P1 接觸探索，建立作戰檔案完整版
A17: ・總分 10–13：觀察培養——維持關係、等待觸發事件，每季重評
A18: ・總分 <10：暫停——寫下「什麼條件改變才重看」，放回雷達
A19: ・★ 一票否決：Q1 預算=0 或 Q6 付款=0，無論總分一律暫停。錢的問題不會因為熱情消失。

Sheet 選單_Lists
A1: 醫院屬性 | B1: 技術層級 | C1: 財務自主 | D1: 關係強度 | E1: HIS廠商 | F1: EMR狀態 | G1: 取得狀態 | H1: 分數 | I1: 案件狀態 | K1: 目標商機
A2: 公立-中央直屬 | B2: 專深 Chuyên sâu | C2: Nhóm 1 全自主(含投資) | D2: 強(可直達拍板者) | E2: FPT | F2: 已上線 | G2: 已取得 | H2: 0 | I2: 進行中 | K2: OPP-01 醫院投資規劃與PPP交易架構顧問
A3: 公立-省級 | B3: 基本 Cơ bản | C3: Nhóm 2 經常性支出自主 | D3: 中(有引薦路徑) | E3: Viettel | F3: 建置中 | G3: 索取中 | H3: 1 | I3: 暫停 | K3: OPP-02 臨床服務定位與營運模式規劃
A4: 公立-縣級 | B4: 初級 Ban đầu | C4: Nhóm 3 部分自主 | D4: 弱(僅事務層) | E4: VNPT | F4: 未達標 | G4: 未行動 | H4: 2 | I4: 結案-贏 | K4: OPP-03 外資醫院綠地投資與經營
A5: 軍系 | B5: 未分級 | C5: Nhóm 4 全額補助 | D5: 無 | E5: 自建 | F5: 未知 | I5: 結案-輸 | K5: OPP-04 公立醫院合作經營高端診區
A6: 私立-集團 | C6: 私立(不適用) | E6: 其他 | I6: 結案-放棄 | K6: OPP-05 省級醫院升級改造整案
A7: 私立-獨立 | E7: 未知 | K7: OPP-06 醫院建築與院區總體規劃設計
K8: OPP-07 千床級醫院統包工程(EPC)
K9: OPP-08 手術室與加護病房潔淨空調（模組化OR）
K10: OPP-09 醫用氣體與真空系統（含竣工確效）
K11: OPP-10 醫院供電韌性與隔離電源系統
K12: OPP-11 醫療廢水與廢棄物處理廠
K13: OPP-12 綠色醫院能源績效合約與屋頂光電
K14: OPP-13 消毒供應中心(CSSD)設備整廠
K15: OPP-14 影像設備整批交鑰匙（CT/MRI/DSA＋機房）
K16: OPP-15 放射腫瘤與核醫中心整廠
K17: OPP-16 心導管室與複合式手術室
K18: OPP-17 洗腎設備與水處理系統
K19: OPP-18 內視鏡與自動清洗消毒追溯
... K86: OPP-85 效益實現與第二院區複製藍圖
