Workbook

Sheet 00_填表說明_Instructions
A1: VMH-EcoMap-3 夥伴提案回覆表 v1.0｜Partner Response Form
A2: 致候選夥伴：感謝參與「越南現代醫院生態導入計畫」。請填寫本表並於指定日期前回覆。本表用於資格審查（關係不等於交付能力，我們以實績評分），不構成採購承諾，亦不取代正式合約。
B4: 一、請填四張分頁
B5: 01 公司基本資料 | C5: 法人名稱、據點、規模、聯絡窗口、公司登記國別。
B6: 02 能力自評 | C6: 針對七個構面自評 0–5 分，並附佐證。自評分數會與我們的審查結果並列比較。
B7: 03 實績與證照 | C7: 三筆最相關實績＋品質、資安、醫材相關證照有效期。
B8: 04 越南落地與來源 | C8: 越南註冊狀態、在地服務能力、產品與韌體來源國、資料存取與次處理者。
B9: 05 彙總輸出 | C9: ★ 夥伴不需填。本頁自動把前四張分頁整理成主工具需要的格式，回收後由 PI 兩次貼上完成建檔。
B11: 二、我們如何使用這份表
B12: • | C12: 七個構面的分數會匯入主工具「04 夥伴拼圖」，自動計算適配分（七項平均）。
B13: • | C13: 「涵蓋領域」決定您出現在夥伴×領域覆蓋矩陣的哪幾格。
B14: • | C14: 「來源風險」為內部稽核欄位，不會出現在對外簡報，但會影響越南官方審查。
B15: • | C15: 通過資格審查後，主工具中對應能力項的拼圖狀態會由「缺口-待尋找」改為「夥伴洽談中」或「夥伴已確認」。
B17: 誠信聲明：填寫本表即表示所提供之實績、證照與註冊狀態均屬真實且可查證。本計畫的獨立驗證單位得要求提供正本文件或聯繫實績客戶查證；資料不實者將自候選名單移除。
B20: 回覆期限 | C20: 年 月 日 | D20: 回覆窗口（PI 辦公室）

Sheet 01_公司基本資料_Company
A1: 01 公司基本資料｜Company Profile
A2: ★ 為必填。請填法人正式名稱，不要用品牌名或簡稱。
A4: ★ 公司法人名稱（中） | G4: 與登記文件一致
A5: ★ 公司法人名稱（英） | G5: 用於對越南官方文件
A6: ★ 統一編號／註冊號
A7: ★ 總部所在國家／城市
A8: ★ 成立年份
A9: ★ 員工人數
A10: ★ 近三年平均年營收（USD） | G10: 區間亦可
A11: ★ 公司網站
A12: ★ 主要業務一句話描述 | G12: 請具體，不要寫「全方位解決方案」
A14: 聯絡窗口（本計畫唯一對口）
A15: ★ 姓名／職稱 | G15: 須為可決策或可直達決策者
A16: ★ 電子郵件
A17: ★ 電話／通訊軟體
A18: ★ 可決策層級 | G18: 例：可簽署 NDA 與 MOU
A20: 您希望在聯盟中的定位
A21: ★ 夥伴類型 | G21: 見右側下拉
A22: ★ 公司登記國別 | G22: 見右側下拉；影響主工具的夥伴×國別統計
A23: ★ 涵蓋領域（可複選，用分號隔開） | G23: D01 治理與投資／D02 臨床服務模式／D03 醫院設施與機電／D04 數位基建與物聯網／D05 醫材與診斷／D06 醫療資訊與資料／D07 品質與病安／D08 人才與技轉／D09 供應鏈與維運／D10 商模與病人生態
A24: ★ 您想承接的能力編號（CAP-xxx） | G24: 可從「11 缺口招募清單」挑選，用分號隔開
A25: ★ 可提供的角色 | G25: 例：主責交付／分包／技術授權／顧問

Sheet 02_能力自評_SelfAssessment
A1: 02 能力自評｜Capability Self-Assessment（0–5 分）
A2: 請誠實自評。0＝完全沒有；3＝有經驗但需協助；5＝可獨立承擔並有可查證實績。每一項都必須填「佐證說明」，只有分數沒有佐證的項目，審查時一律以 0 分計。
A4: 構面 Dimension | B4: 我們要看的是什麼 | C4: 自評 0-5 | D4: 我方 審查 | E4: 佐證說明（必填） | F4: 佐證文件名稱
A5: 實績 References | B5: 同類專案的可查證案例，醫療場域經驗優先。請寫出客戶名稱可否揭露。
A6: 顧問能力 Advisory | B6: 能否協助定義需求與規格，而不只是報價與供貨。
A7: 建置能力 Build | B7: 自有工班或整合團隊，能在越南現場交付的實際能力。
A8: 營運能力 Operate | B8: 交付後的維運、備品供應、回應時間與服務水準承諾。
A9: 財務能力 Finance | B9: 專案期間的現金流承受力；是否可接受階段付款或績效付款。
A10: 互通能力 Interop | B10: 是否採用開放標準與 API（FHIR／HL7／DICOM／IHE），可否接受符合性測試。
A11: 在地化 Localization | B11: 越南據點、越語人員、在地訓練與技術移轉承諾。
B12: 自評平均（適配分） | C12: =IF(COUNT(C5:C11)<7,"請填滿7項",ROUND(AVERAGE(C5:C11),1)) -> 請填滿7項 | D12: =IF(COUNT(D5:D11)<7,"",ROUND(AVERAGE(D5:D11),1)) | E12: ← 我方審查欄由 PI 辦公室填寫，不需夥伴填
A14: 評分標準說明
A15: 0 | B15: 完全沒有此能力，需完全外包
A16: 1 | B16: 僅有理論或旁觀經驗
A17: 2 | B17: 參與過但非主責
A18: 3 | B18: 主責過類似案，但需外部協助
A19: 4 | B19: 主責過同類案並成功交付
A20: 5 | B20: 多次主責同類案，且有醫療場域實績

Sheet 03_實績證照_Track
A1: 03 實績與證照｜Track Record & Certifications
A2: 請填三筆最相關的實績（醫療場域優先）。可查證＝我們可以聯繫該客戶確認；若不可揭露，請說明原因。
A4: # | B4: 專案名稱 | C4: 客戶／醫院 | D4: 國家 | E4: 完成年 | F4: 合約金額(USD) | G4: 您負責的範圍 | H4: 可查證? | I4: 聯絡人
A5: 1
A6: 2
A7: 3
A8: 4
A9: 5
A11: 證照與管理系統（有效期須為現行）
A12: # | B12: 證照／標準 | C12: 發證單位 | D12: 涵蓋範圍 | E12: 有效期至 | F12: 證書編號 | G12: 備註
A13: 1 | B13: ISO 9001 品質管理
A14: 2 | B14: ISO 13485 醫材品質
A15: 3 | B15: ISO 14971 醫材風險
A16: 4 | B16: IEC 60601 醫電安全
A17: 5 | B17: ISO 27001 資訊安全
A18: 6 | B18: ISO 22301 營運持續
A19: 7 | B19: IHE / DICOM 符合性
A20: 8 | B20: 越南醫材流通許可
A21: 9 | B21: 其他（請填）

Sheet 04_越南落地與來源_Vietnam
A1: 04 越南落地與來源｜Vietnam Readiness & Supply-chain Origin
A2: 這一頁決定您的產品能不能進得了越南的醫院。所有欄位都會進入內部稽核紀錄，並影響越南官方審查結果。
A4: A. 越南落地能力
A5: ★ 在越南是否有法人或分公司 | G5: 見右側下拉
A6: ★ 越南辦公室／服務據點城市
A7: ★ 越南在地員工人數
A8: ★ 是否有越語技術人員 | G8: 影響訓練與維運交付
A9: ★ 故障回應時間承諾（小時） | G9: 請分「電話回應」與「到場」
A10: ★ 備品在越南的庫存安排 | G10: 有／無／可建立
A12: B. 法規與註冊狀態
A13: ★ 主要產品在越南的註冊狀態 | G13: 已註冊／申請中／尚未申請／不適用
A14: ★ 若尚未註冊，預估取證時程（月） | G14: 請務實填寫，這是專案關鍵路徑
A15: ★ 越南醫材分類（A/B/C/D） | G15: 依 Decree 98/2021
A16: ★ 已取得之越南許可文號
A17: ★ 是否曾有產品在越南被退件或召回 | G17: 誠實填寫；隱匿將直接失格
A19: C. 供應鏈與資料來源（內部稽核欄位）
A20: ★ 硬體製造國 | G20: 主要生產地
A21: ★ 關鍵零組件來源國 | G21: 如晶片、感測器、影像板
A22: ★ 韌體／作業系統開發國
A23: ★ 軟體開發與維護所在國
A24: ★ 資料是否可能離開越南境內 | G24: 是／否；若是請說明去向
A25: ★ 境外次處理者（Sub-processor）清單 | G25: 雲端、遠端維運、資料分析等
A26: ★ 遠端維護連線方式 | G26: VPN／專線／不需遠端
A27: ★ 可否接受資料完全在越南境內處理 | G27: 是／否／需額外成本
A28: ★ 實質受益人（Beneficial owner）國別 | G28: 母公司與最終控股
A30: 說明：C 段問題並非針對任何國家，而是越南《個人資料保護法令 13/2023》與《網路安全法令 53/2022》要求我們必須能說明健康資料的處理位置與次處理者。無法回答此段的方案，無法通過越南官方審查。
A33: 填表人簽署 | B33: 姓名 | D33: 職稱 | F33: 日期

Sheet 06_商機對照_Opportunities
A1: 06 商機對照｜你加入聯盟，能參與哪些生意（參考頁，不用填）
A2: 左表：把你在「02_能力自評」勾的能力編號拿來對照，看每項能力對應到哪些商機。右表：本聯盟盤點的 85 種越南醫院市場商機摘要——標「③尚未出現」的代表越南目前幾乎沒人做，正是先進場的人定規則的空間。想深入了解任何一項，回覆表寄回時註明代號即可，我們會提供該商機的完整作戰資料。
A4: A. 能力 → 商機 對照（60 項） | F4: B. 85 種商機摘要（族群 A~J）
A5: CAP ID | B5: 能力項目 | C5: 對應商機代號 | D5: 商機數 | F5: 代號 | G5: 商機 | H5: 越南現況 | I5: 典型金額級距 | J5: 族群
A6: CAP-001 | B6: 政府授權與計畫章程 | C6: OPP-01 | D6: 1 | F6: OPP-01 | G6: 醫院投資規劃與PPP交易架構顧問 | H6: ② 起步中： | I6: 500K-2M USD | J6: A
A7: CAP-002 | B7: 利害關係人與權力地圖 | C7: OPP-01 | D7: 1 | F7: OPP-02 | G7: 臨床服務定位與營運模式規劃 | H7: ② 起步中： | I7: 100K-500K USD | J7: A
A8: CAP-003 | B8: 交易模式選擇 | C8: OPP-01; OPP-03; OPP-04 | D8: 3 | F8: OPP-03 | G8: 外資醫院綠地投資與經營 | H8: ② 起步中： | I8: >10M USD | J8: A
A9: CAP-004 | B9: 法規與執照路徑 | C9: OPP-01; OPP-22; OPP-28; OPP-59 | D9: 4 | F9: OPP-04 | G9: 公立醫院合作經營高端診區 | H9: ② 起步中： | I9: 2M-10M USD | J9: A
A10: CAP-005 | B10: 聯盟治理與利益衝突 | C10: OPP-01 | D10: 1 | F10: OPP-05 | G10: 省級醫院升級改造整案 | H10: ① 已成熟： | I10: >10M USD | J10: A
A11: CAP-006 | B11: 績效契約與變更控制 | C11: OPP-01; OPP-04; OPP-85 | D11: 3 | F11: OPP-06 | G11: 醫院建築與院區總體規劃設計 | H11: ② 起步中： | I11: 500K-2M USD | J11: B
A12: CAP-007 | B12: 人口需求與病例量預測 | C12: OPP-02; OPP-75 | D12: 2 | F12: OPP-07 | G12: 千床級醫院統包工程(EPC) | H12: ① 已成熟： | I12: >10M USD | J12: B
A13: CAP-008 | B13: 醫院定位與服務組合 | C13: OPP-02; OPP-03; OPP-04; OPP-74; OPP-75 | D13: 5 | F13: OPP-08 | G13: 手術室與加護病房潔淨空調（模組化OR） | H13: ② 起步中： | I13: 2M-10M USD | J13: B
A14: CAP-009 | B14: 重點專科優先化 | C14: OPP-02; OPP-74 | D14: 2 | F14: OPP-09 | G14: 醫用氣體與真空系統（含竣工確效） | H14: ② 起步中： | I14: 500K-2M USD | J14: B
A15: CAP-010 | B15: 病人流程與容量設計 | C15: OPP-02; OPP-72; OPP-79 | D15: 3 | F15: OPP-10 | G15: 醫院供電韌性與隔離電源系統 | H15: ② 起步中： | I15: 500K-2M USD | J15: B
A16: CAP-011 | B16: 轉診與區域照護網絡 | C16: OPP-02; OPP-77; OPP-78; OPP-79 | D16: 4 | F16: OPP-11 | G16: 醫療廢水與廢棄物處理廠 | H16: ② 起步中： | I16: 500K-2M USD | J16: B
A17: CAP-012 | B17: 臨床治理與責任架構 | C17: OPP-02 | D17: 1 | F17: OPP-12 | G17: 綠色醫院能源績效合約與屋頂光電 | H17: ③ 尚未出現 | I17: 500K-2M USD | J17: B
... A65: CAP-060 | B65: 效益實現與複製藍圖 | C65: OPP-01; OPP-85 | D65: 2 | F65: OPP-60 | G65: JCI品質認證與病安體系導入 | H65: ② 起步中： | I65: 100K-500K USD | J65: G
F66: OPP-61 | G66: ISO 15189檢驗室認證輔導 | H66: ③ 尚未出現 | I66: 100K-500K USD | J66: G
F67: OPP-62 | G67: 臨床人才培訓、模擬中心與技術移轉 | H67: ② 起步中： | I67: 100K-500K USD | J67: G
F68: OPP-63 | G68: 開院前臨床安全驗證與試營運 | H68: ③ 尚未出現 | I68: 100K-500K USD | J68: G
F69: OPP-64 | G69: 院內物流SPD委外 | H69: ③ 尚未出現 | I69: 500K-2M USD | J69: H
F70: OPP-65 | G70: 消毒供應外包（區域CSSD服務化） | H70: ③ 尚未出現 | I70: 500K-2M USD | J70: H
F71: OPP-66 | G71: 醫材維運與託管服務(MES) | H71: ③ 尚未出現 | I71: 500K-2M USD | J71: H
F72: OPP-67 | G72: 醫院設施管理委外（醫療級FM） | H72: ③ 尚未出現 | I72: 500K-2M USD | J72: H
F73: OPP-68 | G73: 冷鏈與特殊物料物流 | H73: ② 起步中： | I73: 100K-500K USD | J73: H
F74: OPP-69 | G74: 醫療廢棄物收運處理服務 | H74: ② 起步中： | I74: 500K-2M USD | J74: H
F75: OPP-70 | G75: 在地備品、維修與汰換服務網 | H75: ② 起步中： | I75: 100K-500K USD | J75: H
F76: OPP-71 | G76: 洗腎連鎖（衛星洗腎中心） | H76: ③ 尚未出現 | I76: 500K-2M USD | J76: I
F77: OPP-72 | G77: 日間手術中心(ASC) | H77: ③ 尚未出現 | I77: 2M-10M USD | J77: I
... F90: OPP-85 | G90: 效益實現與第二院區複製藍圖 | H90: ③ 尚未出現 | I90: 100K-500K USD | J90: J
A92: ★ 本頁為 2026-08 快照，正式商機內容以主工具（PI 維護）為準。一項能力對到越多商機（左表紅字≥4），代表你加入後能參與的生意越多——這正是我們找夥伴的邏輯：一次結盟、多門生意。

Sheet 05_彙總輸出_ExportRow
A1: 05 彙總輸出｜Export Row（PI 辦公室用，夥伴不需填）
A2: 本頁全部是公式，會把前面四張分頁的答案整理成「主工具 04 夥伴拼圖」需要的欄位順序。回收本表後，依下方兩個步驟複製貼上，就完成建檔——不需要逐格重打。
A4: 步驟一：複製 B7:O7（共 14 欄，從B開始、不含A）→ 到主工具「04_夥伴拼圖_Partners」的第一個空白列，在 B 欄按滑鼠右鍵→「選擇性貼上」→「值」。A欄（夥伴ID）不用貼、也不用填，B欄一有名稱就會自動編號。
A5: 步驟二：再複製 Q7:S7（共 3 欄）→ 貼到同一列的 Q 欄。★ P 欄（適配分）主工具本身有公式，刻意不輸出，貼上後會自動算出來。F欄（涵蓋領域）貼上後會變成固定文字，仍可正常比對；若想改回跟著U-AD勾選欄連動，清空F欄再勾選U-AD即可。
A6: 夥伴 ID | B6: 夥伴/角色(中) | C6: Partner (EN) | D6: 類型 | E6: 國別 | F6: 涵蓋領域 | G6: 聯盟定位 | H6: 越南據點 | I6: 實績 | J6: 顧問 | K6: 建置 | L6: 營運 | M6: 財務 | N6: 互通 | O6: 在地 | P6: 適配分 | Q6: 來源風險 | R6: 狀態 | S6: 下一步
A7: ="" | B7: =IF('01_公司基本資料_Company'!$B$4="","",'01_公司基本資料_Company'!$B$4) | C7: =IF('01_公司基本資料_Company'!$B$5="","",'01_公司基本資料_Company'!$B$5) | D7: =IF('01_公司基本資料_Company'!$B$21="","",'01_公司基本資料_Company'!$B$21) | E7: =IF('01_公司基本資料_Company'!$B$22="","",'01_公司基本資料_Company'!$B$22) | F7: =IF('01_公司基本資料_Company'!$B$23="","",'01_公司基本資料_Company'!$B$23) | G7: =IF('01_公司基本資料_Company'!$B$25="","",'01_公司基本資料_Company'!$B$25) | H7: =IF('04_越南落地與來源_Vietnam'!$B$5="","",'04_越南落地與來源_Vietnam'!$B$5) | I7: =IF(AND('02_能力自評_SelfAssessment'!$C$5="",'02_能力自評_SelfAssessment'!$D$5=""),"",IF('02_能力自評_SelfAssessment'!$D$5="",'02_能力自評_SelfAssessment'!$C$5,'02_能力自評_SelfAssessment'!$D$5)) | J7: =IF(AND('02_能力自評_SelfAssessment'!$C$6="",'02_能力自評_SelfAssessment'!$D$6=""),"",IF('02_能力自評_SelfAssessment'!$D$6="",'02_能力自評_SelfAssessment'!$C$6,'02_能力自評_SelfAssessment'!$D$6)) | K7: =IF(AND('02_能力自評_SelfAssessment'!$C$7="",'02_能力自評_SelfAssessment'!$D$7=""),"",IF('02_能力自評_SelfAssessment'!$D$7="",'02_能力自評_SelfAssessment'!$C$7,'02_能力自評_SelfAssessment'!$D$7)) | L7: =IF(AND('02_能力自評_SelfAssessment'!$C$8="",'02_能力自評_SelfAssessment'!$D$8=""),"",IF('02_能力自評_SelfAssessment'!$D$8="",'02_能力自評_SelfAssessment'!$C$8,'02_能力自評_SelfAssessment'!$D$8)) | M7: =IF(AND('02_能力自評_SelfAssessment'!$C$9="",'02_能力自評_SelfAssessment'!$D$9=""),"",IF('02_能力自評_SelfAssessment'!$D$9="",'02_能力自評_SelfAssessment'!$C$9,'02_能力自評_SelfAssessment'!$D$9)) | N7: =IF(AND('02_能力自評_SelfAssessment'!$C$10="",'02_能力自評_SelfAssessment'!$D$10=""),"",IF('02_能力自評_SelfAssessment'!$D$10="",'02_能力自評_SelfAssessment'!$C$10,'02_能力自評_SelfAssessment'!$D$10)) | O7: =IF(AND('02_能力自評_SelfAssessment'!$C$11="",'02_能力自評_SelfAssessment'!$D$11=""),"",IF('02_能力自評_SelfAssessment'!$D$11="",'02_能力自評_SelfAssessment'!$C$11,'02_能力自評_SelfAssessment'!$D$11)) | P7: ="←主工具自動算" -> ←主工具自動算 | Q7: ="" | R7: ="Due diligence / 審查中" -> Due diligence / 審查中 | S7: =IF('01_公司基本資料_Company'!$B$24="","（PI 填）","洽談承接："&'01_公司基本資料_Company'!$B$24) -> （PI 填）
A8: 留白：04的A欄現在自動編號，不用貼這欄（貼B7起即可跳過） | P8: 不輸出：主工具有公式 | Q8: 留白：由 PI 依 04 分頁 C 段判定 | R8: 預設值，PI 可改
A9: 送出前的完整性檢查
A10: 七項能力自評都填了嗎 | F10: =IF(COUNT('02_能力自評_SelfAssessment'!$C$5:$C$11)=7,"✓ 已填滿","✗ 尚缺 "&(7-COUNT('02_能力自評_SelfAssessment'!$C$5:$C$11))&" 項") -> ✗ 尚缺 7 項
A11: 七項佐證說明都填了嗎 | F11: =IF(COUNTA('02_能力自評_SelfAssessment'!$E$5:$E$11)=7,"✓ 已填滿","✗ 尚缺 "&(7-COUNTA('02_能力自評_SelfAssessment'!$E$5:$E$11))&" 項（無佐證以 0 分計）") -> ✗ 尚缺 7 項（無佐證以 0 分計）
A12: 公司法人名稱（中/英） | F12: =IF(AND('01_公司基本資料_Company'!$B$4<>"",'01_公司基本資料_Company'!$B$5<>""),"✓ 已填","✗ 未填") -> ✗ 未填
A13: 夥伴類型與涵蓋領域 | F13: =IF(AND('01_公司基本資料_Company'!$B$21<>"",'01_公司基本資料_Company'!$B$23<>""),"✓ 已填","✗ 未填") -> ✗ 未填
A14: 聯絡窗口 Email | F14: =IF('01_公司基本資料_Company'!$B$16<>"","✓ 已填","✗ 未填") -> ✗ 未填
A15: 越南註冊狀態 | F15: =IF('04_越南落地與來源_Vietnam'!$B$5<>"","✓ 已填","✗ 未填") -> ✗ 未填
A16: 至少一筆實績 | F16: =IF(COUNTA('03_實績證照_Track'!$B$5:$B$9)>0,"✓ 已填","✗ 未填") -> ✗ 未填
A18: 為什麼不是自動連動？ 本表是要寄給外部夥伴填的獨立檔案，每一家的檔案路徑都不同；Excel 的跨檔連結一旦路徑改變就會失效，而且會把外部檔案的內容帶進主工具，造成版本混亂與資安疑慮。因此設計成「結構化貼上」：由本頁把答案排成主工具需要的順序，PI 只要兩次貼上就完成，既不會打錯字，也不會在主工具留下對外部檔案的連結。 ★ 貼上後請記得到主工具 03_能力總表，把該夥伴要承接的能力項，拼圖狀態由「缺口-待尋找」改為「夥伴洽談中」。
