Workbook

Sheet 00A_從這裡開始_Start
A1: 00A 從這裡開始｜夥伴版（選一個身分，照著五步走） | P1: key | R1: 去哪頁 | S1: 做什麼 | T1: 改哪些 | U1: 完成的樣子
A2: 這是 VMH-EcoMap 主工具的夥伴版：只留下 7 個分頁，把顧問在用的盤點工作區收起來了（資料與公式完整保留，沒有刪任何東西）。★ 選完下拉，下面五步會自動換成你的路徑。看完這頁就可以動手。 | P2: ① 夥伴｜第一次打開這個檔-1 | R2: 15_商機字典_OppLibrary | S2: 先看這 85 門越南醫院市場可以做的生意，分成 A~J 十個族群。只看「在賣什麼／誰付錢／大概多少錢／越南現況」四欄，找跟你本業有關的。 | T2: 不用改任何格子 | U2: 圈出 3–5 個你做得到的商機
A3: ⌂ 回導引頁 | P3: ① 夥伴｜第一次打開這個檔-2 | R3: 15_商機字典_OppLibrary | S3: 看 L 欄「★白地商機」——越南有這門生意，但聯盟目前沒有能力接。那是最歡迎你補位的位置。 | T3: 不用改任何格子 | U3: 確認裡面有沒有你的位置
A4: 我是誰 | B4: ① 夥伴｜第一次打開這個檔 | D4: ◀ 先選這裡 | P4: ① 夥伴｜第一次打開這個檔-3 | R4: 17_商機作戰卡_OppView | S4: 在最上面的下拉選單挑一個你圈出來的商機，這一頁會自動組出作戰卡：需要哪些能力、誰在做、還缺什麼、對手是誰。 | T4: 只改下拉那一格 | U4: 知道你要補的是哪一塊
P5: ① 夥伴｜第一次打開這個檔-4 | R5: 11_缺口招募_GapRFI | S5: 看紅底的那幾列——那是「牽動 ≥3 個商機」的缺口，補一個能同時解鎖好幾門生意，聯盟最急著找人。 | T5: 不用改任何格子 | U5: 選出你要認領的缺口
A6: 步驟 | B6: 去哪一頁 | C6: 要做什麼 | D6: 你只要改這些 | E6: 完成的樣子 | P6: ① 夥伴｜第一次打開這個檔-5 | R6: （回報給 PI，不用動這個檔） | S6: 把你能做的商機與想認領的缺口，填進 VMH-EcoMap-3 夥伴提案回覆表交回來。這個主檔由 PI 統一維護。 | T6: 不用改任何格子 | U6: 提案回覆表已寄出
A7: 第 1 步 | B7: =IFERROR(INDEX($R$2:$R$200,MATCH($B$4&"-1",$P$2:$P$200,0)),"") -> 15_商機字典_OppLibrary | C7: =IFERROR(INDEX($S$2:$S$200,MATCH($B$4&"-1",$P$2:$P$200,0)),"") -> 先看這 85 門越南醫院市場可以做的生意，分成 A~J 十個族群。只看「在賣什麼／誰付錢／大概多少錢／越南現況」四欄，找跟你本業有關的。 | D7: =IFERROR(INDEX($T$2:$T$200,MATCH($B$4&"-1",$P$2:$P$200,0)),"") -> 不用改任何格子 | E7: =IFERROR(INDEX($U$2:$U$200,MATCH($B$4&"-1",$P$2:$P$200,0)),"") -> 圈出 3–5 個你做得到的商機 | P7: ② 夥伴｜我已經在夥伴名單上-1 | R7: 12_夥伴視角_PartnerView | S7: 在下拉選單選你的代號（顯示「P-016 影像設備與PACS整合商」這種格式），這一頁自動列出你被指名的所有能力項與所屬商機。 | T7: 只改下拉那一格 | U7: 看到自己被指名的完整清單
A8: 第 2 步 | B8: =IFERROR(INDEX($R$2:$R$200,MATCH($B$4&"-2",$P$2:$P$200,0)),"") -> 15_商機字典_OppLibrary | C8: =IFERROR(INDEX($S$2:$S$200,MATCH($B$4&"-2",$P$2:$P$200,0)),"") -> 看 L 欄「★白地商機」——越南有這門生意，但聯盟目前沒有能力接。那是最歡迎你補位的位置。 | D8: =IFERROR(INDEX($T$2:$T$200,MATCH($B$4&"-2",$P$2:$P$200,0)),"") -> 不用改任何格子 | E8: =IFERROR(INDEX($U$2:$U$200,MATCH($B$4&"-2",$P$2:$P$200,0)),"") -> 確認裡面有沒有你的位置 | P8: ② 夥伴｜我已經在夥伴名單上-2 | R8: 17_商機作戰卡_OppView | S8: 挑一個你有份的商機，看這場仗整體怎麼打：還缺哪些能力、對手是誰、憑什麼贏、卡在哪些法規門檻。 | T8: 只改下拉那一格 | U8: 知道自己在這場仗裡的位置
A9: 第 3 步 | B9: =IFERROR(INDEX($R$2:$R$200,MATCH($B$4&"-3",$P$2:$P$200,0)),"") -> 17_商機作戰卡_OppView | C9: =IFERROR(INDEX($S$2:$S$200,MATCH($B$4&"-3",$P$2:$P$200,0)),"") -> 在最上面的下拉選單挑一個你圈出來的商機，這一頁會自動組出作戰卡：需要哪些能力、誰在做、還缺什麼、對手是誰。 | D9: =IFERROR(INDEX($T$2:$T$200,MATCH($B$4&"-3",$P$2:$P$200,0)),"") -> 只改下拉那一格 | E9: =IFERROR(INDEX($U$2:$U$200,MATCH($B$4&"-3",$P$2:$P$200,0)),"") -> 知道你要補的是哪一塊 | P9: ② 夥伴｜我已經在夥伴名單上-3 | R9: 11_缺口招募_GapRFI | S9: 看你負責的能力旁邊還缺什麼。如果是你能一起接的，主動說，比等 PI 來問快。 | T9: 不用改任何格子 | U9: 列出你可以一起接的缺口
A10: 第 4 步 | B10: =IFERROR(INDEX($R$2:$R$200,MATCH($B$4&"-4",$P$2:$P$200,0)),"") -> 11_缺口招募_GapRFI | C10: =IFERROR(INDEX($S$2:$S$200,MATCH($B$4&"-4",$P$2:$P$200,0)),"") -> 看紅底的那幾列——那是「牽動 ≥3 個商機」的缺口，補一個能同時解鎖好幾門生意，聯盟最急著找人。 | D10: =IFERROR(INDEX($T$2:$T$200,MATCH($B$4&"-4",$P$2:$P$200,0)),"") -> 不用改任何格子 | E10: =IFERROR(INDEX($U$2:$U$200,MATCH($B$4&"-4",$P$2:$P$200,0)),"") -> 選出你要認領的缺口 | P10: ② 夥伴｜我已經在夥伴名單上-4 | R10: 15_商機字典_OppLibrary | S10: 查你「沒有被指名、但其實做得到」的生意。被指名的清單是 PI 的判斷，不一定完整。 | T10: 不用改任何格子 | U10: 列出你想爭取的商機
A11: 第 5 步 | B11: =IFERROR(INDEX($R$2:$R$200,MATCH($B$4&"-5",$P$2:$P$200,0)),"") -> （回報給 PI，不用動這個檔） | C11: =IFERROR(INDEX($S$2:$S$200,MATCH($B$4&"-5",$P$2:$P$200,0)),"") -> 把你能做的商機與想認領的缺口，填進 VMH-EcoMap-3 夥伴提案回覆表交回來。這個主檔由 PI 統一維護。 | D11: =IFERROR(INDEX($T$2:$T$200,MATCH($B$4&"-5",$P$2:$P$200,0)),"") -> 不用改任何格子 | E11: =IFERROR(INDEX($U$2:$U$200,MATCH($B$4&"-5",$P$2:$P$200,0)),"") -> 提案回覆表已寄出 | P11: ② 夥伴｜我已經在夥伴名單上-5 | R11: （回報給 PI，不用動這個檔） | S11: 有任何異動請 PI 更新 03 能力總表與 04 夥伴拼圖，不要自己改——那兩頁是全工具的資料源。 | T11: 不用改任何格子 | U11: 異動已回報
P12: ③ 業主／老闆｜我要看整體與該打哪一個-1 | R12: 儀表板_Dashboard | S12: 六個數字卡加四張圖，三十秒看完整體：商機族群分佈、越南現況、各領域缺口、管線階段。開會先投影這頁。 | T12: 不用改任何格子 | U12: 掌握整體盤勢
A13: 三十秒認識這個工具 | P13: ③ 業主／老闆｜我要看整體與該打哪一個-2 | R13: 儀表板_Dashboard | S13: 看 Top 10 攻擊順位表。分數已自動算好＝價值 × 準備度 × 越南現況 − 缺口扣分。 | T13: 不用改任何格子 | U13: 知道前十名是哪些
A14: 它在回答什麼 | B14: 「大家一起去越南做醫院生意」——哪些生意可以做、我們做得到哪些、缺什麼、誰來補、什麼時候做。 | P14: ③ 業主／老闆｜我要看整體與該打哪一個-3 | R14: 14_商機清單_Pipeline | S14: A 欄下拉選一個商機，名稱、族群、越南現況、涵蓋領域、對應能力數、缺口數、建議付費方與金額級距全部自動帶入。你只要填本案實際的商業判斷。 | T14: 改 A 欄下拉＋商業判斷欄 | U14: 管線上有你拍板過的商機
A15: 它不回答什麼 | B15: 不回答「這一案划不划算」。財務試算在另一個檔：VMH-EcoMap-2 專案商模試算器。 | P15: ③ 業主／老闆｜我要看整體與該打哪一個-4 | R15: 17_商機作戰卡_OppView | S15: 對某一個商機要細節時看這頁：需要哪些能力、誰在做誰還缺、對手是誰、卡哪些門檻。 | T15: 只改下拉那一格 | U15: 知道這一案打不打得動
A16: 核心是兩張表 | B16: 03_能力總表（我們會什麼，60 項）與 15_商機字典（市場有什麼，85 門）。中間用 16_能力商機矩陣 打✓連起來，其餘 19 個分頁全部是這三張表自動算出來的。 | P16: ③ 業主／老闆｜我要看整體與該打哪一個-5 | R16: （跳到另一個檔） | S16: 要算錢請開 VMH-EcoMap-2 專案商模試算器。這個主檔回答「做不做、誰做、何時做」，不回答「划不划算」。 | T16: 不用改任何格子 | U16: 財務結論已另案試算
A17: 顏色怎麼看 | B17: 黃底＝可以改；藍字＝公式，改了會壞；綠＝就緒／通過；橘＝洽談中／注意；紅＝缺口／未通過。 | P17: ④ PI／專案經理｜我要跑週會、追進度-1 | R17: 13_待辦看板_Actions | S17: 未確認強制法規、高風險、缺口三張清單合一。週會直接照這頁跑，不用東翻西找。 | T17: 不用改任何格子 | U17: 本週要解的事已列出
A18: 分頁標籤顏色 | B18: 綠＝入口（從這裡開始）；藍綠＝夥伴看的；深藍＝決策與簡報用；中藍＝顧問工作區；灰＝維護區，平常不用打開。 | P18: ④ PI／專案經理｜我要跑週會、追進度-2 | R18: 01_總藍圖_Blueprint | S18: 紅色缺口與門檻警示就是本週要解的事。各夥伴在這張圖上確認自己的定位。 | T18: 不用改任何格子 | U18: 缺口地圖已對過
P19: ④ PI／專案經理｜我要跑週會、追進度-3 | R19: 03_能力總表_Master | S19: 有任何盤點異動只改這裡——階段、拼圖狀態、分數。這是單一資料源，其他 20 個分頁全部自動連動。 | T19: 只改黃色儲存格 | U19: 異動已寫入，全檔連動
A20: 五個身分一覽（投影時用這塊，讓每個人先認領自己的角色） | P20: ④ PI／專案經理｜我要跑週會、追進度-4 | R20: 05_法規門檻_Gates | S20: 本階段的強制法規確認了沒？未確認不得過關。這是 Gate，不是 Task，不能往後排。 | T20: 只改黃色儲存格 | U20: 本階段法規狀態已更新
A21: ① 夥伴｜第一次打開這個檔 | C21: 第一步就去 → 15_商機字典_OppLibrary | P21: ④ PI／專案經理｜我要跑週會、追進度-5 | R21: 10_決策紀錄_Log | S21: 決議、升級事項、擱置理由都寫這裡。這頁不上鎖，自由書寫。三年後要回答「當初為什麼這樣決定」，靠的就是它。 | T21: 整頁自由書寫 | U21: 本週決議已留痕
A22: ② 夥伴｜我已經在夥伴名單上 | C22: 第一步就去 → 12_夥伴視角_PartnerView | P22: ⑤ 顧問／分析師｜我要更新盤點資料-1 | R22: 03_能力總表_Master | S22: 單一資料源。新增能力請到第一個空白列（第 65 列起）填 CAP-061…，只要 A 欄有 ID，分數、判斷、總藍圖矩陣、缺口計數全部自動出現。 | T22: 只改黃色儲存格 | U22: 新能力已納入全檔統計
A23: ③ 業主／老闆｜我要看整體與該打哪一個 | C23: 第一步就去 → 儀表板_Dashboard | P23: ⑤ 顧問／分析師｜我要更新盤點資料-2 | R23: 16_能力商機矩陣_CapOppMap | S23: 用打「✓」建立能力 ↔ 商機的多對多關聯，不用打字。勾完 03 的 AF 欄、15 與 14 全部自動更新。 | T23: 只在格子裡打 ✓ | U23: 關聯已建立
A24: ④ PI／專案經理｜我要跑週會、追進度 | C24: 第一步就去 → 13_待辦看板_Actions | P24: ⑤ 顧問／分析師｜我要更新盤點資料-3 | R24: 04_夥伴拼圖_Partners | S24: 新夥伴只要填名稱，ID 自動編號；右側 U–AD 勾選 D01–D10，涵蓋領域欄自動組成，不用打「D01; D04」這種格式。 | T24: 改黃色格＋勾選欄 | U24: 夥伴名冊與覆蓋矩陣已更新
A25: ⑤ 顧問／分析師｜我要更新盤點資料 | C25: 第一步就去 → 03_能力總表_Master | P25: ⑤ 顧問／分析師｜我要更新盤點資料-4 | R25: 02_情境權重_Scenario | S25: 調整評分權重（合計必須等於 1），60 項能力的價值分與準備分會同步重算。改這裡等於改全檔的排序邏輯。 | T25: 只改黃色儲存格 | U25: 評分邏輯已調整
P26: ⑤ 顧問／分析師｜我要更新盤點資料-5 | R26: 98_選單維護_Lists | S26: 所有下拉選單的唯一維護處。要新增選項只在該欄最下方接著往下填，全工具的下拉自動增加。請勿刪標題列、勿在清單中間留空白。 | T26: 只改黃色儲存格 | U26: 選單已擴充
A27: ★ 這一頁沒有任何數字要你填。夥伴版的 7 個分頁全部是唯讀的參考資料，你只需要在 17 商機作戰卡與 12 夥伴視角上方的下拉選單挑選項目。要回報請用 VMH-EcoMap-3 夥伴提案回覆表，不要改這個檔。

Sheet 儀表板_Dashboard
A1: 儀表板｜Dashboard（開會先投影這一頁：四張圖與六個數字，全部自動更新）
A2: ❓ 這頁在回答：整體盤勢如何？該打的前十名是哪些？ ▸ 本頁全部是公式與圖表，不需要也不可以輸入。數字來源：03 能力總表、14 商機清單、15 商機字典。看完這頁要細節：能力面→01 總藍圖，商機面→15 商機字典／14 商機清單。
A3: ⌂ 回導引頁 | R3: 商機族群分佈 | T3: 越南現況 | V3: 各領域缺口數 | X3: 商機管線階段
B4: 能力總數 | D4: ○缺口（能力） | F4: 立即推進 Go | R4: 規劃投資與交易架構 | S4: =COUNTIF(15_商機字典_OppLibrary!$D$5:$D$94,"A 規劃投資與交易架構") -> 5 | T4: ①已成熟 | U4: =COUNTIF(15_商機字典_OppLibrary!$F$5:$F$94,"①*") -> 3 | V4: D01 治理與投資 | W4: =COUNTIFS(03_能力總表_Master!$B$5:$B$154,"D01*",03_能力總表_Master!$H$5:$H$154,"缺口*") -> 0 | X4: Lead 潛在 | Y4: =COUNTIF(14_商機清單_Pipeline!$P$5:$P$24,"Lead*") -> 4
B5: =COUNTA(03_能力總表_Master!$A$5:$A$154) -> 60 | D5: =COUNTIF(03_能力總表_Master!$H$5:$H$154,"缺口*") -> 9 | F5: =COUNTIF(03_能力總表_Master!$W$5:$W$154,"立即推進*") -> 19 | R5: 建築工程與設施 | S5: =COUNTIF(15_商機字典_OppLibrary!$D$5:$D$94,"B 建築工程與設施") -> 8 | T5: ②起步中 | U5: =COUNTIF(15_商機字典_OppLibrary!$F$5:$F$94,"②*") -> 42 | V5: D02 臨床服務模式 | W5: =COUNTIFS(03_能力總表_Master!$B$5:$B$154,"D02*",03_能力總表_Master!$H$5:$H$154,"缺口*") -> 0 | X5: Qualified 已篩選 | Y5: =COUNTIF(14_商機清單_Pipeline!$P$5:$P$24,"Qualified*") -> 2
R6: 醫材與臨床設備 | S6: =COUNTIF(15_商機字典_OppLibrary!$D$5:$D$94,"C 醫材與臨床設備") -> 10 | T6: ③尚未出現 | U6: =COUNTIF(15_商機字典_OppLibrary!$F$5:$F$94,"③*") -> 40 | V6: D03 醫院設施與機電 | W6: =COUNTIFS(03_能力總表_Master!$B$5:$B$154,"D03*",03_能力總表_Master!$H$5:$H$154,"缺口*") -> 0 | X6: Proposal 已提案 | Y6: =COUNTIF(14_商機清單_Pipeline!$P$5:$P$24,"Proposal*") -> 1
B7: 商機總數 | D7: ③越南尚未出現 | F7: ★白地商機 | R7: 數位基建與資安 | S7: =COUNTIF(15_商機字典_OppLibrary!$D$5:$D$94,"D 數位基建與資安") -> 7 | V7: D04 數位基建與物聯網 | W7: =COUNTIFS(03_能力總表_Master!$B$5:$B$154,"D04*",03_能力總表_Master!$H$5:$H$154,"缺口*") -> 0 | X7: Negotiation 議約中 | Y7: =COUNTIF(14_商機清單_Pipeline!$P$5:$P$24,"Negotiation*") -> 1
B8: =COUNTA(15_商機字典_OppLibrary!$B$5:$B$94) -> 85 | D8: =COUNTIF(15_商機字典_OppLibrary!$F$5:$F$94,"③*") -> 40 | F8: =COUNTIF(15_商機字典_OppLibrary!$L$5:$L$94,"★*") -> 6 | R8: 醫療資訊與資料 | S8: =COUNTIF(15_商機字典_OppLibrary!$D$5:$D$94,"E 醫療資訊與資料") -> 12 | V8: D05 醫材與診斷 | W8: =COUNTIFS(03_能力總表_Master!$B$5:$B$154,"D05*",03_能力總表_Master!$H$5:$H$154,"缺口*") -> 3 | X8: Won 已簽約 | Y8: =COUNTIF(14_商機清單_Pipeline!$P$5:$P$24,"Won*") -> 0
R9: AI與智慧醫療 | S9: =COUNTIF(15_商機字典_OppLibrary!$D$5:$D$94,"F AI與智慧醫療") -> 17 | V9: D06 醫療資訊與資料 | W9: =COUNTIFS(03_能力總表_Master!$B$5:$B$154,"D06*",03_能力總表_Master!$H$5:$H$154,"缺口*") -> 2
R10: 品質認證與人才 | S10: =COUNTIF(15_商機字典_OppLibrary!$D$5:$D$94,"G 品質認證與人才") -> 4 | V10: D07 品質與病安 | W10: =COUNTIFS(03_能力總表_Master!$B$5:$B$154,"D07*",03_能力總表_Master!$H$5:$H$154,"缺口*") -> 0
R11: 供應鏈與維運服務 | S11: =COUNTIF(15_商機字典_OppLibrary!$D$5:$D$94,"H 供應鏈與維運服務") -> 7 | V11: D08 人才與技轉 | W11: =COUNTIFS(03_能力總表_Master!$B$5:$B$154,"D08*",03_能力總表_Master!$H$5:$H$154,"缺口*") -> 1
R12: 照護服務新業態 | S12: =COUNTIF(15_商機字典_OppLibrary!$D$5:$D$94,"I 照護服務新業態") -> 10 | V12: D09 供應鏈與維運 | W12: =COUNTIFS(03_能力總表_Master!$B$5:$B$154,"D09*",03_能力總表_Master!$H$5:$H$154,"缺口*") -> 0
R13: 商模支付與病人生態 | S13: =COUNTIF(15_商機字典_OppLibrary!$D$5:$D$94,"J 商模支付與病人生態") -> 5 | V13: D10 商模與病人生態 | W13: =COUNTIFS(03_能力總表_Master!$B$5:$B$154,"D10*",03_能力總表_Master!$H$5:$H$154,"缺口*") -> 3
B51: Top 10 攻擊順位（0.45×價值＋0.35×準備＋0.2×越南現況－缺口扣分；白地商機另走 13④）
B52: 順位 | C52: 商機 | G52: 優先分 | I52: 越南現況 | J52: ○缺口
B53: 1 | C53: =IFERROR(INDEX(15_商機字典_OppLibrary!$U$5:$U$94,MATCH(1,15_商機字典_OppLibrary!$Z$5:$Z$94,0)),"") -> OPP-78 居家醫療、居家護理與安寧 | G53: =IFERROR(INDEX(15_商機字典_OppLibrary!$Y$5:$Y$94,MATCH(1,15_商機字典_OppLibrary!$Z$5:$Z$94,0)),"") -> 4.20082 | I53: =IFERROR(LEFT(INDEX(15_商機字典_OppLibrary!$F$5:$F$94,MATCH(1,15_商機字典_OppLibrary!$Z$5:$Z$94,0)),7),"") -> ③ 尚未出現： | J53: =IFERROR(INDEX(15_商機字典_OppLibrary!$K$5:$K$94,MATCH(1,15_商機字典_OppLibrary!$Z$5:$Z$94,0)),"") -> 0
B54: 2 | C54: =IFERROR(INDEX(15_商機字典_OppLibrary!$U$5:$U$94,MATCH(2,15_商機字典_OppLibrary!$Z$5:$Z$94,0)),"") -> OPP-79 復健與亞急性照護中心 | G54: =IFERROR(INDEX(15_商機字典_OppLibrary!$Y$5:$Y$94,MATCH(2,15_商機字典_OppLibrary!$Z$5:$Z$94,0)),"") -> 4.15083 | I54: =IFERROR(LEFT(INDEX(15_商機字典_OppLibrary!$F$5:$F$94,MATCH(2,15_商機字典_OppLibrary!$Z$5:$Z$94,0)),7),"") -> ③ 尚未出現： | J54: =IFERROR(INDEX(15_商機字典_OppLibrary!$K$5:$K$94,MATCH(2,15_商機字典_OppLibrary!$Z$5:$Z$94,0)),"") -> 0
B55: 3 | C55: =IFERROR(INDEX(15_商機字典_OppLibrary!$U$5:$U$94,MATCH(3,15_商機字典_OppLibrary!$Z$5:$Z$94,0)),"") -> OPP-42 閉環給藥與條碼用藥安全 | G55: =IFERROR(INDEX(15_商機字典_OppLibrary!$Y$5:$Y$94,MATCH(3,15_商機字典_OppLibrary!$Z$5:$Z$94,0)),"") -> 4.15046 | I55: =IFERROR(LEFT(INDEX(15_商機字典_OppLibrary!$F$5:$F$94,MATCH(3,15_商機字典_OppLibrary!$Z$5:$Z$94,0)),7),"") -> ③ 尚未出現： | J55: =IFERROR(INDEX(15_商機字典_OppLibrary!$K$5:$K$94,MATCH(3,15_商機字典_OppLibrary!$Z$5:$Z$94,0)),"") -> 0
B56: 4 | C56: =IFERROR(INDEX(15_商機字典_OppLibrary!$U$5:$U$94,MATCH(4,15_商機字典_OppLibrary!$Z$5:$Z$94,0)),"") -> OPP-35 臨床術語與編碼服務 | G56: =IFERROR(INDEX(15_商機字典_OppLibrary!$Y$5:$Y$94,MATCH(4,15_商機字典_OppLibrary!$Z$5:$Z$94,0)),"") -> 4.09039 | I56: =IFERROR(LEFT(INDEX(15_商機字典_OppLibrary!$F$5:$F$94,MATCH(4,15_商機字典_OppLibrary!$Z$5:$Z$94,0)),7),"") -> ③ 尚未出現： | J56: =IFERROR(INDEX(15_商機字典_OppLibrary!$K$5:$K$94,MATCH(4,15_商機字典_OppLibrary!$Z$5:$Z$94,0)),"") -> 0
B57: 5 | C57: =IFERROR(INDEX(15_商機字典_OppLibrary!$U$5:$U$94,MATCH(5,15_商機字典_OppLibrary!$Z$5:$Z$94,0)),"") -> OPP-29 災難復原與營運持續(DR/BCM) | G57: =IFERROR(INDEX(15_商機字典_OppLibrary!$Y$5:$Y$94,MATCH(5,15_商機字典_OppLibrary!$Z$5:$Z$94,0)),"") -> 4.04033 | I57: =IFERROR(LEFT(INDEX(15_商機字典_OppLibrary!$F$5:$F$94,MATCH(5,15_商機字典_OppLibrary!$Z$5:$Z$94,0)),7),"") -> ③ 尚未出現： | J57: =IFERROR(INDEX(15_商機字典_OppLibrary!$K$5:$K$94,MATCH(5,15_商機字典_OppLibrary!$Z$5:$Z$94,0)),"") -> 0
B58: 6 | C58: =IFERROR(INDEX(15_商機字典_OppLibrary!$U$5:$U$94,MATCH(6,15_商機字典_OppLibrary!$Z$5:$Z$94,0)),"") -> OPP-63 開院前臨床安全驗證與試營運 | G58: =IFERROR(INDEX(15_商機字典_OppLibrary!$Y$5:$Y$94,MATCH(6,15_商機字典_OppLibrary!$Z$5:$Z$94,0)),"") -> 4.03067 | I58: =IFERROR(LEFT(INDEX(15_商機字典_OppLibrary!$F$5:$F$94,MATCH(6,15_商機字典_OppLibrary!$Z$5:$Z$94,0)),7),"") -> ③ 尚未出現： | J58: =IFERROR(INDEX(15_商機字典_OppLibrary!$K$5:$K$94,MATCH(6,15_商機字典_OppLibrary!$Z$5:$Z$94,0)),"") -> 0
B59: 7 | C59: =IFERROR(INDEX(15_商機字典_OppLibrary!$U$5:$U$94,MATCH(7,15_商機字典_OppLibrary!$Z$5:$Z$94,0)),"") -> OPP-71 洗腎連鎖（衛星洗腎中心） | G59: =IFERROR(INDEX(15_商機字典_OppLibrary!$Y$5:$Y$94,MATCH(7,15_商機字典_OppLibrary!$Z$5:$Z$94,0)),"") -> 3.96075 | I59: =IFERROR(LEFT(INDEX(15_商機字典_OppLibrary!$F$5:$F$94,MATCH(7,15_商機字典_OppLibrary!$Z$5:$Z$94,0)),7),"") -> ③ 尚未出現： | J59: =IFERROR(INDEX(15_商機字典_OppLibrary!$K$5:$K$94,MATCH(7,15_商機字典_OppLibrary!$Z$5:$Z$94,0)),"") -> 0
B60: 8 | C60: =IFERROR(INDEX(15_商機字典_OppLibrary!$U$5:$U$94,MATCH(8,15_商機字典_OppLibrary!$Z$5:$Z$94,0)),"") -> OPP-65 消毒供應外包（區域CSSD服務化） | G60: =IFERROR(INDEX(15_商機字典_OppLibrary!$Y$5:$Y$94,MATCH(8,15_商機字典_OppLibrary!$Z$5:$Z$94,0)),"") -> 3.96069 | I60: =IFERROR(LEFT(INDEX(15_商機字典_OppLibrary!$F$5:$F$94,MATCH(8,15_商機字典_OppLibrary!$Z$5:$Z$94,0)),7),"") -> ③ 尚未出現： | J60: =IFERROR(INDEX(15_商機字典_OppLibrary!$K$5:$K$94,MATCH(8,15_商機字典_OppLibrary!$Z$5:$Z$94,0)),"") -> 0
B61: 9 | C61: =IFERROR(INDEX(15_商機字典_OppLibrary!$U$5:$U$94,MATCH(9,15_商機字典_OppLibrary!$Z$5:$Z$94,0)),"") -> OPP-46 內視鏡AI息肉偵測 | G61: =IFERROR(INDEX(15_商機字典_OppLibrary!$Y$5:$Y$94,MATCH(9,15_商機字典_OppLibrary!$Z$5:$Z$94,0)),"") -> 3.9605 | I61: =IFERROR(LEFT(INDEX(15_商機字典_OppLibrary!$F$5:$F$94,MATCH(9,15_商機字典_OppLibrary!$Z$5:$Z$94,0)),7),"") -> ③ 尚未出現： | J61: =IFERROR(INDEX(15_商機字典_OppLibrary!$K$5:$K$94,MATCH(9,15_商機字典_OppLibrary!$Z$5:$Z$94,0)),"") -> 0
B62: 10 | C62: =IFERROR(INDEX(15_商機字典_OppLibrary!$U$5:$U$94,MATCH(10,15_商機字典_OppLibrary!$Z$5:$Z$94,0)),"") -> OPP-38 醫材資料介接與床邊自動擷取 | G62: =IFERROR(INDEX(15_商機字典_OppLibrary!$Y$5:$Y$94,MATCH(10,15_商機字典_OppLibrary!$Z$5:$Z$94,0)),"") -> 3.96042 | I62: =IFERROR(LEFT(INDEX(15_商機字典_OppLibrary!$F$5:$F$94,MATCH(10,15_商機字典_OppLibrary!$Z$5:$Z$94,0)),7),"") -> ③ 尚未出現： | J62: =IFERROR(INDEX(15_商機字典_OppLibrary!$K$5:$K$94,MATCH(10,15_商機字典_OppLibrary!$Z$5:$Z$94,0)),"") -> 0
B64: ★ 本頁圖表與數字全部自動連動：03/14/15 的資料一改，重新開啟或按 F9 即更新。不要在本頁輸入任何東西。要看單一商機怎麼打 → 17 商機作戰卡。

Sheet 15_商機字典_OppLibrary
A1: 15 商機字典｜Opportunity Library（越南醫院市場有哪些生意可以做）
A2: ❓ 這頁在回答：越南醫院市場有哪 85 門生意可以做？（★不熟醫療產業先看這頁） ▸ 不熟醫療產業的夥伴請先看這頁：85 種可以獨立談的生意，分成 A~J 十個族群，說明它在賣什麼、誰付錢、大概多少錢、通常什麼階段切入，以及「越南現況」——標③尚未出現的，代表越南目前幾乎沒人在做，是主動出擊的空間。藍字欄位（G-L、T）由 16 能力商機矩陣自動算出。14 商機清單的商機下拉就是從本頁 B 欄來的。
A3: ★ 本頁每一列對應 16 能力商機矩陣的一個欄位（第5列↔D欄、第6列↔E欄…），請不要插入或刪除列，要新增請在最下方空白列往下填。 | G3: ="全部 "&COUNTA($B$5:$B$94)&" 個商機 ｜ ③尚未出現（越南幾乎空白）"&COUNTIF($F$5:$F$94,"③*")&" 個 ｜ ★白地商機（聯盟目前無對應能力）"&COUNTIF($L$5:$L$94,"★*")&" 個 ｜ 有缺口可對外招募 "&COUNTIF($L$5:$L$94,"有缺口*")&" 個 ｜ 已列入14商機清單 "&COUNTIF($T$5:$T$94,">0")&" 個" -> 全部 85 個商機 ｜ ③尚未出現（越南幾乎空白）40 個 ｜ ★白地商機（聯盟目前無對應能力）6 個 ｜ 有缺口可對外招募 26 個 ｜ 已列入14商機清單 8 個 | V3: ⌂ 回導引頁
A4: 商機代號 OPP ID | B4: 商機名稱（中） Opportunity | C4: Opportunity (EN) | D4: 商機族群 Family | E4: 這門生意在賣什麼／誰付錢 What we sell & who pays | F4: 越南現況 VN maturity | G4: 涵蓋領域（自動） Domains | H4: 對應能力 CAP數(自動) | I4: 平均價值分 (自動) | J4: 平均準備分 (自動) | K4: ○缺口數 (自動) | L4: ★聯盟能力對應狀態（自動） Our position | M4: 典型切入階段 Stage | N4: 典型付費方 Typical payer | O4: 典型交易模式 Txn mode | P4: 典型金額級距 Amount tier | Q4: 可否獨立成案 Standalone | R4: 建議主責 Lead | S4: 越南在地重點／注意事項 Vietnam notes | T4: 已列入14 商機清單(自動) | U4: 代號＋名稱 (下拉用·勿刪) | V4: 主要競爭者／在地玩家 Competitors & incumbents | W4: 我們的切入角度 Our angle | X4: 群晶主導 CAP數(自動) | Y4: 攻擊優先分 (自動) | Z4: 攻擊順位 (自動) | AA4: ★層級 Layer | AB4: ★深研提示（本項專屬發現） Research finding | AC4: 信心 Conf | AD4: ★越南現況（家族／領域趨勢） VN status now
A5: OPP-01 | B5: 醫院投資規劃與PPP交易架構顧問 | C5: Hospital Investment & PPP Structuring | D5: A 規劃投資與交易架構 | E5: 把「要不要蓋、誰出錢、風險怎麼分」變成可以簽的交易架構；賣可行性報告、財務模型與契約設計 | F5: ② 起步中：剛開始有人做 | G5: =IF($A5="","",IF($H5=0,"（尚無對應能力）",IFERROR(INDEX(16_能力商機矩陣_CapOppMap!$D$160:$CO$160,MATCH($A5,16_能力商機矩陣_CapOppMap!$D$4:$CO$4,0)),""))) -> D01; D10 | H5: =IF($A5="","",IFERROR(INDEX(16_能力商機矩陣_CapOppMap!$D$156:$CO$156,MATCH($A5,16_能力商機矩陣_CapOppMap!$D$4:$CO$4,0)),"")) -> 9 | I5: =IF($A5="","",IFERROR(INDEX(16_能力商機矩陣_CapOppMap!$D$157:$CO$157,MATCH($A5,16_能力商機矩陣_CapOppMap!$D$4:$CO$4,0)),"")) -> 3.7 | J5: =IF($A5="","",IFERROR(INDEX(16_能力商機矩陣_CapOppMap!$D$158:$CO$158,MATCH($A5,16_能力商機矩陣_CapOppMap!$D$4:$CO$4,0)),"")) -> 2 | K5: =IF($A5="","",IFERROR(INDEX(16_能力商機矩陣_CapOppMap!$D$159:$CO$159,MATCH($A5,16_能力商機矩陣_CapOppMap!$D$4:$CO$4,0)),"")) -> 0 | L5: =IF($A5="","",IF($H5=0,"★白地商機：目前無對應能力，需新增能力或找新夥伴",IF($K5>0,"有缺口："&$K5&"項可對外招募","已有能力可承接"))) -> 已有能力可承接 | M5: G0 | N5: 越南政府／衛生部預算 | O5: 顧問服務 | P5: 500K-2M USD | Q5: 是 | R5: PPP Advisor | S5: ⚠Decree 71/2025 已被 Nghị định 243/2025（2025-09-11生效）第81條全部廢止，現行細則為243/2025體系（另含312/2025財務管理、257/2025 BT合約、19/2026重點專案審定）；醫療PPP門檻在新體系下的條文位置待查。案例面：河內2026-08-10核准醫療綜合體PPP-BT案（逾14.2兆越盾、1,600床）——市場已從「僅2案」進入新階段 | T5: =IF($A5="","",COUNTIF(14_商機清單_Pipeline!$A$5:$A$34,$U5)) -> 1 | U5: =IF($B5="","",$A5&" "&$B5) -> OPP-01 醫院投資規劃與PPP交易架構顧問 | V5: 世銀/ADB體系顧問、四大會計師事務所；越南健康PPP全國僅2案、無成熟本土顧問 | W5: 台灣醫院全生命週期實績＋願意當PPP先行者（PPP細則已改為 Nghị định 243/2025 體系） | X5: =IF($A5="","",IFERROR(INDEX(16_能力商機矩陣_CapOppMap!$D$162:$CO$162,MATCH($A5,16_能力商機矩陣_CapOppMap!$D$4:$CO$4,0)),"")) -> 0 | Y5: =IF(OR($A5="",$H5=""),"",IF($H5=0,"",ROUND(0.45*$I5+0.35*$J5+0.2*IF(LEFT($F5,1)="③",5,IF(LEFT($F5,1)="②",3,1))-IF($K5>0,0.3,0),2)+ROW()/100000)) -> 2.97005 | Z5: =IF($Y5="","",RANK($Y5,$Y$5:$Y$94)) -> 73 | AA5: G 治理合規層（跨層） | AB5: 修正note：門檻取消的法源是Law 57/2024修法（2025-01-15生效）；Decree 71/2025（2025-03-28生效）⚠已被 Nghị định 243/2025（2025-09-11生效）第81條全部廢止，引用時務必改用243/2025體系。「全國健康PPP僅2案（安沛、峴港）」為2024-08官方數據、2026年未見官方重申；新增大案：河內市人民議會2026-08-10核准「醫療綜合體－高齡者照護－河內醫科大學」PPP-BT案，總投資逾14.2兆越盾、含1,600床教學醫院。衛生部醫療PPP指引通知自2024-06徵詢至今仍為草案。 | AC5: A | AD5: Law 57/2024（2025-01生效）取消PPP投資門檻、恢復BT模式；Decree 71/2025（2025-03-28生效）刪除細則限制、招標縮至10-60天，⚠但已被Nghị định 243/2025（2025-09-11）全部廢止。健康PPP原僅2案（安沛、峴港），2026-08-10河內核准逾14.2兆越盾醫療綜合體PPP-BT案。外資交易熱：Thomson收購FV醫院3.81億美元（越南史上最大醫療交易）、Raffles收購AIH。外資可100%持有醫院，門檻2,000萬美元。
A6: OPP-02 | B6: 臨床服務定位與營運模式規劃 | C6: Clinical Service Model & Operations Planning | D6: A 規劃投資與交易架構 | E6: 決定這家醫院要看什麼病、開幾床、病人怎麼走；後面所有採購金額都由它決定 | F6: ② 起步中：剛開始有人做 | G6: =IF($A6="","",IF($H6=0,"（尚無對應能力）",IFERROR(INDEX(16_能力商機矩陣_CapOppMap!$D$160:$CO$160,MATCH($A6,16_能力商機矩陣_CapOppMap!$D$4:$CO$4,0)),""))) -> D02 | H6: =IF($A6="","",IFERROR(INDEX(16_能力商機矩陣_CapOppMap!$D$156:$CO$156,MATCH($A6,16_能力商機矩陣_CapOppMap!$D$4:$CO$4,0)),"")) -> 6 | I6: =IF($A6="","",IFERROR(INDEX(16_能力商機矩陣_CapOppMap!$D$157:$CO$157,MATCH($A6,16_能力商機矩陣_CapOppMap!$D$4:$CO$4,0)),"")) -> 4.7 | J6: =IF($A6="","",IFERROR(INDEX(16_能力商機矩陣_CapOppMap!$D$158:$CO$158,MATCH($A6,16_能力商機矩陣_CapOppMap!$D$4:$CO$4,0)),"")) -> 2.7 | K6: =IF($A6="","",IFERROR(INDEX(16_能力商機矩陣_CapOppMap!$D$159:$CO$159,MATCH($A6,16_能力商機矩陣_CapOppMap!$D$4:$CO$4,0)),"")) -> 0 | L6: =IF($A6="","",IF($H6=0,"★白地商機：目前無對應能力，需新增能力或找新夥伴",IF($K6>0,"有缺口："&$K6&"項可對外招募","已有能力可承接"))) -> 已有能力可承接 | M6: G1 | N6: 醫院業主資本支出(CAPEX) | O6: 顧問服務 | P6: 100K-500K USD | Q6: 是 | R6: Clinical Planner | S6: 河內／胡志明市公立醫院使用率超過設計量能200%，服務組合與分流設計是真正的痛點 | T6: =IF($A6="","",COUNTIF(14_商機清單_Pipeline!$A$5:$A$34,$U6)) -> 0 | U6: =IF($B6="","",$A6&" "&$B6) -> OPP-02 臨床服務定位與營運模式規劃 | V6: 國際醫管顧問零星進場；公立醫院多自行規劃 | W6: 台灣參考醫院的真實營運數據在地化，不是紙上模型 | X6: =IF($A6="","",IFERROR(INDEX(16_能力商機矩陣_CapOppMap!$D$162:$CO$162,MATCH($A6,16_能力商機矩陣_CapOppMap!$D$4:$CO$4,0)),"")) -> 0 | Y6: =IF(OR($A6="",$H6=""),"",IF($H6=0,"",ROUND(0.45*$I6+0.35*$J6+0.2*IF(LEFT($F6,1)="③",5,IF(LEFT($F6,1)="②",3,1))-IF($K6>0,0.3,0),2)+ROW()/100000)) -> 3.66006 | Z6: =IF($Y6="","",RANK($Y6,$Y$5:$Y$94)) -> 36 | AA6: G 治理合規層（跨層） | AB6: （本項無專屬發現——見同列右方的家族／領域趨勢，或 19／20 分頁） | AC6: B | AD6: Law 57/2024（2025-01生效）取消PPP投資門檻、恢復BT模式；Decree 71/2025（2025-03-28生效）刪除細則限制、招標縮至10-60天，⚠但已被Nghị định 243/2025（2025-09-11）全部廢止。健康PPP原僅2案（安沛、峴港），2026-08-10河內核准逾14.2兆越盾醫療綜合體PPP-BT案。外資交易熱：Thomson收購FV醫院3.81億美元（越南史上最大醫療交易）、Raffles收購AIH。外資可100%持有醫院，門檻2,000萬美元。
A7: OPP-03 | B7: 外資醫院綠地投資與經營 | C7: Foreign-invested Greenfield Hospital | D7: A 規劃投資與交易架構 | E7: 自己蓋、自己開一家醫院，賺中產階級自費與商業保險；也接回每年赴海外就醫的病人 | F7: ② 起步中：剛開始有人做 | G7: =IF($A7="","",IF($H7=0,"（尚無對應能力）",IFERROR(INDEX(16_能力商機矩陣_CapOppMap!$D$160:$CO$160,MATCH($A7,16_能力商機矩陣_CapOppMap!$D$4:$CO$4,0)),""))) -> D01; D02; D10 | H7: =IF($A7="","",IFERROR(INDEX(16_能力商機矩陣_CapOppMap!$D$156:$CO$156,MATCH($A7,16_能力商機矩陣_CapOppMap!$D$4:$CO$4,0)),"")) -> 4 | I7: =IF($A7="","",IFERROR(INDEX(16_能力商機矩陣_CapOppMap!$D$157:$CO$157,MATCH($A7,16_能力商機矩陣_CapOppMap!$D$4:$CO$4,0)),"")) -> 4.2 | J7: =IF($A7="","",IFERROR(INDEX(16_能力商機矩陣_CapOppMap!$D$158:$CO$158,MATCH($A7,16_能力商機矩陣_CapOppMap!$D$4:$CO$4,0)),"")) -> 2.2 | K7: =IF($A7="","",IFERROR(INDEX(16_能力商機矩陣_CapOppMap!$D$159:$CO$159,MATCH($A7,16_能力商機矩陣_CapOppMap!$D$4:$CO$4,0)),"")) -> 0 | L7: =IF($A7="","",IF($H7=0,"★白地商機：目前無對應能力，需新增能力或找新夥伴",IF($K7>0,"有缺口："&$K7&"項可對外招募","已有能力可承接"))) -> 已有能力可承接 | M7: G0 | N7: 民間投資方／基金 | O7: 民營醫院投資 | P7: >10M USD | Q7: 是 | R7: Commercial Director | S7: 外資醫院最低註冊資本US$20m、每床樓地板50㎡；私立僅占5.8%床數，政策目標2030年15%、2050年25% | T7: =IF($A7="","",COUNTIF(14_商機清單_Pipeline!$A$5:$A$34,$U7)) -> 0 | U7: =IF($B7="","",$A7&" "&$B7) -> OPP-03 外資醫院綠地投資與經營 | V7: Vinmec(9院)/Hoan My/Tam Anh 連鎖擴張；FV 已被 Thomson Medical 以約US$3.8億收購 | W7: 不與連鎖拚規模，聚焦專科旗艦＋台灣醫療品牌接外流病人 | X7: =IF($A7="","",IFERROR(INDEX(16_能力商機矩陣_CapOppMap!$D$162:$CO$162,MATCH($A7,16_能力商機矩陣_CapOppMap!$D$4:$CO$4,0)),"")) -> 0 | Y7: =IF(OR($A7="",$H7=""),"",IF($H7=0,"",ROUND(0.45*$I7+0.35*$J7+0.2*IF(LEFT($F7,1)="③",5,IF(LEFT($F7,1)="②",3,1))-IF($K7>0,0.3,0),2)+ROW()/100000)) -> 3.26007 | Z7: =IF($Y7="","",RANK($Y7,$Y$5:$Y$94)) -> 64 | AA7: L7 商模金流層 | AB7: WTO承諾允許100%外資醫院；醫院最低投資2,000萬美元、綜合門診200萬、專科20萬。Thomson/FV案（3.81億美元、16.8×EBITDA）為估值標竿。 | AC7: A | AD7: Law 57/2024（2025-01生效）取消PPP投資門檻、恢復BT模式；Decree 71/2025（2025-03-28生效）刪除細則限制、招標縮至10-60天，⚠但已被Nghị định 243/2025（2025-09-11）全部廢止。健康PPP原僅2案（安沛、峴港），2026-08-10河內核准逾14.2兆越盾醫療綜合體PPP-BT案。外資交易熱：Thomson收購FV醫院3.81億美元（越南史上最大醫療交易）、Raffles收購AIH。外資可100%持有醫院，門檻2,000萬美元。
A8: OPP-04 | B8: 公立醫院合作經營高端診區 | C8: Public-hospital Premium Wing (BCC/JV) | D8: A 規劃投資與交易架構 | E8: 出資在公立醫院裡蓋一個高階門診／影像／腫瘤診區，跟院方分帳；病人自費與商業保險付錢 | F8: ② 起步中：剛開始有人做 | G8: =IF($A8="","",IF($H8=0,"（尚無對應能力）",IFERROR(INDEX(16_能力商機矩陣_CapOppMap!$D$160:$CO$160,MATCH($A8,16_能力商機矩陣_CapOppMap!$D$4:$CO$4,0)),""))) -> D01; D02; D10 | H8: =IF($A8="","",IFERROR(INDEX(16_能力商機矩陣_CapOppMap!$D$156:$CO$156,MATCH($A8,16_能力商機矩陣_CapOppMap!$D$4:$CO$4,0)),"")) -> 4 | I8: =IF($A8="","",IFERROR(INDEX(16_能力商機矩陣_CapOppMap!$D$157:$CO$157,MATCH($A8,16_能力商機矩陣_CapOppMap!$D$4:$CO$4,0)),"")) -> 4.2 | J8: =IF($A8="","",IFERROR(INDEX(16_能力商機矩陣_CapOppMap!$D$158:$CO$158,MATCH($A8,16_能力商機矩陣_CapOppMap!$D$4:$CO$4,0)),"")) -> 2.2 | K8: =IF($A8="","",IFERROR(INDEX(16_能力商機矩陣_CapOppMap!$D$159:$CO$159,MATCH($A8,16_能力商機矩陣_CapOppMap!$D$4:$CO$4,0)),"")) -> 0 | L8: =IF($A8="","",IF($H8=0,"★白地商機：目前無對應能力，需新增能力或找新夥伴",IF($K8>0,"有缺口："&$K8&"項可對外招募","已有能力可承接"))) -> 已有能力可承接 | M8: G2 | N8: 民間投資方／基金 | O8: 共址合資 | P8: 2M-10M USD | Q8: 需組合 | R8: Commercial Lead | S8: 越南稱「社會化」，是最快取得公立醫院病人量的路徑，但法律灰帶大，合規設計要先做 | T8: =IF($A8="","",COUNTIF(14_商機清單_Pipeline!$A$5:$A$34,$U8)) -> 0 | U8: =IF($B8="","",$A8&" "&$B8) -> OPP-04 公立醫院合作經營高端診區 | V8: （待調查） | X8: =IF($A8="","",IFERROR(INDEX(16_能力商機矩陣_CapOppMap!$D$162:$CO$162,MATCH($A8,16_能力商機矩陣_CapOppMap!$D$4:$CO$4,0)),"")) -> 0 | Y8: =IF(OR($A8="",$H8=""),"",IF($H8=0,"",ROUND(0.45*$I8+0.35*$J8+0.2*IF(LEFT($F8,1)="③",5,IF(LEFT($F8,1)="②",3,1))-IF($K8>0,0.3,0),2)+ROW()/100000)) -> 3.26008 | Z8: =IF($Y8="","",RANK($Y8,$Y$5:$Y$94)) -> 63 | AA8: L7 商模金流層 | AB8: （本項無專屬發現——見同列右方的家族／領域趨勢，或 19／20 分頁） | AC8: B | AD8: Law 57/2024（2025-01生效）取消PPP投資門檻、恢復BT模式；Decree 71/2025（2025-03-28生效）刪除細則限制、招標縮至10-60天，⚠但已被Nghị định 243/2025（2025-09-11）全部廢止。健康PPP原僅2案（安沛、峴港），2026-08-10河內核准逾14.2兆越盾醫療綜合體PPP-BT案。外資交易熱：Thomson收購FV醫院3.81億美元（越南史上最大醫療交易）、Raffles收購AIH。外資可100%持有醫院，門檻2,000萬美元。
A9: OPP-05 | B9: 省級醫院升級改造整案 | C9: Provincial Hospital Upgrade Programme | D9: A 規劃投資與交易架構 | E9: 把老舊的省級醫院手術室、ICU、影像區整區翻新再配設備；省預算＋中央專項計畫付錢 | F9: ① 已成熟：在地已有供應商 | G9: =IF($A9="","",IF($H9=0,"（尚無對應能力）",IFERROR(INDEX(16_能力商機矩陣_CapOppMap!$D$160:$CO$160,MATCH($A9,16_能力商機矩陣_CapOppMap!$D$4:$CO$4,0)),""))) -> D03; D05 | H9: =IF($A9="","",IFERROR(INDEX(16_能力商機矩陣_CapOppMap!$D$156:$CO$156,MATCH($A9,16_能力商機矩陣_CapOppMap!$D$4:$CO$4,0)),"")) -> 4 | I9: =IF($A9="","",IFERROR(INDEX(16_能力商機矩陣_CapOppMap!$D$157:$CO$157,MATCH($A9,16_能力商機矩陣_CapOppMap!$D$4:$CO$4,0)),"")) -> 4.6 | J9: =IF($A9="","",IFERROR(INDEX(16_能力商機矩陣_CapOppMap!$D$158:$CO$158,MATCH($A9,16_能力商機矩陣_CapOppMap!$D$4:$CO$4,0)),"")) -> 2.4 | K9: =IF($A9="","",IFERROR(INDEX(16_能力商機矩陣_CapOppMap!$D$159:$CO$159,MATCH($A9,16_能力商機矩陣_CapOppMap!$D$4:$CO$4,0)),"")) -> 1 | L9: =IF($A9="","",IF($H9=0,"★白地商機：目前無對應能力，需新增能力或找新夥伴",IF($K9>0,"有缺口："&$K9&"項可對外招募","已有能力可承接"))) -> 有缺口：1項可對外招募 | M9: G2 | N9: 省級衛生局預算 | O9: 政府採購 | P9: >10M USD | Q9: 是 | R9: Healthcare Architect | S9: 60多個省、標案流量穩定，但目前多由在地與中韓廠商拿下，價格競爭激烈 | T9: =IF($A9="","",COUNTIF(14_商機清單_Pipeline!$A$5:$A$34,$U9)) -> 0 | U9: =IF($B9="","",$A9&" "&$B9) -> OPP-05 省級醫院升級改造整案 | V9: 省級標案多由在地與中韓 EPC 低價取得 | W9: 不拚土建低價，賣「機電＋驗證確效＋開院」整包品質 | X9: =IF($A9="","",IFERROR(INDEX(16_能力商機矩陣_CapOppMap!$D$162:$CO$162,MATCH($A9,16_能力商機矩陣_CapOppMap!$D$4:$CO$4,0)),"")) -> 0 | Y9: =IF(OR($A9="",$H9=""),"",IF($H9=0,"",ROUND(0.45*$I9+0.35*$J9+0.2*IF(LEFT($F9,1)="③",5,IF(LEFT($F9,1)="②",3,1))-IF($K9>0,0.3,0),2)+ROW()/100000)) -> 2.81009 | Z9: =IF($Y9="","",RANK($Y9,$Y$5:$Y$94)) -> 76 | AA9: L1 實體基礎層 | AB9: 峴港2021-25規劃7醫院項目13.6兆越盾；白梅二院/越德二院各約5,000億越盾（約1.9億美元）、設計各1,000床，2025-12-19落成、2026-06/07分別收治病人；六大醫院升級國際水準列入2021-2030規劃。 | AC9: A | AD9: Law 57/2024（2025-01生效）取消PPP投資門檻、恢復BT模式；Decree 71/2025（2025-03-28生效）刪除細則限制、招標縮至10-60天，⚠但已被Nghị định 243/2025（2025-09-11）全部廢止。健康PPP原僅2案（安沛、峴港），2026-08-10河內核准逾14.2兆越盾醫療綜合體PPP-BT案。外資交易熱：Thomson收購FV醫院3.81億美元（越南史上最大醫療交易）、Raffles收購AIH。外資可100%持有醫院，門檻2,000萬美元。
A10: OPP-06 | B10: 醫院建築與院區總體規劃設計 | C10: Hospital Master Planning & Design | D10: B 建築工程與設施 | E10: 院區配置、醫療功能空間與感染管制動線的規劃設計服務，是工程統包的前置設計費 | F10: ② 起步中：剛開始有人做 | G10: =IF($A10="","",IF($H10=0,"（尚無對應能力）",IFERROR(INDEX(16_能力商機矩陣_CapOppMap!$D$160:$CO$160,MATCH($A10,16_能力商機矩陣_CapOppMap!$D$4:$CO$4,0)),""))) -> D03 | H10: =IF($A10="","",IFERROR(INDEX(16_能力商機矩陣_CapOppMap!$D$156:$CO$156,MATCH($A10,16_能力商機矩陣_CapOppMap!$D$4:$CO$4,0)),"")) -> 4 | I10: =IF($A10="","",IFERROR(INDEX(16_能力商機矩陣_CapOppMap!$D$157:$CO$157,MATCH($A10,16_能力商機矩陣_CapOppMap!$D$4:$CO$4,0)),"")) -> 4.4 | J10: =IF($A10="","",IFERROR(INDEX(16_能力商機矩陣_CapOppMap!$D$158:$CO$158,MATCH($A10,16_能力商機矩陣_CapOppMap!$D$4:$CO$4,0)),"")) -> 2.4 | K10: =IF($A10="","",IFERROR(INDEX(16_能力商機矩陣_CapOppMap!$D$159:$CO$159,MATCH($A10,16_能力商機矩陣_CapOppMap!$D$4:$CO$4,0)),"")) -> 0 | L10: =IF($A10="","",IF($H10=0,"★白地商機：目前無對應能力，需新增能力或找新夥伴",IF($K10>0,"有缺口："&$K10&"項可對外招募","已有能力可承接"))) -> 已有能力可承接 | M10: G2 | N10: 醫院業主資本支出(CAPEX) | O10: 顧問服務 | P10: 500K-2M USD | Q10: 是 | R10: Healthcare Architect | S10: 須符合 QCVN 01:2021/BXD、TCVN 5687:2024（手術室>36㎡、淨高>3.1m）與消防審查流程 | T10: =IF($A10="","",COUNTIF(14_商機清單_Pipeline!$A$5:$A$34,$U10)) -> 0 | U10: =IF($B10="","",$A10&" "&$B10) -> OPP-06 醫院建築與院區總體規劃設計 | V10: 國際醫療建築事務所＋越南在地設計院 | W10: 醫療機能規劃與感控動線的臨床輸入（台灣參考醫院背書） | X10: =IF($A10="","",IFERROR(INDEX(16_能力商機矩陣_CapOppMap!$D$162:$CO$162,MATCH($A10,16_能力商機矩陣_CapOppMap!$D$4:$CO$4,0)),"")) -> 0 | Y10: =IF(OR($A10="",$H10=""),"",IF($H10=0,"",ROUND(0.45*$I10+0.35*$J10+0.2*IF(LEFT($F10,1)="③",5,IF(LEFT($F10,1)="②",3,1))-IF($K10>0,0.3,0),2)+ROW()/100000)) -> 3.4201 | Z10: =IF($Y10="","",RANK($Y10,$Y$5:$Y$94)) -> 51 | AA10: L1 實體基礎層 | AB10: （本項無專屬發現——見同列右方的家族／領域趨勢，或 19／20 分頁） | AC10: B | AD10: 白梅二院/越德二院已投運：2025-12-19落成，白梅二院2026-06-26收治（首期325床）、越德二院2026-07-09開幕（首期300床），設計各1,000床、各約5,000億越盾。政府監察（2025-04）指兩大標案4,389.9億越盾全流程違規。TCVN 5687:2024（通風空調）更新；Decree 96/2023第40-41條為手術室執照錨點；醫療廢水強制QCVN 28:2010。Decree 58/2025確立屋頂光電自發自用制，已由Nghị định 243/2026（2026-06-26生效）修訂：餘電可售上限由20%提高至50%（2030-12-31前電網條件允許可再協議）、通報門檻改依逆變器容量（<1kW免通報、≥1kW須提前10工作日通報）。
A11: OPP-07 | B11: 千床級醫院統包工程(EPC) | C11: Turnkey Hospital EPC | D11: B 建築工程與設施 | E11: 從設計、土建、機電到醫療設備整合，一次交付一整家醫院；省／中央資本預算或ODA付錢 | F11: ① 已成熟：在地已有供應商 | G11: =IF($A11="","",IF($H11=0,"（尚無對應能力）",IFERROR(INDEX(16_能力商機矩陣_CapOppMap!$D$160:$CO$160,MATCH($A11,16_能力商機矩陣_CapOppMap!$D$4:$CO$4,0)),""))) -> D03 | H11: =IF($A11="","",IFERROR(INDEX(16_能力商機矩陣_CapOppMap!$D$156:$CO$156,MATCH($A11,16_能力商機矩陣_CapOppMap!$D$4:$CO$4,0)),"")) -> 5 | I11: =IF($A11="","",IFERROR(INDEX(16_能力商機矩陣_CapOppMap!$D$157:$CO$157,MATCH($A11,16_能力商機矩陣_CapOppMap!$D$4:$CO$4,0)),"")) -> 4.3 | J11: =IF($A11="","",IFERROR(INDEX(16_能力商機矩陣_CapOppMap!$D$158:$CO$158,MATCH($A11,16_能力商機矩陣_CapOppMap!$D$4:$CO$4,0)),"")) -> 2.5 | K11: =IF($A11="","",IFERROR(INDEX(16_能力商機矩陣_CapOppMap!$D$159:$CO$159,MATCH($A11,16_能力商機矩陣_CapOppMap!$D$4:$CO$4,0)),"")) -> 0 | L11: =IF($A11="","",IF($H11=0,"★白地商機：目前無對應能力，需新增能力或找新夥伴",IF($K11>0,"有缺口："&$K11&"項可對外招募","已有能力可承接"))) -> 已有能力可承接 | M11: G4 | N11: 醫院業主資本支出(CAPEX) | O11: 統包工程(EPC) | P11: >10M USD | Q11: 是 | R11: MEP Lead | S11: 胡志明市三家1000床門戶醫院每家約US$72-75m（≒US$73k/床，2025年開幕）可作為報價基準 | T11: =IF($A11="","",COUNTIF(14_商機清單_Pipeline!$A$5:$A$34,$U11)) -> 0 | U11: =IF($B11="","",$A11&" "&$B11) -> OPP-07 千床級醫院統包工程(EPC) | V11: （待調查） | X11: =IF($A11="","",IFERROR(INDEX(16_能力商機矩陣_CapOppMap!$D$162:$CO$162,MATCH($A11,16_能力商機矩陣_CapOppMap!$D$4:$CO$4,0)),"")) -> 1 | Y11: =IF(OR($A11="",$H11=""),"",IF($H11=0,"",ROUND(0.45*$I11+0.35*$J11+0.2*IF(LEFT($F11,1)="③",5,IF(LEFT($F11,1)="②",3,1))-IF($K11>0,0.3,0),2)+ROW()/100000)) -> 3.01011 | Z11: =IF($Y11="","",RANK($Y11,$Y$5:$Y$94)) -> 72 | AA11: L1 實體基礎層 | AB11: 警示案例：白梅/越德二院停擺6-7年後於2026年終於投運，惟政府監察結論指兩大標案（4,389.9億越盾、占10標案76.6%）從招標文件編製到履約全環節違規，樁基變更浪費約207億越盾、一項設備合約價132億越盾而實際進口價僅40億——公立EPC的付款與治理風險必須在合約層處理。 | AC11: A | AD11: 白梅二院/越德二院已投運：2025-12-19落成，白梅二院2026-06-26收治（首期325床）、越德二院2026-07-09開幕（首期300床），設計各1,000床、各約5,000億越盾。政府監察（2025-04）指兩大標案4,389.9億越盾全流程違規。TCVN 5687:2024（通風空調）更新；Decree 96/2023第40-41條為手術室執照錨點；醫療廢水強制QCVN 28:2010。Decree 58/2025確立屋頂光電自發自用制，已由Nghị định 243/2026（2026-06-26生效）修訂：餘電可售上限由20%提高至50%（2030-12-31前電網條件允許可再協議）、通報門檻改依逆變器容量（<1kW免通報、≥1kW須提前10工作日通報）。
A12: OPP-08 | B12: 手術室與加護病房潔淨空調（模組化OR） | C12: OR/ICU Cleanroom HVAC & Modular OR | D12: B 建築工程與設施 | E12: 層流手術室、負壓隔離病房、模組化手術室隔間板；EPC統包商或醫院付錢 | F12: ② 起步中：剛開始有人做 | G12: =IF($A12="","",IF($H12=0,"（尚無對應能力）",IFERROR(INDEX(16_能力商機矩陣_CapOppMap!$D$160:$CO$160,MATCH($A12,16_能力商機矩陣_CapOppMap!$D$4:$CO$4,0)),""))) -> D03; D05 | H12: =IF($A12="","",IFERROR(INDEX(16_能力商機矩陣_CapOppMap!$D$156:$CO$156,MATCH($A12,16_能力商機矩陣_CapOppMap!$D$4:$CO$4,0)),"")) -> 3 | I12: =IF($A12="","",IFERROR(INDEX(16_能力商機矩陣_CapOppMap!$D$157:$CO$157,MATCH($A12,16_能力商機矩陣_CapOppMap!$D$4:$CO$4,0)),"")) -> 4.6 | J12: =IF($A12="","",IFERROR(INDEX(16_能力商機矩陣_CapOppMap!$D$158:$CO$158,MATCH($A12,16_能力商機矩陣_CapOppMap!$D$4:$CO$4,0)),"")) -> 2.4 | K12: =IF($A12="","",IFERROR(INDEX(16_能力商機矩陣_CapOppMap!$D$159:$CO$159,MATCH($A12,16_能力商機矩陣_CapOppMap!$D$4:$CO$4,0)),"")) -> 1 | L12: =IF($A12="","",IF($H12=0,"★白地商機：目前無對應能力，需新增能力或找新夥伴",IF($K12>0,"有缺口："&$K12&"項可對外招募","已有能力可承接"))) -> 有缺口：1項可對外招募 | M12: G4 | N12: 醫院業主資本支出(CAPEX) | O12: 統包工程(EPC) | P12: 2M-10M USD | Q12: 是 | R12: MEP Lead | S12: 台灣無塵室技術可直接轉用，是本聯盟在工程端最有辨識度的切入點 | T12: =IF($A12="","",COUNTIF(14_商機清單_Pipeline!$A$5:$A$34,$U12)) -> 0 | U12: =IF($B12="","",$A12&" "&$B12) -> OPP-08 手術室與加護病房潔淨空調（模組化OR） | V12: 在地淨化工程商多、品質參差 | W12: 台灣無塵室工藝＋竣工驗收確效文件 | X12: =IF($A12="","",IFERROR(INDEX(16_能力商機矩陣_CapOppMap!$D$162:$CO$162,MATCH($A12,16_能力商機矩陣_CapOppMap!$D$4:$CO$4,0)),"")) -> 0 | Y12: =IF(OR($A12="",$H12=""),"",IF($H12=0,"",ROUND(0.45*$I12+0.35*$J12+0.2*IF(LEFT($F12,1)="③",5,IF(LEFT($F12,1)="②",3,1))-IF($K12>0,0.3,0),2)+ROW()/100000)) -> 3.21012 | Z12: =IF($Y12="","",RANK($Y12,$Y$5:$Y$94)) -> 68 | AA12: L1 實體基礎層 | AB12: 越南無專屬強制醫院潔淨室QCVN，實務援引ISO 14644＋TCVN 5687:2024；Decree 96/2023第40-41條為OR執照法律錨點。 | AC12: A | AD12: 白梅二院/越德二院已投運：2025-12-19落成，白梅二院2026-06-26收治（首期325床）、越德二院2026-07-09開幕（首期300床），設計各1,000床、各約5,000億越盾。政府監察（2025-04）指兩大標案4,389.9億越盾全流程違規。TCVN 5687:2024（通風空調）更新；Decree 96/2023第40-41條為手術室執照錨點；醫療廢水強制QCVN 28:2010。Decree 58/2025確立屋頂光電自發自用制，已由Nghị định 243/2026（2026-06-26生效）修訂：餘電可售上限由20%提高至50%（2030-12-31前電網條件允許可再協議）、通報門檻改依逆變器容量（<1kW免通報、≥1kW須提前10工作日通報）。
A13: OPP-09 | B13: 醫用氣體與真空系統（含竣工確效） | C13: Medical Gas & Vacuum System with Validation | D13: B 建築工程與設施 | E13: 中央氣體機房、分歧管、警報與末端出口，加上在地廠商常省略的竣工驗證與確效 | F13: ② 起步中：剛開始有人做 | G13: =IF($A13="","",IF($H13=0,"（尚無對應能力）",IFERROR(INDEX(16_能力商機矩陣_CapOppMap!$D$160:$CO$160,MATCH($A13,16_能力商機矩陣_CapOppMap!$D$4:$CO$4,0)),""))) -> D03 | H13: =IF($A13="","",IFERROR(INDEX(16_能力商機矩陣_CapOppMap!$D$156:$CO$156,MATCH($A13,16_能力商機矩陣_CapOppMap!$D$4:$CO$4,0)),"")) -> 1 | I13: =IF($A13="","",IFERROR(INDEX(16_能力商機矩陣_CapOppMap!$D$157:$CO$157,MATCH($A13,16_能力商機矩陣_CapOppMap!$D$4:$CO$4,0)),"")) -> 4.4 | J13: =IF($A13="","",IFERROR(INDEX(16_能力商機矩陣_CapOppMap!$D$158:$CO$158,MATCH($A13,16_能力商機矩陣_CapOppMap!$D$4:$CO$4,0)),"")) -> 2.4 | K13: =IF($A13="","",IFERROR(INDEX(16_能力商機矩陣_CapOppMap!$D$159:$CO$159,MATCH($A13,16_能力商機矩陣_CapOppMap!$D$4:$CO$4,0)),"")) -> 0 | L13: =IF($A13="","",IF($H13=0,"★白地商機：目前無對應能力，需新增能力或找新夥伴",IF($K13>0,"有缺口："&$K13&"項可對外招募","已有能力可承接"))) -> 已有能力可承接 | M13: G4 | N13: 醫院業主資本支出(CAPEX) | O13: 統包工程(EPC) | P13: 500K-2M USD | Q13: 是 | R13: MEP Lead | S13: 在地供應商有，但 ISO 7396-1/-2、TCVN 8022 的驗證確效是空白——賣「證明它安全」比賣管路值錢 | T13: =IF($A13="","",COUNTIF(14_商機清單_Pipeline!$A$5:$A$34,$U13)) -> 0 | U13: =IF($B13="","",$A13&" "&$B13) -> OPP-09 醫用氣體與真空系統（含竣工確效） | V13: （待調查） | X13: =IF($A13="","",IFERROR(INDEX(16_能力商機矩陣_CapOppMap!$D$162:$CO$162,MATCH($A13,16_能力商機矩陣_CapOppMap!$D$4:$CO$4,0)),"")) -> 0 | Y13: =IF(OR($A13="",$H13=""),"",IF($H13=0,"",ROUND(0.45*$I13+0.35*$J13+0.2*IF(LEFT($F13,1)="③",5,IF(LEFT($F13,1)="②",3,1))-IF($K13>0,0.3,0),2)+ROW()/100000)) -> 3.42013 | Z13: =IF($Y13="","",RANK($Y13,$Y$5:$Y$94)) -> 50 | AA13: L1 實體基礎層 | AB13: TCVN 8022-1/2:2009等同ISO 7396，國際技術可直接對接。 | AC13: A | AD13: 白梅二院/越德二院已投運：2025-12-19落成，白梅二院2026-06-26收治（首期325床）、越德二院2026-07-09開幕（首期300床），設計各1,000床、各約5,000億越盾。政府監察（2025-04）指兩大標案4,389.9億越盾全流程違規。TCVN 5687:2024（通風空調）更新；Decree 96/2023第40-41條為手術室執照錨點；醫療廢水強制QCVN 28:2010。Decree 58/2025確立屋頂光電自發自用制，已由Nghị định 243/2026（2026-06-26生效）修訂：餘電可售上限由20%提高至50%（2030-12-31前電網條件允許可再協議）、通報門檻改依逆變器容量（<1kW免通報、≥1kW須提前10工作日通報）。
A14: OPP-10 | B14: 醫院供電韌性與隔離電源系統 | C14: Hospital Power Resilience & IT Isolated Power | D14: B 建築工程與設施 | E14: 第2類醫療場所隔離電源盤、UPS、發電機、自動切換與醫療接地；生命安全電力包 | F14: ② 起步中：剛開始有人做 | G14: =IF($A14="","",IF($H14=0,"（尚無對應能力）",IFERROR(INDEX(16_能力商機矩陣_CapOppMap!$D$160:$CO$160,MATCH($A14,16_能力商機矩陣_CapOppMap!$D$4:$CO$4,0)),""))) -> D03 | H14: =IF($A14="","",IFERROR(INDEX(16_能力商機矩陣_CapOppMap!$D$156:$CO$156,MATCH($A14,16_能力商機矩陣_CapOppMap!$D$4:$CO$4,0)),"")) -> 1 | I14: =IF($A14="","",IFERROR(INDEX(16_能力商機矩陣_CapOppMap!$D$157:$CO$157,MATCH($A14,16_能力商機矩陣_CapOppMap!$D$4:$CO$4,0)),"")) -> 4.4 | J14: =IF($A14="","",IFERROR(INDEX(16_能力商機矩陣_CapOppMap!$D$158:$CO$158,MATCH($A14,16_能力商機矩陣_CapOppMap!$D$4:$CO$4,0)),"")) -> 2.7 | K14: =IF($A14="","",IFERROR(INDEX(16_能力商機矩陣_CapOppMap!$D$159:$CO$159,MATCH($A14,16_能力商機矩陣_CapOppMap!$D$4:$CO$4,0)),"")) -> 0 | L14: =IF($A14="","",IF($H14=0,"★白地商機：目前無對應能力，需新增能力或找新夥伴",IF($K14>0,"有缺口："&$K14&"項可對外招募","已有能力可承接"))) -> 已有能力可承接 | M14: G4 | N14: 醫院業主資本支出(CAPEX) | O14: 統包工程(EPC) | P14: 500K-2M USD | Q14: 是 | R14: MEP Lead | S14: IEC 60364-7-710 等級的隔離電源在越南很少被正確規範；電網不穩＋24小時影像/ICU負載使它非做不可 | T14: =IF($A14="","",COUNTIF(14_商機清單_Pipeline!$A$5:$A$34,$U14)) -> 0 | U14: =IF($B14="","",$A14&" "&$B14) -> OPP-10 醫院供電韌性與隔離電源系統 | V14: （待調查） | X14: =IF($A14="","",IFERROR(INDEX(16_能力商機矩陣_CapOppMap!$D$162:$CO$162,MATCH($A14,16_能力商機矩陣_CapOppMap!$D$4:$CO$4,0)),"")) -> 1 | Y14: =IF(OR($A14="",$H14=""),"",IF($H14=0,"",ROUND(0.45*$I14+0.35*$J14+0.2*IF(LEFT($F14,1)="③",5,IF(LEFT($F14,1)="②",3,1))-IF($K14>0,0.3,0),2)+ROW()/100000)) -> 3.53014 | Z14: =IF($Y14="","",RANK($Y14,$Y$5:$Y$94)) -> 45 | AA14: L1 實體基礎層 | AB14: 越南對醫療場所隔離電源（IEC 60364-7-710）專屬強制標準未查得——標準空窗，可用國際標準做差異化。EN建議改：Isolated Power Supply (IPS)，「IT」易誤讀為資訊科技。 | AC14: C | AD14: 白梅二院/越德二院已投運：2025-12-19落成，白梅二院2026-06-26收治（首期325床）、越德二院2026-07-09開幕（首期300床），設計各1,000床、各約5,000億越盾。政府監察（2025-04）指兩大標案4,389.9億越盾全流程違規。TCVN 5687:2024（通風空調）更新；Decree 96/2023第40-41條為手術室執照錨點；醫療廢水強制QCVN 28:2010。Decree 58/2025確立屋頂光電自發自用制，已由Nghị định 243/2026（2026-06-26生效）修訂：餘電可售上限由20%提高至50%（2030-12-31前電網條件允許可再協議）、通報門檻改依逆變器容量（<1kW免通報、≥1kW須提前10工作日通報）。
A15: OPP-11 | B15: 醫療廢水與廢棄物處理廠 | C15: Medical Wastewater & Waste Treatment Plant | D15: B 建築工程與設施 | E15: 院內污水處理廠或高溫滅菌／破碎處理設備，也可做區域處理特許經營 | F15: ② 起步中：剛開始有人做 | G15: =IF($A15="","",IF($H15=0,"（尚無對應能力）",IFERROR(INDEX(16_能力商機矩陣_CapOppMap!$D$160:$CO$160,MATCH($A15,16_能力商機矩陣_CapOppMap!$D$4:$CO$4,0)),""))) -> D03 | H15: =IF($A15="","",IFERROR(INDEX(16_能力商機矩陣_CapOppMap!$D$156:$CO$156,MATCH($A15,16_能力商機矩陣_CapOppMap!$D$4:$CO$4,0)),"")) -> 1 | I15: =IF($A15="","",IFERROR(INDEX(16_能力商機矩陣_CapOppMap!$D$157:$CO$157,MATCH($A15,16_能力商機矩陣_CapOppMap!$D$4:$CO$4,0)),"")) -> 4.1 | J15: =IF($A15="","",IFERROR(INDEX(16_能力商機矩陣_CapOppMap!$D$158:$CO$158,MATCH($A15,16_能力商機矩陣_CapOppMap!$D$4:$CO$4,0)),"")) -> 2.4 | K15: =IF($A15="","",IFERROR(INDEX(16_能力商機矩陣_CapOppMap!$D$159:$CO$159,MATCH($A15,16_能力商機矩陣_CapOppMap!$D$4:$CO$4,0)),"")) -> 0 | L15: =IF($A15="","",IF($H15=0,"★白地商機：目前無對應能力，需新增能力或找新夥伴",IF($K15>0,"有缺口："&$K15&"項可對外招募","已有能力可承接"))) -> 已有能力可承接 | M15: G4 | N15: 醫院營運預算(OPEX) | O15: 管理服務 | P15: 500K-2M USD | Q15: 是 | R15: ESG/Facility Lead | S15: 約70%醫療廢水處理未達標，衛生部正在收緊稽查——是被法規逼出來的大量潛在需求 | T15: =IF($A15="","",COUNTIF(14_商機清單_Pipeline!$A$5:$A$34,$U15)) -> 0 | U15: =IF($B15="","",$A15&" "&$B15) -> OPP-11 醫療廢水與廢棄物處理廠 | V15: 在地環工公司多，但約70%醫療廢水處理未達標 | W15: 達標保證＋代操作年約（衛生部稽查收緊的法規紅利） | X15: =IF($A15="","",IFERROR(INDEX(16_能力商機矩陣_CapOppMap!$D$162:$CO$162,MATCH($A15,16_能力商機矩陣_CapOppMap!$D$4:$CO$4,0)),"")) -> 0 | Y15: =IF(OR($A15="",$H15=""),"",IF($H15=0,"",ROUND(0.45*$I15+0.35*$J15+0.2*IF(LEFT($F15,1)="③",5,IF(LEFT($F15,1)="②",3,1))-IF($K15>0,0.3,0),2)+ROW()/100000)) -> 3.29015 | Z15: =IF($Y15="","",RANK($Y15,$Y$5:$Y$94)) -> 57 | AA15: L1 實體基礎層 | AB15: 強制規範QCVN 28:2010/BTNMT；市場出現0.5-300m³/日模組化產品線；工業廢水已更新QCVN 40:2025＝環境規範翻新訊號。 | AC15: A | AD15: 白梅二院/越德二院已投運：2025-12-19落成，白梅二院2026-06-26收治（首期325床）、越德二院2026-07-09開幕（首期300床），設計各1,000床、各約5,000億越盾。政府監察（2025-04）指兩大標案4,389.9億越盾全流程違規。TCVN 5687:2024（通風空調）更新；Decree 96/2023第40-41條為手術室執照錨點；醫療廢水強制QCVN 28:2010。Decree 58/2025確立屋頂光電自發自用制，已由Nghị định 243/2026（2026-06-26生效）修訂：餘電可售上限由20%提高至50%（2030-12-31前電網條件允許可再協議）、通報門檻改依逆變器容量（<1kW免通報、≥1kW須提前10工作日通報）。
A16: OPP-12 | B16: 綠色醫院能源績效合約與屋頂光電 | C16: Green Hospital ESCO & Rooftop Solar | D16: B 建築工程與設施 | E16: 用節省下來的電費付款，醫院零資本支出；屋頂光電也可用購電合約(PPA)模式 | F16: ③ 尚未出現：幾乎空白 | G16: =IF($A16="","",IF($H16=0,"（尚無對應能力）",IFERROR(INDEX(16_能力商機矩陣_CapOppMap!$D$160:$CO$160,MATCH($A16,16_能力商機矩陣_CapOppMap!$D$4:$CO$4,0)),""))) -> D03 | H16: =IF($A16="","",IFERROR(INDEX(16_能力商機矩陣_CapOppMap!$D$156:$CO$156,MATCH($A16,16_能力商機矩陣_CapOppMap!$D$4:$CO$4,0)),"")) -> 2 | I16: =IF($A16="","",IFERROR(INDEX(16_能力商機矩陣_CapOppMap!$D$157:$CO$157,MATCH($A16,16_能力商機矩陣_CapOppMap!$D$4:$CO$4,0)),"")) -> 4.3 | J16: =IF($A16="","",IFERROR(INDEX(16_能力商機矩陣_CapOppMap!$D$158:$CO$158,MATCH($A16,16_能力商機矩陣_CapOppMap!$D$4:$CO$4,0)),"")) -> 2.6 | K16: =IF($A16="","",IFERROR(INDEX(16_能力商機矩陣_CapOppMap!$D$159:$CO$159,MATCH($A16,16_能力商機矩陣_CapOppMap!$D$4:$CO$4,0)),"")) -> 0 | L16: =IF($A16="","",IF($H16=0,"★白地商機：目前無對應能力，需新增能力或找新夥伴",IF($K16>0,"有缺口："&$K16&"項可對外招募","已有能力可承接"))) -> 已有能力可承接 | M16: G5 | N16: 醫院營運預算(OPEX) | O16: 分潤／服務分成 | P16: 500K-2M USD | Q16: 需組合 | R16: ESG Lead | S16: 越南目標2030年50%公共建築屋頂裝光電；醫院端幾乎沒人做，是政策順風的空白 | T16: =IF($A16="","",COUNTIF(14_商機清單_Pipeline!$A$5:$A$34,$U16)) -> 0 | U16: =IF($B16="","",$A16&" "&$B16) -> OPP-12 綠色醫院能源績效合約與屋頂光電 | V16: （待調查） | X16: =IF($A16="","",IFERROR(INDEX(16_能力商機矩陣_CapOppMap!$D$162:$CO$162,MATCH($A16,16_能力商機矩陣_CapOppMap!$D$4:$CO$4,0)),"")) -> 1 | Y16: =IF(OR($A16="",$H16=""),"",IF($H16=0,"",ROUND(0.45*$I16+0.35*$J16+0.2*IF(LEFT($F16,1)="③",5,IF(LEFT($F16,1)="②",3,1))-IF($K16>0,0.3,0),2)+ROW()/100000)) -> 3.85016 | Z16: =IF($Y16="","",RANK($Y16,$Y$5:$Y$94)) -> 17 | AA16: L1 實體基礎層 | AB16: Decree 58/2025（2025-03-03生效）已由Nghị định 243/2026（2026-06-26生效）修訂：餘電可售上限20%→50%、2030-12-31前電網條件允許可協議更高、未併網之山區離島不限售電量；通報門檻改依逆變器容量（<1kW免通報、≥1kW提前10工作日通報），分級改依併網電壓等級——醫院大屋頂＋日間高負載是典型受益者，額度放寬後自用外售的回收年限明顯改善。ESCO市場「有潛力未成形」，融資與M&V是瓶頸。 | AC16: A | AD16: 白梅二院/越德二院已投運：2025-12-19落成，白梅二院2026-06-26收治（首期325床）、越德二院2026-07-09開幕（首期300床），設計各1,000床、各約5,000億越盾。政府監察（2025-04）指兩大標案4,389.9億越盾全流程違規。TCVN 5687:2024（通風空調）更新；Decree 96/2023第40-41條為手術室執照錨點；醫療廢水強制QCVN 28:2010。Decree 58/2025確立屋頂光電自發自用制，已由Nghị định 243/2026（2026-06-26生效）修訂：餘電可售上限由20%提高至50%（2030-12-31前電網條件允許可再協議）、通報門檻改依逆變器容量（<1kW免通報、≥1kW須提前10工作日通報）。
A17: OPP-13 | B17: 消毒供應中心(CSSD)設備整廠 | C17: Central Sterile Supply Department Turnkey | D17: B 建築工程與設施 | E17: 清洗消毒機、蒸氣／過氧化氫滅菌鍋、器械追溯軟體與符合標準的動線設計 | F17: ② 起步中：剛開始有人做 | G17: =IF($A17="","",IF($H17=0,"（尚無對應能力）",IFERROR(INDEX(16_能力商機矩陣_CapOppMap!$D$160:$CO$160,MATCH($A17,16_能力商機矩陣_CapOppMap!$D$4:$CO$4,0)),""))) -> D03; D05 | H17: =IF($A17="","",IFERROR(INDEX(16_能力商機矩陣_CapOppMap!$D$156:$CO$156,MATCH($A17,16_能力商機矩陣_CapOppMap!$D$4:$CO$4,0)),"")) -> 2 | I17: =IF($A17="","",IFERROR(INDEX(16_能力商機矩陣_CapOppMap!$D$157:$CO$157,MATCH($A17,16_能力商機矩陣_CapOppMap!$D$4:$CO$4,0)),"")) -> 4.7 | J17: =IF($A17="","",IFERROR(INDEX(16_能力商機矩陣_CapOppMap!$D$158:$CO$158,MATCH($A17,16_能力商機矩陣_CapOppMap!$D$4:$CO$4,0)),"")) -> 2.4 | K17: =IF($A17="","",IFERROR(INDEX(16_能力商機矩陣_CapOppMap!$D$159:$CO$159,MATCH($A17,16_能力商機矩陣_CapOppMap!$D$4:$CO$4,0)),"")) -> 0 | L17: =IF($A17="","",IF($H17=0,"★白地商機：目前無對應能力，需新增能力或找新夥伴",IF($K17>0,"有缺口："&$K17&"項可對外招募","已有能力可承接"))) -> 已有能力可承接 | M17: G4 | N17: 醫院業主資本支出(CAPEX) | O17: 設備銷售＋耗材 | P17: 500K-2M USD | Q17: 是 | R17: Clinical Engineering Lead | S17: 省級醫院多半還在用單槽高壓釜，清洗消毒與器械追溯鏈幾乎空白 | T17: =IF($A17="","",COUNTIF(14_商機清單_Pipeline!$A$5:$A$34,$U17)) -> 0 | U17: =IF($B17="","",$A17&" "&$B17) -> OPP-13 消毒供應中心(CSSD)設備整廠 | V17: （待調查） | X17: =IF($A17="","",IFERROR(INDEX(16_能力商機矩陣_CapOppMap!$D$162:$CO$162,MATCH($A17,16_能力商機矩陣_CapOppMap!$D$4:$CO$4,0)),"")) -> 0 | Y17: =IF(OR($A17="",$H17=""),"",IF($H17=0,"",ROUND(0.45*$I17+0.35*$J17+0.2*IF(LEFT($F17,1)="③",5,IF(LEFT($F17,1)="②",3,1))-IF($K17>0,0.3,0),2)+ROW()/100000)) -> 3.56017 | Z17: =IF($Y17="","",RANK($Y17,$Y$5:$Y$94)) -> 43 | AA17: L1 實體基礎層 | AB17: （本項無專屬發現——見同列右方的家族／領域趨勢，或 19／20 分頁） | AC17: B | AD17: 白梅二院/越德二院已投運：2025-12-19落成，白梅二院2026-06-26收治（首期325床）、越德二院2026-07-09開幕（首期300床），設計各1,000床、各約5,000億越盾。政府監察（2025-04）指兩大標案4,389.9億越盾全流程違規。TCVN 5687:2024（通風空調）更新；Decree 96/2023第40-41條為手術室執照錨點；醫療廢水強制QCVN 28:2010。Decree 58/2025確立屋頂光電自發自用制，已由Nghị định 243/2026（2026-06-26生效）修訂：餘電可售上限由20%提高至50%（2030-12-31前電網條件允許可再協議）、通報門檻改依逆變器容量（<1kW免通報、≥1kW須提前10工作日通報）。
A18: OPP-14 | B18: 影像設備整批交鑰匙（CT/MRI/DSA＋機房） | C18: Imaging Fleet Turnkey | D18: C 醫材與臨床設備 | E18: 影像設備＋機房屏蔽＋PACS＋維運一起賣；醫院發展基金、省預算或設備租賃付錢 | F18: ① 已成熟：在地已有供應商 | G18: =IF($A18="","",IF($H18=0,"（尚無對應能力）",IFERROR(INDEX(16_能力商機矩陣_CapOppMap!$D$160:$CO$160,MATCH($A18,16_能力商機矩陣_CapOppMap!$D$4:$CO$4,0)),""))) -> D05 | H18: =IF($A18="","",IFERROR(INDEX(16_能力商機矩陣_CapOppMap!$D$156:$CO$156,MATCH($A18,16_能力商機矩陣_CapOppMap!$D$4:$CO$4,0)),"")) -> 2 | I18: =IF($A18="","",IFERROR(INDEX(16_能力商機矩陣_CapOppMap!$D$157:$CO$157,MATCH($A18,16_能力商機矩陣_CapOppMap!$D$4:$CO$4,0)),"")) -> 4.7 | J18: =IF($A18="","",IFERROR(INDEX(16_能力商機矩陣_CapOppMap!$D$158:$CO$158,MATCH($A18,16_能力商機矩陣_CapOppMap!$D$4:$CO$4,0)),"")) -> 2.4 | K18: =IF($A18="","",IFERROR(INDEX(16_能力商機矩陣_CapOppMap!$D$159:$CO$159,MATCH($A18,16_能力商機矩陣_CapOppMap!$D$4:$CO$4,0)),"")) -> 1 | L18: =IF($A18="","",IF($H18=0,"★白地商機：目前無對應能力，需新增能力或找新夥伴",IF($K18>0,"有缺口："&$K18&"項可對外招募","已有能力可承接"))) -> 有缺口：1項可對外招募 | M18: G3 | N18: 醫院業主資本支出(CAPEX) | O18: 設施/設備PPP | P18: 2M-10M USD | Q18: 是 | R18: Imaging Lead | S18: GE／西門子／飛利浦／中國廠競爭激烈——台灣的切點在機房建置＋PACS整合＋維運包，不是球管本身 | T18: =IF($A18="","",COUNTIF(14_商機清單_Pipeline!$A$5:$A$34,$U18)) -> 1 | U18: =IF($B18="","",$A18&" "&$B18) -> OPP-14 影像設備整批交鑰匙（CT/MRI/DSA＋機房） | V18: GE/西門子/飛利浦＋中國聯影等，設備端價格戰激烈 | W18: 賣機房建置＋PACS整合＋維運SLA，不與原廠拚設備價 | X18: =IF($A18="","",IFERROR(INDEX(16_能力商機矩陣_CapOppMap!$D$162:$CO$162,MATCH($A18,16_能力商機矩陣_CapOppMap!$D$4:$CO$4,0)),"")) -> 0 | Y18: =IF(OR($A18="",$H18=""),"",IF($H18=0,"",ROUND(0.45*$I18+0.35*$J18+0.2*IF(LEFT($F18,1)="③",5,IF(LEFT($F18,1)="②",3,1))-IF($K18>0,0.3,0),2)+ROW()/100000)) -> 2.86018 | Z18: =IF($Y18="","",RANK($Y18,$Y$5:$Y$94)) -> 75 | AA18: L3 臨床設備層 | AB18: 診斷影像列美商務部最大商機類別之一；河內/胡志明吸納全國60%病人＝省級影像缺口。 | AC18: A | AD18: 醫材市場（三家口徑）：TechSci 2024年15.5億美元→2030年25.3億（CAGR 8.45%）、Statista 2025年17.7億→2029年24.7億（CAGR 8.62%）、越南藥管局2024年約17億——CAGR一致約8.1-8.6%。2025-07-01起過渡措施全面終止：須在地MAH、ISO 13485、C/D類CSDT申報。Bidding Law 2023承認設備寄放／按次計費／委外檢驗等模式；⚠承包商選擇方式已於2025-07-01（Luật 90/2025/QH15）由6種增為10種（新增đặt hàng），另有線上詢價與線上採購兩種方式。硬缺口：直線加速器85台、分布近100家中心，放療量能僅滿足約60%需求（越南原子能主管機關2025-08）；透析實際僅4.5-5萬人接受治療、成人CKD達1,000-1,050萬人；PET/CT僅12台。2026-02 Tâm Anh採購全國首套質子治療系統（Mevion S250-FIT，近2兆越盾）。
A19: OPP-15 | B19: 放射腫瘤與核醫中心整廠 | C19: Radiotherapy & Nuclear Medicine Centre Turnkey | D19: C 醫材與臨床設備 | E19: 直線加速器、近接治療、治療計畫系統、防護機房土建、PET/CT；省預算或腫瘤合資公司付錢 | F19: ③ 尚未出現：幾乎空白 | G19: =IF($A19="","",IF($H19=0,"（尚無對應能力）",IFERROR(INDEX(16_能力商機矩陣_CapOppMap!$D$160:$CO$160,MATCH($A19,16_能力商機矩陣_CapOppMap!$D$4:$CO$4,0)),""))) -> D05 | H19: =IF($A19="","",IFERROR(INDEX(16_能力商機矩陣_CapOppMap!$D$156:$CO$156,MATCH($A19,16_能力商機矩陣_CapOppMap!$D$4:$CO$4,0)),"")) -> 3 | I19: =IF($A19="","",IFERROR(INDEX(16_能力商機矩陣_CapOppMap!$D$157:$CO$157,MATCH($A19,16_能力商機矩陣_CapOppMap!$D$4:$CO$4,0)),"")) -> 4.7 | J19: =IF($A19="","",IFERROR(INDEX(16_能力商機矩陣_CapOppMap!$D$158:$CO$158,MATCH($A19,16_能力商機矩陣_CapOppMap!$D$4:$CO$4,0)),"")) -> 2.4 | K19: =IF($A19="","",IFERROR(INDEX(16_能力商機矩陣_CapOppMap!$D$159:$CO$159,MATCH($A19,16_能力商機矩陣_CapOppMap!$D$4:$CO$4,0)),"")) -> 1 | L19: =IF($A19="","",IF($H19=0,"★白地商機：目前無對應能力，需新增能力或找新夥伴",IF($K19>0,"有缺口："&$K19&"項可對外招募","已有能力可承接"))) -> 有缺口：1項可對外招募 | M19: G4 | N19: 省級衛生局預算 | O19: 政府採購 | P19: >10M USD | Q19: 是 | R19: Clinical Engineering Lead | S19: ★放療與核醫設備嚴重不足且集中在河內／胡志明市，腫瘤醫院長期超載，是最大的臨床量能缺口 | T19: =IF($A19="","",COUNTIF(14_商機清單_Pipeline!$A$5:$A$34,$U19)) -> 0 | U19: =IF($B19="","",$A19&" "&$B19) -> OPP-15 放射腫瘤與核醫中心整廠 | V19: Varian/Elekta 原廠直營；量能集中河內/胡志明兩大城 | W19: 整廠輸出（防護土建＋TPS＋物理師訓練）＋ODA組案能力 | X19: =IF($A19="","",IFERROR(INDEX(16_能力商機矩陣_CapOppMap!$D$162:$CO$162,MATCH($A19,16_能力商機矩陣_CapOppMap!$D$4:$CO$4,0)),"")) -> 0 | Y19: =IF(OR($A19="",$H19=""),"",IF($H19=0,"",ROUND(0.45*$I19+0.35*$J19+0.2*IF(LEFT($F19,1)="③",5,IF(LEFT($F19,1)="②",3,1))-IF($K19>0,0.3,0),2)+ROW()/100000)) -> 3.66019 | Z19: =IF($Y19="","",RANK($Y19,$Y$5:$Y$94)) -> 35 | AA19: L3 臨床設備層 | AB19: 全國85台體外放療加速器、分布近100家中心，量能僅滿足約60%需求（越南原子能主管機關2025-08）；約0.84台/百萬人 vs 標準4-8台、43%老舊；PET/CT僅12台、迴旋加速器3台；放療等待2-6週。質子治療：K醫院籌建北越首座質子中心（4.2兆越盾）；Tâm Anh已於2026-02採購全國首套質子系統（Mevion S250-FIT，近2兆越盾）。達低標需增至約400台。 | AC19: A | AD19: 醫材市場（三家口徑）：TechSci 2024年15.5億美元→2030年25.3億（CAGR 8.45%）、Statista 2025年17.7億→2029年24.7億（CAGR 8.62%）、越南藥管局2024年約17億——CAGR一致約8.1-8.6%。2025-07-01起過渡措施全面終止：須在地MAH、ISO 13485、C/D類CSDT申報。Bidding Law 2023承認設備寄放／按次計費／委外檢驗等模式；⚠承包商選擇方式已於2025-07-01（Luật 90/2025/QH15）由6種增為10種（新增đặt hàng），另有線上詢價與線上採購兩種方式。硬缺口：直線加速器85台、分布近100家中心，放療量能僅滿足約60%需求（越南原子能主管機關2025-08）；透析實際僅4.5-5萬人接受治療、成人CKD達1,000-1,050萬人；PET/CT僅12台。2026-02 Tâm Anh採購全國首套質子治療系統（Mevion S250-FIT，近2兆越盾）。
A20: OPP-16 | B20: 心導管室與複合式手術室 | C20: Cath Lab & Hybrid OR | D20: C 醫材與臨床設備 | E20: 心導管室、DSA、血液動力學監測與複合式手術室；醫院資本支出 | F20: ② 起步中：剛開始有人做 | G20: =IF($A20="","",IF($H20=0,"（尚無對應能力）",IFERROR(INDEX(16_能力商機矩陣_CapOppMap!$D$160:$CO$160,MATCH($A20,16_能力商機矩陣_CapOppMap!$D$4:$CO$4,0)),""))) -> D05 | H20: =IF($A20="","",IFERROR(INDEX(16_能力商機矩陣_CapOppMap!$D$156:$CO$156,MATCH($A20,16_能力商機矩陣_CapOppMap!$D$4:$CO$4,0)),"")) -> 1 | I20: =IF($A20="","",IFERROR(INDEX(16_能力商機矩陣_CapOppMap!$D$157:$CO$157,MATCH($A20,16_能力商機矩陣_CapOppMap!$D$4:$CO$4,0)),"")) -> 4.7 | J20: =IF($A20="","",IFERROR(INDEX(16_能力商機矩陣_CapOppMap!$D$158:$CO$158,MATCH($A20,16_能力商機矩陣_CapOppMap!$D$4:$CO$4,0)),"")) -> 2.4 | K20: =IF($A20="","",IFERROR(INDEX(16_能力商機矩陣_CapOppMap!$D$159:$CO$159,MATCH($A20,16_能力商機矩陣_CapOppMap!$D$4:$CO$4,0)),"")) -> 1 | L20: =IF($A20="","",IF($H20=0,"★白地商機：目前無對應能力，需新增能力或找新夥伴",IF($K20>0,"有缺口："&$K20&"項可對外招募","已有能力可承接"))) -> 有缺口：1項可對外招募 | M20: G4 | N20: 醫院業主資本支出(CAPEX) | O20: 設備銷售＋耗材 | P20: 2M-10M USD | Q20: 是 | R20: Clinical Engineering Lead | S20: 心血管是最大的醫材次領域（約US$293m），中央醫院已有、省級還很薄 | T20: =IF($A20="","",COUNTIF(14_商機清單_Pipeline!$A$5:$A$34,$U20)) -> 0 | U20: =IF($B20="","",$A20&" "&$B20) -> OPP-16 心導管室與複合式手術室 | V20: （待調查） | X20: =IF($A20="","",IFERROR(INDEX(16_能力商機矩陣_CapOppMap!$D$162:$CO$162,MATCH($A20,16_能力商機矩陣_CapOppMap!$D$4:$CO$4,0)),"")) -> 0 | Y20: =IF(OR($A20="",$H20=""),"",IF($H20=0,"",ROUND(0.45*$I20+0.35*$J20+0.2*IF(LEFT($F20,1)="③",5,IF(LEFT($F20,1)="②",3,1))-IF($K20>0,0.3,0),2)+ROW()/100000)) -> 3.2602 | Z20: =IF($Y20="","",RANK($Y20,$Y$5:$Y$94)) -> 62 | AA20: L3 臨床設備層 | AB20: 介入心臟市場：Data Bridge估2024年5,849萬美元→2032年9,901萬（CAGR 6.8%）；Expert Market Research估2025年8.6億美元（CAGR 7.45%）——兩者相差約15倍，涵蓋範圍不同（器材 vs 含手術服務）。⚠「越南占東南亞36.4%」僅見Data Bridge自家頁面、其東南亞母報告已404，反推東南亞總額僅約1.6億美元與各國PCI手術量常識不符，不可採信為事實。複合手術室專屬數據未查得。 | AC20: A | AD20: 醫材市場（三家口徑）：TechSci 2024年15.5億美元→2030年25.3億（CAGR 8.45%）、Statista 2025年17.7億→2029年24.7億（CAGR 8.62%）、越南藥管局2024年約17億——CAGR一致約8.1-8.6%。2025-07-01起過渡措施全面終止：須在地MAH、ISO 13485、C/D類CSDT申報。Bidding Law 2023承認設備寄放／按次計費／委外檢驗等模式；⚠承包商選擇方式已於2025-07-01（Luật 90/2025/QH15）由6種增為10種（新增đặt hàng），另有線上詢價與線上採購兩種方式。硬缺口：直線加速器85台、分布近100家中心，放療量能僅滿足約60%需求（越南原子能主管機關2025-08）；透析實際僅4.5-5萬人接受治療、成人CKD達1,000-1,050萬人；PET/CT僅12台。2026-02 Tâm Anh採購全國首套質子治療系統（Mevion S250-FIT，近2兆越盾）。
A21: OPP-17 | B21: 洗腎設備與水處理系統 | C21: Dialysis Plant & RO Water Treatment | D21: C 醫材與臨床設備 | E21: 洗腎機、逆滲透水處理、濃縮液供應；設備一次收入加上耗材長期續收 | F21: ② 起步中：剛開始有人做 | G21: =IF($A21="","",IF($H21=0,"（尚無對應能力）",IFERROR(INDEX(16_能力商機矩陣_CapOppMap!$D$160:$CO$160,MATCH($A21,16_能力商機矩陣_CapOppMap!$D$4:$CO$4,0)),""))) -> D05 | H21: =IF($A21="","",IFERROR(INDEX(16_能力商機矩陣_CapOppMap!$D$156:$CO$156,MATCH($A21,16_能力商機矩陣_CapOppMap!$D$4:$CO$4,0)),"")) -> 2 | I21: =IF($A21="","",IFERROR(INDEX(16_能力商機矩陣_CapOppMap!$D$157:$CO$157,MATCH($A21,16_能力商機矩陣_CapOppMap!$D$4:$CO$4,0)),"")) -> 4.7 | J21: =IF($A21="","",IFERROR(INDEX(16_能力商機矩陣_CapOppMap!$D$158:$CO$158,MATCH($A21,16_能力商機矩陣_CapOppMap!$D$4:$CO$4,0)),"")) -> 2.4 | K21: =IF($A21="","",IFERROR(INDEX(16_能力商機矩陣_CapOppMap!$D$159:$CO$159,MATCH($A21,16_能力商機矩陣_CapOppMap!$D$4:$CO$4,0)),"")) -> 0 | L21: =IF($A21="","",IF($H21=0,"★白地商機：目前無對應能力，需新增能力或找新夥伴",IF($K21>0,"有缺口："&$K21&"項可對外招募","已有能力可承接"))) -> 已有能力可承接 | M21: G4 | N21: 醫院業主資本支出(CAPEX) | O21: 設備銷售＋耗材 | P21: 500K-2M USD | Q21: 是 | R21: Clinical Engineering Lead | S21: 約1300萬慢性腎病人口，但80%洗腎中心集中在都市；健保給付洗腎，付費來源最明確 | T21: =IF($A21="","",COUNTIF(14_商機清單_Pipeline!$A$5:$A$34,$U21)) -> 0 | U21: =IF($B21="","",$A21&" "&$B21) -> OPP-17 洗腎設備與水處理系統 | V21: Fresenius/B.Braun 設備商；在地私人洗腎中心約50家在展開 | W21: 設備＋水處理＋耗材長約＋衛星中心營運知識整包 | X21: =IF($A21="","",IFERROR(INDEX(16_能力商機矩陣_CapOppMap!$D$162:$CO$162,MATCH($A21,16_能力商機矩陣_CapOppMap!$D$4:$CO$4,0)),"")) -> 0 | Y21: =IF(OR($A21="",$H21=""),"",IF($H21=0,"",ROUND(0.45*$I21+0.35*$J21+0.2*IF(LEFT($F21,1)="③",5,IF(LEFT($F21,1)="②",3,1))-IF($K21>0,0.3,0),2)+ROW()/100000)) -> 3.56021 | Z21: =IF($Y21="","",RANK($Y21,$Y$5:$Y$94)) -> 42 | AA21: L3 臨床設備層 | AB21: 透析市場2025年5.04億美元→2034年7.18億；需求>10萬人、實際3.6萬（覆蓋~1/3）；健保給付約25美元/次；全國僅約400透析單位。 | AC21: A | AD21: 醫材市場（三家口徑）：TechSci 2024年15.5億美元→2030年25.3億（CAGR 8.45%）、Statista 2025年17.7億→2029年24.7億（CAGR 8.62%）、越南藥管局2024年約17億——CAGR一致約8.1-8.6%。2025-07-01起過渡措施全面終止：須在地MAH、ISO 13485、C/D類CSDT申報。Bidding Law 2023承認設備寄放／按次計費／委外檢驗等模式；⚠承包商選擇方式已於2025-07-01（Luật 90/2025/QH15）由6種增為10種（新增đặt hàng），另有線上詢價與線上採購兩種方式。硬缺口：直線加速器85台、分布近100家中心，放療量能僅滿足約60%需求（越南原子能主管機關2025-08）；透析實際僅4.5-5萬人接受治療、成人CKD達1,000-1,050萬人；PET/CT僅12台。2026-02 Tâm Anh採購全國首套質子治療系統（Mevion S250-FIT，近2兆越盾）。
A22: OPP-18 | B22: 內視鏡與自動清洗消毒追溯 | C22: Endoscopy Suite & Automated Reprocessing | D22: C 醫材與臨床設備 | E22: 內視鏡主機加上越南醫院普遍買不足的清洗消毒(AER)、乾燥櫃與追溯系統 | F22: ③ 尚未出現：幾乎空白 | G22: =IF($A22="","",IF($H22=0,"（尚無對應能力）",IFERROR(INDEX(16_能力商機矩陣_CapOppMap!$D$160:$CO$160,MATCH($A22,16_能力商機矩陣_CapOppMap!$D$4:$CO$4,0)),""))) -> D05 | H22: =IF($A22="","",IFERROR(INDEX(16_能力商機矩陣_CapOppMap!$D$156:$CO$156,MATCH($A22,16_能力商機矩陣_CapOppMap!$D$4:$CO$4,0)),"")) -> 1 | I22: =IF($A22="","",IFERROR(INDEX(16_能力商機矩陣_CapOppMap!$D$157:$CO$157,MATCH($A22,16_能力商機矩陣_CapOppMap!$D$4:$CO$4,0)),"")) -> 4.7 | J22: =IF($A22="","",IFERROR(INDEX(16_能力商機矩陣_CapOppMap!$D$158:$CO$158,MATCH($A22,16_能力商機矩陣_CapOppMap!$D$4:$CO$4,0)),"")) -> 2.4 | K22: =IF($A22="","",IFERROR(INDEX(16_能力商機矩陣_CapOppMap!$D$159:$CO$159,MATCH($A22,16_能力商機矩陣_CapOppMap!$D$4:$CO$4,0)),"")) -> 0 | L22: =IF($A22="","",IF($H22=0,"★白地商機：目前無對應能力，需新增能力或找新夥伴",IF($K22>0,"有缺口："&$K22&"項可對外招募","已有能力可承接"))) -> 已有能力可承接 | M22: G4 | N22: 醫院業主資本支出(CAPEX) | O22: 設備銷售＋耗材 | P22: 500K-2M USD | Q22: 是 | R22: Clinical Engineering Lead | S22: 內視鏡主機有人賣，但清洗消毒與追溯這一段幾乎沒人做，是感染管制稽查的下一個焦點 | T22: =IF($A22="","",COUNTIF(14_商機清單_Pipeline!$A$5:$A$34,$U22)) -> 0 | U22: =IF($B22="","",$A22&" "&$B22) -> OPP-18 內視鏡與自動清洗消毒追溯 | V22: （待調查） | X22: =IF($A22="","",IFERROR(INDEX(16_能力商機矩陣_CapOppMap!$D$162:$CO$162,MATCH($A22,16_能力商機矩陣_CapOppMap!$D$4:$CO$4,0)),"")) -> 0 | Y22: =IF(OR($A22="",$H22=""),"",IF($H22=0,"",ROUND(0.45*$I22+0.35*$J22+0.2*IF(LEFT($F22,1)="③",5,IF(LEFT($F22,1)="②",3,1))-IF($K22>0,0.3,0),2)+ROW()/100000)) -> 3.96022 | Z22: =IF($Y22="","",RANK($Y22,$Y$5:$Y$94)) -> 11 | AA22: L3 臨床設備層 | AB22: 越南專屬市場數據與法規未查得；Olympus已在Cho Ray/108醫院驗證內視鏡AI（2022-23）可作切入參照。 | AC22: C | AD22: 醫材市場（三家口徑）：TechSci 2024年15.5億美元→2030年25.3億（CAGR 8.45%）、Statista 2025年17.7億→2029年24.7億（CAGR 8.62%）、越南藥管局2024年約17億——CAGR一致約8.1-8.6%。2025-07-01起過渡措施全面終止：須在地MAH、ISO 13485、C/D類CSDT申報。Bidding Law 2023承認設備寄放／按次計費／委外檢驗等模式；⚠承包商選擇方式已於2025-07-01（Luật 90/2025/QH15）由6種增為10種（新增đặt hàng），另有線上詢價與線上採購兩種方式。硬缺口：直線加速器85台、分布近100家中心，放療量能僅滿足約60%需求（越南原子能主管機關2025-08）；透析實際僅4.5-5萬人接受治療、成人CKD達1,000-1,050萬人；PET/CT僅12台。2026-02 Tâm Anh採購全國首套質子治療系統（Mevion S250-FIT，近2兆越盾）。
A23: OPP-19 | B23: 加護病房與整合手術室設備包 | C23: ICU & Integrated OR Equipment Package | D23: C 醫材與臨床設備 | E23: 吊塔、影像整合、呼吸器、ECMO、麻醉機、監視系統與中央站的整區交付 | F23: ② 起步中：剛開始有人做 | G23: =IF($A23="","",IF($H23=0,"（尚無對應能力）",IFERROR(INDEX(16_能力商機矩陣_CapOppMap!$D$160:$CO$160,MATCH($A23,16_能力商機矩陣_CapOppMap!$D$4:$CO$4,0)),""))) -> D05 | H23: =IF($A23="","",IFERROR(INDEX(16_能力商機矩陣_CapOppMap!$D$156:$CO$156,MATCH($A23,16_能力商機矩陣_CapOppMap!$D$4:$CO$4,0)),"")) -> 2 | I23: =IF($A23="","",IFERROR(INDEX(16_能力商機矩陣_CapOppMap!$D$157:$CO$157,MATCH($A23,16_能力商機矩陣_CapOppMap!$D$4:$CO$4,0)),"")) -> 4.5 | J23: =IF($A23="","",IFERROR(INDEX(16_能力商機矩陣_CapOppMap!$D$158:$CO$158,MATCH($A23,16_能力商機矩陣_CapOppMap!$D$4:$CO$4,0)),"")) -> 2.4 | K23: =IF($A23="","",IFERROR(INDEX(16_能力商機矩陣_CapOppMap!$D$159:$CO$159,MATCH($A23,16_能力商機矩陣_CapOppMap!$D$4:$CO$4,0)),"")) -> 1 | L23: =IF($A23="","",IF($H23=0,"★白地商機：目前無對應能力，需新增能力或找新夥伴",IF($K23>0,"有缺口："&$K23&"項可對外招募","已有能力可承接"))) -> 有缺口：1項可對外招募 | M23: G4 | N23: 醫院業主資本支出(CAPEX) | O23: 設備銷售＋耗材 | P23: 2M-10M USD | Q23: 是 | R23: Clinical Engineering Lead | S23: 衛生部指出90%中央醫院在急救、ICU、心血管與外科設備上有短缺 | T23: =IF($A23="","",COUNTIF(14_商機清單_Pipeline!$A$5:$A$34,$U23)) -> 0 | U23: =IF($B23="","",$A23&" "&$B23) -> OPP-19 加護病房與整合手術室設備包 | V23: （待調查） | X23: =IF($A23="","",IFERROR(INDEX(16_能力商機矩陣_CapOppMap!$D$162:$CO$162,MATCH($A23,16_能力商機矩陣_CapOppMap!$D$4:$CO$4,0)),"")) -> 0 | Y23: =IF(OR($A23="",$H23=""),"",IF($H23=0,"",ROUND(0.45*$I23+0.35*$J23+0.2*IF(LEFT($F23,1)="③",5,IF(LEFT($F23,1)="②",3,1))-IF($K23>0,0.3,0),2)+ROW()/100000)) -> 3.17023 | Z23: =IF($Y23="","",RANK($Y23,$Y$5:$Y$94)) -> 69 | AA23: L3 臨床設備層 | AB23: （本項無專屬發現——見同列右方的家族／領域趨勢，或 19／20 分頁） | AC23: B | AD23: 醫材市場（三家口徑）：TechSci 2024年15.5億美元→2030年25.3億（CAGR 8.45%）、Statista 2025年17.7億→2029年24.7億（CAGR 8.62%）、越南藥管局2024年約17億——CAGR一致約8.1-8.6%。2025-07-01起過渡措施全面終止：須在地MAH、ISO 13485、C/D類CSDT申報。Bidding Law 2023承認設備寄放／按次計費／委外檢驗等模式；⚠承包商選擇方式已於2025-07-01（Luật 90/2025/QH15）由6種增為10種（新增đặt hàng），另有線上詢價與線上採購兩種方式。硬缺口：直線加速器85台、分布近100家中心，放療量能僅滿足約60%需求（越南原子能主管機關2025-08）；透析實際僅4.5-5萬人接受治療、成人CKD達1,000-1,050萬人；PET/CT僅12台。2026-02 Tâm Anh採購全國首套質子治療系統（Mevion S250-FIT，近2兆越盾）。
A24: OPP-20 | B24: 生殖醫學(IVF)實驗室整廠 | C24: IVF Laboratory Turnkey | D24: C 醫材與臨床設備 | E24: 培養箱、顯微操作、縮時攝影、冷凍保存與潔淨等級空調，加上訓練與流程建置 | F24: ② 起步中：剛開始有人做 | G24: =IF($A24="","",IF($H24=0,"（尚無對應能力）",IFERROR(INDEX(16_能力商機矩陣_CapOppMap!$D$160:$CO$160,MATCH($A24,16_能力商機矩陣_CapOppMap!$D$4:$CO$4,0)),""))) -> D05 | H24: =IF($A24="","",IFERROR(INDEX(16_能力商機矩陣_CapOppMap!$D$156:$CO$156,MATCH($A24,16_能力商機矩陣_CapOppMap!$D$4:$CO$4,0)),"")) -> 2 | I24: =IF($A24="","",IFERROR(INDEX(16_能力商機矩陣_CapOppMap!$D$157:$CO$157,MATCH($A24,16_能力商機矩陣_CapOppMap!$D$4:$CO$4,0)),"")) -> 4.7 | J24: =IF($A24="","",IFERROR(INDEX(16_能力商機矩陣_CapOppMap!$D$158:$CO$158,MATCH($A24,16_能力商機矩陣_CapOppMap!$D$4:$CO$4,0)),"")) -> 2.4 | K24: =IF($A24="","",IFERROR(INDEX(16_能力商機矩陣_CapOppMap!$D$159:$CO$159,MATCH($A24,16_能力商機矩陣_CapOppMap!$D$4:$CO$4,0)),"")) -> 0 | L24: =IF($A24="","",IF($H24=0,"★白地商機：目前無對應能力，需新增能力或找新夥伴",IF($K24>0,"有缺口："&$K24&"項可對外招募","已有能力可承接"))) -> 已有能力可承接 | M24: G4 | N24: 病人自費 | O24: 設備銷售＋耗材 | P24: 500K-2M USD | Q24: 是 | R24: Clinical Engineering Lead | S24: 全自費、不涉健保，台灣／日本臨床品牌有明顯溢價 | T24: =IF($A24="","",COUNTIF(14_商機清單_Pipeline!$A$5:$A$34,$U24)) -> 0 | U24: =IF($B24="","",$A24&" "&$B24) -> OPP-20 生殖醫學(IVF)實驗室整廠 | V24: （待調查） | X24: =IF($A24="","",IFERROR(INDEX(16_能力商機矩陣_CapOppMap!$D$162:$CO$162,MATCH($A24,16_能力商機矩陣_CapOppMap!$D$4:$CO$4,0)),"")) -> 0 | Y24: =IF(OR($A24="",$H24=""),"",IF($H24=0,"",ROUND(0.45*$I24+0.35*$J24+0.2*IF(LEFT($F24,1)="③",5,IF(LEFT($F24,1)="②",3,1))-IF($K24>0,0.3,0),2)+ROW()/100000)) -> 3.56024 | Z24: =IF($Y24="","",RANK($Y24,$Y$5:$Y$94)) -> 41 | AA24: L3 臨床設備層 | AB24: 全國65家持照生殖中心、年5萬+週期、成功率40-50%、單週期約3,000-4,600美元（已開發國家1/5）；1998年來累計20萬IVF嬰兒。 | AC24: A | AD24: 醫材市場（三家口徑）：TechSci 2024年15.5億美元→2030年25.3億（CAGR 8.45%）、Statista 2025年17.7億→2029年24.7億（CAGR 8.62%）、越南藥管局2024年約17億——CAGR一致約8.1-8.6%。2025-07-01起過渡措施全面終止：須在地MAH、ISO 13485、C/D類CSDT申報。Bidding Law 2023承認設備寄放／按次計費／委外檢驗等模式；⚠承包商選擇方式已於2025-07-01（Luật 90/2025/QH15）由6種增為10種（新增đặt hàng），另有線上詢價與線上採購兩種方式。硬缺口：直線加速器85台、分布近100家中心，放療量能僅滿足約60%需求（越南原子能主管機關2025-08）；透析實際僅4.5-5萬人接受治療、成人CKD達1,000-1,050萬人；PET/CT僅12台。2026-02 Tâm Anh採購全國首套質子治療系統（Mevion S250-FIT，近2兆越盾）。
A25: OPP-21 | B25: 檢驗中心自動化與LIS | C25: Lab Automation Track & LIS | D25: C 醫材與臨床設備 | E25: 自動化生化免疫產線＋中介軟體＋ISO 15189認證輔導；醫院或私立檢驗連鎖付錢 | F25: ③ 尚未出現：幾乎空白 | G25: =IF($A25="","",IF($H25=0,"（尚無對應能力）",IFERROR(INDEX(16_能力商機矩陣_CapOppMap!$D$160:$CO$160,MATCH($A25,16_能力商機矩陣_CapOppMap!$D$4:$CO$4,0)),""))) -> D05; D06 | H25: =IF($A25="","",IFERROR(INDEX(16_能力商機矩陣_CapOppMap!$D$156:$CO$156,MATCH($A25,16_能力商機矩陣_CapOppMap!$D$4:$CO$4,0)),"")) -> 3 | I25: =IF($A25="","",IFERROR(INDEX(16_能力商機矩陣_CapOppMap!$D$157:$CO$157,MATCH($A25,16_能力商機矩陣_CapOppMap!$D$4:$CO$4,0)),"")) -> 4.5 | J25: =IF($A25="","",IFERROR(INDEX(16_能力商機矩陣_CapOppMap!$D$158:$CO$158,MATCH($A25,16_能力商機矩陣_CapOppMap!$D$4:$CO$4,0)),"")) -> 2.4 | K25: =IF($A25="","",IFERROR(INDEX(16_能力商機矩陣_CapOppMap!$D$159:$CO$159,MATCH($A25,16_能力商機矩陣_CapOppMap!$D$4:$CO$4,0)),"")) -> 1 | L25: =IF($A25="","",IF($H25=0,"★白地商機：目前無對應能力，需新增能力或找新夥伴",IF($K25>0,"有缺口："&$K25&"項可對外招募","已有能力可承接"))) -> 有缺口：1項可對外招募 | M25: G3 | N25: 醫院業主資本支出(CAPEX) | O25: 設施/設備PPP | P25: 2M-10M USD | Q25: 是 | R25: Laboratory Lead | S25: ★全國約3000家檢驗室只有約10%達到標準化，是最大的品質缺口之一 | T25: =IF($A25="","",COUNTIF(14_商機清單_Pipeline!$A$5:$A$34,$U25)) -> 0 | U25: =IF($B25="","",$A25&" "&$B25) -> OPP-21 檢驗中心自動化與LIS | V25: Roche/Abbott 自動化產線；Diag/PATHLAB 等檢驗連鎖整併中 | W25: ISO 15189 認證輔導綁自動化，吃全民健檢的送檢量 | X25: =IF($A25="","",IFERROR(INDEX(16_能力商機矩陣_CapOppMap!$D$162:$CO$162,MATCH($A25,16_能力商機矩陣_CapOppMap!$D$4:$CO$4,0)),"")) -> 0 | Y25: =IF(OR($A25="",$H25=""),"",IF($H25=0,"",ROUND(0.45*$I25+0.35*$J25+0.2*IF(LEFT($F25,1)="③",5,IF(LEFT($F25,1)="②",3,1))-IF($K25>0,0.3,0),2)+ROW()/100000)) -> 3.57025 | Z25: =IF($Y25="","",RANK($Y25,$Y$5:$Y$94)) -> 40 | AA25: L3 臨床設備層 | AB25: EN建議改：Total Laboratory Automation (TLA) & LIS（行業標準術語）。cost-per-test 2024年入法＝自動化+試劑綁定商模解套；僅23家無片化醫院＝數位化滲透仍低。 | AC25: A | AD25: 醫材市場（三家口徑）：TechSci 2024年15.5億美元→2030年25.3億（CAGR 8.45%）、Statista 2025年17.7億→2029年24.7億（CAGR 8.62%）、越南藥管局2024年約17億——CAGR一致約8.1-8.6%。2025-07-01起過渡措施全面終止：須在地MAH、ISO 13485、C/D類CSDT申報。Bidding Law 2023承認設備寄放／按次計費／委外檢驗等模式；⚠承包商選擇方式已於2025-07-01（Luật 90/2025/QH15）由6種增為10種（新增đặt hàng），另有線上詢價與線上採購兩種方式。硬缺口：直線加速器85台、分布近100家中心，放療量能僅滿足約60%需求（越南原子能主管機關2025-08）；透析實際僅4.5-5萬人接受治療、成人CKD達1,000-1,050萬人；PET/CT僅12台。2026-02 Tâm Anh採購全國首套質子治療系統（Mevion S250-FIT，近2兆越盾）。
A26: OPP-22 | B26: 醫材登記與市場准入代理 | C26: Regulatory Affairs & Market Access Service | D26: C 醫材與臨床設備 | E26: 當越南的法定註冊證持有人，做分類、技術文件(CSDT)、價格申報與標案支援；台／外商付錢 | F26: ② 起步中：剛開始有人做 | G26: =IF($A26="","",IF($H26=0,"（尚無對應能力）",IFERROR(INDEX(16_能力商機矩陣_CapOppMap!$D$160:$CO$160,MATCH($A26,16_能力商機矩陣_CapOppMap!$D$4:$CO$4,0)),""))) -> D01 | H26: =IF($A26="","",IFERROR(INDEX(16_能力商機矩陣_CapOppMap!$D$156:$CO$156,MATCH($A26,16_能力商機矩陣_CapOppMap!$D$4:$CO$4,0)),"")) -> 1 | I26: =IF($A26="","",IFERROR(INDEX(16_能力商機矩陣_CapOppMap!$D$157:$CO$157,MATCH($A26,16_能力商機矩陣_CapOppMap!$D$4:$CO$4,0)),"")) -> 4.4 | J26: =IF($A26="","",IFERROR(INDEX(16_能力商機矩陣_CapOppMap!$D$158:$CO$158,MATCH($A26,16_能力商機矩陣_CapOppMap!$D$4:$CO$4,0)),"")) -> 2 | K26: =IF($A26="","",IFERROR(INDEX(16_能力商機矩陣_CapOppMap!$D$159:$CO$159,MATCH($A26,16_能力商機矩陣_CapOppMap!$D$4:$CO$4,0)),"")) -> 0 | L26: =IF($A26="","",IF($H26=0,"★白地商機：目前無對應能力，需新增能力或找新夥伴",IF($K26>0,"有缺口："&$K26&"項可對外招募","已有能力可承接"))) -> 已有能力可承接 | M26: G1 | N26: 設備／軟體供應商（含代理商） | O26: 顧問服務 | P26: 100K-500K USD | Q26: 是 | R26: Regulatory Lead | S26: C/D類醫材必須有在地註冊證持有人；11300件申請中約3000件未核准是真實瓶頸，2025/7-2026/12註冊費減半 | T26: =IF($A26="","",COUNTIF(14_商機清單_Pipeline!$A$5:$A$34,$U26)) -> 0 | U26: =IF($B26="","",$A26&" "&$B26) -> OPP-22 醫材登記與市場准入代理 | V26: Asia Actual 等區域法規代理 | W26: 台灣藥證團隊＋在地持證人合資，服務台商設備進場 | X26: =IF($A26="","",IFERROR(INDEX(16_能力商機矩陣_CapOppMap!$D$162:$CO$162,MATCH($A26,16_能力商機矩陣_CapOppMap!$D$4:$CO$4,0)),"")) -> 0 | Y26: =IF(OR($A26="",$H26=""),"",IF($H26=0,"",ROUND(0.45*$I26+0.35*$J26+0.2*IF(LEFT($F26,1)="③",5,IF(LEFT($F26,1)="②",3,1))-IF($K26>0,0.3,0),2)+ROW()/100000)) -> 3.28026 | Z26: =IF($Y26="","",RANK($Y26,$Y$5:$Y$94)) -> 59 | AA26: G 治理合規層（跨層） | AB26: 2025-07-01起所有過渡措施終止：在地MAH＋ISO 13485＋C/D類CSDT強制→登記代理需求剛性化；註冊流程約2-3年。 | AC26: A | AD26: 醫材市場（三家口徑）：TechSci 2024年15.5億美元→2030年25.3億（CAGR 8.45%）、Statista 2025年17.7億→2029年24.7億（CAGR 8.62%）、越南藥管局2024年約17億——CAGR一致約8.1-8.6%。2025-07-01起過渡措施全面終止：須在地MAH、ISO 13485、C/D類CSDT申報。Bidding Law 2023承認設備寄放／按次計費／委外檢驗等模式；⚠承包商選擇方式已於2025-07-01（Luật 90/2025/QH15）由6種增為10種（新增đặt hàng），另有線上詢價與線上採購兩種方式。硬缺口：直線加速器85台、分布近100家中心，放療量能僅滿足約60%需求（越南原子能主管機關2025-08）；透析實際僅4.5-5萬人接受治療、成人CKD達1,000-1,050萬人；PET/CT僅12台。2026-02 Tâm Anh採購全國首套質子治療系統（Mevion S250-FIT，近2兆越盾）。
A27: OPP-23 | B27: 行動篩檢車與定點篩檢設備 | C27: Mobile Screening Units & Point-of-care | D27: C 醫材與臨床設備 | E27: 篩檢巴士、行動X光／乳攝、快篩設備；省級衛生局執行全民健檢政策時付錢 | F27: ② 起步中：剛開始有人做 | G27: =IF($A27="","",IF($H27=0,"（尚無對應能力）",IFERROR(INDEX(16_能力商機矩陣_CapOppMap!$D$160:$CO$160,MATCH($A27,16_能力商機矩陣_CapOppMap!$D$4:$CO$4,0)),""))) -> D05 | H27: =IF($A27="","",IFERROR(INDEX(16_能力商機矩陣_CapOppMap!$D$156:$CO$156,MATCH($A27,16_能力商機矩陣_CapOppMap!$D$4:$CO$4,0)),"")) -> 2 | I27: =IF($A27="","",IFERROR(INDEX(16_能力商機矩陣_CapOppMap!$D$157:$CO$157,MATCH($A27,16_能力商機矩陣_CapOppMap!$D$4:$CO$4,0)),"")) -> 4.7 | J27: =IF($A27="","",IFERROR(INDEX(16_能力商機矩陣_CapOppMap!$D$158:$CO$158,MATCH($A27,16_能力商機矩陣_CapOppMap!$D$4:$CO$4,0)),"")) -> 2.4 | K27: =IF($A27="","",IFERROR(INDEX(16_能力商機矩陣_CapOppMap!$D$159:$CO$159,MATCH($A27,16_能力商機矩陣_CapOppMap!$D$4:$CO$4,0)),"")) -> 1 | L27: =IF($A27="","",IF($H27=0,"★白地商機：目前無對應能力，需新增能力或找新夥伴",IF($K27>0,"有缺口："&$K27&"項可對外招募","已有能力可承接"))) -> 有缺口：1項可對外招募 | M27: G4 | N27: 省級衛生局預算 | O27: 政府採購 | P27: 500K-2M USD | Q27: 是 | R27: Imaging Lead | S27: ★2026年起全民免費健檢：胡志明市單一城市每年約US$95m（每人VND350k×1500萬人），需求時程確定 | T27: =IF($A27="","",COUNTIF(14_商機清單_Pipeline!$A$5:$A$34,$U27)) -> 0 | U27: =IF($B27="","",$A27&" "&$B27) -> OPP-23 行動篩檢車與定點篩檢設備 | V27: （待調查） | X27: =IF($A27="","",IFERROR(INDEX(16_能力商機矩陣_CapOppMap!$D$162:$CO$162,MATCH($A27,16_能力商機矩陣_CapOppMap!$D$4:$CO$4,0)),"")) -> 0 | Y27: =IF(OR($A27="",$H27=""),"",IF($H27=0,"",ROUND(0.45*$I27+0.35*$J27+0.2*IF(LEFT($F27,1)="③",5,IF(LEFT($F27,1)="②",3,1))-IF($K27>0,0.3,0),2)+ROW()/100000)) -> 3.26027 | Z27: =IF($Y27="","",RANK($Y27,$Y$5:$Y$94)) -> 61 | AA27: L3 臨床設備層 | AB27: （本項無專屬發現——見同列右方的家族／領域趨勢，或 19／20 分頁） | AC27: B | AD27: 醫材市場（三家口徑）：TechSci 2024年15.5億美元→2030年25.3億（CAGR 8.45%）、Statista 2025年17.7億→2029年24.7億（CAGR 8.62%）、越南藥管局2024年約17億——CAGR一致約8.1-8.6%。2025-07-01起過渡措施全面終止：須在地MAH、ISO 13485、C/D類CSDT申報。Bidding Law 2023承認設備寄放／按次計費／委外檢驗等模式；⚠承包商選擇方式已於2025-07-01（Luật 90/2025/QH15）由6種增為10種（新增đặt hàng），另有線上詢價與線上採購兩種方式。硬缺口：直線加速器85台、分布近100家中心，放療量能僅滿足約60%需求（越南原子能主管機關2025-08）；透析實際僅4.5-5萬人接受治療、成人CKD達1,000-1,050萬人；PET/CT僅12台。2026-02 Tâm Anh採購全國首套質子治療系統（Mevion S250-FIT，近2兆越盾）。
A28: OPP-24 | B28: 醫院IDC機房與院區網路建置 | C28: Hospital IDC & Campus Network | D28: D 數位基建與資安 | E28: 機房、網路分區、邊緣運算底座；是其他所有數位商機的共同前提 | F28: ② 起步中：剛開始有人做 | G28: =IF($A28="","",IF($H28=0,"（尚無對應能力）",IFERROR(INDEX(16_能力商機矩陣_CapOppMap!$D$160:$CO$160,MATCH($A28,16_能力商機矩陣_CapOppMap!$D$4:$CO$4,0)),""))) -> D04 | H28: =IF($A28="","",IFERROR(INDEX(16_能力商機矩陣_CapOppMap!$D$156:$CO$156,MATCH($A28,16_能力商機矩陣_CapOppMap!$D$4:$CO$4,0)),"")) -> 3 | I28: =IF($A28="","",IFERROR(INDEX(16_能力商機矩陣_CapOppMap!$D$157:$CO$157,MATCH($A28,16_能力商機矩陣_CapOppMap!$D$4:$CO$4,0)),"")) -> 3.9 | J28: =IF($A28="","",IFERROR(INDEX(16_能力商機矩陣_CapOppMap!$D$158:$CO$158,MATCH($A28,16_能力商機矩陣_CapOppMap!$D$4:$CO$4,0)),"")) -> 3.4 | K28: =IF($A28="","",IFERROR(INDEX(16_能力商機矩陣_CapOppMap!$D$159:$CO$159,MATCH($A28,16_能力商機矩陣_CapOppMap!$D$4:$CO$4,0)),"")) -> 0 | L28: =IF($A28="","",IF($H28=0,"★白地商機：目前無對應能力，需新增能力或找新夥伴",IF($K28>0,"有缺口："&$K28&"項可對外招募","已有能力可承接"))) -> 已有能力可承接 | M28: G4 | N28: 醫院業主資本支出(CAPEX) | O28: 統包工程(EPC) | P28: 2M-10M USD | Q28: 是 | R28: Digital Infrastructure Lead | S28: ★群晶核心強項。越南資料在地化(Decree 53)與資安法要求機房落地，機房選址須與OPP-10供電一起談 | T28: =IF($A28="","",COUNTIF(14_商機清單_Pipeline!$A$5:$A$34,$U28)) -> 1 | U28: =IF($B28="","",$A28&" "&$B28) -> OPP-24 醫院IDC機房與院區網路建置 | V28: Viettel IDC/VNPT/FPT 自有機房（通用型） | W28: 醫院級機房（IEC 80001＋隔離電源整合），非通用機房 | X28: =IF($A28="","",IFERROR(INDEX(16_能力商機矩陣_CapOppMap!$D$162:$CO$162,MATCH($A28,16_能力商機矩陣_CapOppMap!$D$4:$CO$4,0)),"")) -> 3 | Y28: =IF(OR($A28="",$H28=""),"",IF($H28=0,"",ROUND(0.45*$I28+0.35*$J28+0.2*IF(LEFT($F28,1)="③",5,IF(LEFT($F28,1)="②",3,1))-IF($K28>0,0.3,0),2)+ROW()/100000)) -> 3.55028 | Z28: =IF($Y28="","",RANK($Y28,$Y$5:$Y$94)) -> 44 | AA28: L2 數位基礎層 | AB28: EN建議：Hospital Data Centre (IDC) & Campus Network——IDC為亞洲用語，國際文件慣用Data Centre。DC市場22億美元/41座/221MW；電信法2024-07開放外資100%。 | AC28: A | AD28: 資料主權三法疊加：Decree 53/2022（在地化）＋資料法60/2024（2025-07生效，核心資料出境管制）＋PDPL 91/2025（2026-01-01生效，罰款上限年營收5%）。電信法2023開放外資100%資料中心；市場2025年約22億美元、41座DC/221MW。Circular 13/2025明文要求EMR備援與復原能力＝醫院DR採購直接法源。
A29: OPP-25 | B29: 醫療主權雲與境內代管 | C29: Healthcare Sovereign Cloud & Colocation | D29: D 數位基建與資安 | E29: 境內IaaS／主機代管，讓病歷與影像符合資料在地化；醫院以營運費用按年付 | F29: ② 起步中：剛開始有人做 | G29: =IF($A29="","",IF($H29=0,"（尚無對應能力）",IFERROR(INDEX(16_能力商機矩陣_CapOppMap!$D$160:$CO$160,MATCH($A29,16_能力商機矩陣_CapOppMap!$D$4:$CO$4,0)),""))) -> D04 | H29: =IF($A29="","",IFERROR(INDEX(16_能力商機矩陣_CapOppMap!$D$156:$CO$156,MATCH($A29,16_能力商機矩陣_CapOppMap!$D$4:$CO$4,0)),"")) -> 2 | I29: =IF($A29="","",IFERROR(INDEX(16_能力商機矩陣_CapOppMap!$D$157:$CO$157,MATCH($A29,16_能力商機矩陣_CapOppMap!$D$4:$CO$4,0)),"")) -> 4.1 | J29: =IF($A29="","",IFERROR(INDEX(16_能力商機矩陣_CapOppMap!$D$158:$CO$158,MATCH($A29,16_能力商機矩陣_CapOppMap!$D$4:$CO$4,0)),"")) -> 3.4 | K29: =IF($A29="","",IFERROR(INDEX(16_能力商機矩陣_CapOppMap!$D$159:$CO$159,MATCH($A29,16_能力商機矩陣_CapOppMap!$D$4:$CO$4,0)),"")) -> 0 | L29: =IF($A29="","",IF($H29=0,"★白地商機：目前無對應能力，需新增能力或找新夥伴",IF($K29>0,"有缺口："&$K29&"項可對外招募","已有能力可承接"))) -> 已有能力可承接 | M29: G4 | N29: 醫院營運預算(OPEX) | O29: 軟體授權／訂閱 | P29: 100K-500K USD | Q29: 是 | R29: Digital Infrastructure Lead | S29: PDPL＋Decree 356（2026/1/1生效）把病歷列為敏感資料、跨境傳輸須報備——境內代管是合規解 | T29: =IF($A29="","",COUNTIF(14_商機清單_Pipeline!$A$5:$A$34,$U29)) -> 0 | U29: =IF($B29="","",$A29&" "&$B29) -> OPP-25 醫療主權雲與境內代管 | V29: （待調查） | X29: =IF($A29="","",IFERROR(INDEX(16_能力商機矩陣_CapOppMap!$D$162:$CO$162,MATCH($A29,16_能力商機矩陣_CapOppMap!$D$4:$CO$4,0)),"")) -> 2 | Y29: =IF(OR($A29="",$H29=""),"",IF($H29=0,"",ROUND(0.45*$I29+0.35*$J29+0.2*IF(LEFT($F29,1)="③",5,IF(LEFT($F29,1)="②",3,1))-IF($K29>0,0.3,0),2)+ROW()/100000)) -> 3.64029 | Z29: =IF($Y29="","",RANK($Y29,$Y$5:$Y$94)) -> 39 | AA29: L2 數位基礎層 | AB29: 法源三重疊加：Decree 53/2022在地化＋資料法60/2024核心資料出境管制（2025-07生效）＋PDPL跨境評估（2026-01生效）——把醫療核心系統推向境內。本土雲四強（Viettel/VNPT/CMC/FPT）為主要受益者。 | AC29: A | AD29: 資料主權三法疊加：Decree 53/2022（在地化）＋資料法60/2024（2025-07生效，核心資料出境管制）＋PDPL 91/2025（2026-01-01生效，罰款上限年營收5%）。電信法2023開放外資100%資料中心；市場2025年約22億美元、41座DC/221MW。Circular 13/2025明文要求EMR備援與復原能力＝醫院DR採購直接法源。
A30: OPP-26 | B30: 智慧院區AIoT（BMS／RTLS／智慧病房） | C30: Smart Campus AIoT | D30: D 數位基建與資安 | E30: BMS能源管理、人員資產定位、智慧病房與護理呼叫；可用節能績效或服務訂閱收費 | F30: ③ 尚未出現：幾乎空白 | G30: =IF($A30="","",IF($H30=0,"（尚無對應能力）",IFERROR(INDEX(16_能力商機矩陣_CapOppMap!$D$160:$CO$160,MATCH($A30,16_能力商機矩陣_CapOppMap!$D$4:$CO$4,0)),""))) -> D04; D09 | H30: =IF($A30="","",IFERROR(INDEX(16_能力商機矩陣_CapOppMap!$D$156:$CO$156,MATCH($A30,16_能力商機矩陣_CapOppMap!$D$4:$CO$4,0)),"")) -> 4 | I30: =IF($A30="","",IFERROR(INDEX(16_能力商機矩陣_CapOppMap!$D$157:$CO$157,MATCH($A30,16_能力商機矩陣_CapOppMap!$D$4:$CO$4,0)),"")) -> 3.4 | J30: =IF($A30="","",IFERROR(INDEX(16_能力商機矩陣_CapOppMap!$D$158:$CO$158,MATCH($A30,16_能力商機矩陣_CapOppMap!$D$4:$CO$4,0)),"")) -> 3.4 | K30: =IF($A30="","",IFERROR(INDEX(16_能力商機矩陣_CapOppMap!$D$159:$CO$159,MATCH($A30,16_能力商機矩陣_CapOppMap!$D$4:$CO$4,0)),"")) -> 0 | L30: =IF($A30="","",IF($H30=0,"★白地商機：目前無對應能力，需新增能力或找新夥伴",IF($K30>0,"有缺口："&$K30&"項可對外招募","已有能力可承接"))) -> 已有能力可承接 | M30: G4 | N30: 醫院營運預算(OPEX) | O30: 管理服務 | P30: 2M-10M USD | Q30: 是 | R30: Smart Hospital Lead | S30: 幾乎只有新建私立醫院有；建議與院方營運KPI綁定計價 | T30: =IF($A30="","",COUNTIF(14_商機清單_Pipeline!$A$5:$A$34,$U30)) -> 0 | U30: =IF($B30="","",$A30&" "&$B30) -> OPP-26 智慧院區AIoT（BMS／RTLS／智慧病房） | V30: （待調查） | X30: =IF($A30="","",IFERROR(INDEX(16_能力商機矩陣_CapOppMap!$D$162:$CO$162,MATCH($A30,16_能力商機矩陣_CapOppMap!$D$4:$CO$4,0)),"")) -> 4 | Y30: =IF(OR($A30="",$H30=""),"",IF($H30=0,"",ROUND(0.45*$I30+0.35*$J30+0.2*IF(LEFT($F30,1)="③",5,IF(LEFT($F30,1)="②",3,1))-IF($K30>0,0.3,0),2)+ROW()/100000)) -> 3.7203 | Z30: =IF($Y30="","",RANK($Y30,$Y$5:$Y$94)) -> 27 | AA30: L2 數位基礎層 | AB30: ★重大更新：法規從「無」變成「有」。QCVN 04-3:2026/BXD（Thông tư 61/2026/TT-BXD，2026-07-30 簽發、2027-02-01 生效）取代 QCVN 09:2017/BXD，適用 ≥2,500m² 新建與改建醫院，五大管制構面之一即「建築能效監控」——這是越南第一次把醫院納入強制建築節能規範並要求能源監控。市場實證：BMS 有（BV108 軍醫院標案、Tâm Anh 醫院節能 20-30% 獲 2025 建築能效獎）、護士呼叫有（多家，Ackermann/Honeywell 經 Việt Toàn Phát）、★RTLS 零具名案例（供應商在位、需求端未啟動）。通路認知要改：BMS 綁在 HVAC 機電包裡不從 IT 預算走（BV108 第19號標 HVAC+BMS 149.6 tỷ VND ≈ 總投資 1,000 tỷ 的 15%）。競爭：研華已在越南做完智慧醫院整案（Thai Hoa 2022、Hong Ngoc），其 iHospital 含 RTLS 與 iBuilding。市場推估 2026-2030 累計 USD 2.5-5 億。 | AC30: A | AD30: 資料主權三法疊加：Decree 53/2022（在地化）＋資料法60/2024（2025-07生效，核心資料出境管制）＋PDPL 91/2025（2026-01-01生效，罰款上限年營收5%）。電信法2023開放外資100%資料中心；市場2025年約22億美元、41座DC/221MW。Circular 13/2025明文要求EMR備援與復原能力＝醫院DR採購直接法源。
A31: OPP-27 | B31: 醫院資安與等級保護認證 | C31: Hospital Cybersecurity & Level Certification | D31: D 數位基建與資安 | E31: 資安等級文件、SIEM/SOC、勒索軟體復原、不可竄改備份；醫院營運預算或資安委外月費 | F31: ③ 尚未出現：幾乎空白 | G31: =IF($A31="","",IF($H31=0,"（尚無對應能力）",IFERROR(INDEX(16_能力商機矩陣_CapOppMap!$D$160:$CO$160,MATCH($A31,16_能力商機矩陣_CapOppMap!$D$4:$CO$4,0)),""))) -> D04 | H31: =IF($A31="","",IFERROR(INDEX(16_能力商機矩陣_CapOppMap!$D$156:$CO$156,MATCH($A31,16_能力商機矩陣_CapOppMap!$D$4:$CO$4,0)),"")) -> 2 | I31: =IF($A31="","",IFERROR(INDEX(16_能力商機矩陣_CapOppMap!$D$157:$CO$157,MATCH($A31,16_能力商機矩陣_CapOppMap!$D$4:$CO$4,0)),"")) -> 3.9 | J31: =IF($A31="","",IFERROR(INDEX(16_能力商機矩陣_CapOppMap!$D$158:$CO$158,MATCH($A31,16_能力商機矩陣_CapOppMap!$D$4:$CO$4,0)),"")) -> 3.4 | K31: =IF($A31="","",IFERROR(INDEX(16_能力商機矩陣_CapOppMap!$D$159:$CO$159,MATCH($A31,16_能力商機矩陣_CapOppMap!$D$4:$CO$4,0)),"")) -> 0 | L31: =IF($A31="","",IF($H31=0,"★白地商機：目前無對應能力，需新增能力或找新夥伴",IF($K31>0,"有缺口："&$K31&"項可對外招募","已有能力可承接"))) -> 已有能力可承接 | M31: G3 | N31: 醫院營運預算(OPEX) | O31: 管理服務 | P31: 100K-500K USD | Q31: 是 | R31: CISO / Security Lead | S31: ★順化中央醫院2025/1遭勒索(>500GB加密)、德江醫院9台伺服器、鴻玉11.2萬筆病歷外流——需求已被事件創造 | T31: =IF($A31="","",COUNTIF(14_商機清單_Pipeline!$A$5:$A$34,$U31)) -> 0 | U31: =IF($B31="","",$A31&" "&$B31) -> OPP-27 醫院資安與等級保護認證 | V31: Viettel Cyber Security 在企業端；醫院端幾乎無專業者 | W31: 醫療 OT/IoMT 專科資安；順化中央醫院勒索案已創造需求 | X31: =IF($A31="","",IFERROR(INDEX(16_能力商機矩陣_CapOppMap!$D$162:$CO$162,MATCH($A31,16_能力商機矩陣_CapOppMap!$D$4:$CO$4,0)),"")) -> 1 | Y31: =IF(OR($A31="",$H31=""),"",IF($H31=0,"",ROUND(0.45*$I31+0.35*$J31+0.2*IF(LEFT($F31,1)="③",5,IF(LEFT($F31,1)="②",3,1))-IF($K31>0,0.3,0),2)+ROW()/100000)) -> 3.95031 | Z31: =IF($Y31="","",RANK($Y31,$Y$5:$Y$94)) -> 12 | AA31: L2 數位基礎層 | AB31: 定級框架＝Decree 85/2016五級制；醫院實際定級分佈未查得。EMR倉促上線後2026-2028是定級補課窗口。 | AC31: A | AD31: 資料主權三法疊加：Decree 53/2022（在地化）＋資料法60/2024（2025-07生效，核心資料出境管制）＋PDPL 91/2025（2026-01-01生效，罰款上限年營收5%）。電信法2023開放外資100%資料中心；市場2025年約22億美元、41座DC/221MW。Circular 13/2025明文要求EMR備援與復原能力＝醫院DR採購直接法源。
A32: OPP-28 | B32: 個資合規與跨境傳輸顧問(PDPL) | C32: Personal Data Protection Compliance | D32: D 數位基建與資安 | E32: 個資影響評估、跨境傳輸文件、同意管理、外部資料保護長服務、72小時通報演練 | F32: ③ 尚未出現：幾乎空白 | G32: =IF($A32="","",IF($H32=0,"（尚無對應能力）",IFERROR(INDEX(16_能力商機矩陣_CapOppMap!$D$160:$CO$160,MATCH($A32,16_能力商機矩陣_CapOppMap!$D$4:$CO$4,0)),""))) -> D01; D04 | H32: =IF($A32="","",IFERROR(INDEX(16_能力商機矩陣_CapOppMap!$D$156:$CO$156,MATCH($A32,16_能力商機矩陣_CapOppMap!$D$4:$CO$4,0)),"")) -> 2 | I32: =IF($A32="","",IFERROR(INDEX(16_能力商機矩陣_CapOppMap!$D$157:$CO$157,MATCH($A32,16_能力商機矩陣_CapOppMap!$D$4:$CO$4,0)),"")) -> 4.1 | J32: =IF($A32="","",IFERROR(INDEX(16_能力商機矩陣_CapOppMap!$D$158:$CO$158,MATCH($A32,16_能力商機矩陣_CapOppMap!$D$4:$CO$4,0)),"")) -> 2.7 | K32: =IF($A32="","",IFERROR(INDEX(16_能力商機矩陣_CapOppMap!$D$159:$CO$159,MATCH($A32,16_能力商機矩陣_CapOppMap!$D$4:$CO$4,0)),"")) -> 0 | L32: =IF($A32="","",IF($H32=0,"★白地商機：目前無對應能力，需新增能力或找新夥伴",IF($K32>0,"有缺口："&$K32&"項可對外招募","已有能力可承接"))) -> 已有能力可承接 | M32: G1 | N32: 醫院營運預算(OPEX) | O32: 顧問服務 | P32: 100K-500K USD | Q32: 是 | R32: Legal Lead | S32: PDPL 91/2025＋Decree 356 自2026/1/1生效：72小時通報、跨境傳輸影響評估60日內報公安部 | T32: =IF($A32="","",COUNTIF(14_商機清單_Pipeline!$A$5:$A$34,$U32)) -> 0 | U32: =IF($B32="","",$A32&" "&$B32) -> OPP-28 個資合規與跨境傳輸顧問(PDPL) | V32: （待調查） | X32: =IF($A32="","",IFERROR(INDEX(16_能力商機矩陣_CapOppMap!$D$162:$CO$162,MATCH($A32,16_能力商機矩陣_CapOppMap!$D$4:$CO$4,0)),"")) -> 0 | Y32: =IF(OR($A32="",$H32=""),"",IF($H32=0,"",ROUND(0.45*$I32+0.35*$J32+0.2*IF(LEFT($F32,1)="③",5,IF(LEFT($F32,1)="②",3,1))-IF($K32>0,0.3,0),2)+ROW()/100000)) -> 3.79032 | Z32: =IF($Y32="","",RANK($Y32,$Y$5:$Y$94)) -> 22 | AA32: G 治理合規層（跨層） | AB32: 重大更新：PDPL 91/2025/QH15（2025-06-26通過、2026-01-01生效）取代Decree 13/2023；罰款上限年營收5%（下限30億越盾）；健康資料屬敏感個資、跨境須DPIA＋A05備案；施行細則Decree 356/2025。項目描述應從「Decree 13時代」更新為「PDPL時代」。 | AC32: A | AD32: 資料主權三法疊加：Decree 53/2022（在地化）＋資料法60/2024（2025-07生效，核心資料出境管制）＋PDPL 91/2025（2026-01-01生效，罰款上限年營收5%）。電信法2023開放外資100%資料中心；市場2025年約22億美元、41座DC/221MW。Circular 13/2025明文要求EMR備援與復原能力＝醫院DR採購直接法源。
A33: OPP-29 | B33: 災難復原與營運持續(DR/BCM) | C33: Disaster Recovery & Business Continuity | D33: D 數位基建與資安 | E33: 異地備援、演練、RTO/RPO驗證；電子病歷法規的硬性前提之一 | F33: ③ 尚未出現：幾乎空白 | G33: =IF($A33="","",IF($H33=0,"（尚無對應能力）",IFERROR(INDEX(16_能力商機矩陣_CapOppMap!$D$160:$CO$160,MATCH($A33,16_能力商機矩陣_CapOppMap!$D$4:$CO$4,0)),""))) -> D04 | H33: =IF($A33="","",IFERROR(INDEX(16_能力商機矩陣_CapOppMap!$D$156:$CO$156,MATCH($A33,16_能力商機矩陣_CapOppMap!$D$4:$CO$4,0)),"")) -> 1 | I33: =IF($A33="","",IFERROR(INDEX(16_能力商機矩陣_CapOppMap!$D$157:$CO$157,MATCH($A33,16_能力商機矩陣_CapOppMap!$D$4:$CO$4,0)),"")) -> 4.1 | J33: =IF($A33="","",IFERROR(INDEX(16_能力商機矩陣_CapOppMap!$D$158:$CO$158,MATCH($A33,16_能力商機矩陣_CapOppMap!$D$4:$CO$4,0)),"")) -> 3.4 | K33: =IF($A33="","",IFERROR(INDEX(16_能力商機矩陣_CapOppMap!$D$159:$CO$159,MATCH($A33,16_能力商機矩陣_CapOppMap!$D$4:$CO$4,0)),"")) -> 0 | L33: =IF($A33="","",IF($H33=0,"★白地商機：目前無對應能力，需新增能力或找新夥伴",IF($K33>0,"有缺口："&$K33&"項可對外招募","已有能力可承接"))) -> 已有能力可承接 | M33: G4 | N33: 醫院營運預算(OPEX) | O33: 管理服務 | P33: 100K-500K USD | Q33: 是 | R33: BCM Lead | S33: Circular 13/2025 要求具備資安與異地備援能力，但實際做到的醫院極少 | T33: =IF($A33="","",COUNTIF(14_商機清單_Pipeline!$A$5:$A$34,$U33)) -> 0 | U33: =IF($B33="","",$A33&" "&$B33) -> OPP-29 災難復原與營運持續(DR/BCM) | V33: （待調查） | X33: =IF($A33="","",IFERROR(INDEX(16_能力商機矩陣_CapOppMap!$D$162:$CO$162,MATCH($A33,16_能力商機矩陣_CapOppMap!$D$4:$CO$4,0)),"")) -> 1 | Y33: =IF(OR($A33="",$H33=""),"",IF($H33=0,"",ROUND(0.45*$I33+0.35*$J33+0.2*IF(LEFT($F33,1)="③",5,IF(LEFT($F33,1)="②",3,1))-IF($K33>0,0.3,0),2)+ROW()/100000)) -> 4.04033 | Z33: =IF($Y33="","",RANK($Y33,$Y$5:$Y$94)) -> 5 | AA33: L2 數位基礎層 | AB33: Circular 13/2025明文要求EMR備援儲存與資料復原能力——DR/BCM第一次有直接法源，是D家族中合規驅動最強項目。 | AC33: A | AD33: 資料主權三法疊加：Decree 53/2022（在地化）＋資料法60/2024（2025-07生效，核心資料出境管制）＋PDPL 91/2025（2026-01-01生效，罰款上限年營收5%）。電信法2023開放外資100%資料中心；市場2025年約22億美元、41座DC/221MW。Circular 13/2025明文要求EMR備援與復原能力＝醫院DR採購直接法源。
A34: OPP-30 | B34: 醫療數位簽章與PKI憑證 | C34: Clinical Digital Signature & PKI | D34: D 數位基建與資安 | E34: 醫師個人憑證、硬體安全模組、時戳服務；按人／年訂閱 | F34: ② 起步中：剛開始有人做 | G34: =IF($A34="","",IF($H34=0,"（尚無對應能力）",IFERROR(INDEX(16_能力商機矩陣_CapOppMap!$D$160:$CO$160,MATCH($A34,16_能力商機矩陣_CapOppMap!$D$4:$CO$4,0)),""))) -> D04; D06 | H34: =IF($A34="","",IFERROR(INDEX(16_能力商機矩陣_CapOppMap!$D$156:$CO$156,MATCH($A34,16_能力商機矩陣_CapOppMap!$D$4:$CO$4,0)),"")) -> 2 | I34: =IF($A34="","",IFERROR(INDEX(16_能力商機矩陣_CapOppMap!$D$157:$CO$157,MATCH($A34,16_能力商機矩陣_CapOppMap!$D$4:$CO$4,0)),"")) -> 4.2 | J34: =IF($A34="","",IFERROR(INDEX(16_能力商機矩陣_CapOppMap!$D$158:$CO$158,MATCH($A34,16_能力商機矩陣_CapOppMap!$D$4:$CO$4,0)),"")) -> 2.9 | K34: =IF($A34="","",IFERROR(INDEX(16_能力商機矩陣_CapOppMap!$D$159:$CO$159,MATCH($A34,16_能力商機矩陣_CapOppMap!$D$4:$CO$4,0)),"")) -> 0 | L34: =IF($A34="","",IF($H34=0,"★白地商機：目前無對應能力，需新增能力或找新夥伴",IF($K34>0,"有缺口："&$K34&"項可對外招募","已有能力可承接"))) -> 已有能力可承接 | M34: G4 | N34: 醫院營運預算(OPEX) | O34: 軟體授權／訂閱 | P34: 100K-500K USD | Q34: 是 | R34: Health IT Lead | S34: Circular 13/2025 明文要求電子簽章／生物辨識，是無紙化病歷跑不掉的一環 | T34: =IF($A34="","",COUNTIF(14_商機清單_Pipeline!$A$5:$A$34,$U34)) -> 0 | U34: =IF($B34="","",$A34&" "&$B34) -> OPP-30 醫療數位簽章與PKI憑證 | V34: （待調查） | X34: =IF($A34="","",IFERROR(INDEX(16_能力商機矩陣_CapOppMap!$D$162:$CO$162,MATCH($A34,16_能力商機矩陣_CapOppMap!$D$4:$CO$4,0)),"")) -> 0 | Y34: =IF(OR($A34="",$H34=""),"",IF($H34=0,"",ROUND(0.45*$I34+0.35*$J34+0.2*IF(LEFT($F34,1)="③",5,IF(LEFT($F34,1)="②",3,1))-IF($K34>0,0.3,0),2)+ROW()/100000)) -> 3.51034 | Z34: =IF($Y34="","",RANK($Y34,$Y$5:$Y$94)) -> 46 | AA34: L2 數位基礎層 | AB34: Circular 13/2025允許以合法數位簽章/生物特徵/核准之電子認證簽署電子病歷；國家電子認證中心NEAC專文宣導。上位法為電子交易法2023。 | AC34: A | AD34: 資料主權三法疊加：Decree 53/2022（在地化）＋資料法60/2024（2025-07生效，核心資料出境管制）＋PDPL 91/2025（2026-01-01生效，罰款上限年營收5%）。電信法2023開放外資100%資料中心；市場2025年約22億美元、41座DC/221MW。Circular 13/2025明文要求EMR備援與復原能力＝醫院DR採購直接法源。
A35: OPP-31 | B35: HIS／EMR核心平台導入 | C35: HIS / EMR Core Platform | D35: E 醫療資訊與資料 | E35: 無紙化電子病歷與醫院資訊系統；醫院發展基金或以租代購付費 | F35: ② 起步中：剛開始有人做 | G35: =IF($A35="","",IF($H35=0,"（尚無對應能力）",IFERROR(INDEX(16_能力商機矩陣_CapOppMap!$D$160:$CO$160,MATCH($A35,16_能力商機矩陣_CapOppMap!$D$4:$CO$4,0)),""))) -> D06 | H35: =IF($A35="","",IFERROR(INDEX(16_能力商機矩陣_CapOppMap!$D$156:$CO$156,MATCH($A35,16_能力商機矩陣_CapOppMap!$D$4:$CO$4,0)),"")) -> 2 | I35: =IF($A35="","",IFERROR(INDEX(16_能力商機矩陣_CapOppMap!$D$157:$CO$157,MATCH($A35,16_能力商機矩陣_CapOppMap!$D$4:$CO$4,0)),"")) -> 4.9 | J35: =IF($A35="","",IFERROR(INDEX(16_能力商機矩陣_CapOppMap!$D$158:$CO$158,MATCH($A35,16_能力商機矩陣_CapOppMap!$D$4:$CO$4,0)),"")) -> 2.4 | K35: =IF($A35="","",IFERROR(INDEX(16_能力商機矩陣_CapOppMap!$D$159:$CO$159,MATCH($A35,16_能力商機矩陣_CapOppMap!$D$4:$CO$4,0)),"")) -> 0 | L35: =IF($A35="","",IF($H35=0,"★白地商機：目前無對應能力，需新增能力或找新夥伴",IF($K35>0,"有缺口："&$K35&"項可對外招募","已有能力可承接"))) -> 已有能力可承接 | M35: G4 | N35: 醫院業主資本支出(CAPEX) | O35: 軟體授權／訂閱 | P35: 500K-2M USD | Q35: 是 | R35: Health IT Lead | S35: ★Circular 13/2025 原要求2025/9/30無紙化未達成；Quyết định 965/QĐ-BYT（2026-04-10）改訂2026-12-31完成、2027-01-01停用紙本、2030年100%。完成率2025年底64.6%（1,062/1,645家） | T35: =IF($A35="","",COUNTIF(14_商機清單_Pipeline!$A$5:$A$34,$U35)) -> 1 | U35: =IF($B35="","",$A35&" "&$B35) -> OPP-31 HIS／EMR核心平台導入 | V35: Viettel/FPT/VNPT 與本土 HIS 商，價格低 | W35: 不搶基層 HIS，賣旗艦醫院級 EMR＋無紙化驗收整包 | X35: =IF($A35="","",IFERROR(INDEX(16_能力商機矩陣_CapOppMap!$D$162:$CO$162,MATCH($A35,16_能力商機矩陣_CapOppMap!$D$4:$CO$4,0)),"")) -> 0 | Y35: =IF(OR($A35="",$H35=""),"",IF($H35=0,"",ROUND(0.45*$I35+0.35*$J35+0.2*IF(LEFT($F35,1)="③",5,IF(LEFT($F35,1)="②",3,1))-IF($K35>0,0.3,0),2)+ROW()/100000)) -> 3.65035 | Z35: =IF($Y35="","",RANK($Y35,$Y$5:$Y$94)) -> 37 | AA35: L4 資料平台層 | AB35: Circular 13/2025（取代46/2018）：原訂醫院2025-09-30、其他機構2026-12-31；⚠Quyết định 965/QĐ-BYT（2026-04-10）改訂全體2026-12-31完成、2027-01-01停用紙本、2030年100%。完成率2025-12-31為64.6%（1,062/1,645家）、2026-08登錄1,260家。本土三強主導：Viettel Solutions逾200家（曾2個月為27家軍醫院導入）、FPT 6個月70+家（2025-11與白梅醫院簽戰略合作、2026-08發布醫療AI框架MediSight）、VNPT——外商切入點在深化模組與國際私立醫院。IT成本未計入醫療服務價格是最大瓶頸。 | AC35: A | AD35: Circular 13/2025（2025-07-21生效，取代46/2018）：醫院限2025-09-30完成EMR、其他機構限2026-12-31。⚠期限已由Quyết định 965/QĐ-BYT（2026-04-10）改訂為2026-12-31完成、2027-01-01起停用紙本，2030年100%。完成率：2025-12-31為64.6%（1,062/1,645家），2026-04衛生部長稱逾75%已公告，衛生部登錄平台2026-08顯示1,260家。Circular 26/2025：2025-10-01起醫院強制電子處方。本土三強主導（FPT eHospital 6個月部署70+家、Viettel、VNPT）。數位健康市場2025年28.4億美元→2034年95.2億（CAGR 14.4%）。VNeID健康簿約3,280萬人（2026-07），Quyết định 31/QĐ-BYT（2026-01-06）已明定與紙本同等法律效力、機關不得再要求紙本。
A36: OPP-32 | B36: PACS／RIS影像資訊系統 | C36: PACS / RIS | D36: E 醫療資訊與資料 | E36: 影像儲存傳輸與放射資訊系統，是電子病歷驗收的硬前提 | F36: ② 起步中：剛開始有人做 | G36: =IF($A36="","",IF($H36=0,"（尚無對應能力）",IFERROR(INDEX(16_能力商機矩陣_CapOppMap!$D$160:$CO$160,MATCH($A36,16_能力商機矩陣_CapOppMap!$D$4:$CO$4,0)),""))) -> D05; D06 | H36: =IF($A36="","",IFERROR(INDEX(16_能力商機矩陣_CapOppMap!$D$156:$CO$156,MATCH($A36,16_能力商機矩陣_CapOppMap!$D$4:$CO$4,0)),"")) -> 2 | I36: =IF($A36="","",IFERROR(INDEX(16_能力商機矩陣_CapOppMap!$D$157:$CO$157,MATCH($A36,16_能力商機矩陣_CapOppMap!$D$4:$CO$4,0)),"")) -> 4.9 | J36: =IF($A36="","",IFERROR(INDEX(16_能力商機矩陣_CapOppMap!$D$158:$CO$158,MATCH($A36,16_能力商機矩陣_CapOppMap!$D$4:$CO$4,0)),"")) -> 2.4 | K36: =IF($A36="","",IFERROR(INDEX(16_能力商機矩陣_CapOppMap!$D$159:$CO$159,MATCH($A36,16_能力商機矩陣_CapOppMap!$D$4:$CO$4,0)),"")) -> 1 | L36: =IF($A36="","",IF($H36=0,"★白地商機：目前無對應能力，需新增能力或找新夥伴",IF($K36>0,"有缺口："&$K36&"項可對外招募","已有能力可承接"))) -> 有缺口：1項可對外招募 | M36: G4 | N36: 醫院業主資本支出(CAPEX) | O36: 軟體授權／訂閱 | P36: 100K-500K USD | Q36: 是 | R36: Imaging Lead | S36: 衛生部正在催各省核定「使用PACS的影像服務價格」，等於替這一項打開了可收費路徑 | T36: =IF($A36="","",COUNTIF(14_商機清單_Pipeline!$A$5:$A$34,$U36)) -> 0 | U36: =IF($B36="","",$A36&" "&$B36) -> OPP-32 PACS／RIS影像資訊系統 | V36: 本土 PACS 商＋影像原廠附帶銷售 | W36: 跨廠牌 VNA＋法定十年保存合規 | X36: =IF($A36="","",IFERROR(INDEX(16_能力商機矩陣_CapOppMap!$D$162:$CO$162,MATCH($A36,16_能力商機矩陣_CapOppMap!$D$4:$CO$4,0)),"")) -> 0 | Y36: =IF(OR($A36="",$H36=""),"",IF($H36=0,"",ROUND(0.45*$I36+0.35*$J36+0.2*IF(LEFT($F36,1)="③",5,IF(LEFT($F36,1)="②",3,1))-IF($K36>0,0.3,0),2)+ROW()/100000)) -> 3.35036 | Z36: =IF($Y36="","",RANK($Y36,$Y$5:$Y$94)) -> 54 | AA36: L4 資料平台層 | AB36: 僅23家無片化醫院＝PACS滲透仍低、成長空間大；無片化是Circular 13/2025無紙化條件之一。 | AC36: A | AD36: Circular 13/2025（2025-07-21生效，取代46/2018）：醫院限2025-09-30完成EMR、其他機構限2026-12-31。⚠期限已由Quyết định 965/QĐ-BYT（2026-04-10）改訂為2026-12-31完成、2027-01-01起停用紙本，2030年100%。完成率：2025-12-31為64.6%（1,062/1,645家），2026-04衛生部長稱逾75%已公告，衛生部登錄平台2026-08顯示1,260家。Circular 26/2025：2025-10-01起醫院強制電子處方。本土三強主導（FPT eHospital 6個月部署70+家、Viettel、VNPT）。數位健康市場2025年28.4億美元→2034年95.2億（CAGR 14.4%）。VNeID健康簿約3,280萬人（2026-07），Quyết định 31/QĐ-BYT（2026-01-06）已明定與紙本同等法律效力、機關不得再要求紙本。
A37: OPP-33 | B37: FHIR互通平台與資料交換 | C37: FHIR Integration Engine | D37: E 醫療資訊與資料 | E37: HL7 v2→FHIR R4 轉換、DICOM閘道、串接衛生部健康資料入口與VNeID | F37: ② 起步中：剛開始有人做 | G37: =IF($A37="","",IF($H37=0,"（尚無對應能力）",IFERROR(INDEX(16_能力商機矩陣_CapOppMap!$D$160:$CO$160,MATCH($A37,16_能力商機矩陣_CapOppMap!$D$4:$CO$4,0)),""))) -> D06 | H37: =IF($A37="","",IFERROR(INDEX(16_能力商機矩陣_CapOppMap!$D$156:$CO$156,MATCH($A37,16_能力商機矩陣_CapOppMap!$D$4:$CO$4,0)),"")) -> 2 | I37: =IF($A37="","",IFERROR(INDEX(16_能力商機矩陣_CapOppMap!$D$157:$CO$157,MATCH($A37,16_能力商機矩陣_CapOppMap!$D$4:$CO$4,0)),"")) -> 5 | J37: =IF($A37="","",IFERROR(INDEX(16_能力商機矩陣_CapOppMap!$D$158:$CO$158,MATCH($A37,16_能力商機矩陣_CapOppMap!$D$4:$CO$4,0)),"")) -> 2.4 | K37: =IF($A37="","",IFERROR(INDEX(16_能力商機矩陣_CapOppMap!$D$159:$CO$159,MATCH($A37,16_能力商機矩陣_CapOppMap!$D$4:$CO$4,0)),"")) -> 0 | L37: =IF($A37="","",IF($H37=0,"★白地商機：目前無對應能力，需新增能力或找新夥伴",IF($K37>0,"有缺口："&$K37&"項可對外招募","已有能力可承接"))) -> 已有能力可承接 | M37: G4 | N37: 醫院業主資本支出(CAPEX) | O37: 軟體授權／訂閱 | P37: 100K-500K USD | Q37: 是 | R37: Interoperability Architect | S37: Decision 2146/QĐ-BYT 指定 HL7 FHIR R4＋DICOM 為國家標準；越南本地 FHIR IG 仍在試用版 | T37: =IF($A37="","",COUNTIF(14_商機清單_Pipeline!$A$5:$A$34,$U37)) -> 0 | U37: =IF($B37="","",$A37&" "&$B37) -> OPP-33 FHIR互通平台與資料交換 | V37: 幾乎無在地專業商（國家 FHIR IG 仍試用版） | W37: Decision 2146 國家標準的首波實作者 | X37: =IF($A37="","",IFERROR(INDEX(16_能力商機矩陣_CapOppMap!$D$162:$CO$162,MATCH($A37,16_能力商機矩陣_CapOppMap!$D$4:$CO$4,0)),"")) -> 0 | Y37: =IF(OR($A37="",$H37=""),"",IF($H37=0,"",ROUND(0.45*$I37+0.35*$J37+0.2*IF(LEFT($F37,1)="③",5,IF(LEFT($F37,1)="②",3,1))-IF($K37>0,0.3,0),2)+ROW()/100000)) -> 3.69037 | Z37: =IF($Y37="","",RANK($Y37,$Y$5:$Y$94)) -> 30 | AA37: L4 資料平台層 | AB37: 重要修正認知：FHIR無越南官方強制法規——互通實務以健保申報XML與國家平台API為主。建議項目描述加註「以接入VNeID/國家平台優先，FHIR為前瞻布局」。 | AC37: A | AD37: Circular 13/2025（2025-07-21生效，取代46/2018）：醫院限2025-09-30完成EMR、其他機構限2026-12-31。⚠期限已由Quyết định 965/QĐ-BYT（2026-04-10）改訂為2026-12-31完成、2027-01-01起停用紙本，2030年100%。完成率：2025-12-31為64.6%（1,062/1,645家），2026-04衛生部長稱逾75%已公告，衛生部登錄平台2026-08顯示1,260家。Circular 26/2025：2025-10-01起醫院強制電子處方。本土三強主導（FPT eHospital 6個月部署70+家、Viettel、VNPT）。數位健康市場2025年28.4億美元→2034年95.2億（CAGR 14.4%）。VNeID健康簿約3,280萬人（2026-07），Quyết định 31/QĐ-BYT（2026-01-06）已明定與紙本同等法律效力、機關不得再要求紙本。
A38: OPP-34 | B38: 主病人索引(MPI)與資料清理 | C38: Master Patient Index & Data Cleansing | D38: E 醫療資訊與資料 | E38: 把病人資料與國民身分證／VNeID比對去重、清理歷史資料，才能上傳國家平台 | F38: ③ 尚未出現：幾乎空白 | G38: =IF($A38="","",IF($H38=0,"（尚無對應能力）",IFERROR(INDEX(16_能力商機矩陣_CapOppMap!$D$160:$CO$160,MATCH($A38,16_能力商機矩陣_CapOppMap!$D$4:$CO$4,0)),""))) -> D06 | H38: =IF($A38="","",IFERROR(INDEX(16_能力商機矩陣_CapOppMap!$D$156:$CO$156,MATCH($A38,16_能力商機矩陣_CapOppMap!$D$4:$CO$4,0)),"")) -> 2 | I38: =IF($A38="","",IFERROR(INDEX(16_能力商機矩陣_CapOppMap!$D$157:$CO$157,MATCH($A38,16_能力商機矩陣_CapOppMap!$D$4:$CO$4,0)),"")) -> 4.7 | J38: =IF($A38="","",IFERROR(INDEX(16_能力商機矩陣_CapOppMap!$D$158:$CO$158,MATCH($A38,16_能力商機矩陣_CapOppMap!$D$4:$CO$4,0)),"")) -> 2.4 | K38: =IF($A38="","",IFERROR(INDEX(16_能力商機矩陣_CapOppMap!$D$159:$CO$159,MATCH($A38,16_能力商機矩陣_CapOppMap!$D$4:$CO$4,0)),"")) -> 1 | L38: =IF($A38="","",IF($H38=0,"★白地商機：目前無對應能力，需新增能力或找新夥伴",IF($K38>0,"有缺口："&$K38&"項可對外招募","已有能力可承接"))) -> 有缺口：1項可對外招募 | M38: G3 | N38: 醫院業主資本支出(CAPEX) | O38: 顧問服務 | P38: 100K-500K USD | Q38: 是 | R38: Data Governance Lead | S38: 幾乎沒有在地供應商；資料沒清乾淨，後面的互通與BI一定失真 | T38: =IF($A38="","",COUNTIF(14_商機清單_Pipeline!$A$5:$A$34,$U38)) -> 0 | U38: =IF($B38="","",$A38&" "&$B38) -> OPP-34 主病人索引(MPI)與資料清理 | V38: 無在地供應商 | W38: VNeID 串接經驗＋病人主檔清理方法論 | X38: =IF($A38="","",IFERROR(INDEX(16_能力商機矩陣_CapOppMap!$D$162:$CO$162,MATCH($A38,16_能力商機矩陣_CapOppMap!$D$4:$CO$4,0)),"")) -> 0 | Y38: =IF(OR($A38="",$H38=""),"",IF($H38=0,"",ROUND(0.45*$I38+0.35*$J38+0.2*IF(LEFT($F38,1)="③",5,IF(LEFT($F38,1)="②",3,1))-IF($K38>0,0.3,0),2)+ROW()/100000)) -> 3.66038 | Z38: =IF($Y38="","",RANK($Y38,$Y$5:$Y$94)) -> 34 | AA38: L4 資料平台層 | AB38: MPI實質＝國民ID/VNeID（Circular 13/2025強制EMR連結人口資料庫）；獨立MPI產品需求轉為「與VNeID/BHYT對接＋資料清理」。 | AC38: A | AD38: Circular 13/2025（2025-07-21生效，取代46/2018）：醫院限2025-09-30完成EMR、其他機構限2026-12-31。⚠期限已由Quyết định 965/QĐ-BYT（2026-04-10）改訂為2026-12-31完成、2027-01-01起停用紙本，2030年100%。完成率：2025-12-31為64.6%（1,062/1,645家），2026-04衛生部長稱逾75%已公告，衛生部登錄平台2026-08顯示1,260家。Circular 26/2025：2025-10-01起醫院強制電子處方。本土三強主導（FPT eHospital 6個月部署70+家、Viettel、VNPT）。數位健康市場2025年28.4億美元→2034年95.2億（CAGR 14.4%）。VNeID健康簿約3,280萬人（2026-07），Quyết định 31/QĐ-BYT（2026-01-06）已明定與紙本同等法律效力、機關不得再要求紙本。
A39: OPP-35 | B39: 臨床術語與編碼服務 | C39: Clinical Terminology Services | D39: E 醫療資訊與資料 | E39: ICD-10→ICD-11、SNOMED CT、LOINC、RxNorm 對應與術語伺服器 | F39: ③ 尚未出現：幾乎空白 | G39: =IF($A39="","",IF($H39=0,"（尚無對應能力）",IFERROR(INDEX(16_能力商機矩陣_CapOppMap!$D$160:$CO$160,MATCH($A39,16_能力商機矩陣_CapOppMap!$D$4:$CO$4,0)),""))) -> D06 | H39: =IF($A39="","",IFERROR(INDEX(16_能力商機矩陣_CapOppMap!$D$156:$CO$156,MATCH($A39,16_能力商機矩陣_CapOppMap!$D$4:$CO$4,0)),"")) -> 1 | I39: =IF($A39="","",IFERROR(INDEX(16_能力商機矩陣_CapOppMap!$D$157:$CO$157,MATCH($A39,16_能力商機矩陣_CapOppMap!$D$4:$CO$4,0)),"")) -> 5 | J39: =IF($A39="","",IFERROR(INDEX(16_能力商機矩陣_CapOppMap!$D$158:$CO$158,MATCH($A39,16_能力商機矩陣_CapOppMap!$D$4:$CO$4,0)),"")) -> 2.4 | K39: =IF($A39="","",IFERROR(INDEX(16_能力商機矩陣_CapOppMap!$D$159:$CO$159,MATCH($A39,16_能力商機矩陣_CapOppMap!$D$4:$CO$4,0)),"")) -> 0 | L39: =IF($A39="","",IF($H39=0,"★白地商機：目前無對應能力，需新增能力或找新夥伴",IF($K39>0,"有缺口："&$K39&"項可對外招募","已有能力可承接"))) -> 已有能力可承接 | M39: G3 | N39: 醫院業主資本支出(CAPEX) | O39: 軟體授權／訂閱 | P39: 100K-500K USD | Q39: 是 | R39: Data Governance Lead | S39: Decision 2146 已指定術語標準，但在地幾乎沒有供應商——法規造出來的空白市場 | T39: =IF($A39="","",COUNTIF(14_商機清單_Pipeline!$A$5:$A$34,$U39)) -> 0 | U39: =IF($B39="","",$A39&" "&$B39) -> OPP-35 臨床術語與編碼服務 | V39: （待調查） | X39: =IF($A39="","",IFERROR(INDEX(16_能力商機矩陣_CapOppMap!$D$162:$CO$162,MATCH($A39,16_能力商機矩陣_CapOppMap!$D$4:$CO$4,0)),"")) -> 0 | Y39: =IF(OR($A39="",$H39=""),"",IF($H39=0,"",ROUND(0.45*$I39+0.35*$J39+0.2*IF(LEFT($F39,1)="③",5,IF(LEFT($F39,1)="②",3,1))-IF($K39>0,0.3,0),2)+ROW()/100000)) -> 4.09039 | Z39: =IF($Y39="","",RANK($Y39,$Y$5:$Y$94)) -> 4 | AA39: L4 資料平台層 | AB39: （本項無專屬發現——見同列右方的家族／領域趨勢，或 19／20 分頁） | AC39: B | AD39: Circular 13/2025（2025-07-21生效，取代46/2018）：醫院限2025-09-30完成EMR、其他機構限2026-12-31。⚠期限已由Quyết định 965/QĐ-BYT（2026-04-10）改訂為2026-12-31完成、2027-01-01起停用紙本，2030年100%。完成率：2025-12-31為64.6%（1,062/1,645家），2026-04衛生部長稱逾75%已公告，衛生部登錄平台2026-08顯示1,260家。Circular 26/2025：2025-10-01起醫院強制電子處方。本土三強主導（FPT eHospital 6個月部署70+家、Viettel、VNPT）。數位健康市場2025年28.4億美元→2034年95.2億（CAGR 14.4%）。VNeID健康簿約3,280萬人（2026-07），Quyết định 31/QĐ-BYT（2026-01-06）已明定與紙本同等法律效力、機關不得再要求紙本。
A40: OPP-36 | B40: 省級健康資料中台 | C40: Provincial Health Data Platform | D40: E 醫療資訊與資料 | E40: 市／省級資料湖與資料調度平台；省級衛生局預算 | F40: ② 起步中：剛開始有人做 | G40: =IF($A40="","",IF($H40=0,"（尚無對應能力）",IFERROR(INDEX(16_能力商機矩陣_CapOppMap!$D$160:$CO$160,MATCH($A40,16_能力商機矩陣_CapOppMap!$D$4:$CO$4,0)),""))) -> D06 | H40: =IF($A40="","",IFERROR(INDEX(16_能力商機矩陣_CapOppMap!$D$156:$CO$156,MATCH($A40,16_能力商機矩陣_CapOppMap!$D$4:$CO$4,0)),"")) -> 1 | I40: =IF($A40="","",IFERROR(INDEX(16_能力商機矩陣_CapOppMap!$D$157:$CO$157,MATCH($A40,16_能力商機矩陣_CapOppMap!$D$4:$CO$4,0)),"")) -> 4 | J40: =IF($A40="","",IFERROR(INDEX(16_能力商機矩陣_CapOppMap!$D$158:$CO$158,MATCH($A40,16_能力商機矩陣_CapOppMap!$D$4:$CO$4,0)),"")) -> 2.4 | K40: =IF($A40="","",IFERROR(INDEX(16_能力商機矩陣_CapOppMap!$D$159:$CO$159,MATCH($A40,16_能力商機矩陣_CapOppMap!$D$4:$CO$4,0)),"")) -> 0 | L40: =IF($A40="","",IF($H40=0,"★白地商機：目前無對應能力，需新增能力或找新夥伴",IF($K40>0,"有缺口："&$K40&"項可對外招募","已有能力可承接"))) -> 已有能力可承接 | M40: G4 | N40: 省級衛生局預算 | O40: 政府採購 | P40: 500K-2M USD | Q40: 是 | R40: Data Architect | S40: 河內須於2026/5/30前完成就醫資料互通，省級資料平台是下一波編列的預算 | T40: =IF($A40="","",COUNTIF(14_商機清單_Pipeline!$A$5:$A$34,$U40)) -> 0 | U40: =IF($B40="","",$A40&" "&$B40) -> OPP-36 省級健康資料中台 | V40: （待調查） | X40: =IF($A40="","",IFERROR(INDEX(16_能力商機矩陣_CapOppMap!$D$162:$CO$162,MATCH($A40,16_能力商機矩陣_CapOppMap!$D$4:$CO$4,0)),"")) -> 0 | Y40: =IF(OR($A40="",$H40=""),"",IF($H40=0,"",ROUND(0.45*$I40+0.35*$J40+0.2*IF(LEFT($F40,1)="③",5,IF(LEFT($F40,1)="②",3,1))-IF($K40>0,0.3,0),2)+ROW()/100000)) -> 3.2404 | Z40: =IF($Y40="","",RANK($Y40,$Y$5:$Y$94)) -> 67 | AA40: L4 資料平台層 | AB40: 34/34省市已上線VNeID電子健康簿、約3,280萬人（2026-07）；Quyết định 31/QĐ-BYT（2026-01-06）已明定與紙本同等法律效力，1551/QĐ-BYT（2026-05-31生效）規範醫療資料上鏈VNeID；省級HIE統一技術規範未查得。 | AC40: A | AD40: Circular 13/2025（2025-07-21生效，取代46/2018）：醫院限2025-09-30完成EMR、其他機構限2026-12-31。⚠期限已由Quyết định 965/QĐ-BYT（2026-04-10）改訂為2026-12-31完成、2027-01-01起停用紙本，2030年100%。完成率：2025-12-31為64.6%（1,062/1,645家），2026-04衛生部長稱逾75%已公告，衛生部登錄平台2026-08顯示1,260家。Circular 26/2025：2025-10-01起醫院強制電子處方。本土三強主導（FPT eHospital 6個月部署70+家、Viettel、VNPT）。數位健康市場2025年28.4億美元→2034年95.2億（CAGR 14.4%）。VNeID健康簿約3,280萬人（2026-07），Quyết định 31/QĐ-BYT（2026-01-06）已明定與紙本同等法律效力、機關不得再要求紙本。
A41: OPP-37 | B41: 醫院BI與營運指揮中心 | C41: Hospital BI & Command Centre | D41: E 醫療資訊與資料 | E41: 營運指標儀表板、床位與手術室流量、對衛生部的報表；醫院或衛生局付錢 | F41: ③ 尚未出現：幾乎空白 | G41: =IF($A41="","",IF($H41=0,"（尚無對應能力）",IFERROR(INDEX(16_能力商機矩陣_CapOppMap!$D$160:$CO$160,MATCH($A41,16_能力商機矩陣_CapOppMap!$D$4:$CO$4,0)),""))) -> D06; D09 | H41: =IF($A41="","",IFERROR(INDEX(16_能力商機矩陣_CapOppMap!$D$156:$CO$156,MATCH($A41,16_能力商機矩陣_CapOppMap!$D$4:$CO$4,0)),"")) -> 2 | I41: =IF($A41="","",IFERROR(INDEX(16_能力商機矩陣_CapOppMap!$D$157:$CO$157,MATCH($A41,16_能力商機矩陣_CapOppMap!$D$4:$CO$4,0)),"")) -> 3.9 | J41: =IF($A41="","",IFERROR(INDEX(16_能力商機矩陣_CapOppMap!$D$158:$CO$158,MATCH($A41,16_能力商機矩陣_CapOppMap!$D$4:$CO$4,0)),"")) -> 2.9 | K41: =IF($A41="","",IFERROR(INDEX(16_能力商機矩陣_CapOppMap!$D$159:$CO$159,MATCH($A41,16_能力商機矩陣_CapOppMap!$D$4:$CO$4,0)),"")) -> 0 | L41: =IF($A41="","",IF($H41=0,"★白地商機：目前無對應能力，需新增能力或找新夥伴",IF($K41>0,"有缺口："&$K41&"項可對外招募","已有能力可承接"))) -> 已有能力可承接 | M41: G4 | N41: 醫院營運預算(OPEX) | O41: 軟體授權／訂閱 | P41: 100K-500K USD | Q41: 是 | R41: Data/Analytics Lead | S41: 衛生部自己已經在跑儀表板並要求院級回報，需求會由上而下壓下來 | T41: =IF($A41="","",COUNTIF(14_商機清單_Pipeline!$A$5:$A$34,$U41)) -> 0 | U41: =IF($B41="","",$A41&" "&$B41) -> OPP-37 醫院BI與營運指揮中心 | V41: （待調查） | X41: =IF($A41="","",IFERROR(INDEX(16_能力商機矩陣_CapOppMap!$D$162:$CO$162,MATCH($A41,16_能力商機矩陣_CapOppMap!$D$4:$CO$4,0)),"")) -> 1 | Y41: =IF(OR($A41="",$H41=""),"",IF($H41=0,"",ROUND(0.45*$I41+0.35*$J41+0.2*IF(LEFT($F41,1)="③",5,IF(LEFT($F41,1)="②",3,1))-IF($K41>0,0.3,0),2)+ROW()/100000)) -> 3.77041 | Z41: =IF($Y41="","",RANK($Y41,$Y$5:$Y$94)) -> 23 | AA41: L4 資料平台層 | AB41: （本項無專屬發現——見同列右方的家族／領域趨勢，或 19／20 分頁） | AC41: B | AD41: Circular 13/2025（2025-07-21生效，取代46/2018）：醫院限2025-09-30完成EMR、其他機構限2026-12-31。⚠期限已由Quyết định 965/QĐ-BYT（2026-04-10）改訂為2026-12-31完成、2027-01-01起停用紙本，2030年100%。完成率：2025-12-31為64.6%（1,062/1,645家），2026-04衛生部長稱逾75%已公告，衛生部登錄平台2026-08顯示1,260家。Circular 26/2025：2025-10-01起醫院強制電子處方。本土三強主導（FPT eHospital 6個月部署70+家、Viettel、VNPT）。數位健康市場2025年28.4億美元→2034年95.2億（CAGR 14.4%）。VNeID健康簿約3,280萬人（2026-07），Quyết định 31/QĐ-BYT（2026-01-06）已明定與紙本同等法律效力、機關不得再要求紙本。
A42: OPP-38 | B42: 醫材資料介接與床邊自動擷取 | C42: Medical Device Integration | D42: E 醫療資訊與資料 | E42: 把監視器、呼吸器、麻醉機的資料自動送進病歷；ICU優先 | F42: ③ 尚未出現：幾乎空白 | G42: =IF($A42="","",IF($H42=0,"（尚無對應能力）",IFERROR(INDEX(16_能力商機矩陣_CapOppMap!$D$160:$CO$160,MATCH($A42,16_能力商機矩陣_CapOppMap!$D$4:$CO$4,0)),""))) -> D05; D06 | H42: =IF($A42="","",IFERROR(INDEX(16_能力商機矩陣_CapOppMap!$D$156:$CO$156,MATCH($A42,16_能力商機矩陣_CapOppMap!$D$4:$CO$4,0)),"")) -> 2 | I42: =IF($A42="","",IFERROR(INDEX(16_能力商機矩陣_CapOppMap!$D$157:$CO$157,MATCH($A42,16_能力商機矩陣_CapOppMap!$D$4:$CO$4,0)),"")) -> 4.7 | J42: =IF($A42="","",IFERROR(INDEX(16_能力商機矩陣_CapOppMap!$D$158:$CO$158,MATCH($A42,16_能力商機矩陣_CapOppMap!$D$4:$CO$4,0)),"")) -> 2.4 | K42: =IF($A42="","",IFERROR(INDEX(16_能力商機矩陣_CapOppMap!$D$159:$CO$159,MATCH($A42,16_能力商機矩陣_CapOppMap!$D$4:$CO$4,0)),"")) -> 0 | L42: =IF($A42="","",IF($H42=0,"★白地商機：目前無對應能力，需新增能力或找新夥伴",IF($K42>0,"有缺口："&$K42&"項可對外招募","已有能力可承接"))) -> 已有能力可承接 | M42: G4 | N42: 醫院業主資本支出(CAPEX) | O42: 軟體授權／訂閱 | P42: 100K-500K USD | Q42: 是 | R42: Interoperability Architect | S42: ★是所有臨床AI的前提。沒有這一層，敗血症預警之類的AI根本沒有即時資料可用 | T42: =IF($A42="","",COUNTIF(14_商機清單_Pipeline!$A$5:$A$34,$U42)) -> 0 | U42: =IF($B42="","",$A42&" "&$B42) -> OPP-38 醫材資料介接與床邊自動擷取 | V42: （待調查） | X42: =IF($A42="","",IFERROR(INDEX(16_能力商機矩陣_CapOppMap!$D$162:$CO$162,MATCH($A42,16_能力商機矩陣_CapOppMap!$D$4:$CO$4,0)),"")) -> 0 | Y42: =IF(OR($A42="",$H42=""),"",IF($H42=0,"",ROUND(0.45*$I42+0.35*$J42+0.2*IF(LEFT($F42,1)="③",5,IF(LEFT($F42,1)="②",3,1))-IF($K42>0,0.3,0),2)+ROW()/100000)) -> 3.96042 | Z42: =IF($Y42="","",RANK($Y42,$Y$5:$Y$94)) -> 10 | AA42: L4 資料平台層 | AB42: （本項無專屬發現——見同列右方的家族／領域趨勢，或 19／20 分頁） | AC42: B | AD42: Circular 13/2025（2025-07-21生效，取代46/2018）：醫院限2025-09-30完成EMR、其他機構限2026-12-31。⚠期限已由Quyết định 965/QĐ-BYT（2026-04-10）改訂為2026-12-31完成、2027-01-01起停用紙本，2030年100%。完成率：2025-12-31為64.6%（1,062/1,645家），2026-04衛生部長稱逾75%已公告，衛生部登錄平台2026-08顯示1,260家。Circular 26/2025：2025-10-01起醫院強制電子處方。本土三強主導（FPT eHospital 6個月部署70+家、Viettel、VNPT）。數位健康市場2025年28.4億美元→2034年95.2億（CAGR 14.4%）。VNeID健康簿約3,280萬人（2026-07），Quyết định 31/QĐ-BYT（2026-01-06）已明定與紙本同等法律效力、機關不得再要求紙本。
A43: OPP-39 | B43: 影像長期歸檔(VNA)與異地備援 | C43: Vendor Neutral Archive & Long-term Storage | D43: E 醫療資訊與資料 | E43: 法定10年保存、異地備援與分層儲存；越來越多醫院改用「租儲存服務」 | F43: ③ 尚未出現：幾乎空白 | G43: =IF($A43="","",IF($H43=0,"（尚無對應能力）",IFERROR(INDEX(16_能力商機矩陣_CapOppMap!$D$160:$CO$160,MATCH($A43,16_能力商機矩陣_CapOppMap!$D$4:$CO$4,0)),""))) -> D04; D05 | H43: =IF($A43="","",IFERROR(INDEX(16_能力商機矩陣_CapOppMap!$D$156:$CO$156,MATCH($A43,16_能力商機矩陣_CapOppMap!$D$4:$CO$4,0)),"")) -> 2 | I43: =IF($A43="","",IFERROR(INDEX(16_能力商機矩陣_CapOppMap!$D$157:$CO$157,MATCH($A43,16_能力商機矩陣_CapOppMap!$D$4:$CO$4,0)),"")) -> 4.4 | J43: =IF($A43="","",IFERROR(INDEX(16_能力商機矩陣_CapOppMap!$D$158:$CO$158,MATCH($A43,16_能力商機矩陣_CapOppMap!$D$4:$CO$4,0)),"")) -> 2.9 | K43: =IF($A43="","",IFERROR(INDEX(16_能力商機矩陣_CapOppMap!$D$159:$CO$159,MATCH($A43,16_能力商機矩陣_CapOppMap!$D$4:$CO$4,0)),"")) -> 1 | L43: =IF($A43="","",IF($H43=0,"★白地商機：目前無對應能力，需新增能力或找新夥伴",IF($K43>0,"有缺口："&$K43&"項可對外招募","已有能力可承接"))) -> 有缺口：1項可對外招募 | M43: G4 | N43: 醫院營運預算(OPEX) | O43: 軟體授權／訂閱 | P43: 100K-500K USD | Q43: 是 | R43: Health IT Lead | S43: 影像量隨CT/MRI普及暴增，但保存與備援幾乎沒被編列——先賣儲存再賣AI是可行的順序 | T43: =IF($A43="","",COUNTIF(14_商機清單_Pipeline!$A$5:$A$34,$U43)) -> 0 | U43: =IF($B43="","",$A43&" "&$B43) -> OPP-39 影像長期歸檔(VNA)與異地備援 | V43: （待調查） | X43: =IF($A43="","",IFERROR(INDEX(16_能力商機矩陣_CapOppMap!$D$162:$CO$162,MATCH($A43,16_能力商機矩陣_CapOppMap!$D$4:$CO$4,0)),"")) -> 1 | Y43: =IF(OR($A43="",$H43=""),"",IF($H43=0,"",ROUND(0.45*$I43+0.35*$J43+0.2*IF(LEFT($F43,1)="③",5,IF(LEFT($F43,1)="②",3,1))-IF($K43>0,0.3,0),2)+ROW()/100000)) -> 3.70043 | Z43: =IF($Y43="","",RANK($Y43,$Y$5:$Y$94)) -> 28 | AA43: L4 資料平台層 | AB43: （本項無專屬發現——見同列右方的家族／領域趨勢，或 19／20 分頁） | AC43: B | AD43: Circular 13/2025（2025-07-21生效，取代46/2018）：醫院限2025-09-30完成EMR、其他機構限2026-12-31。⚠期限已由Quyết định 965/QĐ-BYT（2026-04-10）改訂為2026-12-31完成、2027-01-01起停用紙本，2030年100%。完成率：2025-12-31為64.6%（1,062/1,645家），2026-04衛生部長稱逾75%已公告，衛生部登錄平台2026-08顯示1,260家。Circular 26/2025：2025-10-01起醫院強制電子處方。本土三強主導（FPT eHospital 6個月部署70+家、Viettel、VNPT）。數位健康市場2025年28.4億美元→2034年95.2億（CAGR 14.4%）。VNeID健康簿約3,280萬人（2026-07），Quyết định 31/QĐ-BYT（2026-01-06）已明定與紙本同等法律效力、機關不得再要求紙本。
A44: OPP-40 | B44: 醫療IT代管與以租代購 | C44: Managed IT Services / OpEx Financing | D44: E 醫療資訊與資料 | E44: 由供應商出資建置EMR＋PACS＋雲端，醫院從營運收入按年付服務費（thuê dịch vụ CNTT） | F44: ② 起步中：剛開始有人做 | G44: =IF($A44="","",IF($H44=0,"（尚無對應能力）",IFERROR(INDEX(16_能力商機矩陣_CapOppMap!$D$160:$CO$160,MATCH($A44,16_能力商機矩陣_CapOppMap!$D$4:$CO$4,0)),""))) -> D04; D06; D10 | H44: =IF($A44="","",IFERROR(INDEX(16_能力商機矩陣_CapOppMap!$D$156:$CO$156,MATCH($A44,16_能力商機矩陣_CapOppMap!$D$4:$CO$4,0)),"")) -> 3 | I44: =IF($A44="","",IFERROR(INDEX(16_能力商機矩陣_CapOppMap!$D$157:$CO$157,MATCH($A44,16_能力商機矩陣_CapOppMap!$D$4:$CO$4,0)),"")) -> 4.3 | J44: =IF($A44="","",IFERROR(INDEX(16_能力商機矩陣_CapOppMap!$D$158:$CO$158,MATCH($A44,16_能力商機矩陣_CapOppMap!$D$4:$CO$4,0)),"")) -> 2.6 | K44: =IF($A44="","",IFERROR(INDEX(16_能力商機矩陣_CapOppMap!$D$159:$CO$159,MATCH($A44,16_能力商機矩陣_CapOppMap!$D$4:$CO$4,0)),"")) -> 0 | L44: =IF($A44="","",IF($H44=0,"★白地商機：目前無對應能力，需新增能力或找新夥伴",IF($K44>0,"有缺口："&$K44&"項可對外招募","已有能力可承接"))) -> 已有能力可承接 | M44: G4 | N44: 醫院營運預算(OPEX) | O44: 租賃／以租代購 | P44: 500K-2M USD | Q44: 是 | R44: Commercial Lead | S44: ★關鍵商模：越南醫療服務價格結構至今不含IT成本、資本支出審批極慢，代管模式是目前成長最快的成交方式 | T44: =IF($A44="","",COUNTIF(14_商機清單_Pipeline!$A$5:$A$34,$U44)) -> 0 | U44: =IF($B44="","",$A44&" "&$B44) -> OPP-40 醫療IT代管與以租代購 | V44: FPT/Viettel 有通用 IT 代管 | W44: 醫療級 SLA（EMR 不停機）＋以租代購財務設計，繞開資本支出審批 | X44: =IF($A44="","",IFERROR(INDEX(16_能力商機矩陣_CapOppMap!$D$162:$CO$162,MATCH($A44,16_能力商機矩陣_CapOppMap!$D$4:$CO$4,0)),"")) -> 1 | Y44: =IF(OR($A44="",$H44=""),"",IF($H44=0,"",ROUND(0.45*$I44+0.35*$J44+0.2*IF(LEFT($F44,1)="③",5,IF(LEFT($F44,1)="②",3,1))-IF($K44>0,0.3,0),2)+ROW()/100000)) -> 3.45044 | Z44: =IF($Y44="","",RANK($Y44,$Y$5:$Y$94)) -> 49 | AA44: L4 資料平台層 | AB44: IT人力短缺被官方點名為EMR瓶頸→代管/託運維空間大；「IT成本未入醫療服務定價」既是障礙也是以租代購（OpEx）模式的賣點。 | AC44: A | AD44: Circular 13/2025（2025-07-21生效，取代46/2018）：醫院限2025-09-30完成EMR、其他機構限2026-12-31。⚠期限已由Quyết định 965/QĐ-BYT（2026-04-10）改訂為2026-12-31完成、2027-01-01起停用紙本，2030年100%。完成率：2025-12-31為64.6%（1,062/1,645家），2026-04衛生部長稱逾75%已公告，衛生部登錄平台2026-08顯示1,260家。Circular 26/2025：2025-10-01起醫院強制電子處方。本土三強主導（FPT eHospital 6個月部署70+家、Viettel、VNPT）。數位健康市場2025年28.4億美元→2034年95.2億（CAGR 14.4%）。VNeID健康簿約3,280萬人（2026-07），Quyết định 31/QĐ-BYT（2026-01-06）已明定與紙本同等法律效力、機關不得再要求紙本。
A45: OPP-41 | B45: 電子處方與國家藥品資料庫介接 | C45: E-prescription & National Drug Database | D45: E 醫療資訊與資料 | E45: 合規開方＋即時上傳國家處方系統；醫院與診所按站點訂閱 | F45: ② 起步中：剛開始有人做 | G45: =IF($A45="","",IF($H45=0,"（尚無對應能力）",IFERROR(INDEX(16_能力商機矩陣_CapOppMap!$D$160:$CO$160,MATCH($A45,16_能力商機矩陣_CapOppMap!$D$4:$CO$4,0)),""))) -> D06 | H45: =IF($A45="","",IFERROR(INDEX(16_能力商機矩陣_CapOppMap!$D$156:$CO$156,MATCH($A45,16_能力商機矩陣_CapOppMap!$D$4:$CO$4,0)),"")) -> 1 | I45: =IF($A45="","",IFERROR(INDEX(16_能力商機矩陣_CapOppMap!$D$157:$CO$157,MATCH($A45,16_能力商機矩陣_CapOppMap!$D$4:$CO$4,0)),"")) -> 5 | J45: =IF($A45="","",IFERROR(INDEX(16_能力商機矩陣_CapOppMap!$D$158:$CO$158,MATCH($A45,16_能力商機矩陣_CapOppMap!$D$4:$CO$4,0)),"")) -> 2.4 | K45: =IF($A45="","",IFERROR(INDEX(16_能力商機矩陣_CapOppMap!$D$159:$CO$159,MATCH($A45,16_能力商機矩陣_CapOppMap!$D$4:$CO$4,0)),"")) -> 0 | L45: =IF($A45="","",IF($H45=0,"★白地商機：目前無對應能力，需新增能力或找新夥伴",IF($K45>0,"有缺口："&$K45&"項可對外招募","已有能力可承接"))) -> 已有能力可承接 | M45: G4 | N45: 醫院營運預算(OPEX) | O45: 軟體授權／訂閱 | P45: <100K USD | Q45: 是 | R45: CMIO / Pharmacy Lead | S45: Circular 26/2025：醫院2025/10/1、其他機構2026/1/1起強制；全國約5萬家診所是長尾市場 | T45: =IF($A45="","",COUNTIF(14_商機清單_Pipeline!$A$5:$A$34,$U45)) -> 0 | U45: =IF($B45="","",$A45&" "&$B45) -> OPP-41 電子處方與國家藥品資料庫介接 | V45: （待調查） | X45: =IF($A45="","",IFERROR(INDEX(16_能力商機矩陣_CapOppMap!$D$162:$CO$162,MATCH($A45,16_能力商機矩陣_CapOppMap!$D$4:$CO$4,0)),"")) -> 0 | Y45: =IF(OR($A45="",$H45=""),"",IF($H45=0,"",ROUND(0.45*$I45+0.35*$J45+0.2*IF(LEFT($F45,1)="③",5,IF(LEFT($F45,1)="②",3,1))-IF($K45>0,0.3,0),2)+ROW()/100000)) -> 3.69045 | Z45: =IF($Y45="","",RANK($Y45,$Y$5:$Y$94)) -> 29 | AA45: L4 資料平台層 | AB45: 重大更新：Circular 26/2025規定2025-10-01起所有醫院強制電子處方、其他機構2026-01-01起——成熟度應從「起步中」上調，市場由「要不要做」變「怎麼做完」。 | AC45: A | AD45: Circular 13/2025（2025-07-21生效，取代46/2018）：醫院限2025-09-30完成EMR、其他機構限2026-12-31。⚠期限已由Quyết định 965/QĐ-BYT（2026-04-10）改訂為2026-12-31完成、2027-01-01起停用紙本，2030年100%。完成率：2025-12-31為64.6%（1,062/1,645家），2026-04衛生部長稱逾75%已公告，衛生部登錄平台2026-08顯示1,260家。Circular 26/2025：2025-10-01起醫院強制電子處方。本土三強主導（FPT eHospital 6個月部署70+家、Viettel、VNPT）。數位健康市場2025年28.4億美元→2034年95.2億（CAGR 14.4%）。VNeID健康簿約3,280萬人（2026-07），Quyết định 31/QĐ-BYT（2026-01-06）已明定與紙本同等法律效力、機關不得再要求紙本。
A46: OPP-42 | B46: 閉環給藥與條碼用藥安全 | C46: Closed-loop Medication Administration | D46: E 醫療資訊與資料 | E46: 給藥掃碼、病人手圈、藥櫃管理；醫院藥劑部付錢 | F46: ③ 尚未出現：幾乎空白 | G46: =IF($A46="","",IF($H46=0,"（尚無對應能力）",IFERROR(INDEX(16_能力商機矩陣_CapOppMap!$D$160:$CO$160,MATCH($A46,16_能力商機矩陣_CapOppMap!$D$4:$CO$4,0)),""))) -> D06; D07 | H46: =IF($A46="","",IFERROR(INDEX(16_能力商機矩陣_CapOppMap!$D$156:$CO$156,MATCH($A46,16_能力商機矩陣_CapOppMap!$D$4:$CO$4,0)),"")) -> 2 | I46: =IF($A46="","",IFERROR(INDEX(16_能力商機矩陣_CapOppMap!$D$157:$CO$157,MATCH($A46,16_能力商機矩陣_CapOppMap!$D$4:$CO$4,0)),"")) -> 4.9 | J46: =IF($A46="","",IFERROR(INDEX(16_能力商機矩陣_CapOppMap!$D$158:$CO$158,MATCH($A46,16_能力商機矩陣_CapOppMap!$D$4:$CO$4,0)),"")) -> 2.7 | K46: =IF($A46="","",IFERROR(INDEX(16_能力商機矩陣_CapOppMap!$D$159:$CO$159,MATCH($A46,16_能力商機矩陣_CapOppMap!$D$4:$CO$4,0)),"")) -> 0 | L46: =IF($A46="","",IF($H46=0,"★白地商機：目前無對應能力，需新增能力或找新夥伴",IF($K46>0,"有缺口："&$K46&"項可對外招募","已有能力可承接"))) -> 已有能力可承接 | M46: G4 | N46: 醫院業主資本支出(CAPEX) | O46: 軟體授權／訂閱 | P46: 100K-500K USD | Q46: 需組合 | R46: Pharmacy Lead | S46: 是JCI與病安評鑑的重點項目，但越南導入率極低 | T46: =IF($A46="","",COUNTIF(14_商機清單_Pipeline!$A$5:$A$34,$U46)) -> 0 | U46: =IF($B46="","",$A46&" "&$B46) -> OPP-42 閉環給藥與條碼用藥安全 | V46: （待調查） | X46: =IF($A46="","",IFERROR(INDEX(16_能力商機矩陣_CapOppMap!$D$162:$CO$162,MATCH($A46,16_能力商機矩陣_CapOppMap!$D$4:$CO$4,0)),"")) -> 0 | Y46: =IF(OR($A46="",$H46=""),"",IF($H46=0,"",ROUND(0.45*$I46+0.35*$J46+0.2*IF(LEFT($F46,1)="③",5,IF(LEFT($F46,1)="②",3,1))-IF($K46>0,0.3,0),2)+ROW()/100000)) -> 4.15046 | Z46: =IF($Y46="","",RANK($Y46,$Y$5:$Y$94)) -> 3 | AA46: L4 資料平台層 | AB46: （本項無專屬發現——見同列右方的家族／領域趨勢，或 19／20 分頁） | AC46: B | AD46: Circular 13/2025（2025-07-21生效，取代46/2018）：醫院限2025-09-30完成EMR、其他機構限2026-12-31。⚠期限已由Quyết định 965/QĐ-BYT（2026-04-10）改訂為2026-12-31完成、2027-01-01起停用紙本，2030年100%。完成率：2025-12-31為64.6%（1,062/1,645家），2026-04衛生部長稱逾75%已公告，衛生部登錄平台2026-08顯示1,260家。Circular 26/2025：2025-10-01起醫院強制電子處方。本土三強主導（FPT eHospital 6個月部署70+家、Viettel、VNPT）。數位健康市場2025年28.4億美元→2034年95.2億（CAGR 14.4%）。VNeID健康簿約3,280萬人（2026-07），Quyết định 31/QĐ-BYT（2026-01-06）已明定與紙本同等法律效力、機關不得再要求紙本。
A47: OPP-43 | B47: 結核胸片AI篩檢(CAD) | C47: TB Chest X-ray CAD Screening | D47: F AI與智慧醫療 | E47: 每台X光機年授權，賣給國家結核防治計畫、省衛生局與國際捐助方案 | F47: ② 起步中：剛開始有人做 | G47: =IF($A47="","",IF($H47=0,"（尚無對應能力）",IFERROR(INDEX(16_能力商機矩陣_CapOppMap!$D$160:$CO$160,MATCH($A47,16_能力商機矩陣_CapOppMap!$D$4:$CO$4,0)),""))) -> （尚無對應能力） | H47: =IF($A47="","",IFERROR(INDEX(16_能力商機矩陣_CapOppMap!$D$156:$CO$156,MATCH($A47,16_能力商機矩陣_CapOppMap!$D$4:$CO$4,0)),"")) -> 0 | I47: =IF($A47="","",IFERROR(INDEX(16_能力商機矩陣_CapOppMap!$D$157:$CO$157,MATCH($A47,16_能力商機矩陣_CapOppMap!$D$4:$CO$4,0)),"")) | J47: =IF($A47="","",IFERROR(INDEX(16_能力商機矩陣_CapOppMap!$D$158:$CO$158,MATCH($A47,16_能力商機矩陣_CapOppMap!$D$4:$CO$4,0)),"")) | K47: =IF($A47="","",IFERROR(INDEX(16_能力商機矩陣_CapOppMap!$D$159:$CO$159,MATCH($A47,16_能力商機矩陣_CapOppMap!$D$4:$CO$4,0)),"")) -> 0 | L47: =IF($A47="","",IF($H47=0,"★白地商機：目前無對應能力，需新增能力或找新夥伴",IF($K47>0,"有缺口："&$K47&"項可對外招募","已有能力可承接"))) -> ★白地商機：目前無對應能力，需新增能力或找新夥伴 | M47: G3 | N47: 國際開發援助(ODA／世銀／ADB) | O47: ODA／贈款 | P47: 100K-500K USD | Q47: 是 | R47: Imaging Lead | S47: ★WHO 2025/6核准6項CAD產品；Unitaid/CHAI已把價格壓到每台X光機每年US$2500-2850。越南結核負擔全球第12、每年約18.2萬例——捐助資金＋政策背書都到位 | T47: =IF($A47="","",COUNTIF(14_商機清單_Pipeline!$A$5:$A$34,$U47)) -> 1 | U47: =IF($B47="","",$A47&" "&$B47) -> OPP-43 結核胸片AI篩檢(CAD) | V47: WHO 已核准6項CAD產品（Qure.ai qXR、Lunit INSIGHT 等） | W47: 不自研：代理＋篩檢巴士整合＋ODA 組案（Unitaid 已把價壓到每機每年US$2500-2850） | X47: =IF($A47="","",IFERROR(INDEX(16_能力商機矩陣_CapOppMap!$D$162:$CO$162,MATCH($A47,16_能力商機矩陣_CapOppMap!$D$4:$CO$4,0)),"")) -> 0 | Y47: =IF(OR($A47="",$H47=""),"",IF($H47=0,"",ROUND(0.45*$I47+0.35*$J47+0.2*IF(LEFT($F47,1)="③",5,IF(LEFT($F47,1)="②",3,1))-IF($K47>0,0.3,0),2)+ROW()/100000)) | Z47: =IF($Y47="","",RANK($Y47,$Y$5:$Y$94)) | AA47: L5 智慧應用層 | AB47: 證據最強的AI項目：qXR 3.0（USAID/NTP，9省57萬人篩檢）＋VinBrain×全球基金（32授權、目標100萬人、單例成本降至約1美元）。風險：USAID退場、國際經費下滑，買單方轉換中。年新發結核估18.2萬例。 | AC47: A | AD47: 結核AI已規模化：9省57萬人篩檢；VinBrain×全球基金32套授權、目標100萬人、單例成本從50-60美元降至約1美元。《數位科技產業法》2026-01-01生效（越南首部含AI專章法律）；AI專法草案2025-10徵詢中（風險分級、參考歐盟）。已實證：影像AI（結核、放射、內視鏡Olympus於Cho Ray/108醫院、眼底Orbis）；未查得實證：營運AI（排程、供應鏈、敗血症、申報審核）、數位病理、越南語臨床LLM——空白即機會，但需承擔市場教育成本。
A48: OPP-44 | B48: 放射影像分診AI（中風／出血／結節／骨折） | C48: Radiology Triage & Detection AI | D48: F AI與智慧醫療 | E48: 按檢查次數或每院年授權賣給影像科；醫院自付，健保沒有給付碼 | F48: ② 起步中：剛開始有人做 | G48: =IF($A48="","",IF($H48=0,"（尚無對應能力）",IFERROR(INDEX(16_能力商機矩陣_CapOppMap!$D$160:$CO$160,MATCH($A48,16_能力商機矩陣_CapOppMap!$D$4:$CO$4,0)),""))) -> D05; D06 | H48: =IF($A48="","",IFERROR(INDEX(16_能力商機矩陣_CapOppMap!$D$156:$CO$156,MATCH($A48,16_能力商機矩陣_CapOppMap!$D$4:$CO$4,0)),"")) -> 2 | I48: =IF($A48="","",IFERROR(INDEX(16_能力商機矩陣_CapOppMap!$D$157:$CO$157,MATCH($A48,16_能力商機矩陣_CapOppMap!$D$4:$CO$4,0)),"")) -> 4.9 | J48: =IF($A48="","",IFERROR(INDEX(16_能力商機矩陣_CapOppMap!$D$158:$CO$158,MATCH($A48,16_能力商機矩陣_CapOppMap!$D$4:$CO$4,0)),"")) -> 2.4 | K48: =IF($A48="","",IFERROR(INDEX(16_能力商機矩陣_CapOppMap!$D$159:$CO$159,MATCH($A48,16_能力商機矩陣_CapOppMap!$D$4:$CO$4,0)),"")) -> 1 | L48: =IF($A48="","",IF($H48=0,"★白地商機：目前無對應能力，需新增能力或找新夥伴",IF($K48>0,"有缺口："&$K48&"項可對外招募","已有能力可承接"))) -> 有缺口：1項可對外招募 | M48: G4 | N48: 醫院營運預算(OPEX) | O48: 軟體授權／訂閱 | P48: 100K-500K USD | Q48: 是 | R48: Imaging Lead | S48: 河內2026/3已在德江、聖保羅、腫瘤三家醫院試辦；VinBrain（已被NVIDIA收購）進入100+醫院但多為試用 | T48: =IF($A48="","",COUNTIF(14_商機清單_Pipeline!$A$5:$A$34,$U48)) -> 0 | U48: =IF($B48="","",$A48&" "&$B48) -> OPP-44 放射影像分診AI（中風／出血／結節／骨折） | V48: VinBrain（NVIDIA 已收購，進入100+醫院）；河內三院試辦中 | W48: 避開通用分診紅海，選利基病種＋與設備綁售 | X48: =IF($A48="","",IFERROR(INDEX(16_能力商機矩陣_CapOppMap!$D$162:$CO$162,MATCH($A48,16_能力商機矩陣_CapOppMap!$D$4:$CO$4,0)),"")) -> 0 | Y48: =IF(OR($A48="",$H48=""),"",IF($H48=0,"",ROUND(0.45*$I48+0.35*$J48+0.2*IF(LEFT($F48,1)="③",5,IF(LEFT($F48,1)="②",3,1))-IF($K48>0,0.3,0),2)+ROW()/100000)) -> 3.35048 | Z48: =IF($Y48="","",RANK($Y48,$Y$5:$Y$94)) -> 53 | AA48: L5 智慧應用層 | AB48: VinBrain DrAid宣稱部署100+醫院；Hoan My×Annalise.ai簽MoU（2023-04）——已有人做，競爭者具名。 | AC48: A | AD48: 結核AI已規模化：9省57萬人篩檢；VinBrain×全球基金32套授權、目標100萬人、單例成本從50-60美元降至約1美元。《數位科技產業法》2026-01-01生效（越南首部含AI專章法律）；AI專法草案2025-10徵詢中（風險分級、參考歐盟）。已實證：影像AI（結核、放射、內視鏡Olympus於Cho Ray/108醫院、眼底Orbis）；未查得實證：營運AI（排程、供應鏈、敗血症、申報審核）、數位病理、越南語臨床LLM——空白即機會，但需承擔市場教育成本。
A49: OPP-45 | B49: 肺癌CT早篩AI | C49: Lung Cancer CT Screening AI | D49: F AI與智慧醫療 | E49: 結節偵測與風險分層，搭自費健檢套餐按人次分潤 | F49: ② 起步中：剛開始有人做 | G49: =IF($A49="","",IF($H49=0,"（尚無對應能力）",IFERROR(INDEX(16_能力商機矩陣_CapOppMap!$D$160:$CO$160,MATCH($A49,16_能力商機矩陣_CapOppMap!$D$4:$CO$4,0)),""))) -> D05 | H49: =IF($A49="","",IFERROR(INDEX(16_能力商機矩陣_CapOppMap!$D$156:$CO$156,MATCH($A49,16_能力商機矩陣_CapOppMap!$D$4:$CO$4,0)),"")) -> 1 | I49: =IF($A49="","",IFERROR(INDEX(16_能力商機矩陣_CapOppMap!$D$157:$CO$157,MATCH($A49,16_能力商機矩陣_CapOppMap!$D$4:$CO$4,0)),"")) -> 4.7 | J49: =IF($A49="","",IFERROR(INDEX(16_能力商機矩陣_CapOppMap!$D$158:$CO$158,MATCH($A49,16_能力商機矩陣_CapOppMap!$D$4:$CO$4,0)),"")) -> 2.4 | K49: =IF($A49="","",IFERROR(INDEX(16_能力商機矩陣_CapOppMap!$D$159:$CO$159,MATCH($A49,16_能力商機矩陣_CapOppMap!$D$4:$CO$4,0)),"")) -> 1 | L49: =IF($A49="","",IF($H49=0,"★白地商機：目前無對應能力，需新增能力或找新夥伴",IF($K49>0,"有缺口："&$K49&"項可對外招募","已有能力可承接"))) -> 有缺口：1項可對外招募 | M49: G4 | N49: 病人自費 | O49: 分潤／服務分成 | P49: 100K-500K USD | Q49: 需組合 | R49: Imaging Lead | S49: 白梅醫院已有三個國家級肺癌AI模型（CT／即時支氣管鏡／病理）——在地國家隊會低價競爭，要挑差異化角度 | T49: =IF($A49="","",COUNTIF(14_商機清單_Pipeline!$A$5:$A$34,$U49)) -> 0 | U49: =IF($B49="","",$A49&" "&$B49) -> OPP-45 肺癌CT早篩AI | V49: 白梅醫院三個國家級肺癌AI模型（低價/免費推廣） | W49: 走自費健檢通路＋報告品質差異化，不與國家隊拚公立醫院端 | X49: =IF($A49="","",IFERROR(INDEX(16_能力商機矩陣_CapOppMap!$D$162:$CO$162,MATCH($A49,16_能力商機矩陣_CapOppMap!$D$4:$CO$4,0)),"")) -> 0 | Y49: =IF(OR($A49="",$H49=""),"",IF($H49=0,"",ROUND(0.45*$I49+0.35*$J49+0.2*IF(LEFT($F49,1)="③",5,IF(LEFT($F49,1)="②",3,1))-IF($K49>0,0.3,0),2)+ROW()/100000)) -> 3.26049 | Z49: =IF($Y49="","",RANK($Y49,$Y$5:$Y$94)) -> 60 | AA49: L5 智慧應用層 | AB49: （本項無專屬發現——見同列右方的家族／領域趨勢，或 19／20 分頁） | AC49: B | AD49: 結核AI已規模化：9省57萬人篩檢；VinBrain×全球基金32套授權、目標100萬人、單例成本從50-60美元降至約1美元。《數位科技產業法》2026-01-01生效（越南首部含AI專章法律）；AI專法草案2025-10徵詢中（風險分級、參考歐盟）。已實證：影像AI（結核、放射、內視鏡Olympus於Cho Ray/108醫院、眼底Orbis）；未查得實證：營運AI（排程、供應鏈、敗血症、申報審核）、數位病理、越南語臨床LLM——空白即機會，但需承擔市場教育成本。
A50: OPP-46 | B50: 內視鏡AI息肉偵測 | C50: Endoscopy AI (Polyp CADe) | D50: F AI與智慧醫療 | E50: 硬體模組隨內視鏡主機綁售，走設備商／代理商通路 | F50: ③ 尚未出現：幾乎空白 | G50: =IF($A50="","",IF($H50=0,"（尚無對應能力）",IFERROR(INDEX(16_能力商機矩陣_CapOppMap!$D$160:$CO$160,MATCH($A50,16_能力商機矩陣_CapOppMap!$D$4:$CO$4,0)),""))) -> D05 | H50: =IF($A50="","",IFERROR(INDEX(16_能力商機矩陣_CapOppMap!$D$156:$CO$156,MATCH($A50,16_能力商機矩陣_CapOppMap!$D$4:$CO$4,0)),"")) -> 1 | I50: =IF($A50="","",IFERROR(INDEX(16_能力商機矩陣_CapOppMap!$D$157:$CO$157,MATCH($A50,16_能力商機矩陣_CapOppMap!$D$4:$CO$4,0)),"")) -> 4.7 | J50: =IF($A50="","",IFERROR(INDEX(16_能力商機矩陣_CapOppMap!$D$158:$CO$158,MATCH($A50,16_能力商機矩陣_CapOppMap!$D$4:$CO$4,0)),"")) -> 2.4 | K50: =IF($A50="","",IFERROR(INDEX(16_能力商機矩陣_CapOppMap!$D$159:$CO$159,MATCH($A50,16_能力商機矩陣_CapOppMap!$D$4:$CO$4,0)),"")) -> 0 | L50: =IF($A50="","",IF($H50=0,"★白地商機：目前無對應能力，需新增能力或找新夥伴",IF($K50>0,"有缺口："&$K50&"項可對外招募","已有能力可承接"))) -> 已有能力可承接 | M50: G4 | N50: 醫院業主資本支出(CAPEX) | O50: 設備銷售＋耗材 | P50: 100K-500K USD | Q50: 是 | R50: Clinical Engineering Lead | S50: ★與已註冊硬體綁售可免除單獨的軟體醫材許可，是所有醫療AI裡最省法規事的通路打法 | T50: =IF($A50="","",COUNTIF(14_商機清單_Pipeline!$A$5:$A$34,$U50)) -> 0 | U50: =IF($B50="","",$A50&" "&$B50) -> OPP-46 內視鏡AI息肉偵測 | V50: （待調查） | X50: =IF($A50="","",IFERROR(INDEX(16_能力商機矩陣_CapOppMap!$D$162:$CO$162,MATCH($A50,16_能力商機矩陣_CapOppMap!$D$4:$CO$4,0)),"")) -> 0 | Y50: =IF(OR($A50="",$H50=""),"",IF($H50=0,"",ROUND(0.45*$I50+0.35*$J50+0.2*IF(LEFT($F50,1)="③",5,IF(LEFT($F50,1)="②",3,1))-IF($K50>0,0.3,0),2)+ROW()/100000)) -> 3.9605 | Z50: =IF($Y50="","",RANK($Y50,$Y$5:$Y$94)) -> 9 | AA50: L5 智慧應用層 | AB50: Olympus EndoBRAIN-EYE已在Cho Ray、108軍醫院完成驗證（2022-11至2023-03，日本總務省計畫）；常規採購未查得。 | AC50: A | AD50: 結核AI已規模化：9省57萬人篩檢；VinBrain×全球基金32套授權、目標100萬人、單例成本從50-60美元降至約1美元。《數位科技產業法》2026-01-01生效（越南首部含AI專章法律）；AI專法草案2025-10徵詢中（風險分級、參考歐盟）。已實證：影像AI（結核、放射、內視鏡Olympus於Cho Ray/108醫院、眼底Orbis）；未查得實證：營運AI（排程、供應鏈、敗血症、申報審核）、數位病理、越南語臨床LLM——空白即機會，但需承擔市場教育成本。
A51: OPP-47 | B51: 糖尿病視網膜病變AI篩檢 | C51: Diabetic Retinopathy Screening AI | D51: F AI與智慧醫療 | E51: 按篩檢人次或眼底相機綁售；搭慢性病篩檢方案或自費健檢 | F51: ③ 尚未出現：幾乎空白 | G51: =IF($A51="","",IF($H51=0,"（尚無對應能力）",IFERROR(INDEX(16_能力商機矩陣_CapOppMap!$D$160:$CO$160,MATCH($A51,16_能力商機矩陣_CapOppMap!$D$4:$CO$4,0)),""))) -> （尚無對應能力） | H51: =IF($A51="","",IFERROR(INDEX(16_能力商機矩陣_CapOppMap!$D$156:$CO$156,MATCH($A51,16_能力商機矩陣_CapOppMap!$D$4:$CO$4,0)),"")) -> 0 | I51: =IF($A51="","",IFERROR(INDEX(16_能力商機矩陣_CapOppMap!$D$157:$CO$157,MATCH($A51,16_能力商機矩陣_CapOppMap!$D$4:$CO$4,0)),"")) | J51: =IF($A51="","",IFERROR(INDEX(16_能力商機矩陣_CapOppMap!$D$158:$CO$158,MATCH($A51,16_能力商機矩陣_CapOppMap!$D$4:$CO$4,0)),"")) | K51: =IF($A51="","",IFERROR(INDEX(16_能力商機矩陣_CapOppMap!$D$159:$CO$159,MATCH($A51,16_能力商機矩陣_CapOppMap!$D$4:$CO$4,0)),"")) -> 0 | L51: =IF($A51="","",IF($H51=0,"★白地商機：目前無對應能力，需新增能力或找新夥伴",IF($K51>0,"有缺口："&$K51&"項可對外招募","已有能力可承接"))) -> ★白地商機：目前無對應能力，需新增能力或找新夥伴 | M51: G4 | N51: 省級衛生局預算 | O51: 分潤／服務分成 | P51: 100K-500K USD | Q51: 需組合 | R51: Clinical Planner | S51: 糖尿病人口大、眼科醫師少；沒有健保給付碼，一定要掛在篩檢方案或健檢套餐底下才有付費方 | T51: =IF($A51="","",COUNTIF(14_商機清單_Pipeline!$A$5:$A$34,$U51)) -> 0 | U51: =IF($B51="","",$A51&" "&$B51) -> OPP-47 糖尿病視網膜病變AI篩檢 | V51: （待調查） | X51: =IF($A51="","",IFERROR(INDEX(16_能力商機矩陣_CapOppMap!$D$162:$CO$162,MATCH($A51,16_能力商機矩陣_CapOppMap!$D$4:$CO$4,0)),"")) -> 0 | Y51: =IF(OR($A51="",$H51=""),"",IF($H51=0,"",ROUND(0.45*$I51+0.35*$J51+0.2*IF(LEFT($F51,1)="③",5,IF(LEFT($F51,1)="②",3,1))-IF($K51>0,0.3,0),2)+ROW()/100000)) | Z51: =IF($Y51="","",RANK($Y51,$Y$5:$Y$94)) | AA51: L5 智慧應用層 | AB51: Orbis Cybersight AI 2024年起在越南啟動眼底篩檢；全國性計畫未查得。 | AC51: A | AD51: 結核AI已規模化：9省57萬人篩檢；VinBrain×全球基金32套授權、目標100萬人、單例成本從50-60美元降至約1美元。《數位科技產業法》2026-01-01生效（越南首部含AI專章法律）；AI專法草案2025-10徵詢中（風險分級、參考歐盟）。已實證：影像AI（結核、放射、內視鏡Olympus於Cho Ray/108醫院、眼底Orbis）；未查得實證：營運AI（排程、供應鏈、敗血症、申報審核）、數位病理、越南語臨床LLM——空白即機會，但需承擔市場教育成本。
A52: OPP-48 | B52: 病理數位化與AI判讀 | C52: Digital Pathology & AI | D52: F AI與智慧醫療 | E52: 全玻片掃描器＋AI判讀；賣給中央／腫瘤醫院與私立檢驗連鎖 | F52: ③ 尚未出現：幾乎空白 | G52: =IF($A52="","",IF($H52=0,"（尚無對應能力）",IFERROR(INDEX(16_能力商機矩陣_CapOppMap!$D$160:$CO$160,MATCH($A52,16_能力商機矩陣_CapOppMap!$D$4:$CO$4,0)),""))) -> （尚無對應能力） | H52: =IF($A52="","",IFERROR(INDEX(16_能力商機矩陣_CapOppMap!$D$156:$CO$156,MATCH($A52,16_能力商機矩陣_CapOppMap!$D$4:$CO$4,0)),"")) -> 0 | I52: =IF($A52="","",IFERROR(INDEX(16_能力商機矩陣_CapOppMap!$D$157:$CO$157,MATCH($A52,16_能力商機矩陣_CapOppMap!$D$4:$CO$4,0)),"")) | J52: =IF($A52="","",IFERROR(INDEX(16_能力商機矩陣_CapOppMap!$D$158:$CO$158,MATCH($A52,16_能力商機矩陣_CapOppMap!$D$4:$CO$4,0)),"")) | K52: =IF($A52="","",IFERROR(INDEX(16_能力商機矩陣_CapOppMap!$D$159:$CO$159,MATCH($A52,16_能力商機矩陣_CapOppMap!$D$4:$CO$4,0)),"")) -> 0 | L52: =IF($A52="","",IF($H52=0,"★白地商機：目前無對應能力，需新增能力或找新夥伴",IF($K52>0,"有缺口："&$K52&"項可對外招募","已有能力可承接"))) -> ★白地商機：目前無對應能力，需新增能力或找新夥伴 | M52: G5 | N52: 醫院業主資本支出(CAPEX) | O52: 設備銷售＋耗材 | P52: 500K-2M USD | Q52: 需組合 | R52: Laboratory Lead | S52: 卡在掃描器基數太小（每台US$100-250k），現實上是2028年以後的題目，但可以先卡位 | T52: =IF($A52="","",COUNTIF(14_商機清單_Pipeline!$A$5:$A$34,$U52)) -> 0 | U52: =IF($B52="","",$A52&" "&$B52) -> OPP-48 病理數位化與AI判讀 | V52: 掃描器基數極小，暫無在地玩家 | W52: 先卡位腫瘤中心合作，隨 OPP-15 放腫整案綁入 | X52: =IF($A52="","",IFERROR(INDEX(16_能力商機矩陣_CapOppMap!$D$162:$CO$162,MATCH($A52,16_能力商機矩陣_CapOppMap!$D$4:$CO$4,0)),"")) -> 0 | Y52: =IF(OR($A52="",$H52=""),"",IF($H52=0,"",ROUND(0.45*$I52+0.35*$J52+0.2*IF(LEFT($F52,1)="③",5,IF(LEFT($F52,1)="②",3,1))-IF($K52>0,0.3,0),2)+ROW()/100000)) | Z52: =IF($Y52="","",RANK($Y52,$Y$5:$Y$94)) | AA52: L5 智慧應用層 | AB52: 越南本地部署實證未查得——真空白，需自帶市場教育。 | AC52: C | AD52: 結核AI已規模化：9省57萬人篩檢；VinBrain×全球基金32套授權、目標100萬人、單例成本從50-60美元降至約1美元。《數位科技產業法》2026-01-01生效（越南首部含AI專章法律）；AI專法草案2025-10徵詢中（風險分級、參考歐盟）。已實證：影像AI（結核、放射、內視鏡Olympus於Cho Ray/108醫院、眼底Orbis）；未查得實證：營運AI（排程、供應鏈、敗血症、申報審核）、數位病理、越南語臨床LLM——空白即機會，但需承擔市場教育成本。
A53: OPP-49 | B53: 越南語AI病歷書寫助理 | C53: Vietnamese Ambient Clinical Documentation | D53: F AI與智慧醫療 | E53: 按醫師人數月費訂閱，把看診對話自動變成病歷；醫院營運預算或私立連鎖付錢 | F53: ③ 尚未出現：幾乎空白 | G53: =IF($A53="","",IF($H53=0,"（尚無對應能力）",IFERROR(INDEX(16_能力商機矩陣_CapOppMap!$D$160:$CO$160,MATCH($A53,16_能力商機矩陣_CapOppMap!$D$4:$CO$4,0)),""))) -> （尚無對應能力） | H53: =IF($A53="","",IFERROR(INDEX(16_能力商機矩陣_CapOppMap!$D$156:$CO$156,MATCH($A53,16_能力商機矩陣_CapOppMap!$D$4:$CO$4,0)),"")) -> 0 | I53: =IF($A53="","",IFERROR(INDEX(16_能力商機矩陣_CapOppMap!$D$157:$CO$157,MATCH($A53,16_能力商機矩陣_CapOppMap!$D$4:$CO$4,0)),"")) | J53: =IF($A53="","",IFERROR(INDEX(16_能力商機矩陣_CapOppMap!$D$158:$CO$158,MATCH($A53,16_能力商機矩陣_CapOppMap!$D$4:$CO$4,0)),"")) | K53: =IF($A53="","",IFERROR(INDEX(16_能力商機矩陣_CapOppMap!$D$159:$CO$159,MATCH($A53,16_能力商機矩陣_CapOppMap!$D$4:$CO$4,0)),"")) -> 0 | L53: =IF($A53="","",IF($H53=0,"★白地商機：目前無對應能力，需新增能力或找新夥伴",IF($K53>0,"有缺口："&$K53&"項可對外招募","已有能力可承接"))) -> ★白地商機：目前無對應能力，需新增能力或找新夥伴 | M53: G4 | N53: 醫院營運預算(OPEX) | O53: 軟體授權／訂閱 | P53: 100K-500K USD | Q53: 是 | R53: Health IT Lead | S53: ★最大的白地：越南語醫療語音辨識是護城河、不依賴健保給付，而且無紙化病歷政策直接製造需求 | T53: =IF($A53="","",COUNTIF(14_商機清單_Pipeline!$A$5:$A$34,$U53)) -> 1 | U53: =IF($B53="","",$A53&" "&$B53) -> OPP-49 越南語AI病歷書寫助理 | V53: 無越南語成熟產品 | W53: 越南語醫療語音是護城河；與 HIS 商白標合作進場 | X53: =IF($A53="","",IFERROR(INDEX(16_能力商機矩陣_CapOppMap!$D$162:$CO$162,MATCH($A53,16_能力商機矩陣_CapOppMap!$D$4:$CO$4,0)),"")) -> 0 | Y53: =IF(OR($A53="",$H53=""),"",IF($H53=0,"",ROUND(0.45*$I53+0.35*$J53+0.2*IF(LEFT($F53,1)="③",5,IF(LEFT($F53,1)="②",3,1))-IF($K53>0,0.3,0),2)+ROW()/100000)) | Z53: =IF($Y53="","",RANK($Y53,$Y$5:$Y$94)) | AA53: L5 智慧應用層 | AB53: 具名的越南語臨床LLM/AI scribe上線案例未查得——空白即機會，但需自建越南語語料。 | AC53: C | AD53: 結核AI已規模化：9省57萬人篩檢；VinBrain×全球基金32套授權、目標100萬人、單例成本從50-60美元降至約1美元。《數位科技產業法》2026-01-01生效（越南首部含AI專章法律）；AI專法草案2025-10徵詢中（風險分級、參考歐盟）。已實證：影像AI（結核、放射、內視鏡Olympus於Cho Ray/108醫院、眼底Orbis）；未查得實證：營運AI（排程、供應鏈、敗血症、申報審核）、數位病理、越南語臨床LLM——空白即機會，但需承擔市場教育成本。
A54: OPP-50 | B54: 臨床大模型助理與知識庫 | C54: Clinical LLM Assistant | D54: F AI與智慧醫療 | E54: 院級授權的臨床問答、病歷摘要與指引查詢；也可白標給HIS廠商 | F54: ③ 尚未出現：幾乎空白 | G54: =IF($A54="","",IF($H54=0,"（尚無對應能力）",IFERROR(INDEX(16_能力商機矩陣_CapOppMap!$D$160:$CO$160,MATCH($A54,16_能力商機矩陣_CapOppMap!$D$4:$CO$4,0)),""))) -> （尚無對應能力） | H54: =IF($A54="","",IFERROR(INDEX(16_能力商機矩陣_CapOppMap!$D$156:$CO$156,MATCH($A54,16_能力商機矩陣_CapOppMap!$D$4:$CO$4,0)),"")) -> 0 | I54: =IF($A54="","",IFERROR(INDEX(16_能力商機矩陣_CapOppMap!$D$157:$CO$157,MATCH($A54,16_能力商機矩陣_CapOppMap!$D$4:$CO$4,0)),"")) | J54: =IF($A54="","",IFERROR(INDEX(16_能力商機矩陣_CapOppMap!$D$158:$CO$158,MATCH($A54,16_能力商機矩陣_CapOppMap!$D$4:$CO$4,0)),"")) | K54: =IF($A54="","",IFERROR(INDEX(16_能力商機矩陣_CapOppMap!$D$159:$CO$159,MATCH($A54,16_能力商機矩陣_CapOppMap!$D$4:$CO$4,0)),"")) -> 0 | L54: =IF($A54="","",IF($H54=0,"★白地商機：目前無對應能力，需新增能力或找新夥伴",IF($K54>0,"有缺口："&$K54&"項可對外招募","已有能力可承接"))) -> ★白地商機：目前無對應能力，需新增能力或找新夥伴 | M54: G5 | N54: 醫院營運預算(OPEX) | O54: 軟體授權／訂閱 | P54: 100K-500K USD | Q54: 需組合 | R54: Health IT Lead | S54: 越南AI法（2026/3/1生效）把醫療列為高風險：須登記、留存訓練資料與操作紀錄、外商要有在地法律代表 | T54: =IF($A54="","",COUNTIF(14_商機清單_Pipeline!$A$5:$A$34,$U54)) -> 0 | U54: =IF($B54="","",$A54&" "&$B54) -> OPP-50 臨床大模型助理與知識庫 | V54: VinBrain 與國際大廠通用模型可能進入 | W54: 合規包裝（AI法高風險文件）＋院內部署（資料不出院區） | X54: =IF($A54="","",IFERROR(INDEX(16_能力商機矩陣_CapOppMap!$D$162:$CO$162,MATCH($A54,16_能力商機矩陣_CapOppMap!$D$4:$CO$4,0)),"")) -> 0 | Y54: =IF(OR($A54="",$H54=""),"",IF($H54=0,"",ROUND(0.45*$I54+0.35*$J54+0.2*IF(LEFT($F54,1)="③",5,IF(LEFT($F54,1)="②",3,1))-IF($K54>0,0.3,0),2)+ROW()/100000)) | Z54: =IF($Y54="","",RANK($Y54,$Y$5:$Y$94)) | AA54: L5 智慧應用層 | AB54: （本項無專屬發現——見同列右方的家族／領域趨勢，或 19／20 分頁） | AC54: B | AD54: 結核AI已規模化：9省57萬人篩檢；VinBrain×全球基金32套授權、目標100萬人、單例成本從50-60美元降至約1美元。《數位科技產業法》2026-01-01生效（越南首部含AI專章法律）；AI專法草案2025-10徵詢中（風險分級、參考歐盟）。已實證：影像AI（結核、放射、內視鏡Olympus於Cho Ray/108醫院、眼底Orbis）；未查得實證：營運AI（排程、供應鏈、敗血症、申報審核）、數位病理、越南語臨床LLM——空白即機會，但需承擔市場教育成本。
A55: OPP-51 | B55: 健保申報AI審核與拒付管理 | C55: Claims Audit & Denial Management AI | D55: F AI與智慧醫療 | E55: 付費方側：替越南社會保險自動審核申報、抓高編與拆帳；醫院側：送件前先自我檢查 | F55: ③ 尚未出現：幾乎空白 | G55: =IF($A55="","",IF($H55=0,"（尚無對應能力）",IFERROR(INDEX(16_能力商機矩陣_CapOppMap!$D$160:$CO$160,MATCH($A55,16_能力商機矩陣_CapOppMap!$D$4:$CO$4,0)),""))) -> D10 | H55: =IF($A55="","",IFERROR(INDEX(16_能力商機矩陣_CapOppMap!$D$156:$CO$156,MATCH($A55,16_能力商機矩陣_CapOppMap!$D$4:$CO$4,0)),"")) -> 1 | I55: =IF($A55="","",IFERROR(INDEX(16_能力商機矩陣_CapOppMap!$D$157:$CO$157,MATCH($A55,16_能力商機矩陣_CapOppMap!$D$4:$CO$4,0)),"")) -> 4.1 | J55: =IF($A55="","",IFERROR(INDEX(16_能力商機矩陣_CapOppMap!$D$158:$CO$158,MATCH($A55,16_能力商機矩陣_CapOppMap!$D$4:$CO$4,0)),"")) -> 2 | K55: =IF($A55="","",IFERROR(INDEX(16_能力商機矩陣_CapOppMap!$D$159:$CO$159,MATCH($A55,16_能力商機矩陣_CapOppMap!$D$4:$CO$4,0)),"")) -> 1 | L55: =IF($A55="","",IF($H55=0,"★白地商機：目前無對應能力，需新增能力或找新夥伴",IF($K55>0,"有缺口："&$K55&"項可對外招募","已有能力可承接"))) -> 有缺口：1項可對外招募 | M55: G5 | N55: 越南健保(VSS)給付 | O55: 分潤／服務分成 | P55: 100K-500K USD | Q55: 需組合 | R55: Revenue Cycle Lead | S55: 付費方(VSS)側是更好的門：單一買方、追回金額就是可量化的ROI | T55: =IF($A55="","",COUNTIF(14_商機清單_Pipeline!$A$5:$A$34,$U55)) -> 0 | U55: =IF($B55="","",$A55&" "&$B55) -> OPP-51 健保申報AI審核與拒付管理 | V55: （待調查） | X55: =IF($A55="","",IFERROR(INDEX(16_能力商機矩陣_CapOppMap!$D$162:$CO$162,MATCH($A55,16_能力商機矩陣_CapOppMap!$D$4:$CO$4,0)),"")) -> 0 | Y55: =IF(OR($A55="",$H55=""),"",IF($H55=0,"",ROUND(0.45*$I55+0.35*$J55+0.2*IF(LEFT($F55,1)="③",5,IF(LEFT($F55,1)="②",3,1))-IF($K55>0,0.3,0),2)+ROW()/100000)) -> 3.25055 | Z55: =IF($Y55="","",RANK($Y55,$Y$5:$Y$94)) -> 65 | AA55: L5 智慧應用層 | AB55: VSS已有連接12,000+機構的規則式電子審查系統；AI化升級案未查得＝明確缺口。DRG準備期（資料庫＋分組軟體建置中）正是切入窗口。 | AC55: A | AD55: 結核AI已規模化：9省57萬人篩檢；VinBrain×全球基金32套授權、目標100萬人、單例成本從50-60美元降至約1美元。《數位科技產業法》2026-01-01生效（越南首部含AI專章法律）；AI專法草案2025-10徵詢中（風險分級、參考歐盟）。已實證：影像AI（結核、放射、內視鏡Olympus於Cho Ray/108醫院、眼底Orbis）；未查得實證：營運AI（排程、供應鏈、敗血症、申報審核）、數位病理、越南語臨床LLM——空白即機會，但需承擔市場教育成本。
A56: OPP-52 | B56: 病床病人流AI與手術室排程優化 | C56: Patient Flow & OR Scheduling AI | D56: F AI與智慧醫療 | E56: 預測住院量、出院規劃、手術室檔期釋出與使用率優化；醫院年費訂閱 | F56: ③ 尚未出現：幾乎空白 | G56: =IF($A56="","",IF($H56=0,"（尚無對應能力）",IFERROR(INDEX(16_能力商機矩陣_CapOppMap!$D$160:$CO$160,MATCH($A56,16_能力商機矩陣_CapOppMap!$D$4:$CO$4,0)),""))) -> D04; D09 | H56: =IF($A56="","",IFERROR(INDEX(16_能力商機矩陣_CapOppMap!$D$156:$CO$156,MATCH($A56,16_能力商機矩陣_CapOppMap!$D$4:$CO$4,0)),"")) -> 2 | I56: =IF($A56="","",IFERROR(INDEX(16_能力商機矩陣_CapOppMap!$D$157:$CO$157,MATCH($A56,16_能力商機矩陣_CapOppMap!$D$4:$CO$4,0)),"")) -> 3.7 | J56: =IF($A56="","",IFERROR(INDEX(16_能力商機矩陣_CapOppMap!$D$158:$CO$158,MATCH($A56,16_能力商機矩陣_CapOppMap!$D$4:$CO$4,0)),"")) -> 3.4 | K56: =IF($A56="","",IFERROR(INDEX(16_能力商機矩陣_CapOppMap!$D$159:$CO$159,MATCH($A56,16_能力商機矩陣_CapOppMap!$D$4:$CO$4,0)),"")) -> 0 | L56: =IF($A56="","",IF($H56=0,"★白地商機：目前無對應能力，需新增能力或找新夥伴",IF($K56>0,"有缺口："&$K56&"項可對外招募","已有能力可承接"))) -> 已有能力可承接 | M56: G5 | N56: 醫院營運預算(OPEX) | O56: 軟體授權／訂閱 | P56: 100K-500K USD | Q56: 需組合 | R56: Data/Analytics Lead | S56: 每搶回一個手術室小時就是可計價的收入，是所有營運AI裡ROI最硬的一項 | T56: =IF($A56="","",COUNTIF(14_商機清單_Pipeline!$A$5:$A$34,$U56)) -> 0 | U56: =IF($B56="","",$A56&" "&$B56) -> OPP-52 病床病人流AI與手術室排程優化 | V56: （待調查） | X56: =IF($A56="","",IFERROR(INDEX(16_能力商機矩陣_CapOppMap!$D$162:$CO$162,MATCH($A56,16_能力商機矩陣_CapOppMap!$D$4:$CO$4,0)),"")) -> 2 | Y56: =IF(OR($A56="",$H56=""),"",IF($H56=0,"",ROUND(0.45*$I56+0.35*$J56+0.2*IF(LEFT($F56,1)="③",5,IF(LEFT($F56,1)="②",3,1))-IF($K56>0,0.3,0),2)+ROW()/100000)) -> 3.86056 | Z56: =IF($Y56="","",RANK($Y56,$Y$5:$Y$94)) -> 16 | AA56: L5 智慧應用層 | AB56: （本項無專屬發現——見同列右方的家族／領域趨勢，或 19／20 分頁） | AC56: B | AD56: 結核AI已規模化：9省57萬人篩檢；VinBrain×全球基金32套授權、目標100萬人、單例成本從50-60美元降至約1美元。《數位科技產業法》2026-01-01生效（越南首部含AI專章法律）；AI專法草案2025-10徵詢中（風險分級、參考歐盟）。已實證：影像AI（結核、放射、內視鏡Olympus於Cho Ray/108醫院、眼底Orbis）；未查得實證：營運AI（排程、供應鏈、敗血症、申報審核）、數位病理、越南語臨床LLM——空白即機會，但需承擔市場教育成本。
A57: OPP-53 | B57: 藥品耗材需求預測AI | C57: Pharmacy & Supply Chain Forecasting AI | D57: F AI與智慧醫療 | E57: 需求預測與自動補貨；醫院藥劑／採購付錢，或由經銷商買單綁住客戶 | F57: ③ 尚未出現：幾乎空白 | G57: =IF($A57="","",IF($H57=0,"（尚無對應能力）",IFERROR(INDEX(16_能力商機矩陣_CapOppMap!$D$160:$CO$160,MATCH($A57,16_能力商機矩陣_CapOppMap!$D$4:$CO$4,0)),""))) -> D09 | H57: =IF($A57="","",IFERROR(INDEX(16_能力商機矩陣_CapOppMap!$D$156:$CO$156,MATCH($A57,16_能力商機矩陣_CapOppMap!$D$4:$CO$4,0)),"")) -> 2 | I57: =IF($A57="","",IFERROR(INDEX(16_能力商機矩陣_CapOppMap!$D$157:$CO$157,MATCH($A57,16_能力商機矩陣_CapOppMap!$D$4:$CO$4,0)),"")) -> 3.9 | J57: =IF($A57="","",IFERROR(INDEX(16_能力商機矩陣_CapOppMap!$D$158:$CO$158,MATCH($A57,16_能力商機矩陣_CapOppMap!$D$4:$CO$4,0)),"")) -> 3 | K57: =IF($A57="","",IFERROR(INDEX(16_能力商機矩陣_CapOppMap!$D$159:$CO$159,MATCH($A57,16_能力商機矩陣_CapOppMap!$D$4:$CO$4,0)),"")) -> 0 | L57: =IF($A57="","",IF($H57=0,"★白地商機：目前無對應能力，需新增能力或找新夥伴",IF($K57>0,"有缺口："&$K57&"項可對外招募","已有能力可承接"))) -> 已有能力可承接 | M57: G5 | N57: 醫院營運預算(OPEX) | O57: 軟體授權／訂閱 | P57: 100K-500K USD | Q57: 需組合 | R57: Supply Chain Lead | S57: 越南反覆發生缺藥事件、政治敏感度高；走經銷商通路是最快的路徑 | T57: =IF($A57="","",COUNTIF(14_商機清單_Pipeline!$A$5:$A$34,$U57)) -> 0 | U57: =IF($B57="","",$A57&" "&$B57) -> OPP-53 藥品耗材需求預測AI | V57: （待調查） | X57: =IF($A57="","",IFERROR(INDEX(16_能力商機矩陣_CapOppMap!$D$162:$CO$162,MATCH($A57,16_能力商機矩陣_CapOppMap!$D$4:$CO$4,0)),"")) -> 0 | Y57: =IF(OR($A57="",$H57=""),"",IF($H57=0,"",ROUND(0.45*$I57+0.35*$J57+0.2*IF(LEFT($F57,1)="③",5,IF(LEFT($F57,1)="②",3,1))-IF($K57>0,0.3,0),2)+ROW()/100000)) -> 3.81057 | Z57: =IF($Y57="","",RANK($Y57,$Y$5:$Y$94)) -> 21 | AA57: L5 智慧應用層 | AB57: （本項無專屬發現——見同列右方的家族／領域趨勢，或 19／20 分頁） | AC57: B | AD57: 結核AI已規模化：9省57萬人篩檢；VinBrain×全球基金32套授權、目標100萬人、單例成本從50-60美元降至約1美元。《數位科技產業法》2026-01-01生效（越南首部含AI專章法律）；AI專法草案2025-10徵詢中（風險分級、參考歐盟）。已實證：影像AI（結核、放射、內視鏡Olympus於Cho Ray/108醫院、眼底Orbis）；未查得實證：營運AI（排程、供應鏈、敗血症、申報審核）、數位病理、越南語臨床LLM——空白即機會，但需承擔市場教育成本。
A58: OPP-54 | B58: 設備預測維護與能耗優化AI | C58: Predictive Maintenance & Energy AI | D58: F AI與智慧醫療 | E58: 影像設備妥善率與空調冰水主機能耗優化，用實測節省額分成 | F58: ③ 尚未出現：幾乎空白 | G58: =IF($A58="","",IF($H58=0,"（尚無對應能力）",IFERROR(INDEX(16_能力商機矩陣_CapOppMap!$D$160:$CO$160,MATCH($A58,16_能力商機矩陣_CapOppMap!$D$4:$CO$4,0)),""))) -> D05; D09 | H58: =IF($A58="","",IFERROR(INDEX(16_能力商機矩陣_CapOppMap!$D$156:$CO$156,MATCH($A58,16_能力商機矩陣_CapOppMap!$D$4:$CO$4,0)),"")) -> 2 | I58: =IF($A58="","",IFERROR(INDEX(16_能力商機矩陣_CapOppMap!$D$157:$CO$157,MATCH($A58,16_能力商機矩陣_CapOppMap!$D$4:$CO$4,0)),"")) -> 4.2 | J58: =IF($A58="","",IFERROR(INDEX(16_能力商機矩陣_CapOppMap!$D$158:$CO$158,MATCH($A58,16_能力商機矩陣_CapOppMap!$D$4:$CO$4,0)),"")) -> 2.9 | K58: =IF($A58="","",IFERROR(INDEX(16_能力商機矩陣_CapOppMap!$D$159:$CO$159,MATCH($A58,16_能力商機矩陣_CapOppMap!$D$4:$CO$4,0)),"")) -> 0 | L58: =IF($A58="","",IF($H58=0,"★白地商機：目前無對應能力，需新增能力或找新夥伴",IF($K58>0,"有缺口："&$K58&"項可對外招募","已有能力可承接"))) -> 已有能力可承接 | M58: G5 | N58: 醫院營運預算(OPEX) | O58: 分潤／服務分成 | P58: 100K-500K USD | Q58: 需組合 | R58: FM Lead | S58: 能耗這一半可以自籌財源、不需臨床法規核准，是最容易先做起來的AI應用 | T58: =IF($A58="","",COUNTIF(14_商機清單_Pipeline!$A$5:$A$34,$U58)) -> 0 | U58: =IF($B58="","",$A58&" "&$B58) -> OPP-54 設備預測維護與能耗優化AI | V58: （待調查） | X58: =IF($A58="","",IFERROR(INDEX(16_能力商機矩陣_CapOppMap!$D$162:$CO$162,MATCH($A58,16_能力商機矩陣_CapOppMap!$D$4:$CO$4,0)),"")) -> 1 | Y58: =IF(OR($A58="",$H58=""),"",IF($H58=0,"",ROUND(0.45*$I58+0.35*$J58+0.2*IF(LEFT($F58,1)="③",5,IF(LEFT($F58,1)="②",3,1))-IF($K58>0,0.3,0),2)+ROW()/100000)) -> 3.91058 | Z58: =IF($Y58="","",RANK($Y58,$Y$5:$Y$94)) -> 13 | AA58: L5 智慧應用層 | AB58: （本項無專屬發現——見同列右方的家族／領域趨勢，或 19／20 分頁） | AC58: B | AD58: 結核AI已規模化：9省57萬人篩檢；VinBrain×全球基金32套授權、目標100萬人、單例成本從50-60美元降至約1美元。《數位科技產業法》2026-01-01生效（越南首部含AI專章法律）；AI專法草案2025-10徵詢中（風險分級、參考歐盟）。已實證：影像AI（結核、放射、內視鏡Olympus於Cho Ray/108醫院、眼底Orbis）；未查得實證：營運AI（排程、供應鏈、敗血症、申報審核）、數位病理、越南語臨床LLM——空白即機會，但需承擔市場教育成本。
A59: OPP-55 | B59: 敗血症與病情惡化預警AI | C59: Sepsis & Deterioration Early Warning AI | D59: F AI與智慧醫療 | E59: 即時生命徵象與檢驗值預警，按床或按院授權給ICU與急診 | F59: ③ 尚未出現：幾乎空白 | G59: =IF($A59="","",IF($H59=0,"（尚無對應能力）",IFERROR(INDEX(16_能力商機矩陣_CapOppMap!$D$160:$CO$160,MATCH($A59,16_能力商機矩陣_CapOppMap!$D$4:$CO$4,0)),""))) -> （尚無對應能力） | H59: =IF($A59="","",IFERROR(INDEX(16_能力商機矩陣_CapOppMap!$D$156:$CO$156,MATCH($A59,16_能力商機矩陣_CapOppMap!$D$4:$CO$4,0)),"")) -> 0 | I59: =IF($A59="","",IFERROR(INDEX(16_能力商機矩陣_CapOppMap!$D$157:$CO$157,MATCH($A59,16_能力商機矩陣_CapOppMap!$D$4:$CO$4,0)),"")) | J59: =IF($A59="","",IFERROR(INDEX(16_能力商機矩陣_CapOppMap!$D$158:$CO$158,MATCH($A59,16_能力商機矩陣_CapOppMap!$D$4:$CO$4,0)),"")) | K59: =IF($A59="","",IFERROR(INDEX(16_能力商機矩陣_CapOppMap!$D$159:$CO$159,MATCH($A59,16_能力商機矩陣_CapOppMap!$D$4:$CO$4,0)),"")) -> 0 | L59: =IF($A59="","",IF($H59=0,"★白地商機：目前無對應能力，需新增能力或找新夥伴",IF($K59>0,"有缺口："&$K59&"項可對外招募","已有能力可承接"))) -> ★白地商機：目前無對應能力，需新增能力或找新夥伴 | M59: G5 | N59: 醫院營運預算(OPEX) | O59: 軟體授權／訂閱 | P59: 100K-500K USD | Q59: 需組合 | R59: CMIO / Pharmacy Lead | S59: 需要即時結構化病歷資料，被 OPP-38 醫材介接與 OPP-31 電子病歷卡住，順序上要排在它們後面 | T59: =IF($A59="","",COUNTIF(14_商機清單_Pipeline!$A$5:$A$34,$U59)) -> 0 | U59: =IF($B59="","",$A59&" "&$B59) -> OPP-55 敗血症與病情惡化預警AI | V59: （待調查） | X59: =IF($A59="","",IFERROR(INDEX(16_能力商機矩陣_CapOppMap!$D$162:$CO$162,MATCH($A59,16_能力商機矩陣_CapOppMap!$D$4:$CO$4,0)),"")) -> 0 | Y59: =IF(OR($A59="",$H59=""),"",IF($H59=0,"",ROUND(0.45*$I59+0.35*$J59+0.2*IF(LEFT($F59,1)="③",5,IF(LEFT($F59,1)="②",3,1))-IF($K59>0,0.3,0),2)+ROW()/100000)) | Z59: =IF($Y59="","",RANK($Y59,$Y$5:$Y$94)) | AA59: L5 智慧應用層 | AB59: （本項無專屬發現——見同列右方的家族／領域趨勢，或 19／20 分頁） | AC59: B | AD59: 結核AI已規模化：9省57萬人篩檢；VinBrain×全球基金32套授權、目標100萬人、單例成本從50-60美元降至約1美元。《數位科技產業法》2026-01-01生效（越南首部含AI專章法律）；AI專法草案2025-10徵詢中（風險分級、參考歐盟）。已實證：影像AI（結核、放射、內視鏡Olympus於Cho Ray/108醫院、眼底Orbis）；未查得實證：營運AI（排程、供應鏈、敗血症、申報審核）、數位病理、越南語臨床LLM——空白即機會，但需承擔市場教育成本。
A60: OPP-56 | B60: 越南語分診聊天機器人與病人助理 | C60: Vietnamese Triage Chatbot | D60: F AI與智慧醫療 | E60: 症狀分診、預約導引與就診前資料收集；醫院、保險公司或電信業者付錢 | F60: ③ 尚未出現：幾乎空白 | G60: =IF($A60="","",IF($H60=0,"（尚無對應能力）",IFERROR(INDEX(16_能力商機矩陣_CapOppMap!$D$160:$CO$160,MATCH($A60,16_能力商機矩陣_CapOppMap!$D$4:$CO$4,0)),""))) -> D06 | H60: =IF($A60="","",IFERROR(INDEX(16_能力商機矩陣_CapOppMap!$D$156:$CO$156,MATCH($A60,16_能力商機矩陣_CapOppMap!$D$4:$CO$4,0)),"")) -> 1 | I60: =IF($A60="","",IFERROR(INDEX(16_能力商機矩陣_CapOppMap!$D$157:$CO$157,MATCH($A60,16_能力商機矩陣_CapOppMap!$D$4:$CO$4,0)),"")) -> 4 | J60: =IF($A60="","",IFERROR(INDEX(16_能力商機矩陣_CapOppMap!$D$158:$CO$158,MATCH($A60,16_能力商機矩陣_CapOppMap!$D$4:$CO$4,0)),"")) -> 2.4 | K60: =IF($A60="","",IFERROR(INDEX(16_能力商機矩陣_CapOppMap!$D$159:$CO$159,MATCH($A60,16_能力商機矩陣_CapOppMap!$D$4:$CO$4,0)),"")) -> 1 | L60: =IF($A60="","",IF($H60=0,"★白地商機：目前無對應能力，需新增能力或找新夥伴",IF($K60>0,"有缺口："&$K60&"項可對外招募","已有能力可承接"))) -> 有缺口：1項可對外招募 | M60: G5 | N60: 醫院營運預算(OPEX) | O60: 軟體授權／訂閱 | P60: 100K-500K USD | Q60: 需組合 | R60: Digital Patient Lead | S60: 市面上多為行銷用玩具、缺臨床治理；2026/3起中風險AI有揭露義務，做得合規反而是差異化 | T60: =IF($A60="","",COUNTIF(14_商機清單_Pipeline!$A$5:$A$34,$U60)) -> 0 | U60: =IF($B60="","",$A60&" "&$B60) -> OPP-56 越南語分診聊天機器人與病人助理 | V60: （待調查） | X60: =IF($A60="","",IFERROR(INDEX(16_能力商機矩陣_CapOppMap!$D$162:$CO$162,MATCH($A60,16_能力商機矩陣_CapOppMap!$D$4:$CO$4,0)),"")) -> 0 | Y60: =IF(OR($A60="",$H60=""),"",IF($H60=0,"",ROUND(0.45*$I60+0.35*$J60+0.2*IF(LEFT($F60,1)="③",5,IF(LEFT($F60,1)="②",3,1))-IF($K60>0,0.3,0),2)+ROW()/100000)) -> 3.3406 | Z60: =IF($Y60="","",RANK($Y60,$Y$5:$Y$94)) -> 55 | AA60: L5 智慧應用層 | AB60: （本項無專屬發現——見同列右方的家族／領域趨勢，或 19／20 分頁） | AC60: B | AD60: 結核AI已規模化：9省57萬人篩檢；VinBrain×全球基金32套授權、目標100萬人、單例成本從50-60美元降至約1美元。《數位科技產業法》2026-01-01生效（越南首部含AI專章法律）；AI專法草案2025-10徵詢中（風險分級、參考歐盟）。已實證：影像AI（結核、放射、內視鏡Olympus於Cho Ray/108醫院、眼底Orbis）；未查得實證：營運AI（排程、供應鏈、敗血症、申報審核）、數位病理、越南語臨床LLM——空白即機會，但需承擔市場教育成本。
A61: OPP-57 | B61: 院內GPU與邊緣推論基礎設施 | C61: In-hospital GPU & Edge Inference | D61: F AI與智慧醫療 | E61: 把推論主機放在PACS／HIS旁邊，病人資料不出院區；硬體加維護，或按月代管 | F61: ② 起步中：剛開始有人做 | G61: =IF($A61="","",IF($H61=0,"（尚無對應能力）",IFERROR(INDEX(16_能力商機矩陣_CapOppMap!$D$160:$CO$160,MATCH($A61,16_能力商機矩陣_CapOppMap!$D$4:$CO$4,0)),""))) -> D04 | H61: =IF($A61="","",IFERROR(INDEX(16_能力商機矩陣_CapOppMap!$D$156:$CO$156,MATCH($A61,16_能力商機矩陣_CapOppMap!$D$4:$CO$4,0)),"")) -> 1 | I61: =IF($A61="","",IFERROR(INDEX(16_能力商機矩陣_CapOppMap!$D$157:$CO$157,MATCH($A61,16_能力商機矩陣_CapOppMap!$D$4:$CO$4,0)),"")) -> 4.1 | J61: =IF($A61="","",IFERROR(INDEX(16_能力商機矩陣_CapOppMap!$D$158:$CO$158,MATCH($A61,16_能力商機矩陣_CapOppMap!$D$4:$CO$4,0)),"")) -> 3.4 | K61: =IF($A61="","",IFERROR(INDEX(16_能力商機矩陣_CapOppMap!$D$159:$CO$159,MATCH($A61,16_能力商機矩陣_CapOppMap!$D$4:$CO$4,0)),"")) -> 0 | L61: =IF($A61="","",IF($H61=0,"★白地商機：目前無對應能力，需新增能力或找新夥伴",IF($K61>0,"有缺口："&$K61&"項可對外招募","已有能力可承接"))) -> 已有能力可承接 | M61: G4 | N61: 醫院業主資本支出(CAPEX) | O61: 設備銷售＋耗材 | P61: 100K-500K USD | Q61: 是 | R61: Digital Infrastructure Lead | S61: ★是個資法跨境限制的合規解，賣在所有臨床AI的下面——群晶最自然的AI搭售點 | T61: =IF($A61="","",COUNTIF(14_商機清單_Pipeline!$A$5:$A$34,$U61)) -> 0 | U61: =IF($B61="","",$A61&" "&$B61) -> OPP-57 院內GPU與邊緣推論基礎設施 | V61: NVIDIA 經銷體系與雲端業者 | W61: 醫院級邊緣部署（合規＋整合PACS/HIS），群晶本業的自然延伸 | X61: =IF($A61="","",IFERROR(INDEX(16_能力商機矩陣_CapOppMap!$D$162:$CO$162,MATCH($A61,16_能力商機矩陣_CapOppMap!$D$4:$CO$4,0)),"")) -> 1 | Y61: =IF(OR($A61="",$H61=""),"",IF($H61=0,"",ROUND(0.45*$I61+0.35*$J61+0.2*IF(LEFT($F61,1)="③",5,IF(LEFT($F61,1)="②",3,1))-IF($K61>0,0.3,0),2)+ROW()/100000)) -> 3.64061 | Z61: =IF($Y61="","",RANK($Y61,$Y$5:$Y$94)) -> 38 | AA61: L2 數位基礎層 | AB61: AI負載推升機櫃密度>20kW與液冷需求（DC市場趨勢）；醫療專屬邊緣案例未查得。 | AC61: B | AD61: 結核AI已規模化：9省57萬人篩檢；VinBrain×全球基金32套授權、目標100萬人、單例成本從50-60美元降至約1美元。《數位科技產業法》2026-01-01生效（越南首部含AI專章法律）；AI專法草案2025-10徵詢中（風險分級、參考歐盟）。已實證：影像AI（結核、放射、內視鏡Olympus於Cho Ray/108醫院、眼底Orbis）；未查得實證：營運AI（排程、供應鏈、敗血症、申報審核）、數位病理、越南語臨床LLM——空白即機會，但需承擔市場教育成本。
A62: OPP-58 | B62: 醫院資料湖、去識別化與AI訓練資料層 | C62: Hospital Data Lake & De-identification | D62: F AI與智慧醫療 | E62: DICOM/HL7/FHIR正規化、去識別化與治理層；醫院專案或省級計畫付錢 | F62: ② 起步中：剛開始有人做 | G62: =IF($A62="","",IF($H62=0,"（尚無對應能力）",IFERROR(INDEX(16_能力商機矩陣_CapOppMap!$D$160:$CO$160,MATCH($A62,16_能力商機矩陣_CapOppMap!$D$4:$CO$4,0)),""))) -> D06 | H62: =IF($A62="","",IFERROR(INDEX(16_能力商機矩陣_CapOppMap!$D$156:$CO$156,MATCH($A62,16_能力商機矩陣_CapOppMap!$D$4:$CO$4,0)),"")) -> 2 | I62: =IF($A62="","",IFERROR(INDEX(16_能力商機矩陣_CapOppMap!$D$157:$CO$157,MATCH($A62,16_能力商機矩陣_CapOppMap!$D$4:$CO$4,0)),"")) -> 4.5 | J62: =IF($A62="","",IFERROR(INDEX(16_能力商機矩陣_CapOppMap!$D$158:$CO$158,MATCH($A62,16_能力商機矩陣_CapOppMap!$D$4:$CO$4,0)),"")) -> 2.4 | K62: =IF($A62="","",IFERROR(INDEX(16_能力商機矩陣_CapOppMap!$D$159:$CO$159,MATCH($A62,16_能力商機矩陣_CapOppMap!$D$4:$CO$4,0)),"")) -> 0 | L62: =IF($A62="","",IF($H62=0,"★白地商機：目前無對應能力，需新增能力或找新夥伴",IF($K62>0,"有缺口："&$K62&"項可對外招募","已有能力可承接"))) -> 已有能力可承接 | M62: G4 | N62: 醫院業主資本支出(CAPEX) | O62: 軟體授權／訂閱 | P62: 500K-2M USD | Q62: 是 | R62: Data Architect | S62: ★2026-2028實際被編到預算的就是這一層，而且是OPP-49/50/52/55的共同前提 | T62: =IF($A62="","",COUNTIF(14_商機清單_Pipeline!$A$5:$A$34,$U62)) -> 0 | U62: =IF($B62="","",$A62&" "&$B62) -> OPP-58 醫院資料湖、去識別化與AI訓練資料層 | V62: （待調查） | X62: =IF($A62="","",IFERROR(INDEX(16_能力商機矩陣_CapOppMap!$D$162:$CO$162,MATCH($A62,16_能力商機矩陣_CapOppMap!$D$4:$CO$4,0)),"")) -> 0 | Y62: =IF(OR($A62="",$H62=""),"",IF($H62=0,"",ROUND(0.45*$I62+0.35*$J62+0.2*IF(LEFT($F62,1)="③",5,IF(LEFT($F62,1)="②",3,1))-IF($K62>0,0.3,0),2)+ROW()/100000)) -> 3.47062 | Z62: =IF($Y62="","",RANK($Y62,$Y$5:$Y$94)) -> 47 | AA62: L4 資料平台層 | AB62: （本項無專屬發現——見同列右方的家族／領域趨勢，或 19／20 分頁） | AC62: B | AD62: 結核AI已規模化：9省57萬人篩檢；VinBrain×全球基金32套授權、目標100萬人、單例成本從50-60美元降至約1美元。《數位科技產業法》2026-01-01生效（越南首部含AI專章法律）；AI專法草案2025-10徵詢中（風險分級、參考歐盟）。已實證：影像AI（結核、放射、內視鏡Olympus於Cho Ray/108醫院、眼底Orbis）；未查得實證：營運AI（排程、供應鏈、敗血症、申報審核）、數位病理、越南語臨床LLM——空白即機會，但需承擔市場教育成本。
A63: OPP-59 | B63: 醫療AI法規登記、在地驗證與模型治理 | C63: SaMD Registration, Validation & AI Governance | D63: F AI與智慧醫療 | E63: 軟體醫材登記、在地臨床驗證、上線後效能監控與AI法高風險文件包；賣給要進越南的AI廠商與醫院 | F63: ③ 尚未出現：幾乎空白 | G63: =IF($A63="","",IF($H63=0,"（尚無對應能力）",IFERROR(INDEX(16_能力商機矩陣_CapOppMap!$D$160:$CO$160,MATCH($A63,16_能力商機矩陣_CapOppMap!$D$4:$CO$4,0)),""))) -> D01; D04 | H63: =IF($A63="","",IFERROR(INDEX(16_能力商機矩陣_CapOppMap!$D$156:$CO$156,MATCH($A63,16_能力商機矩陣_CapOppMap!$D$4:$CO$4,0)),"")) -> 2 | I63: =IF($A63="","",IFERROR(INDEX(16_能力商機矩陣_CapOppMap!$D$157:$CO$157,MATCH($A63,16_能力商機矩陣_CapOppMap!$D$4:$CO$4,0)),"")) -> 4.3 | J63: =IF($A63="","",IFERROR(INDEX(16_能力商機矩陣_CapOppMap!$D$158:$CO$158,MATCH($A63,16_能力商機矩陣_CapOppMap!$D$4:$CO$4,0)),"")) -> 2.7 | K63: =IF($A63="","",IFERROR(INDEX(16_能力商機矩陣_CapOppMap!$D$159:$CO$159,MATCH($A63,16_能力商機矩陣_CapOppMap!$D$4:$CO$4,0)),"")) -> 0 | L63: =IF($A63="","",IF($H63=0,"★白地商機：目前無對應能力，需新增能力或找新夥伴",IF($K63>0,"有缺口："&$K63&"項可對外招募","已有能力可承接"))) -> 已有能力可承接 | M63: G3 | N63: 設備／軟體供應商（含代理商） | O63: 顧問服務 | P63: 100K-500K USD | Q63: 是 | R63: Regulatory Lead | S63: ★法規造出來的新市場：越南AI法2026/3/1生效、既有醫療AI系統2027/9/1前須補齊；越南的資料標註量能可轉作在地驗證的供應鏈 | T63: =IF($A63="","",COUNTIF(14_商機清單_Pipeline!$A$5:$A$34,$U63)) -> 0 | U63: =IF($B63="","",$A63&" "&$B63) -> OPP-59 醫療AI法規登記、在地驗證與模型治理 | V63: 無在地專業者（AI法 2026/3 才生效） | W63: 首波 SaMD＋AI 法雙證顧問，賣給要進越南的 AI 廠商 | X63: =IF($A63="","",IFERROR(INDEX(16_能力商機矩陣_CapOppMap!$D$162:$CO$162,MATCH($A63,16_能力商機矩陣_CapOppMap!$D$4:$CO$4,0)),"")) -> 1 | Y63: =IF(OR($A63="",$H63=""),"",IF($H63=0,"",ROUND(0.45*$I63+0.35*$J63+0.2*IF(LEFT($F63,1)="③",5,IF(LEFT($F63,1)="②",3,1))-IF($K63>0,0.3,0),2)+ROW()/100000)) -> 3.88063 | Z63: =IF($Y63="","",RANK($Y63,$Y$5:$Y$94)) -> 14 | AA63: G 治理合規層（跨層） | AB63: SaMD循Decree 98/2021醫材分類；《數位科技產業法》2026-01-01生效（首部含AI專章，高風險AI須許可）；AI專法草案2025-10徵詢、風險分級參考歐盟——雙軌合規顧問本身即商機。 | AC63: A | AD63: 結核AI已規模化：9省57萬人篩檢；VinBrain×全球基金32套授權、目標100萬人、單例成本從50-60美元降至約1美元。《數位科技產業法》2026-01-01生效（越南首部含AI專章法律）；AI專法草案2025-10徵詢中（風險分級、參考歐盟）。已實證：影像AI（結核、放射、內視鏡Olympus於Cho Ray/108醫院、眼底Orbis）；未查得實證：營運AI（排程、供應鏈、敗血症、申報審核）、數位病理、越南語臨床LLM——空白即機會，但需承擔市場教育成本。
A64: OPP-60 | B64: JCI品質認證與病安體系導入 | C64: JCI Accreditation & Patient Safety | D64: G 品質認證與人才 | E64: 品質管理制度、感控、用藥安全與事件通報體系導入；認證本身就是醫院的招牌與定價依據 | F64: ② 起步中：剛開始有人做 | G64: =IF($A64="","",IF($H64=0,"（尚無對應能力）",IFERROR(INDEX(16_能力商機矩陣_CapOppMap!$D$160:$CO$160,MATCH($A64,16_能力商機矩陣_CapOppMap!$D$4:$CO$4,0)),""))) -> D07 | H64: =IF($A64="","",IFERROR(INDEX(16_能力商機矩陣_CapOppMap!$D$156:$CO$156,MATCH($A64,16_能力商機矩陣_CapOppMap!$D$4:$CO$4,0)),"")) -> 5 | I64: =IF($A64="","",IFERROR(INDEX(16_能力商機矩陣_CapOppMap!$D$157:$CO$157,MATCH($A64,16_能力商機矩陣_CapOppMap!$D$4:$CO$4,0)),"")) -> 4.5 | J64: =IF($A64="","",IFERROR(INDEX(16_能力商機矩陣_CapOppMap!$D$158:$CO$158,MATCH($A64,16_能力商機矩陣_CapOppMap!$D$4:$CO$4,0)),"")) -> 3 | K64: =IF($A64="","",IFERROR(INDEX(16_能力商機矩陣_CapOppMap!$D$159:$CO$159,MATCH($A64,16_能力商機矩陣_CapOppMap!$D$4:$CO$4,0)),"")) -> 0 | L64: =IF($A64="","",IF($H64=0,"★白地商機：目前無對應能力，需新增能力或找新夥伴",IF($K64>0,"有缺口："&$K64&"項可對外招募","已有能力可承接"))) -> 已有能力可承接 | M64: G2 | N64: 醫院業主資本支出(CAPEX) | O64: 顧問服務 | P64: 100K-500K USD | Q64: 是 | R64: Quality Director | S64: JCI為國際自願性認證，可與越南醫院評鑑並行；顧問期通常18-24個月 | T64: =IF($A64="","",COUNTIF(14_商機清單_Pipeline!$A$5:$A$34,$U64)) -> 0 | U64: =IF($B64="","",$A64&" "&$B64) -> OPP-60 JCI品質認證與病安體系導入 | V64: 國際自由顧問＋新加坡體系 | W64: 台灣 JCI 醫院實地見習＋中文輔導 | X64: =IF($A64="","",IFERROR(INDEX(16_能力商機矩陣_CapOppMap!$D$162:$CO$162,MATCH($A64,16_能力商機矩陣_CapOppMap!$D$4:$CO$4,0)),"")) -> 0 | Y64: =IF(OR($A64="",$H64=""),"",IF($H64=0,"",ROUND(0.45*$I64+0.35*$J64+0.2*IF(LEFT($F64,1)="③",5,IF(LEFT($F64,1)="②",3,1))-IF($K64>0,0.3,0),2)+ROW()/100000)) -> 3.68064 | Z64: =IF($Y64="","",RANK($Y64,$Y$5:$Y$94)) -> 31 | AA64: L6 照護營運層 | AB64: 官方2025-12-31以4024/QĐ-BYT承認JCI；現況9機構（公立1家）；2030年目標15-20家（含公立5家）——輔導市場從私立選配變公立政策任務。公立首例：血液醫院16個月完成、9.89/10。 | AC64: A | AD64: 衛生部2025-12-31以4024/QĐ-BYT正式承認JCI標準；截至2026-01全越9機構持JCI認證（公立僅1家：胡志明市血液醫院，首評9.89/10、費時16個月）。35/2024/TT-BYT五項基本品質標準2025-01-01生效。VILAS Med累計200+實驗室。2027-01-01起醫師須通過國家執業能力考試（新制5年換照＋CME）。
A65: OPP-61 | B65: ISO 15189檢驗室認證輔導 | C65: ISO 15189 Laboratory Accreditation | D65: G 品質認證與人才 | E65: 檢驗室品質系統建置與認證輔導；醫院或私立檢驗連鎖付錢 | F65: ③ 尚未出現：幾乎空白 | G65: =IF($A65="","",IF($H65=0,"（尚無對應能力）",IFERROR(INDEX(16_能力商機矩陣_CapOppMap!$D$160:$CO$160,MATCH($A65,16_能力商機矩陣_CapOppMap!$D$4:$CO$4,0)),""))) -> D05; D07 | H65: =IF($A65="","",IFERROR(INDEX(16_能力商機矩陣_CapOppMap!$D$156:$CO$156,MATCH($A65,16_能力商機矩陣_CapOppMap!$D$4:$CO$4,0)),"")) -> 2 | I65: =IF($A65="","",IFERROR(INDEX(16_能力商機矩陣_CapOppMap!$D$157:$CO$157,MATCH($A65,16_能力商機矩陣_CapOppMap!$D$4:$CO$4,0)),"")) -> 4.5 | J65: =IF($A65="","",IFERROR(INDEX(16_能力商機矩陣_CapOppMap!$D$158:$CO$158,MATCH($A65,16_能力商機矩陣_CapOppMap!$D$4:$CO$4,0)),"")) -> 2.7 | K65: =IF($A65="","",IFERROR(INDEX(16_能力商機矩陣_CapOppMap!$D$159:$CO$159,MATCH($A65,16_能力商機矩陣_CapOppMap!$D$4:$CO$4,0)),"")) -> 1 | L65: =IF($A65="","",IF($H65=0,"★白地商機：目前無對應能力，需新增能力或找新夥伴",IF($K65>0,"有缺口："&$K65&"項可對外招募","已有能力可承接"))) -> 有缺口：1項可對外招募 | M65: G3 | N65: 醫院業主資本支出(CAPEX) | O65: 顧問服務 | P65: 100K-500K USD | Q65: 是 | R65: Quality Director | S65: 全國3000家檢驗室僅約10%標準化——全民健檢政策上路後，認證會變成接案門票 | T65: =IF($A65="","",COUNTIF(14_商機清單_Pipeline!$A$5:$A$34,$U65)) -> 0 | U65: =IF($B65="","",$A65&" "&$B65) -> OPP-61 ISO 15189檢驗室認證輔導 | V65: （待調查） | X65: =IF($A65="","",IFERROR(INDEX(16_能力商機矩陣_CapOppMap!$D$162:$CO$162,MATCH($A65,16_能力商機矩陣_CapOppMap!$D$4:$CO$4,0)),"")) -> 0 | Y65: =IF(OR($A65="",$H65=""),"",IF($H65=0,"",ROUND(0.45*$I65+0.35*$J65+0.2*IF(LEFT($F65,1)="③",5,IF(LEFT($F65,1)="②",3,1))-IF($K65>0,0.3,0),2)+ROW()/100000)) -> 3.67065 | Z65: =IF($Y65="","",RANK($Y65,$Y$5:$Y$94)) -> 32 | AA65: L6 照護營運層 | AB65: VILAS Med累計200+實驗室、具ILAC MRA地位——本土認證體系成熟，外部輔導空間在15189:2022轉版、POCT、影像、細胞治療實驗室等新範圍。 | AC65: A | AD65: 衛生部2025-12-31以4024/QĐ-BYT正式承認JCI標準；截至2026-01全越9機構持JCI認證（公立僅1家：胡志明市血液醫院，首評9.89/10、費時16個月）。35/2024/TT-BYT五項基本品質標準2025-01-01生效。VILAS Med累計200+實驗室。2027-01-01起醫師須通過國家執業能力考試（新制5年換照＋CME）。
A66: OPP-62 | B66: 臨床人才培訓、模擬中心與技術移轉 | C66: Clinical Workforce & Tech Transfer | D66: G 品質認證與人才 | E66: 種子教師培訓、模擬中心、開院演練與職能認證；常可爭取政府或ODA預算單獨立案 | F66: ② 起步中：剛開始有人做 | G66: =IF($A66="","",IF($H66=0,"（尚無對應能力）",IFERROR(INDEX(16_能力商機矩陣_CapOppMap!$D$160:$CO$160,MATCH($A66,16_能力商機矩陣_CapOppMap!$D$4:$CO$4,0)),""))) -> D08 | H66: =IF($A66="","",IFERROR(INDEX(16_能力商機矩陣_CapOppMap!$D$156:$CO$156,MATCH($A66,16_能力商機矩陣_CapOppMap!$D$4:$CO$4,0)),"")) -> 5 | I66: =IF($A66="","",IFERROR(INDEX(16_能力商機矩陣_CapOppMap!$D$157:$CO$157,MATCH($A66,16_能力商機矩陣_CapOppMap!$D$4:$CO$4,0)),"")) -> 4.2 | J66: =IF($A66="","",IFERROR(INDEX(16_能力商機矩陣_CapOppMap!$D$158:$CO$158,MATCH($A66,16_能力商機矩陣_CapOppMap!$D$4:$CO$4,0)),"")) -> 3 | K66: =IF($A66="","",IFERROR(INDEX(16_能力商機矩陣_CapOppMap!$D$159:$CO$159,MATCH($A66,16_能力商機矩陣_CapOppMap!$D$4:$CO$4,0)),"")) -> 1 | L66: =IF($A66="","",IF($H66=0,"★白地商機：目前無對應能力，需新增能力或找新夥伴",IF($K66>0,"有缺口："&$K66&"項可對外招募","已有能力可承接"))) -> 有缺口：1項可對外招募 | M66: G2 | N66: 國際開發援助(ODA／世銀／ADB) | O66: ODA／贈款 | P66: 100K-500K USD | Q66: 是 | R66: Clinical Education Lead | S66: 需與越南醫護大學合作取得學分／認證資格；台灣參考醫院是主要供給端 | T66: =IF($A66="","",COUNTIF(14_商機清單_Pipeline!$A$5:$A$34,$U66)) -> 0 | U66: =IF($B66="","",$A66&" "&$B66) -> OPP-62 臨床人才培訓、模擬中心與技術移轉 | V66: （待調查） | X66: =IF($A66="","",IFERROR(INDEX(16_能力商機矩陣_CapOppMap!$D$162:$CO$162,MATCH($A66,16_能力商機矩陣_CapOppMap!$D$4:$CO$4,0)),"")) -> 0 | Y66: =IF(OR($A66="",$H66=""),"",IF($H66=0,"",ROUND(0.45*$I66+0.35*$J66+0.2*IF(LEFT($F66,1)="③",5,IF(LEFT($F66,1)="②",3,1))-IF($K66>0,0.3,0),2)+ROW()/100000)) -> 3.24066 | Z66: =IF($Y66="","",RANK($Y66,$Y$5:$Y$94)) -> 66 | AA66: L6 照護營運層 | AB66: 2027-01-01起醫師國家執業能力考試（後逐年擴及護理助產）＋5年換照＋CME→考前培訓、題庫、OSCE/模擬是新產業鏈；VinUni模擬中心已對外承接公立醫院訓練＝商模已被驗證。 | AC66: A | AD66: 衛生部2025-12-31以4024/QĐ-BYT正式承認JCI標準；截至2026-01全越9機構持JCI認證（公立僅1家：胡志明市血液醫院，首評9.89/10、費時16個月）。35/2024/TT-BYT五項基本品質標準2025-01-01生效。VILAS Med累計200+實驗室。2027-01-01起醫師須通過國家執業能力考試（新制5年換照＋CME）。
A67: OPP-63 | B67: 開院前臨床安全驗證與試營運 | C67: Pre-opening Clinical Assurance & Commissioning | D67: G 品質認證與人才 | E67: 開院前的臨床流程驗證、模擬病人演練與缺失關閉；業主或PPP公司付錢 | F67: ③ 尚未出現：幾乎空白 | G67: =IF($A67="","",IF($H67=0,"（尚無對應能力）",IFERROR(INDEX(16_能力商機矩陣_CapOppMap!$D$160:$CO$160,MATCH($A67,16_能力商機矩陣_CapOppMap!$D$4:$CO$4,0)),""))) -> D07; D08 | H67: =IF($A67="","",IFERROR(INDEX(16_能力商機矩陣_CapOppMap!$D$156:$CO$156,MATCH($A67,16_能力商機矩陣_CapOppMap!$D$4:$CO$4,0)),"")) -> 3 | I67: =IF($A67="","",IFERROR(INDEX(16_能力商機矩陣_CapOppMap!$D$157:$CO$157,MATCH($A67,16_能力商機矩陣_CapOppMap!$D$4:$CO$4,0)),"")) -> 4.4 | J67: =IF($A67="","",IFERROR(INDEX(16_能力商機矩陣_CapOppMap!$D$158:$CO$158,MATCH($A67,16_能力商機矩陣_CapOppMap!$D$4:$CO$4,0)),"")) -> 3 | K67: =IF($A67="","",IFERROR(INDEX(16_能力商機矩陣_CapOppMap!$D$159:$CO$159,MATCH($A67,16_能力商機矩陣_CapOppMap!$D$4:$CO$4,0)),"")) -> 0 | L67: =IF($A67="","",IF($H67=0,"★白地商機：目前無對應能力，需新增能力或找新夥伴",IF($K67>0,"有缺口："&$K67&"項可對外招募","已有能力可承接"))) -> 已有能力可承接 | M67: G5 | N67: 醫院業主資本支出(CAPEX) | O67: 顧問服務 | P67: 100K-500K USD | Q67: 需組合 | R67: Independent Clinical Assurance | S67: 越南新醫院常「硬體完工但開不了院」，這一段是台灣醫院經驗最值錢的地方 | T67: =IF($A67="","",COUNTIF(14_商機清單_Pipeline!$A$5:$A$34,$U67)) -> 0 | U67: =IF($B67="","",$A67&" "&$B67) -> OPP-63 開院前臨床安全驗證與試營運 | V67: （待調查） | X67: =IF($A67="","",IFERROR(INDEX(16_能力商機矩陣_CapOppMap!$D$162:$CO$162,MATCH($A67,16_能力商機矩陣_CapOppMap!$D$4:$CO$4,0)),"")) -> 0 | Y67: =IF(OR($A67="",$H67=""),"",IF($H67=0,"",ROUND(0.45*$I67+0.35*$J67+0.2*IF(LEFT($F67,1)="③",5,IF(LEFT($F67,1)="②",3,1))-IF($K67>0,0.3,0),2)+ROW()/100000)) -> 4.03067 | Z67: =IF($Y67="","",RANK($Y67,$Y$5:$Y$94)) -> 6 | AA67: L6 照護營運層 | AB67: 越南無開院commissioning專屬法規；35/2024/TT-BYT五項基本標準（2025-01生效）是最接近的法定錨點——空白市場、可帶國際框架進場。 | AC67: A | AD67: 衛生部2025-12-31以4024/QĐ-BYT正式承認JCI標準；截至2026-01全越9機構持JCI認證（公立僅1家：胡志明市血液醫院，首評9.89/10、費時16個月）。35/2024/TT-BYT五項基本品質標準2025-01-01生效。VILAS Med累計200+實驗室。2027-01-01起醫師須通過國家執業能力考試（新制5年換照＋CME）。
A68: OPP-64 | B68: 院內物流SPD委外 | C68: In-hospital SPD Logistics Outsourcing | D68: H 供應鏈與維運服務 | E68: 耗材寄售、條碼揀貨、氣送與AGV，按耗材金額比例收管理費 | F68: ③ 尚未出現：幾乎空白 | G68: =IF($A68="","",IF($H68=0,"（尚無對應能力）",IFERROR(INDEX(16_能力商機矩陣_CapOppMap!$D$160:$CO$160,MATCH($A68,16_能力商機矩陣_CapOppMap!$D$4:$CO$4,0)),""))) -> D09 | H68: =IF($A68="","",IFERROR(INDEX(16_能力商機矩陣_CapOppMap!$D$156:$CO$156,MATCH($A68,16_能力商機矩陣_CapOppMap!$D$4:$CO$4,0)),"")) -> 2 | I68: =IF($A68="","",IFERROR(INDEX(16_能力商機矩陣_CapOppMap!$D$157:$CO$157,MATCH($A68,16_能力商機矩陣_CapOppMap!$D$4:$CO$4,0)),"")) -> 3.9 | J68: =IF($A68="","",IFERROR(INDEX(16_能力商機矩陣_CapOppMap!$D$158:$CO$158,MATCH($A68,16_能力商機矩陣_CapOppMap!$D$4:$CO$4,0)),"")) -> 3 | K68: =IF($A68="","",IFERROR(INDEX(16_能力商機矩陣_CapOppMap!$D$159:$CO$159,MATCH($A68,16_能力商機矩陣_CapOppMap!$D$4:$CO$4,0)),"")) -> 0 | L68: =IF($A68="","",IF($H68=0,"★白地商機：目前無對應能力，需新增能力或找新夥伴",IF($K68>0,"有缺口："&$K68&"項可對外招募","已有能力可承接"))) -> 已有能力可承接 | M68: G5 | N68: 醫院營運預算(OPEX) | O68: 管理服務 | P68: 500K-2M USD | Q68: 是 | R68: Supply Chain Lead | S68: ★越南沒有SPD業者，台日模式可直接移植；而且是營運費用，繞開資本支出採購的價格管制 | T68: =IF($A68="","",COUNTIF(14_商機清單_Pipeline!$A$5:$A$34,$U68)) -> 1 | U68: =IF($B68="","",$A68&" "&$B68) -> OPP-64 院內物流SPD委外 | V68: 越南無 SPD 業者 | W68: 台日模式直接移植；先簽一家示範醫院建立標竿 | X68: =IF($A68="","",IFERROR(INDEX(16_能力商機矩陣_CapOppMap!$D$162:$CO$162,MATCH($A68,16_能力商機矩陣_CapOppMap!$D$4:$CO$4,0)),"")) -> 0 | Y68: =IF(OR($A68="",$H68=""),"",IF($H68=0,"",ROUND(0.45*$I68+0.35*$J68+0.2*IF(LEFT($F68,1)="③",5,IF(LEFT($F68,1)="②",3,1))-IF($K68>0,0.3,0),2)+ROW()/100000)) -> 3.81068 | Z68: =IF($Y68="","",RANK($Y68,$Y$5:$Y$94)) -> 20 | AA68: L6 照護營運層 | AB68: 越南SPD委外市場數據未查得＝萌芽前期；需自建市場情報。 | AC68: C | AD68: FM市場2024年約25億美元（JLL、CBRE、ISS、Sodexo等，醫療列重點場域）；冷鏈2023年1.63億美元、CAGR 14.1%（Zuellig、DKSH主導醫藥端）；設備寄放/按次計費模式2024年入法＝醫材託管服務（MES）首次有法源。SPD/CSSD/CMMS：越南無公開市場統計——政策先行、資料空白的早期市場。
A69: OPP-65 | B69: 消毒供應外包（區域CSSD服務化） | C69: Off-site CSSD as a Service | D69: H 供應鏈與維運服務 | E69: 區域滅菌中心服務多家醫院與日間手術中心，按器械盤計價 | F69: ③ 尚未出現：幾乎空白 | G69: =IF($A69="","",IF($H69=0,"（尚無對應能力）",IFERROR(INDEX(16_能力商機矩陣_CapOppMap!$D$160:$CO$160,MATCH($A69,16_能力商機矩陣_CapOppMap!$D$4:$CO$4,0)),""))) -> D03; D05 | H69: =IF($A69="","",IFERROR(INDEX(16_能力商機矩陣_CapOppMap!$D$156:$CO$156,MATCH($A69,16_能力商機矩陣_CapOppMap!$D$4:$CO$4,0)),"")) -> 2 | I69: =IF($A69="","",IFERROR(INDEX(16_能力商機矩陣_CapOppMap!$D$157:$CO$157,MATCH($A69,16_能力商機矩陣_CapOppMap!$D$4:$CO$4,0)),"")) -> 4.7 | J69: =IF($A69="","",IFERROR(INDEX(16_能力商機矩陣_CapOppMap!$D$158:$CO$158,MATCH($A69,16_能力商機矩陣_CapOppMap!$D$4:$CO$4,0)),"")) -> 2.4 | K69: =IF($A69="","",IFERROR(INDEX(16_能力商機矩陣_CapOppMap!$D$159:$CO$159,MATCH($A69,16_能力商機矩陣_CapOppMap!$D$4:$CO$4,0)),"")) -> 0 | L69: =IF($A69="","",IF($H69=0,"★白地商機：目前無對應能力，需新增能力或找新夥伴",IF($K69>0,"有缺口："&$K69&"項可對外招募","已有能力可承接"))) -> 已有能力可承接 | M69: G6 | N69: 醫院營運預算(OPEX) | O69: 管理服務 | P69: 500K-2M USD | Q69: 是 | R69: FM Lead | S69: ★越南沒有第三方滅菌服務市場，是完全的空白產業 | T69: =IF($A69="","",COUNTIF(14_商機清單_Pipeline!$A$5:$A$34,$U69)) -> 0 | U69: =IF($B69="","",$A69&" "&$B69) -> OPP-65 消毒供應外包（區域CSSD服務化） | V69: 無第三方滅菌服務市場 | W69: 區域中心＋日間手術群聚；感控稽查收緊前卡位 | X69: =IF($A69="","",IFERROR(INDEX(16_能力商機矩陣_CapOppMap!$D$162:$CO$162,MATCH($A69,16_能力商機矩陣_CapOppMap!$D$4:$CO$4,0)),"")) -> 0 | Y69: =IF(OR($A69="",$H69=""),"",IF($H69=0,"",ROUND(0.45*$I69+0.35*$J69+0.2*IF(LEFT($F69,1)="③",5,IF(LEFT($F69,1)="②",3,1))-IF($K69>0,0.3,0),2)+ROW()/100000)) -> 3.96069 | Z69: =IF($Y69="","",RANK($Y69,$Y$5:$Y$94)) -> 8 | AA69: L6 照護營運層 | AB69: 越南第三方滅菌服務市場數據未查得；查得資料均為歐美市場。 | AC69: C | AD69: FM市場2024年約25億美元（JLL、CBRE、ISS、Sodexo等，醫療列重點場域）；冷鏈2023年1.63億美元、CAGR 14.1%（Zuellig、DKSH主導醫藥端）；設備寄放/按次計費模式2024年入法＝醫材託管服務（MES）首次有法源。SPD/CSSD/CMMS：越南無公開市場統計——政策先行、資料空白的早期市場。
A70: OPP-66 | B70: 醫材維運與託管服務(MES) | C70: Managed Equipment Services | D70: H 供應鏈與維運服務 | E70: 全險維修或「按掃描次數付費」，用服務合約取代醫院資本支出 | F70: ③ 尚未出現：幾乎空白 | G70: =IF($A70="","",IF($H70=0,"（尚無對應能力）",IFERROR(INDEX(16_能力商機矩陣_CapOppMap!$D$160:$CO$160,MATCH($A70,16_能力商機矩陣_CapOppMap!$D$4:$CO$4,0)),""))) -> D05; D09 | H70: =IF($A70="","",IFERROR(INDEX(16_能力商機矩陣_CapOppMap!$D$156:$CO$156,MATCH($A70,16_能力商機矩陣_CapOppMap!$D$4:$CO$4,0)),"")) -> 2 | I70: =IF($A70="","",IFERROR(INDEX(16_能力商機矩陣_CapOppMap!$D$157:$CO$157,MATCH($A70,16_能力商機矩陣_CapOppMap!$D$4:$CO$4,0)),"")) -> 4.2 | J70: =IF($A70="","",IFERROR(INDEX(16_能力商機矩陣_CapOppMap!$D$158:$CO$158,MATCH($A70,16_能力商機矩陣_CapOppMap!$D$4:$CO$4,0)),"")) -> 2.7 | K70: =IF($A70="","",IFERROR(INDEX(16_能力商機矩陣_CapOppMap!$D$159:$CO$159,MATCH($A70,16_能力商機矩陣_CapOppMap!$D$4:$CO$4,0)),"")) -> 0 | L70: =IF($A70="","",IF($H70=0,"★白地商機：目前無對應能力，需新增能力或找新夥伴",IF($K70>0,"有缺口："&$K70&"項可對外招募","已有能力可承接"))) -> 已有能力可承接 | M70: G6 | N70: 醫院營運預算(OPEX) | O70: 管理服務 | P70: 500K-2M USD | Q70: 是 | R70: Clinical Engineering Lead | S70: ★設備閒置／故障是常態、缺生物醫學工程量能；按次計費正好避開越南的採購價格管制 | T70: =IF($A70="","",COUNTIF(14_商機清單_Pipeline!$A$5:$A$34,$U70)) -> 0 | U70: =IF($B70="","",$A70&" "&$B70) -> OPP-66 醫材維運與託管服務(MES) | V70: 原廠維保各自為政，無跨廠牌整合商 | W70: 跨廠牌整合維保＋按次付費，繞開採購價格管制 | X70: =IF($A70="","",IFERROR(INDEX(16_能力商機矩陣_CapOppMap!$D$162:$CO$162,MATCH($A70,16_能力商機矩陣_CapOppMap!$D$4:$CO$4,0)),"")) -> 0 | Y70: =IF(OR($A70="",$H70=""),"",IF($H70=0,"",ROUND(0.45*$I70+0.35*$J70+0.2*IF(LEFT($F70,1)="③",5,IF(LEFT($F70,1)="②",3,1))-IF($K70>0,0.3,0),2)+ROW()/100000)) -> 3.8407 | Z70: =IF($Y70="","",RANK($Y70,$Y$5:$Y$94)) -> 18 | AA70: L6 照護營運層 | AB70: 法源已備：設備寄放＋按次計費＋委外檢驗等模式2024年入法；承包商選擇方式2025-07-01起由6種增為10種（Luật 90/2025，新增đặt hàng）；商業案例數據未查得——法規先行、市場待開。 | AC70: A | AD70: FM市場2024年約25億美元（JLL、CBRE、ISS、Sodexo等，醫療列重點場域）；冷鏈2023年1.63億美元、CAGR 14.1%（Zuellig、DKSH主導醫藥端）；設備寄放/按次計費模式2024年入法＝醫材託管服務（MES）首次有法源。SPD/CSSD/CMMS：越南無公開市場統計——政策先行、資料空白的早期市場。
A71: OPP-67 | B71: 醫院設施管理委外（醫療級FM） | C71: Healthcare-grade Facility Management | D71: H 供應鏈與維運服務 | E71: 符合感染管制標準的清潔、BMS與機電維運多年約；醫院營運預算 | F71: ③ 尚未出現：幾乎空白 | G71: =IF($A71="","",IF($H71=0,"（尚無對應能力）",IFERROR(INDEX(16_能力商機矩陣_CapOppMap!$D$160:$CO$160,MATCH($A71,16_能力商機矩陣_CapOppMap!$D$4:$CO$4,0)),""))) -> D09 | H71: =IF($A71="","",IFERROR(INDEX(16_能力商機矩陣_CapOppMap!$D$156:$CO$156,MATCH($A71,16_能力商機矩陣_CapOppMap!$D$4:$CO$4,0)),"")) -> 1 | I71: =IF($A71="","",IFERROR(INDEX(16_能力商機矩陣_CapOppMap!$D$157:$CO$157,MATCH($A71,16_能力商機矩陣_CapOppMap!$D$4:$CO$4,0)),"")) -> 3.7 | J71: =IF($A71="","",IFERROR(INDEX(16_能力商機矩陣_CapOppMap!$D$158:$CO$158,MATCH($A71,16_能力商機矩陣_CapOppMap!$D$4:$CO$4,0)),"")) -> 3.4 | K71: =IF($A71="","",IFERROR(INDEX(16_能力商機矩陣_CapOppMap!$D$159:$CO$159,MATCH($A71,16_能力商機矩陣_CapOppMap!$D$4:$CO$4,0)),"")) -> 0 | L71: =IF($A71="","",IF($H71=0,"★白地商機：目前無對應能力，需新增能力或找新夥伴",IF($K71>0,"有缺口："&$K71&"項可對外招募","已有能力可承接"))) -> 已有能力可承接 | M71: G6 | N71: 醫院營運預算(OPEX) | O71: 管理服務 | P71: 500K-2M USD | Q71: 是 | R71: FM Lead | S71: 一般商用FM市場有，但醫療級FM幾乎空白；建議先從私立醫院連鎖切入 | T71: =IF($A71="","",COUNTIF(14_商機清單_Pipeline!$A$5:$A$34,$U71)) -> 0 | U71: =IF($B71="","",$A71&" "&$B71) -> OPP-67 醫院設施管理委外（醫療級FM） | V71: （待調查） | X71: =IF($A71="","",IFERROR(INDEX(16_能力商機矩陣_CapOppMap!$D$162:$CO$162,MATCH($A71,16_能力商機矩陣_CapOppMap!$D$4:$CO$4,0)),"")) -> 1 | Y71: =IF(OR($A71="",$H71=""),"",IF($H71=0,"",ROUND(0.45*$I71+0.35*$J71+0.2*IF(LEFT($F71,1)="③",5,IF(LEFT($F71,1)="②",3,1))-IF($K71>0,0.3,0),2)+ROW()/100000)) -> 3.86071 | Z71: =IF($Y71="","",RANK($Y71,$Y$5:$Y$94)) -> 15 | AA71: L6 照護營運層 | AB71: 與 CAP-053 連動：FM 市場 2024 年約 25 億美元但醫療未單獨拆分；越南醫院 CMMS 採用率未查得。WHO 2025 案例指越南近半數醫療機構能源不安全、2024 年颱風 Yagi 損害逾 800 家機構——韌性論述比純節能更有說服力。 | AC71: A | AD71: FM市場2024年約25億美元（JLL、CBRE、ISS、Sodexo等，醫療列重點場域）；冷鏈2023年1.63億美元、CAGR 14.1%（Zuellig、DKSH主導醫藥端）；設備寄放/按次計費模式2024年入法＝醫材託管服務（MES）首次有法源。SPD/CSSD/CMMS：越南無公開市場統計——政策先行、資料空白的早期市場。
A72: OPP-68 | B72: 冷鏈與特殊物料物流 | C72: Cold Chain & Special Materials Logistics | D72: H 供應鏈與維運服務 | E72: 疫苗、檢體、生物製劑的冷鏈運送與監控；醫院或檢驗連鎖付錢 | F72: ② 起步中：剛開始有人做 | G72: =IF($A72="","",IF($H72=0,"（尚無對應能力）",IFERROR(INDEX(16_能力商機矩陣_CapOppMap!$D$160:$CO$160,MATCH($A72,16_能力商機矩陣_CapOppMap!$D$4:$CO$4,0)),""))) -> D09 | H72: =IF($A72="","",IFERROR(INDEX(16_能力商機矩陣_CapOppMap!$D$156:$CO$156,MATCH($A72,16_能力商機矩陣_CapOppMap!$D$4:$CO$4,0)),"")) -> 1 | I72: =IF($A72="","",IFERROR(INDEX(16_能力商機矩陣_CapOppMap!$D$157:$CO$157,MATCH($A72,16_能力商機矩陣_CapOppMap!$D$4:$CO$4,0)),"")) -> 4 | J72: =IF($A72="","",IFERROR(INDEX(16_能力商機矩陣_CapOppMap!$D$158:$CO$158,MATCH($A72,16_能力商機矩陣_CapOppMap!$D$4:$CO$4,0)),"")) -> 3 | K72: =IF($A72="","",IFERROR(INDEX(16_能力商機矩陣_CapOppMap!$D$159:$CO$159,MATCH($A72,16_能力商機矩陣_CapOppMap!$D$4:$CO$4,0)),"")) -> 0 | L72: =IF($A72="","",IF($H72=0,"★白地商機：目前無對應能力，需新增能力或找新夥伴",IF($K72>0,"有缺口："&$K72&"項可對外招募","已有能力可承接"))) -> 已有能力可承接 | M72: G5 | N72: 醫院營運預算(OPEX) | O72: 管理服務 | P72: 100K-500K USD | Q72: 是 | R72: Supply Chain Lead | S72: 須符合藥品GSP規範；全民健檢與檢體外送量會把這塊撐大 | T72: =IF($A72="","",COUNTIF(14_商機清單_Pipeline!$A$5:$A$34,$U72)) -> 0 | U72: =IF($B72="","",$A72&" "&$B72) -> OPP-68 冷鏈與特殊物料物流 | V72: （待調查） | X72: =IF($A72="","",IFERROR(INDEX(16_能力商機矩陣_CapOppMap!$D$162:$CO$162,MATCH($A72,16_能力商機矩陣_CapOppMap!$D$4:$CO$4,0)),"")) -> 0 | Y72: =IF(OR($A72="",$H72=""),"",IF($H72=0,"",ROUND(0.45*$I72+0.35*$J72+0.2*IF(LEFT($F72,1)="③",5,IF(LEFT($F72,1)="②",3,1))-IF($K72>0,0.3,0),2)+ROW()/100000)) -> 3.45072 | Z72: =IF($Y72="","",RANK($Y72,$Y$5:$Y$94)) -> 48 | AA72: L6 照護營運層 | AB72: 冷鏈2023年1.63億美元、CAGR 14.1%（2024-29）；醫藥端Zuellig/DKSH主導；北越成長最快。 | AC72: A | AD72: FM市場2024年約25億美元（JLL、CBRE、ISS、Sodexo等，醫療列重點場域）；冷鏈2023年1.63億美元、CAGR 14.1%（Zuellig、DKSH主導醫藥端）；設備寄放/按次計費模式2024年入法＝醫材託管服務（MES）首次有法源。SPD/CSSD/CMMS：越南無公開市場統計——政策先行、資料空白的早期市場。
A73: OPP-69 | B73: 醫療廢棄物收運處理服務 | C73: Medical Waste Collection & Treatment | D73: H 供應鏈與維運服務 | E73: 區域收運＋處理特許，按公斤計價服務一群醫院與診所 | F73: ② 起步中：剛開始有人做 | G73: =IF($A73="","",IF($H73=0,"（尚無對應能力）",IFERROR(INDEX(16_能力商機矩陣_CapOppMap!$D$160:$CO$160,MATCH($A73,16_能力商機矩陣_CapOppMap!$D$4:$CO$4,0)),""))) -> D03; D09 | H73: =IF($A73="","",IFERROR(INDEX(16_能力商機矩陣_CapOppMap!$D$156:$CO$156,MATCH($A73,16_能力商機矩陣_CapOppMap!$D$4:$CO$4,0)),"")) -> 2 | I73: =IF($A73="","",IFERROR(INDEX(16_能力商機矩陣_CapOppMap!$D$157:$CO$157,MATCH($A73,16_能力商機矩陣_CapOppMap!$D$4:$CO$4,0)),"")) -> 4.1 | J73: =IF($A73="","",IFERROR(INDEX(16_能力商機矩陣_CapOppMap!$D$158:$CO$158,MATCH($A73,16_能力商機矩陣_CapOppMap!$D$4:$CO$4,0)),"")) -> 2.7 | K73: =IF($A73="","",IFERROR(INDEX(16_能力商機矩陣_CapOppMap!$D$159:$CO$159,MATCH($A73,16_能力商機矩陣_CapOppMap!$D$4:$CO$4,0)),"")) -> 0 | L73: =IF($A73="","",IF($H73=0,"★白地商機：目前無對應能力，需新增能力或找新夥伴",IF($K73>0,"有缺口："&$K73&"項可對外招募","已有能力可承接"))) -> 已有能力可承接 | M73: G6 | N73: 醫院營運預算(OPEX) | O73: 管理服務 | P73: 500K-2M USD | Q73: 是 | R73: ESG/Facility Lead | S73: 市場高度分散、在地執照是門檻，適合與越南夥伴合資 | T73: =IF($A73="","",COUNTIF(14_商機清單_Pipeline!$A$5:$A$34,$U73)) -> 0 | U73: =IF($B73="","",$A73&" "&$B73) -> OPP-69 醫療廢棄物收運處理服務 | V73: （待調查） | X73: =IF($A73="","",IFERROR(INDEX(16_能力商機矩陣_CapOppMap!$D$162:$CO$162,MATCH($A73,16_能力商機矩陣_CapOppMap!$D$4:$CO$4,0)),"")) -> 0 | Y73: =IF(OR($A73="",$H73=""),"",IF($H73=0,"",ROUND(0.45*$I73+0.35*$J73+0.2*IF(LEFT($F73,1)="③",5,IF(LEFT($F73,1)="②",3,1))-IF($K73>0,0.3,0),2)+ROW()/100000)) -> 3.39073 | Z73: =IF($Y73="","",RANK($Y73,$Y$5:$Y$94)) -> 52 | AA73: L6 照護營運層 | AB73: 量能總量夠但區域錯配（全國焚化使用率7.4% vs 胡志明尖峰780%）；院內管理依Circular 20/2021/TT-BYT；業者URENCO系、INSEE Ecocycle。 | AC73: A | AD73: FM市場2024年約25億美元（JLL、CBRE、ISS、Sodexo等，醫療列重點場域）；冷鏈2023年1.63億美元、CAGR 14.1%（Zuellig、DKSH主導醫藥端）；設備寄放/按次計費模式2024年入法＝醫材託管服務（MES）首次有法源。SPD/CSSD/CMMS：越南無公開市場統計——政策先行、資料空白的早期市場。
A74: OPP-70 | B74: 在地備品、維修與汰換服務網 | C74: Local Spare Parts & Service Network | D74: H 供應鏈與維運服務 | E74: 備品庫存、維修、校正與汰換；覆蓋省份與到場時間是賣點 | F74: ② 起步中：剛開始有人做 | G74: =IF($A74="","",IF($H74=0,"（尚無對應能力）",IFERROR(INDEX(16_能力商機矩陣_CapOppMap!$D$160:$CO$160,MATCH($A74,16_能力商機矩陣_CapOppMap!$D$4:$CO$4,0)),""))) -> D09 | H74: =IF($A74="","",IFERROR(INDEX(16_能力商機矩陣_CapOppMap!$D$156:$CO$156,MATCH($A74,16_能力商機矩陣_CapOppMap!$D$4:$CO$4,0)),"")) -> 1 | I74: =IF($A74="","",IFERROR(INDEX(16_能力商機矩陣_CapOppMap!$D$157:$CO$157,MATCH($A74,16_能力商機矩陣_CapOppMap!$D$4:$CO$4,0)),"")) -> 3.7 | J74: =IF($A74="","",IFERROR(INDEX(16_能力商機矩陣_CapOppMap!$D$158:$CO$158,MATCH($A74,16_能力商機矩陣_CapOppMap!$D$4:$CO$4,0)),"")) -> 3 | K74: =IF($A74="","",IFERROR(INDEX(16_能力商機矩陣_CapOppMap!$D$159:$CO$159,MATCH($A74,16_能力商機矩陣_CapOppMap!$D$4:$CO$4,0)),"")) -> 0 | L74: =IF($A74="","",IF($H74=0,"★白地商機：目前無對應能力，需新增能力或找新夥伴",IF($K74>0,"有缺口："&$K74&"項可對外招募","已有能力可承接"))) -> 已有能力可承接 | M74: G6 | N74: 醫院營運預算(OPEX) | O74: 管理服務 | P74: 100K-500K USD | Q74: 是 | R74: FM Lead | S74: 是OPP-66託管服務的執行底層；沒有這張網，任何設備長約都做不下去 | T74: =IF($A74="","",COUNTIF(14_商機清單_Pipeline!$A$5:$A$34,$U74)) -> 0 | U74: =IF($B74="","",$A74&" "&$B74) -> OPP-70 在地備品、維修與汰換服務網 | V74: （待調查） | X74: =IF($A74="","",IFERROR(INDEX(16_能力商機矩陣_CapOppMap!$D$162:$CO$162,MATCH($A74,16_能力商機矩陣_CapOppMap!$D$4:$CO$4,0)),"")) -> 0 | Y74: =IF(OR($A74="",$H74=""),"",IF($H74=0,"",ROUND(0.45*$I74+0.35*$J74+0.2*IF(LEFT($F74,1)="③",5,IF(LEFT($F74,1)="②",3,1))-IF($K74>0,0.3,0),2)+ROW()/100000)) -> 3.32074 | Z74: =IF($Y74="","",RANK($Y74,$Y$5:$Y$94)) -> 56 | AA74: L6 照護營運層 | AB74: （本項無專屬發現——見同列右方的家族／領域趨勢，或 19／20 分頁） | AC74: B | AD74: FM市場2024年約25億美元（JLL、CBRE、ISS、Sodexo等，醫療列重點場域）；冷鏈2023年1.63億美元、CAGR 14.1%（Zuellig、DKSH主導醫藥端）；設備寄放/按次計費模式2024年入法＝醫材託管服務（MES）首次有法源。SPD/CSSD/CMMS：越南無公開市場統計——政策先行、資料空白的早期市場。
A75: OPP-71 | B75: 洗腎連鎖（衛星洗腎中心） | C75: Dialysis Clinic Chain | D75: I 照護服務新業態 | E75: 在都市以外開衛星洗腎站；健保給付每次洗腎，是最明確的經常性收入 | F75: ③ 尚未出現：幾乎空白 | G75: =IF($A75="","",IF($H75=0,"（尚無對應能力）",IFERROR(INDEX(16_能力商機矩陣_CapOppMap!$D$160:$CO$160,MATCH($A75,16_能力商機矩陣_CapOppMap!$D$4:$CO$4,0)),""))) -> D05 | H75: =IF($A75="","",IFERROR(INDEX(16_能力商機矩陣_CapOppMap!$D$156:$CO$156,MATCH($A75,16_能力商機矩陣_CapOppMap!$D$4:$CO$4,0)),"")) -> 1 | I75: =IF($A75="","",IFERROR(INDEX(16_能力商機矩陣_CapOppMap!$D$157:$CO$157,MATCH($A75,16_能力商機矩陣_CapOppMap!$D$4:$CO$4,0)),"")) -> 4.7 | J75: =IF($A75="","",IFERROR(INDEX(16_能力商機矩陣_CapOppMap!$D$158:$CO$158,MATCH($A75,16_能力商機矩陣_CapOppMap!$D$4:$CO$4,0)),"")) -> 2.4 | K75: =IF($A75="","",IFERROR(INDEX(16_能力商機矩陣_CapOppMap!$D$159:$CO$159,MATCH($A75,16_能力商機矩陣_CapOppMap!$D$4:$CO$4,0)),"")) -> 0 | L75: =IF($A75="","",IF($H75=0,"★白地商機：目前無對應能力，需新增能力或找新夥伴",IF($K75>0,"有缺口："&$K75&"項可對外招募","已有能力可承接"))) -> 已有能力可承接 | M75: G6 | N75: 越南健保(VSS)給付 | O75: 民營醫院投資 | P75: 500K-2M USD | Q75: 是 | R75: Clinical Operator | S75: ★約80%洗腎中心集中都市、鄉村是空白；每20床單位約US$50-150萬，連鎖化可做到US$1000-5000萬 | T75: =IF($A75="","",COUNTIF(14_商機清單_Pipeline!$A$5:$A$34,$U75)) -> 0 | U75: =IF($B75="","",$A75&" "&$B75) -> OPP-71 洗腎連鎖（衛星洗腎中心） | V75: 在地私人洗腎中心擴張中，但約80%集中都市 | W75: 下沉省級＋VSS給付現金流＋台灣腎照護protocol | X75: =IF($A75="","",IFERROR(INDEX(16_能力商機矩陣_CapOppMap!$D$162:$CO$162,MATCH($A75,16_能力商機矩陣_CapOppMap!$D$4:$CO$4,0)),"")) -> 0 | Y75: =IF(OR($A75="",$H75=""),"",IF($H75=0,"",ROUND(0.45*$I75+0.35*$J75+0.2*IF(LEFT($F75,1)="③",5,IF(LEFT($F75,1)="②",3,1))-IF($K75>0,0.3,0),2)+ROW()/100000)) -> 3.96075 | Z75: =IF($Y75="","",RANK($Y75,$Y$5:$Y$94)) -> 7 | AA75: L6 照護營運層 | AB75: 中文有「衛星」、EN無→建議：Satellite Dialysis Clinic Chain。需求>10萬vs服務3.6萬＝東南亞最大透析白地之一；本土連鎖品牌未查得、B.Braun有布局。 | AC75: A | AD75: 硬缺口全報告最強：透析需求>10萬人、實際服務僅3.6萬（覆蓋1/3）；放療84台僅滿足60-70%需求（K醫院籌建北越首座質子中心4.2兆越盾）；IVF年5萬+週期、65家中心、價格為已開發國家1/5。遠距醫療法源齊備（Law 15/2023＋Circular 30/2023列50種疾病）。99%長者靠家庭照顧、2036年進入高齡社會、長照保險未立法。醫護人力：2022上半年9,680人離職，人力是最大瓶頸。
A76: OPP-72 | B76: 日間手術中心(ASC) | C76: Ambulatory Surgery Centre | D76: I 照護服務新業態 | E76: 白內障、疝氣、內視鏡、耳鼻喉與骨科的日間手術；自費與商業保險，未來健保 | F76: ③ 尚未出現：幾乎空白 | G76: =IF($A76="","",IF($H76=0,"（尚無對應能力）",IFERROR(INDEX(16_能力商機矩陣_CapOppMap!$D$160:$CO$160,MATCH($A76,16_能力商機矩陣_CapOppMap!$D$4:$CO$4,0)),""))) -> D02; D05 | H76: =IF($A76="","",IFERROR(INDEX(16_能力商機矩陣_CapOppMap!$D$156:$CO$156,MATCH($A76,16_能力商機矩陣_CapOppMap!$D$4:$CO$4,0)),"")) -> 2 | I76: =IF($A76="","",IFERROR(INDEX(16_能力商機矩陣_CapOppMap!$D$157:$CO$157,MATCH($A76,16_能力商機矩陣_CapOppMap!$D$4:$CO$4,0)),"")) -> 4.7 | J76: =IF($A76="","",IFERROR(INDEX(16_能力商機矩陣_CapOppMap!$D$158:$CO$158,MATCH($A76,16_能力商機矩陣_CapOppMap!$D$4:$CO$4,0)),"")) -> 2.6 | K76: =IF($A76="","",IFERROR(INDEX(16_能力商機矩陣_CapOppMap!$D$159:$CO$159,MATCH($A76,16_能力商機矩陣_CapOppMap!$D$4:$CO$4,0)),"")) -> 1 | L76: =IF($A76="","",IF($H76=0,"★白地商機：目前無對應能力，需新增能力或找新夥伴",IF($K76>0,"有缺口："&$K76&"項可對外招募","已有能力可承接"))) -> 有缺口：1項可對外招募 | M76: G6 | N76: 病人自費 | O76: 民營醫院投資 | P76: 2M-10M USD | Q76: 是 | R76: Clinical Operator | S76: 2027年第2季起的分級轉診改革會把病人從中央醫院推下來，需求就是那時候出現 | T76: =IF($A76="","",COUNTIF(14_商機清單_Pipeline!$A$5:$A$34,$U76)) -> 0 | U76: =IF($B76="","",$A76&" "&$B76) -> OPP-72 日間手術中心(ASC) | V76: 幾乎空白；2027Q2 分級轉診改革將創造需求 | W76: 搶改革時間差：白內障/內視鏡日間手術先行 | X76: =IF($A76="","",IFERROR(INDEX(16_能力商機矩陣_CapOppMap!$D$162:$CO$162,MATCH($A76,16_能力商機矩陣_CapOppMap!$D$4:$CO$4,0)),"")) -> 0 | Y76: =IF(OR($A76="",$H76=""),"",IF($H76=0,"",ROUND(0.45*$I76+0.35*$J76+0.2*IF(LEFT($F76,1)="③",5,IF(LEFT($F76,1)="②",3,1))-IF($K76>0,0.3,0),2)+ROW()/100000)) -> 3.73076 | Z76: =IF($Y76="","",RANK($Y76,$Y$5:$Y$94)) -> 26 | AA76: L6 照護營運層 | AB76: 越南獨立ASC業態實證未查得；機構型態是否允許獨立ASC需查Decree 96/2023分類——進場前必做法規確認。 | AC76: C | AD76: 硬缺口全報告最強：透析需求>10萬人、實際服務僅3.6萬（覆蓋1/3）；放療84台僅滿足60-70%需求（K醫院籌建北越首座質子中心4.2兆越盾）；IVF年5萬+週期、65家中心、價格為已開發國家1/5。遠距醫療法源齊備（Law 15/2023＋Circular 30/2023列50種疾病）。99%長者靠家庭照顧、2036年進入高齡社會、長照保險未立法。醫護人力：2022上半年9,680人離職，人力是最大瓶頸。
A77: OPP-73 | B77: 癌症中心合資經營 | C77: Cancer Centre JV | D77: I 照護服務新業態 | E77: 在省級醫院旁邊建置並經營放療＋化療日間病房，用台灣臨床protocol與物理師 | F77: ③ 尚未出現：幾乎空白 | G77: =IF($A77="","",IF($H77=0,"（尚無對應能力）",IFERROR(INDEX(16_能力商機矩陣_CapOppMap!$D$160:$CO$160,MATCH($A77,16_能力商機矩陣_CapOppMap!$D$4:$CO$4,0)),""))) -> D05 | H77: =IF($A77="","",IFERROR(INDEX(16_能力商機矩陣_CapOppMap!$D$156:$CO$156,MATCH($A77,16_能力商機矩陣_CapOppMap!$D$4:$CO$4,0)),"")) -> 2 | I77: =IF($A77="","",IFERROR(INDEX(16_能力商機矩陣_CapOppMap!$D$157:$CO$157,MATCH($A77,16_能力商機矩陣_CapOppMap!$D$4:$CO$4,0)),"")) -> 4.7 | J77: =IF($A77="","",IFERROR(INDEX(16_能力商機矩陣_CapOppMap!$D$158:$CO$158,MATCH($A77,16_能力商機矩陣_CapOppMap!$D$4:$CO$4,0)),"")) -> 2.4 | K77: =IF($A77="","",IFERROR(INDEX(16_能力商機矩陣_CapOppMap!$D$159:$CO$159,MATCH($A77,16_能力商機矩陣_CapOppMap!$D$4:$CO$4,0)),"")) -> 1 | L77: =IF($A77="","",IF($H77=0,"★白地商機：目前無對應能力，需新增能力或找新夥伴",IF($K77>0,"有缺口："&$K77&"項可對外招募","已有能力可承接"))) -> 有缺口：1項可對外招募 | M77: G6 | N77: 越南健保(VSS)給付 | O77: 共址合資 | P77: >10M USD | Q77: 需組合 | R77: Clinical Operator | S77: ★最大的臨床量能缺口，而且健保已經在給付放療——需求與付費方都在，缺的是能力與資金 | T77: =IF($A77="","",COUNTIF(14_商機清單_Pipeline!$A$5:$A$34,$U77)) -> 0 | U77: =IF($B77="","",$A77&" "&$B77) -> OPP-73 癌症中心合資經營 | V77: Vinmec/Tam Anh 腫瘤科在都會擴張 | W77: 省級醫院共址合資＋台灣protocol＋物理師，避開都會私院戰場 | X77: =IF($A77="","",IFERROR(INDEX(16_能力商機矩陣_CapOppMap!$D$162:$CO$162,MATCH($A77,16_能力商機矩陣_CapOppMap!$D$4:$CO$4,0)),"")) -> 0 | Y77: =IF(OR($A77="",$H77=""),"",IF($H77=0,"",ROUND(0.45*$I77+0.35*$J77+0.2*IF(LEFT($F77,1)="③",5,IF(LEFT($F77,1)="②",3,1))-IF($K77>0,0.3,0),2)+ROW()/100000)) -> 3.66077 | Z77: =IF($Y77="","",RANK($Y77,$Y$5:$Y$94)) -> 33 | AA77: L6 照護營運層 | AB77: 放療缺口數據確鑿（84台、滿足60-70%）；K醫院質子中心為公立自建；民間合資具名案例未查得。GLOBOCAN 2022：年新發18.05萬例、死亡12.02萬。 | AC77: A | AD77: 硬缺口全報告最強：透析需求>10萬人、實際服務僅3.6萬（覆蓋1/3）；放療84台僅滿足60-70%需求（K醫院籌建北越首座質子中心4.2兆越盾）；IVF年5萬+週期、65家中心、價格為已開發國家1/5。遠距醫療法源齊備（Law 15/2023＋Circular 30/2023列50種疾病）。99%長者靠家庭照顧、2036年進入高齡社會、長照保險未立法。醫護人力：2022上半年9,680人離職，人力是最大瓶頸。
A78: OPP-74 | B78: 生殖醫學(IVF)連鎖 | C78: IVF Clinic Chain | D78: I 照護服務新業態 | E78: 品牌化生殖中心，台灣實驗室主任掛牌；100%病人自費、單價高 | F78: ② 起步中：剛開始有人做 | G78: =IF($A78="","",IF($H78=0,"（尚無對應能力）",IFERROR(INDEX(16_能力商機矩陣_CapOppMap!$D$160:$CO$160,MATCH($A78,16_能力商機矩陣_CapOppMap!$D$4:$CO$4,0)),""))) -> D02 | H78: =IF($A78="","",IFERROR(INDEX(16_能力商機矩陣_CapOppMap!$D$156:$CO$156,MATCH($A78,16_能力商機矩陣_CapOppMap!$D$4:$CO$4,0)),"")) -> 2 | I78: =IF($A78="","",IFERROR(INDEX(16_能力商機矩陣_CapOppMap!$D$157:$CO$157,MATCH($A78,16_能力商機矩陣_CapOppMap!$D$4:$CO$4,0)),"")) -> 4.9 | J78: =IF($A78="","",IFERROR(INDEX(16_能力商機矩陣_CapOppMap!$D$158:$CO$158,MATCH($A78,16_能力商機矩陣_CapOppMap!$D$4:$CO$4,0)),"")) -> 2.7 | K78: =IF($A78="","",IFERROR(INDEX(16_能力商機矩陣_CapOppMap!$D$159:$CO$159,MATCH($A78,16_能力商機矩陣_CapOppMap!$D$4:$CO$4,0)),"")) -> 0 | L78: =IF($A78="","",IF($H78=0,"★白地商機：目前無對應能力，需新增能力或找新夥伴",IF($K78>0,"有缺口："&$K78&"項可對外招募","已有能力可承接"))) -> 已有能力可承接 | M78: G6 | N78: 病人自費 | O78: 民營醫院投資 | P78: 2M-10M USD | Q78: 是 | R78: Clinical Operator | S78: 外資友善、不涉健保糾纏，是台灣醫療品牌最容易落地的業態之一 | T78: =IF($A78="","",COUNTIF(14_商機清單_Pipeline!$A$5:$A$34,$U78)) -> 0 | U78: =IF($B78="","",$A78&" "&$B78) -> OPP-74 生殖醫學(IVF)連鎖 | V78: （待調查） | X78: =IF($A78="","",IFERROR(INDEX(16_能力商機矩陣_CapOppMap!$D$162:$CO$162,MATCH($A78,16_能力商機矩陣_CapOppMap!$D$4:$CO$4,0)),"")) -> 0 | Y78: =IF(OR($A78="",$H78=""),"",IF($H78=0,"",ROUND(0.45*$I78+0.35*$J78+0.2*IF(LEFT($F78,1)="③",5,IF(LEFT($F78,1)="②",3,1))-IF($K78>0,0.3,0),2)+ROW()/100000)) -> 3.75078 | Z78: =IF($Y78="","",RANK($Y78,$Y$5:$Y$94)) -> 25 | AA78: L6 照護營運層 | AB78: 年5萬+週期、65中心；龍頭My Duc（IVFMD）、Tam Anh；價格優勢（1/5）疊加醫療觀光題材。 | AC78: A | AD78: 硬缺口全報告最強：透析需求>10萬人、實際服務僅3.6萬（覆蓋1/3）；放療84台僅滿足60-70%需求（K醫院籌建北越首座質子中心4.2兆越盾）；IVF年5萬+週期、65家中心、價格為已開發國家1/5。遠距醫療法源齊備（Law 15/2023＋Circular 30/2023列50種疾病）。99%長者靠家庭照顧、2036年進入高齡社會、長照保險未立法。醫護人力：2022上半年9,680人離職，人力是最大瓶頸。
A79: OPP-75 | B79: 健檢連鎖與行動篩檢營運 | C79: Health Screening Chain & Mobile Screening | D79: I 照護服務新業態 | E79: 承接省級的全民健檢量能，也做企業健檢；省預算、健保與雇主付錢 | F79: ② 起步中：剛開始有人做 | G79: =IF($A79="","",IF($H79=0,"（尚無對應能力）",IFERROR(INDEX(16_能力商機矩陣_CapOppMap!$D$160:$CO$160,MATCH($A79,16_能力商機矩陣_CapOppMap!$D$4:$CO$4,0)),""))) -> D02 | H79: =IF($A79="","",IFERROR(INDEX(16_能力商機矩陣_CapOppMap!$D$156:$CO$156,MATCH($A79,16_能力商機矩陣_CapOppMap!$D$4:$CO$4,0)),"")) -> 2 | I79: =IF($A79="","",IFERROR(INDEX(16_能力商機矩陣_CapOppMap!$D$157:$CO$157,MATCH($A79,16_能力商機矩陣_CapOppMap!$D$4:$CO$4,0)),"")) -> 4.9 | J79: =IF($A79="","",IFERROR(INDEX(16_能力商機矩陣_CapOppMap!$D$158:$CO$158,MATCH($A79,16_能力商機矩陣_CapOppMap!$D$4:$CO$4,0)),"")) -> 2.7 | K79: =IF($A79="","",IFERROR(INDEX(16_能力商機矩陣_CapOppMap!$D$159:$CO$159,MATCH($A79,16_能力商機矩陣_CapOppMap!$D$4:$CO$4,0)),"")) -> 0 | L79: =IF($A79="","",IF($H79=0,"★白地商機：目前無對應能力，需新增能力或找新夥伴",IF($K79>0,"有缺口："&$K79&"項可對外招募","已有能力可承接"))) -> 已有能力可承接 | M79: G6 | N79: 省級衛生局預算 | O79: 分潤／服務分成 | P79: 2M-10M USD | Q79: 是 | R79: Clinical Operator | S79: ★2026年起全民免費健檢：全國優先族群約US$227m/年、胡志明市單城約US$95m/年，是時程確定的需求衝擊 | T79: =IF($A79="","",COUNTIF(14_商機清單_Pipeline!$A$5:$A$34,$U79)) -> 1 | U79: =IF($B79="","",$A79&" "&$B79) -> OPP-75 健檢連鎖與行動篩檢營運 | V79: Medlatec/Diag 行動採檢已在做 | W79: 整車隊＋AI判讀＋省級整包承攬（政策量能缺口大） | X79: =IF($A79="","",IFERROR(INDEX(16_能力商機矩陣_CapOppMap!$D$162:$CO$162,MATCH($A79,16_能力商機矩陣_CapOppMap!$D$4:$CO$4,0)),"")) -> 0 | Y79: =IF(OR($A79="",$H79=""),"",IF($H79=0,"",ROUND(0.45*$I79+0.35*$J79+0.2*IF(LEFT($F79,1)="③",5,IF(LEFT($F79,1)="②",3,1))-IF($K79>0,0.3,0),2)+ROW()/100000)) -> 3.75079 | Z79: =IF($Y79="","",RANK($Y79,$Y$5:$Y$94)) -> 24 | AA79: L6 照護營運層 | AB79: Medlatec以檢驗＋到府採檢建立全國網絡＝商模已驗證；獨立檢驗市場成形。 | AC79: A | AD79: 硬缺口全報告最強：透析需求>10萬人、實際服務僅3.6萬（覆蓋1/3）；放療84台僅滿足60-70%需求（K醫院籌建北越首座質子中心4.2兆越盾）；IVF年5萬+週期、65家中心、價格為已開發國家1/5。遠距醫療法源齊備（Law 15/2023＋Circular 30/2023列50種疾病）。99%長者靠家庭照顧、2036年進入高齡社會、長照保險未立法。醫護人力：2022上半年9,680人離職，人力是最大瓶頸。
A80: OPP-76 | B80: 委外檢驗與區域中心實驗室 | C80: Reference Lab & Outsourced Testing | D80: I 照護服務新業態 | E80: 接醫院外送檢體與篩檢方案的量；按件計價向醫院、健保與雇主收費 | F80: ② 起步中：剛開始有人做 | G80: =IF($A80="","",IF($H80=0,"（尚無對應能力）",IFERROR(INDEX(16_能力商機矩陣_CapOppMap!$D$160:$CO$160,MATCH($A80,16_能力商機矩陣_CapOppMap!$D$4:$CO$4,0)),""))) -> D05 | H80: =IF($A80="","",IFERROR(INDEX(16_能力商機矩陣_CapOppMap!$D$156:$CO$156,MATCH($A80,16_能力商機矩陣_CapOppMap!$D$4:$CO$4,0)),"")) -> 1 | I80: =IF($A80="","",IFERROR(INDEX(16_能力商機矩陣_CapOppMap!$D$157:$CO$157,MATCH($A80,16_能力商機矩陣_CapOppMap!$D$4:$CO$4,0)),"")) -> 4.3 | J80: =IF($A80="","",IFERROR(INDEX(16_能力商機矩陣_CapOppMap!$D$158:$CO$158,MATCH($A80,16_能力商機矩陣_CapOppMap!$D$4:$CO$4,0)),"")) -> 2.4 | K80: =IF($A80="","",IFERROR(INDEX(16_能力商機矩陣_CapOppMap!$D$159:$CO$159,MATCH($A80,16_能力商機矩陣_CapOppMap!$D$4:$CO$4,0)),"")) -> 1 | L80: =IF($A80="","",IF($H80=0,"★白地商機：目前無對應能力，需新增能力或找新夥伴",IF($K80>0,"有缺口："&$K80&"項可對外招募","已有能力可承接"))) -> 有缺口：1項可對外招募 | M80: G6 | N80: 醫院營運預算(OPEX) | O80: 分潤／服務分成 | P80: 2M-10M USD | Q80: 是 | R80: Laboratory Lead | S80: Diag、PATHLAB等已在整併；健檢政策是量能驅動力 | T80: =IF($A80="","",COUNTIF(14_商機清單_Pipeline!$A$5:$A$34,$U80)) -> 0 | U80: =IF($B80="","",$A80&" "&$B80) -> OPP-76 委外檢驗與區域中心實驗室 | V80: Diag/PATHLAB/Himedic/Chemedic 四強整併中 | W80: 不自建連鎖：賣 hub lab 自動化＋認證給整併者 | X80: =IF($A80="","",IFERROR(INDEX(16_能力商機矩陣_CapOppMap!$D$162:$CO$162,MATCH($A80,16_能力商機矩陣_CapOppMap!$D$4:$CO$4,0)),"")) -> 0 | Y80: =IF(OR($A80="",$H80=""),"",IF($H80=0,"",ROUND(0.45*$I80+0.35*$J80+0.2*IF(LEFT($F80,1)="③",5,IF(LEFT($F80,1)="②",3,1))-IF($K80>0,0.3,0),2)+ROW()/100000)) -> 3.0808 | Z80: =IF($Y80="","",RANK($Y80,$Y$5:$Y$94)) -> 70 | AA80: L6 照護營運層 | AB80: （本項無專屬發現——見同列右方的家族／領域趨勢，或 19／20 分頁） | AC80: B | AD80: 硬缺口全報告最強：透析需求>10萬人、實際服務僅3.6萬（覆蓋1/3）；放療84台僅滿足60-70%需求（K醫院籌建北越首座質子中心4.2兆越盾）；IVF年5萬+週期、65家中心、價格為已開發國家1/5。遠距醫療法源齊備（Law 15/2023＋Circular 30/2023列50種疾病）。99%長者靠家庭照顧、2036年進入高齡社會、長照保險未立法。醫護人力：2022上半年9,680人離職，人力是最大瓶頸。
A81: OPP-77 | B81: 長照機構與失智照護 | C81: Long-term Care & Dementia Facility | D81: I 照護服務新業態 | E81: 住宿型照護與失智專區，加上營運know-how；目前幾乎全是家屬自費 | F81: ③ 尚未出現：幾乎空白 | G81: =IF($A81="","",IF($H81=0,"（尚無對應能力）",IFERROR(INDEX(16_能力商機矩陣_CapOppMap!$D$160:$CO$160,MATCH($A81,16_能力商機矩陣_CapOppMap!$D$4:$CO$4,0)),""))) -> D02; D08 | H81: =IF($A81="","",IFERROR(INDEX(16_能力商機矩陣_CapOppMap!$D$156:$CO$156,MATCH($A81,16_能力商機矩陣_CapOppMap!$D$4:$CO$4,0)),"")) -> 2 | I81: =IF($A81="","",IFERROR(INDEX(16_能力商機矩陣_CapOppMap!$D$157:$CO$157,MATCH($A81,16_能力商機矩陣_CapOppMap!$D$4:$CO$4,0)),"")) -> 4.7 | J81: =IF($A81="","",IFERROR(INDEX(16_能力商機矩陣_CapOppMap!$D$158:$CO$158,MATCH($A81,16_能力商機矩陣_CapOppMap!$D$4:$CO$4,0)),"")) -> 2.9 | K81: =IF($A81="","",IFERROR(INDEX(16_能力商機矩陣_CapOppMap!$D$159:$CO$159,MATCH($A81,16_能力商機矩陣_CapOppMap!$D$4:$CO$4,0)),"")) -> 1 | L81: =IF($A81="","",IF($H81=0,"★白地商機：目前無對應能力，需新增能力或找新夥伴",IF($K81>0,"有缺口："&$K81&"項可對外招募","已有能力可承接"))) -> 有缺口：1項可對外招募 | M81: G6 | N81: 病人自費 | O81: 民營醫院投資 | P81: 2M-10M USD | Q81: 是 | R81: Clinical Operator | S81: ★全國僅約80家私立養護中心、1家老年醫院；需日常照護人口將從400萬(2019)增至1000萬(2030) | T81: =IF($A81="","",COUNTIF(14_商機清單_Pipeline!$A$5:$A$34,$U81)) -> 0 | U81: =IF($B81="","",$A81&" "&$B81) -> OPP-77 長照機構與失智照護 | V81: 全國僅約80家私立養護、無外資連鎖 | W81: 台灣長照體系輸出＋失智照護，先做高端自費 | X81: =IF($A81="","",IFERROR(INDEX(16_能力商機矩陣_CapOppMap!$D$162:$CO$162,MATCH($A81,16_能力商機矩陣_CapOppMap!$D$4:$CO$4,0)),"")) -> 0 | Y81: =IF(OR($A81="",$H81=""),"",IF($H81=0,"",ROUND(0.45*$I81+0.35*$J81+0.2*IF(LEFT($F81,1)="③",5,IF(LEFT($F81,1)="②",3,1))-IF($K81>0,0.3,0),2)+ROW()/100000)) -> 3.83081 | Z81: =IF($Y81="","",RANK($Y81,$Y$5:$Y$94)) -> 19 | AA81: L6 照護營運層 | AB81: 99%長者依賴家庭照顧、76%無年金；約2036年進入高齡社會；長照保險僅學術討論——政策空窗＋自費市場先行。 | AC81: A | AD81: 硬缺口全報告最強：透析需求>10萬人、實際服務僅3.6萬（覆蓋1/3）；放療84台僅滿足60-70%需求（K醫院籌建北越首座質子中心4.2兆越盾）；IVF年5萬+週期、65家中心、價格為已開發國家1/5。遠距醫療法源齊備（Law 15/2023＋Circular 30/2023列50種疾病）。99%長者靠家庭照顧、2036年進入高齡社會、長照保險未立法。醫護人力：2022上半年9,680人離職，人力是最大瓶頸。
A82: OPP-78 | B82: 居家醫療、居家護理與安寧 | C82: Home Care, Home Nursing & Hospice | D82: I 照護服務新業態 | E82: 訂閱制到宅護理、術後照護與安寧；自費與商業保險，未來健保可能給付 | F82: ③ 尚未出現：幾乎空白 | G82: =IF($A82="","",IF($H82=0,"（尚無對應能力）",IFERROR(INDEX(16_能力商機矩陣_CapOppMap!$D$160:$CO$160,MATCH($A82,16_能力商機矩陣_CapOppMap!$D$4:$CO$4,0)),""))) -> D02 | H82: =IF($A82="","",IFERROR(INDEX(16_能力商機矩陣_CapOppMap!$D$156:$CO$156,MATCH($A82,16_能力商機矩陣_CapOppMap!$D$4:$CO$4,0)),"")) -> 1 | I82: =IF($A82="","",IFERROR(INDEX(16_能力商機矩陣_CapOppMap!$D$157:$CO$157,MATCH($A82,16_能力商機矩陣_CapOppMap!$D$4:$CO$4,0)),"")) -> 5 | J82: =IF($A82="","",IFERROR(INDEX(16_能力商機矩陣_CapOppMap!$D$158:$CO$158,MATCH($A82,16_能力商機矩陣_CapOppMap!$D$4:$CO$4,0)),"")) -> 2.7 | K82: =IF($A82="","",IFERROR(INDEX(16_能力商機矩陣_CapOppMap!$D$159:$CO$159,MATCH($A82,16_能力商機矩陣_CapOppMap!$D$4:$CO$4,0)),"")) -> 0 | L82: =IF($A82="","",IF($H82=0,"★白地商機：目前無對應能力，需新增能力或找新夥伴",IF($K82>0,"有缺口："&$K82&"項可對外招募","已有能力可承接"))) -> 已有能力可承接 | M82: G6 | N82: 病人自費 | O82: 分潤／服務分成 | P82: 100K-500K USD | Q82: 是 | R82: Clinical Operator | S82: ★約90%越南長者希望在家受照顧，但沒有任何規模化業者；輕資產、適合當第一步落地 | T82: =IF($A82="","",COUNTIF(14_商機清單_Pipeline!$A$5:$A$34,$U82)) -> 0 | U82: =IF($B82="","",$A82&" "&$B82) -> OPP-78 居家醫療、居家護理與安寧 | V82: 無規模化業者（約90%長者盼在宅照顧） | W82: 輕資產訂閱制，綁醫院出院轉銜 | X82: =IF($A82="","",IFERROR(INDEX(16_能力商機矩陣_CapOppMap!$D$162:$CO$162,MATCH($A82,16_能力商機矩陣_CapOppMap!$D$4:$CO$4,0)),"")) -> 0 | Y82: =IF(OR($A82="",$H82=""),"",IF($H82=0,"",ROUND(0.45*$I82+0.35*$J82+0.2*IF(LEFT($F82,1)="③",5,IF(LEFT($F82,1)="②",3,1))-IF($K82>0,0.3,0),2)+ROW()/100000)) -> 4.20082 | Z82: =IF($Y82="","",RANK($Y82,$Y$5:$Y$94)) -> 1 | AA82: L6 照護營運層 | AB82: （本項無專屬發現——見同列右方的家族／領域趨勢，或 19／20 分頁） | AC82: B | AD82: 硬缺口全報告最強：透析需求>10萬人、實際服務僅3.6萬（覆蓋1/3）；放療84台僅滿足60-70%需求（K醫院籌建北越首座質子中心4.2兆越盾）；IVF年5萬+週期、65家中心、價格為已開發國家1/5。遠距醫療法源齊備（Law 15/2023＋Circular 30/2023列50種疾病）。99%長者靠家庭照顧、2036年進入高齡社會、長照保險未立法。醫護人力：2022上半年9,680人離職，人力是最大瓶頸。
A83: OPP-79 | B83: 復健與亞急性照護中心 | C83: Rehabilitation & Sub-acute Care | D83: I 照護服務新業態 | E83: 中風、骨科術後與長者失能的復健床；健保部分給付＋自費 | F83: ③ 尚未出現：幾乎空白 | G83: =IF($A83="","",IF($H83=0,"（尚無對應能力）",IFERROR(INDEX(16_能力商機矩陣_CapOppMap!$D$160:$CO$160,MATCH($A83,16_能力商機矩陣_CapOppMap!$D$4:$CO$4,0)),""))) -> D02 | H83: =IF($A83="","",IFERROR(INDEX(16_能力商機矩陣_CapOppMap!$D$156:$CO$156,MATCH($A83,16_能力商機矩陣_CapOppMap!$D$4:$CO$4,0)),"")) -> 2 | I83: =IF($A83="","",IFERROR(INDEX(16_能力商機矩陣_CapOppMap!$D$157:$CO$157,MATCH($A83,16_能力商機矩陣_CapOppMap!$D$4:$CO$4,0)),"")) -> 4.9 | J83: =IF($A83="","",IFERROR(INDEX(16_能力商機矩陣_CapOppMap!$D$158:$CO$158,MATCH($A83,16_能力商機矩陣_CapOppMap!$D$4:$CO$4,0)),"")) -> 2.7 | K83: =IF($A83="","",IFERROR(INDEX(16_能力商機矩陣_CapOppMap!$D$159:$CO$159,MATCH($A83,16_能力商機矩陣_CapOppMap!$D$4:$CO$4,0)),"")) -> 0 | L83: =IF($A83="","",IF($H83=0,"★白地商機：目前無對應能力，需新增能力或找新夥伴",IF($K83>0,"有缺口："&$K83&"項可對外招募","已有能力可承接"))) -> 已有能力可承接 | M83: G6 | N83: 越南健保(VSS)給付 | O83: 民營醫院投資 | P83: 500K-2M USD | Q83: 是 | R83: Clinical Operator | S83: 中央醫院沒有床位留給復健，是分級轉診改革會釋出的另一塊需求 | T83: =IF($A83="","",COUNTIF(14_商機清單_Pipeline!$A$5:$A$34,$U83)) -> 0 | U83: =IF($B83="","",$A83&" "&$B83) -> OPP-79 復健與亞急性照護中心 | V83: （待調查） | X83: =IF($A83="","",IFERROR(INDEX(16_能力商機矩陣_CapOppMap!$D$162:$CO$162,MATCH($A83,16_能力商機矩陣_CapOppMap!$D$4:$CO$4,0)),"")) -> 0 | Y83: =IF(OR($A83="",$H83=""),"",IF($H83=0,"",ROUND(0.45*$I83+0.35*$J83+0.2*IF(LEFT($F83,1)="③",5,IF(LEFT($F83,1)="②",3,1))-IF($K83>0,0.3,0),2)+ROW()/100000)) -> 4.15083 | Z83: =IF($Y83="","",RANK($Y83,$Y$5:$Y$94)) -> 2 | AA83: L6 照護營運層 | AB83: 具名連鎖案例未查得＝空白。 | AC83: C | AD83: 硬缺口全報告最強：透析需求>10萬人、實際服務僅3.6萬（覆蓋1/3）；放療84台僅滿足60-70%需求（K醫院籌建北越首座質子中心4.2兆越盾）；IVF年5萬+週期、65家中心、價格為已開發國家1/5。遠距醫療法源齊備（Law 15/2023＋Circular 30/2023列50種疾病）。99%長者靠家庭照顧、2036年進入高齡社會、長照保險未立法。醫護人力：2022上半年9,680人離職，人力是最大瓶頸。
A84: OPP-80 | B84: 遠距醫療與居家遠端監測 | C84: Telehealth & Remote Patient Monitoring | D84: I 照護服務新業態 | E84: 遠距會診平台與居家監測設備＋警示；目前醫院自付，健保給付草案預計2027初生效 | F84: ② 起步中：剛開始有人做 | G84: =IF($A84="","",IF($H84=0,"（尚無對應能力）",IFERROR(INDEX(16_能力商機矩陣_CapOppMap!$D$160:$CO$160,MATCH($A84,16_能力商機矩陣_CapOppMap!$D$4:$CO$4,0)),""))) -> D06 | H84: =IF($A84="","",IFERROR(INDEX(16_能力商機矩陣_CapOppMap!$D$156:$CO$156,MATCH($A84,16_能力商機矩陣_CapOppMap!$D$4:$CO$4,0)),"")) -> 1 | I84: =IF($A84="","",IFERROR(INDEX(16_能力商機矩陣_CapOppMap!$D$157:$CO$157,MATCH($A84,16_能力商機矩陣_CapOppMap!$D$4:$CO$4,0)),"")) -> 4 | J84: =IF($A84="","",IFERROR(INDEX(16_能力商機矩陣_CapOppMap!$D$158:$CO$158,MATCH($A84,16_能力商機矩陣_CapOppMap!$D$4:$CO$4,0)),"")) -> 2.4 | K84: =IF($A84="","",IFERROR(INDEX(16_能力商機矩陣_CapOppMap!$D$159:$CO$159,MATCH($A84,16_能力商機矩陣_CapOppMap!$D$4:$CO$4,0)),"")) -> 1 | L84: =IF($A84="","",IF($H84=0,"★白地商機：目前無對應能力，需新增能力或找新夥伴",IF($K84>0,"有缺口："&$K84&"項可對外招募","已有能力可承接"))) -> 有缺口：1項可對外招募 | M84: G6 | N84: 越南健保(VSS)給付 | O84: 軟體授權／訂閱 | P84: 100K-500K USD | Q84: 需組合 | R84: Digital Patient Lead | S84: ★衛生部2026/8草案擬讓健保給付遠距與居家醫療、基金負擔50%價差——商機時程要押在2027 | T84: =IF($A84="","",COUNTIF(14_商機清單_Pipeline!$A$5:$A$34,$U84)) -> 0 | U84: =IF($B84="","",$A84&" "&$B84) -> OPP-80 遠距醫療與居家遠端監測 | V84: Viettel/VNPT 平台＋醫院自建 | W84: 押 2027 健保給付遠距的時點；先做自費慢病管理 | X84: =IF($A84="","",IFERROR(INDEX(16_能力商機矩陣_CapOppMap!$D$162:$CO$162,MATCH($A84,16_能力商機矩陣_CapOppMap!$D$4:$CO$4,0)),"")) -> 0 | Y84: =IF(OR($A84="",$H84=""),"",IF($H84=0,"",ROUND(0.45*$I84+0.35*$J84+0.2*IF(LEFT($F84,1)="③",5,IF(LEFT($F84,1)="②",3,1))-IF($K84>0,0.3,0),2)+ROW()/100000)) -> 2.94084 | Z84: =IF($Y84="","",RANK($Y84,$Y$5:$Y$94)) -> 74 | AA84: L6 照護營運層 | AB84: 法源齊備：Law 15/2023（2024-01生效）正式承認遠距診療＋Circular 30/2023列約20專科50種疾病；衛生部建VTelehealth平台；RPM健保給付碼未查得。 | AC84: A | AD84: 硬缺口全報告最強：透析需求>10萬人、實際服務僅3.6萬（覆蓋1/3）；放療84台僅滿足60-70%需求（K醫院籌建北越首座質子中心4.2兆越盾）；IVF年5萬+週期、65家中心、價格為已開發國家1/5。遠距醫療法源齊備（Law 15/2023＋Circular 30/2023列50種疾病）。99%長者靠家庭照顧、2036年進入高齡社會、長照保險未立法。醫護人力：2022上半年9,680人離職，人力是最大瓶頸。
A85: OPP-81 | B85: 病人App、無現金支付與報到機 | C85: Patient App, Cashless Payment & Kiosk | D85: J 商模支付與病人生態 | E85: 預約、掛號、QR／電子錢包支付、身分證晶片＋人臉報到；銀行與電子錢包願意共同出資 | F85: ② 起步中：剛開始有人做 | G85: =IF($A85="","",IF($H85=0,"（尚無對應能力）",IFERROR(INDEX(16_能力商機矩陣_CapOppMap!$D$160:$CO$160,MATCH($A85,16_能力商機矩陣_CapOppMap!$D$4:$CO$4,0)),""))) -> D06; D10 | H85: =IF($A85="","",IFERROR(INDEX(16_能力商機矩陣_CapOppMap!$D$156:$CO$156,MATCH($A85,16_能力商機矩陣_CapOppMap!$D$4:$CO$4,0)),"")) -> 2 | I85: =IF($A85="","",IFERROR(INDEX(16_能力商機矩陣_CapOppMap!$D$157:$CO$157,MATCH($A85,16_能力商機矩陣_CapOppMap!$D$4:$CO$4,0)),"")) -> 3.6 | J85: =IF($A85="","",IFERROR(INDEX(16_能力商機矩陣_CapOppMap!$D$158:$CO$158,MATCH($A85,16_能力商機矩陣_CapOppMap!$D$4:$CO$4,0)),"")) -> 2.2 | K85: =IF($A85="","",IFERROR(INDEX(16_能力商機矩陣_CapOppMap!$D$159:$CO$159,MATCH($A85,16_能力商機矩陣_CapOppMap!$D$4:$CO$4,0)),"")) -> 2 | L85: =IF($A85="","",IF($H85=0,"★白地商機：目前無對應能力，需新增能力或找新夥伴",IF($K85>0,"有缺口："&$K85&"項可對外招募","已有能力可承接"))) -> 有缺口：2項可對外招募 | M85: G5 | N85: 醫院營運預算(OPEX) | O85: 分潤／服務分成 | P85: 100K-500K USD | Q85: 是 | R85: Digital Patient Lead | S85: 紙本健保卡2025/6/1起停用，改用VNeID／VssID／晶片身分證——報到流程一定要改，就是切入時機 | T85: =IF($A85="","",COUNTIF(14_商機清單_Pipeline!$A$5:$A$34,$U85)) -> 0 | U85: =IF($B85="","",$A85&" "&$B85) -> OPP-81 病人App、無現金支付與報到機 | V85: （待調查） | X85: =IF($A85="","",IFERROR(INDEX(16_能力商機矩陣_CapOppMap!$D$162:$CO$162,MATCH($A85,16_能力商機矩陣_CapOppMap!$D$4:$CO$4,0)),"")) -> 0 | Y85: =IF(OR($A85="",$H85=""),"",IF($H85=0,"",ROUND(0.45*$I85+0.35*$J85+0.2*IF(LEFT($F85,1)="③",5,IF(LEFT($F85,1)="②",3,1))-IF($K85>0,0.3,0),2)+ROW()/100000)) -> 2.69085 | Z85: =IF($Y85="","",RANK($Y85,$Y$5:$Y$94)) -> 77 | AA85: L7 商模金流層 | AB85: 滲透已高（95%機構受理非現金、89%支援QR）——單純支付閘道已非藍海，競爭轉向全流程整合（掛號-繳費-病歷-理賠）與對帳效率。 | AC85: A | AD85: BHYT覆蓋率2025年底95.2%（提前5年達標）、年給付1.955億人次；修正健保法2025-07-01生效，取消行政界線轉診限制。無現金：95%機構受理、89%支援QR、大醫院電子收費70-90%——支付閘道已非藍海。出境就醫：衛生部2026-08草案估每年20-30億美元（人次數字未見2026年更新，原「4萬人/年」待覆核）；入境約30萬人次，2030年目標75萬人次、醫療直接收入10億美元。健康險市場2025年約83億美元→2034年142億。DRG：資料庫與分組軟體準備中、無正式時程。
A86: OPP-82 | B86: 健保申報介接與收入循環管理 | C86: BHYT Claims Integration & Revenue Cycle | D86: J 商模支付與病人生態 | E86: 申報XML產生與驗證、拒付分析、自費收款；醫院付錢且與收入直接相關 | F86: ② 起步中：剛開始有人做 | G86: =IF($A86="","",IF($H86=0,"（尚無對應能力）",IFERROR(INDEX(16_能力商機矩陣_CapOppMap!$D$160:$CO$160,MATCH($A86,16_能力商機矩陣_CapOppMap!$D$4:$CO$4,0)),""))) -> D10 | H86: =IF($A86="","",IFERROR(INDEX(16_能力商機矩陣_CapOppMap!$D$156:$CO$156,MATCH($A86,16_能力商機矩陣_CapOppMap!$D$4:$CO$4,0)),"")) -> 2 | I86: =IF($A86="","",IFERROR(INDEX(16_能力商機矩陣_CapOppMap!$D$157:$CO$157,MATCH($A86,16_能力商機矩陣_CapOppMap!$D$4:$CO$4,0)),"")) -> 3.6 | J86: =IF($A86="","",IFERROR(INDEX(16_能力商機矩陣_CapOppMap!$D$158:$CO$158,MATCH($A86,16_能力商機矩陣_CapOppMap!$D$4:$CO$4,0)),"")) -> 2 | K86: =IF($A86="","",IFERROR(INDEX(16_能力商機矩陣_CapOppMap!$D$159:$CO$159,MATCH($A86,16_能力商機矩陣_CapOppMap!$D$4:$CO$4,0)),"")) -> 2 | L86: =IF($A86="","",IF($H86=0,"★白地商機：目前無對應能力，需新增能力或找新夥伴",IF($K86>0,"有缺口："&$K86&"項可對外招募","已有能力可承接"))) -> 有缺口：2項可對外招募 | M86: G5 | N86: 醫院營運預算(OPEX) | O86: 軟體授權／訂閱 | P86: 100K-500K USD | Q86: 是 | R86: Revenue Cycle Lead | S86: 越南社保正在修訂申報資料閘道規則，介接規格會變，是重新洗牌的時機 | T86: =IF($A86="","",COUNTIF(14_商機清單_Pipeline!$A$5:$A$34,$U86)) -> 0 | U86: =IF($B86="","",$A86&" "&$B86) -> OPP-82 健保申報介接與收入循環管理 | V86: （待調查） | X86: =IF($A86="","",IFERROR(INDEX(16_能力商機矩陣_CapOppMap!$D$162:$CO$162,MATCH($A86,16_能力商機矩陣_CapOppMap!$D$4:$CO$4,0)),"")) -> 0 | Y86: =IF(OR($A86="",$H86=""),"",IF($H86=0,"",ROUND(0.45*$I86+0.35*$J86+0.2*IF(LEFT($F86,1)="③",5,IF(LEFT($F86,1)="②",3,1))-IF($K86>0,0.3,0),2)+ROW()/100000)) -> 2.62086 | Z86: =IF($Y86="","",RANK($Y86,$Y$5:$Y$94)) -> 78 | AA86: L7 商模金流層 | AB86: BHYT覆蓋95.2%（2025年底）、年1.955億人次、給付161.6兆越盾；FFS仍主導、DRG無正式時程——拒付管理與編碼是醫院現在的痛點、DRG前置期是RCM顧問進場窗口。 | AC86: A | AD86: BHYT覆蓋率2025年底95.2%（提前5年達標）、年給付1.955億人次；修正健保法2025-07-01生效，取消行政界線轉診限制。無現金：95%機構受理、89%支援QR、大醫院電子收費70-90%——支付閘道已非藍海。出境就醫：衛生部2026-08草案估每年20-30億美元（人次數字未見2026年更新，原「4萬人/年」待覆核）；入境約30萬人次，2030年目標75萬人次、醫療直接收入10億美元。健康險市場2025年約83億美元→2034年142億。DRG：資料庫與分組軟體準備中、無正式時程。
A87: OPP-83 | B87: 國際醫療與病患回流方案 | C87: Medical Tourism & Patient Repatriation | D87: J 商模支付與病人生態 | E87: 國際病人中心、台灣標準套餐，把外流的病人接回越南境內的台資機構 | F87: ② 起步中：剛開始有人做 | G87: =IF($A87="","",IF($H87=0,"（尚無對應能力）",IFERROR(INDEX(16_能力商機矩陣_CapOppMap!$D$160:$CO$160,MATCH($A87,16_能力商機矩陣_CapOppMap!$D$4:$CO$4,0)),""))) -> D10 | H87: =IF($A87="","",IFERROR(INDEX(16_能力商機矩陣_CapOppMap!$D$156:$CO$156,MATCH($A87,16_能力商機矩陣_CapOppMap!$D$4:$CO$4,0)),"")) -> 1 | I87: =IF($A87="","",IFERROR(INDEX(16_能力商機矩陣_CapOppMap!$D$157:$CO$157,MATCH($A87,16_能力商機矩陣_CapOppMap!$D$4:$CO$4,0)),"")) -> 3.1 | J87: =IF($A87="","",IFERROR(INDEX(16_能力商機矩陣_CapOppMap!$D$158:$CO$158,MATCH($A87,16_能力商機矩陣_CapOppMap!$D$4:$CO$4,0)),"")) -> 2 | K87: =IF($A87="","",IFERROR(INDEX(16_能力商機矩陣_CapOppMap!$D$159:$CO$159,MATCH($A87,16_能力商機矩陣_CapOppMap!$D$4:$CO$4,0)),"")) -> 1 | L87: =IF($A87="","",IF($H87=0,"★白地商機：目前無對應能力，需新增能力或找新夥伴",IF($K87>0,"有缺口："&$K87&"項可對外招募","已有能力可承接"))) -> 有缺口：1項可對外招募 | M87: G6 | N87: 商業保險／國際保險 | O87: 分潤／服務分成 | P87: 500K-2M USD | Q87: 是 | R87: Commercial Director | S87: 每年約4萬名越南人赴海外就醫、花費約US$20億；入境醫療觀光2025年約US$8.5億、年增18% | T87: =IF($A87="","",COUNTIF(14_商機清單_Pipeline!$A$5:$A$34,$U87)) -> 0 | U87: =IF($B87="","",$A87&" "&$B87) -> OPP-83 國際醫療與病患回流方案 | V87: 泰國/新加坡搶客；越南院所各自為政 | W87: 把每年約4萬外流病人（約US$20億）接回台資機構＋保險直付通路 | X87: =IF($A87="","",IFERROR(INDEX(16_能力商機矩陣_CapOppMap!$D$162:$CO$162,MATCH($A87,16_能力商機矩陣_CapOppMap!$D$4:$CO$4,0)),"")) -> 0 | Y87: =IF(OR($A87="",$H87=""),"",IF($H87=0,"",ROUND(0.45*$I87+0.35*$J87+0.2*IF(LEFT($F87,1)="③",5,IF(LEFT($F87,1)="②",3,1))-IF($K87>0,0.3,0),2)+ROW()/100000)) -> 2.40087 | Z87: =IF($Y87="","",RANK($Y87,$Y$5:$Y$94)) -> 79 | AA87: L7 商模金流層 | AB87: 「20億美元」查證結果：衛生部估計值（2025年口徑4萬人/20億、上看30-40億；2018年同源估10億且稱無法精確統計）——引用時應標註為MOH估計。入境約30萬人次；2030目標75萬人次/直接收入10億美元（2026-28五城市試點：河內、胡志明、峴港、廣寧、慶和）。 | AC87: A | AD87: BHYT覆蓋率2025年底95.2%（提前5年達標）、年給付1.955億人次；修正健保法2025-07-01生效，取消行政界線轉診限制。無現金：95%機構受理、89%支援QR、大醫院電子收費70-90%——支付閘道已非藍海。出境就醫：衛生部2026-08草案估每年20-30億美元（人次數字未見2026年更新，原「4萬人/年」待覆核）；入境約30萬人次，2030年目標75萬人次、醫療直接收入10億美元。健康險市場2025年約83億美元→2034年142億。DRG：資料庫與分組軟體準備中、無正式時程。
A88: OPP-84 | B88: 商業健康保險合作與給付方案設計 | C88: Private Health Insurance Partnership | D88: J 商模支付與病人生態 | E88: 與保險公司共同設計給付方案與直付網絡；保險公司付錢 | F88: ③ 尚未出現：幾乎空白 | G88: =IF($A88="","",IF($H88=0,"（尚無對應能力）",IFERROR(INDEX(16_能力商機矩陣_CapOppMap!$D$160:$CO$160,MATCH($A88,16_能力商機矩陣_CapOppMap!$D$4:$CO$4,0)),""))) -> D10 | H88: =IF($A88="","",IFERROR(INDEX(16_能力商機矩陣_CapOppMap!$D$156:$CO$156,MATCH($A88,16_能力商機矩陣_CapOppMap!$D$4:$CO$4,0)),"")) -> 2 | I88: =IF($A88="","",IFERROR(INDEX(16_能力商機矩陣_CapOppMap!$D$157:$CO$157,MATCH($A88,16_能力商機矩陣_CapOppMap!$D$4:$CO$4,0)),"")) -> 3.6 | J88: =IF($A88="","",IFERROR(INDEX(16_能力商機矩陣_CapOppMap!$D$158:$CO$158,MATCH($A88,16_能力商機矩陣_CapOppMap!$D$4:$CO$4,0)),"")) -> 2 | K88: =IF($A88="","",IFERROR(INDEX(16_能力商機矩陣_CapOppMap!$D$159:$CO$159,MATCH($A88,16_能力商機矩陣_CapOppMap!$D$4:$CO$4,0)),"")) -> 1 | L88: =IF($A88="","",IF($H88=0,"★白地商機：目前無對應能力，需新增能力或找新夥伴",IF($K88>0,"有缺口："&$K88&"項可對外招募","已有能力可承接"))) -> 有缺口：1項可對外招募 | M88: G6 | N88: 商業保險／國際保險 | O88: 分潤／服務分成 | P88: 100K-500K USD | Q88: 需組合 | R88: Commercial Director | S88: 私立醫療已占醫療支出約一半但只有6%床數，保險端的直付網絡是尚未整合的一塊 | T88: =IF($A88="","",COUNTIF(14_商機清單_Pipeline!$A$5:$A$34,$U88)) -> 0 | U88: =IF($B88="","",$A88&" "&$B88) -> OPP-84 商業健康保險合作與給付方案設計 | V88: （待調查） | X88: =IF($A88="","",IFERROR(INDEX(16_能力商機矩陣_CapOppMap!$D$162:$CO$162,MATCH($A88,16_能力商機矩陣_CapOppMap!$D$4:$CO$4,0)),"")) -> 0 | Y88: =IF(OR($A88="",$H88=""),"",IF($H88=0,"",ROUND(0.45*$I88+0.35*$J88+0.2*IF(LEFT($F88,1)="③",5,IF(LEFT($F88,1)="②",3,1))-IF($K88>0,0.3,0),2)+ROW()/100000)) -> 3.02088 | Z88: =IF($Y88="","",RANK($Y88,$Y$5:$Y$94)) -> 71 | AA88: L7 商模金流層 | AB88: 健康險市場2025年約83億美元→2034年142億（CAGR 6.17%）；注意IMARC口徑疑含社保；純商保滲透率未查得。 | AC88: A | AD88: BHYT覆蓋率2025年底95.2%（提前5年達標）、年給付1.955億人次；修正健保法2025-07-01生效，取消行政界線轉診限制。無現金：95%機構受理、89%支援QR、大醫院電子收費70-90%——支付閘道已非藍海。出境就醫：衛生部2026-08草案估每年20-30億美元（人次數字未見2026年更新，原「4萬人/年」待覆核）；入境約30萬人次，2030年目標75萬人次、醫療直接收入10億美元。健康險市場2025年約83億美元→2034年142億。DRG：資料庫與分組軟體準備中、無正式時程。
A89: OPP-85 | B89: 效益實現與第二院區複製藍圖 | C89: Benefits Realisation & Replication Blueprint | D89: J 商模支付與病人生態 | E89: 把第一家做成的模式標準化成可複製的第二、第三院區；業主或投資方付錢 | F89: ③ 尚未出現：幾乎空白 | G89: =IF($A89="","",IF($H89=0,"（尚無對應能力）",IFERROR(INDEX(16_能力商機矩陣_CapOppMap!$D$160:$CO$160,MATCH($A89,16_能力商機矩陣_CapOppMap!$D$4:$CO$4,0)),""))) -> D01; D10 | H89: =IF($A89="","",IFERROR(INDEX(16_能力商機矩陣_CapOppMap!$D$156:$CO$156,MATCH($A89,16_能力商機矩陣_CapOppMap!$D$4:$CO$4,0)),"")) -> 2 | I89: =IF($A89="","",IFERROR(INDEX(16_能力商機矩陣_CapOppMap!$D$157:$CO$157,MATCH($A89,16_能力商機矩陣_CapOppMap!$D$4:$CO$4,0)),"")) -> 3.5 | J89: =IF($A89="","",IFERROR(INDEX(16_能力商機矩陣_CapOppMap!$D$158:$CO$158,MATCH($A89,16_能力商機矩陣_CapOppMap!$D$4:$CO$4,0)),"")) -> 2 | K89: =IF($A89="","",IFERROR(INDEX(16_能力商機矩陣_CapOppMap!$D$159:$CO$159,MATCH($A89,16_能力商機矩陣_CapOppMap!$D$4:$CO$4,0)),"")) -> 0 | L89: =IF($A89="","",IF($H89=0,"★白地商機：目前無對應能力，需新增能力或找新夥伴",IF($K89>0,"有缺口："&$K89&"項可對外招募","已有能力可承接"))) -> 已有能力可承接 | M89: G6 | N89: 醫院業主資本支出(CAPEX) | O89: 顧問服務 | P89: 100K-500K USD | Q89: 需組合 | R89: PI Office | S89: 單案賺一次，複製藍圖賺很多次——這是聯盟從專案商轉成平台商的關鍵一步 | T89: =IF($A89="","",COUNTIF(14_商機清單_Pipeline!$A$5:$A$34,$U89)) -> 0 | U89: =IF($B89="","",$A89&" "&$B89) -> OPP-85 效益實現與第二院區複製藍圖 | V89: （待調查） | X89: =IF($A89="","",IFERROR(INDEX(16_能力商機矩陣_CapOppMap!$D$162:$CO$162,MATCH($A89,16_能力商機矩陣_CapOppMap!$D$4:$CO$4,0)),"")) -> 0 | Y89: =IF(OR($A89="",$H89=""),"",IF($H89=0,"",ROUND(0.45*$I89+0.35*$J89+0.2*IF(LEFT($F89,1)="③",5,IF(LEFT($F89,1)="②",3,1))-IF($K89>0,0.3,0),2)+ROW()/100000)) -> 3.28089 | Z89: =IF($Y89="","",RANK($Y89,$Y$5:$Y$94)) -> 58 | AA89: L7 商模金流層 | AB89: EN拼字統一：Benefits Realisation（與CAP-060的realization不一致）。Vinmec（JCI多院區＋Cleveland Clinic Connected）與Hoan My是跨院複製的在地範本。 | AC89: A | AD89: BHYT覆蓋率2025年底95.2%（提前5年達標）、年給付1.955億人次；修正健保法2025-07-01生效，取消行政界線轉診限制。無現金：95%機構受理、89%支援QR、大醫院電子收費70-90%——支付閘道已非藍海。出境就醫：衛生部2026-08草案估每年20-30億美元（人次數字未見2026年更新，原「4萬人/年」待覆核）；入境約30萬人次，2030年目標75萬人次、醫療直接收入10億美元。健康險市場2025年約83億美元→2034年142億。DRG：資料庫與分組軟體準備中、無正式時程。
A90: =IF($B90="","",IFERROR("OPP-"&TEXT(VALUE(MID($A89,5,2))+1,"00"),"OPP-??")) | G90: =IF($A90="","",IF($H90=0,"（尚無對應能力）",IFERROR(INDEX(16_能力商機矩陣_CapOppMap!$D$160:$CO$160,MATCH($A90,16_能力商機矩陣_CapOppMap!$D$4:$CO$4,0)),""))) | H90: =IF($A90="","",IFERROR(INDEX(16_能力商機矩陣_CapOppMap!$D$156:$CO$156,MATCH($A90,16_能力商機矩陣_CapOppMap!$D$4:$CO$4,0)),"")) | I90: =IF($A90="","",IFERROR(INDEX(16_能力商機矩陣_CapOppMap!$D$157:$CO$157,MATCH($A90,16_能力商機矩陣_CapOppMap!$D$4:$CO$4,0)),"")) | J90: =IF($A90="","",IFERROR(INDEX(16_能力商機矩陣_CapOppMap!$D$158:$CO$158,MATCH($A90,16_能力商機矩陣_CapOppMap!$D$4:$CO$4,0)),"")) | K90: =IF($A90="","",IFERROR(INDEX(16_能力商機矩陣_CapOppMap!$D$159:$CO$159,MATCH($A90,16_能力商機矩陣_CapOppMap!$D$4:$CO$4,0)),"")) | L90: =IF($A90="","",IF($H90=0,"★白地商機：目前無對應能力，需新增能力或找新夥伴",IF($K90>0,"有缺口："&$K90&"項可對外招募","已有能力可承接"))) | T90: =IF($A90="","",COUNTIF(14_商機清單_Pipeline!$A$5:$A$34,$U90)) | U90: =IF($B90="","",$A90&" "&$B90) | X90: =IF($A90="","",IFERROR(INDEX(16_能力商機矩陣_CapOppMap!$D$162:$CO$162,MATCH($A90,16_能力商機矩陣_CapOppMap!$D$4:$CO$4,0)),"")) | Y90: =IF(OR($A90="",$H90=""),"",IF($H90=0,"",ROUND(0.45*$I90+0.35*$J90+0.2*IF(LEFT($F90,1)="③",5,IF(LEFT($F90,1)="②",3,1))-IF($K90>0,0.3,0),2)+ROW()/100000)) | Z90: =IF($Y90="","",RANK($Y90,$Y$5:$Y$94))
A91: =IF($B91="","",IFERROR("OPP-"&TEXT(VALUE(MID($A90,5,2))+1,"00"),"OPP-??")) | G91: =IF($A91="","",IF($H91=0,"（尚無對應能力）",IFERROR(INDEX(16_能力商機矩陣_CapOppMap!$D$160:$CO$160,MATCH($A91,16_能力商機矩陣_CapOppMap!$D$4:$CO$4,0)),""))) | H91: =IF($A91="","",IFERROR(INDEX(16_能力商機矩陣_CapOppMap!$D$156:$CO$156,MATCH($A91,16_能力商機矩陣_CapOppMap!$D$4:$CO$4,0)),"")) | I91: =IF($A91="","",IFERROR(INDEX(16_能力商機矩陣_CapOppMap!$D$157:$CO$157,MATCH($A91,16_能力商機矩陣_CapOppMap!$D$4:$CO$4,0)),"")) | J91: =IF($A91="","",IFERROR(INDEX(16_能力商機矩陣_CapOppMap!$D$158:$CO$158,MATCH($A91,16_能力商機矩陣_CapOppMap!$D$4:$CO$4,0)),"")) | K91: =IF($A91="","",IFERROR(INDEX(16_能力商機矩陣_CapOppMap!$D$159:$CO$159,MATCH($A91,16_能力商機矩陣_CapOppMap!$D$4:$CO$4,0)),"")) | L91: =IF($A91="","",IF($H91=0,"★白地商機：目前無對應能力，需新增能力或找新夥伴",IF($K91>0,"有缺口："&$K91&"項可對外招募","已有能力可承接"))) | T91: =IF($A91="","",COUNTIF(14_商機清單_Pipeline!$A$5:$A$34,$U91)) | U91: =IF($B91="","",$A91&" "&$B91) | X91: =IF($A91="","",IFERROR(INDEX(16_能力商機矩陣_CapOppMap!$D$162:$CO$162,MATCH($A91,16_能力商機矩陣_CapOppMap!$D$4:$CO$4,0)),"")) | Y91: =IF(OR($A91="",$H91=""),"",IF($H91=0,"",ROUND(0.45*$I91+0.35*$J91+0.2*IF(LEFT($F91,1)="③",5,IF(LEFT($F91,1)="②",3,1))-IF($K91>0,0.3,0),2)+ROW()/100000)) | Z91: =IF($Y91="","",RANK($Y91,$Y$5:$Y$94))
A92: =IF($B92="","",IFERROR("OPP-"&TEXT(VALUE(MID($A91,5,2))+1,"00"),"OPP-??")) | G92: =IF($A92="","",IF($H92=0,"（尚無對應能力）",IFERROR(INDEX(16_能力商機矩陣_CapOppMap!$D$160:$CO$160,MATCH($A92,16_能力商機矩陣_CapOppMap!$D$4:$CO$4,0)),""))) | H92: =IF($A92="","",IFERROR(INDEX(16_能力商機矩陣_CapOppMap!$D$156:$CO$156,MATCH($A92,16_能力商機矩陣_CapOppMap!$D$4:$CO$4,0)),"")) | I92: =IF($A92="","",IFERROR(INDEX(16_能力商機矩陣_CapOppMap!$D$157:$CO$157,MATCH($A92,16_能力商機矩陣_CapOppMap!$D$4:$CO$4,0)),"")) | J92: =IF($A92="","",IFERROR(INDEX(16_能力商機矩陣_CapOppMap!$D$158:$CO$158,MATCH($A92,16_能力商機矩陣_CapOppMap!$D$4:$CO$4,0)),"")) | K92: =IF($A92="","",IFERROR(INDEX(16_能力商機矩陣_CapOppMap!$D$159:$CO$159,MATCH($A92,16_能力商機矩陣_CapOppMap!$D$4:$CO$4,0)),"")) | L92: =IF($A92="","",IF($H92=0,"★白地商機：目前無對應能力，需新增能力或找新夥伴",IF($K92>0,"有缺口："&$K92&"項可對外招募","已有能力可承接"))) | T92: =IF($A92="","",COUNTIF(14_商機清單_Pipeline!$A$5:$A$34,$U92)) | U92: =IF($B92="","",$A92&" "&$B92) | X92: =IF($A92="","",IFERROR(INDEX(16_能力商機矩陣_CapOppMap!$D$162:$CO$162,MATCH($A92,16_能力商機矩陣_CapOppMap!$D$4:$CO$4,0)),"")) | Y92: =IF(OR($A92="",$H92=""),"",IF($H92=0,"",ROUND(0.45*$I92+0.35*$J92+0.2*IF(LEFT($F92,1)="③",5,IF(LEFT($F92,1)="②",3,1))-IF($K92>0,0.3,0),2)+ROW()/100000)) | Z92: =IF($Y92="","",RANK($Y92,$Y$5:$Y$94))
A93: =IF($B93="","",IFERROR("OPP-"&TEXT(VALUE(MID($A92,5,2))+1,"00"),"OPP-??")) | G93: =IF($A93="","",IF($H93=0,"（尚無對應能力）",IFERROR(INDEX(16_能力商機矩陣_CapOppMap!$D$160:$CO$160,MATCH($A93,16_能力商機矩陣_CapOppMap!$D$4:$CO$4,0)),""))) | H93: =IF($A93="","",IFERROR(INDEX(16_能力商機矩陣_CapOppMap!$D$156:$CO$156,MATCH($A93,16_能力商機矩陣_CapOppMap!$D$4:$CO$4,0)),"")) | I93: =IF($A93="","",IFERROR(INDEX(16_能力商機矩陣_CapOppMap!$D$157:$CO$157,MATCH($A93,16_能力商機矩陣_CapOppMap!$D$4:$CO$4,0)),"")) | J93: =IF($A93="","",IFERROR(INDEX(16_能力商機矩陣_CapOppMap!$D$158:$CO$158,MATCH($A93,16_能力商機矩陣_CapOppMap!$D$4:$CO$4,0)),"")) | K93: =IF($A93="","",IFERROR(INDEX(16_能力商機矩陣_CapOppMap!$D$159:$CO$159,MATCH($A93,16_能力商機矩陣_CapOppMap!$D$4:$CO$4,0)),"")) | L93: =IF($A93="","",IF($H93=0,"★白地商機：目前無對應能力，需新增能力或找新夥伴",IF($K93>0,"有缺口："&$K93&"項可對外招募","已有能力可承接"))) | T93: =IF($A93="","",COUNTIF(14_商機清單_Pipeline!$A$5:$A$34,$U93)) | U93: =IF($B93="","",$A93&" "&$B93) | X93: =IF($A93="","",IFERROR(INDEX(16_能力商機矩陣_CapOppMap!$D$162:$CO$162,MATCH($A93,16_能力商機矩陣_CapOppMap!$D$4:$CO$4,0)),"")) | Y93: =IF(OR($A93="",$H93=""),"",IF($H93=0,"",ROUND(0.45*$I93+0.35*$J93+0.2*IF(LEFT($F93,1)="③",5,IF(LEFT($F93,1)="②",3,1))-IF($K93>0,0.3,0),2)+ROW()/100000)) | Z93: =IF($Y93="","",RANK($Y93,$Y$5:$Y$94))
A94: =IF($B94="","",IFERROR("OPP-"&TEXT(VALUE(MID($A93,5,2))+1,"00"),"OPP-??")) | G94: =IF($A94="","",IF($H94=0,"（尚無對應能力）",IFERROR(INDEX(16_能力商機矩陣_CapOppMap!$D$160:$CO$160,MATCH($A94,16_能力商機矩陣_CapOppMap!$D$4:$CO$4,0)),""))) | H94: =IF($A94="","",IFERROR(INDEX(16_能力商機矩陣_CapOppMap!$D$156:$CO$156,MATCH($A94,16_能力商機矩陣_CapOppMap!$D$4:$CO$4,0)),"")) | I94: =IF($A94="","",IFERROR(INDEX(16_能力商機矩陣_CapOppMap!$D$157:$CO$157,MATCH($A94,16_能力商機矩陣_CapOppMap!$D$4:$CO$4,0)),"")) | J94: =IF($A94="","",IFERROR(INDEX(16_能力商機矩陣_CapOppMap!$D$158:$CO$158,MATCH($A94,16_能力商機矩陣_CapOppMap!$D$4:$CO$4,0)),"")) | K94: =IF($A94="","",IFERROR(INDEX(16_能力商機矩陣_CapOppMap!$D$159:$CO$159,MATCH($A94,16_能力商機矩陣_CapOppMap!$D$4:$CO$4,0)),"")) | L94: =IF($A94="","",IF($H94=0,"★白地商機：目前無對應能力，需新增能力或找新夥伴",IF($K94>0,"有缺口："&$K94&"項可對外招募","已有能力可承接"))) | T94: =IF($A94="","",COUNTIF(14_商機清單_Pipeline!$A$5:$A$34,$U94)) | U94: =IF($B94="","",$A94&" "&$B94) | X94: =IF($A94="","",IFERROR(INDEX(16_能力商機矩陣_CapOppMap!$D$162:$CO$162,MATCH($A94,16_能力商機矩陣_CapOppMap!$D$4:$CO$4,0)),"")) | Y94: =IF(OR($A94="",$H94=""),"",IF($H94=0,"",ROUND(0.45*$I94+0.35*$J94+0.2*IF(LEFT($F94,1)="③",5,IF(LEFT($F94,1)="②",3,1))-IF($K94>0,0.3,0),2)+ROW()/100000)) | Z94: =IF($Y94="","",RANK($Y94,$Y$5:$Y$94))
A96: 怎麼用：① 先讀 E 欄「這門生意在賣什麼／誰付錢」，挑出你們公司做得到的那幾列；再看 F 欄「越南現況」——標③的表示越南幾乎沒人在做，先進去的人定規則。② L 欄「聯盟能力對應狀態」是主動出擊的訊號：標「★白地商機」代表越南有這個生意、但 03 能力總表裡目前沒有任何一項能力對得上它，要嘛去 03 新增能力、要嘛去 04 找新夥伴；標「有缺口」代表能力有列出來但還沒人承接，可以直接拿 11 缺口招募去談。③ 要把某個商機變成正在談的案子 → 到 14 商機清單新增一列，商機用下拉直接選，其他欄位會自動帶入。④ 要新增一種商機 → 直接在本頁最下方空白列填 B 欄商機名稱（代號會自動編），再到 16 能力商機矩陣把相關能力打「✓」。★ Y欄「攻擊優先分」＝0.45×平均價值分＋0.35×平均準備分＋0.2×現況分(③=5/②=3/①=1)－0.3(仍有缺口)，Z欄順位前10名綠底＝建議優先攻擊清單（儀表板有同步的Top 10表）；白地商機(CAP數=0)不列入排序，走13④商機行動另案評估。★ 金額級距與付費方是「典型值」，用來讓不熟醫療產業的人有概念，實際談案請在 14 商機清單那列覆寫成本案的數字。★ 越南現況與在地重點取自 2025-2026 年公開法規與市場研究（電子病歷 Circular 13/2025、電子處方 Circular 26/2025、FHIR Decision 2146、醫材 Decree 98/2021+04/2025、PPP Nghị định 243/2025（廢止 Decree 71/2025）、個資 PDPL 91/2025+Decree 356、AI法 134/2025、Resolution 72-NQ/TW 全民健檢），屬規劃參考值，正式報價與承諾前請再向在地夥伴查證。

Sheet 17_商機作戰卡_OppView
A1: 17 商機作戰卡｜Opportunity Battle Card（推進單一商機的作戰會議，投影這一頁）
A2: ❓ 這頁在回答：這個商機怎麼打？需要誰？贏在哪？ ▸ 在下方黃色儲存格選一個商機，本頁自動組出作戰卡：這門生意需要哪些能力、每項誰在做／誰還缺、對手是誰、我們憑什麼贏、卡在哪些法規門檻。跟 12 夥伴視角是一對：12 回答「這個夥伴做什麼」，本頁回答「這個商機怎麼打」。
A3: ⌂ 回導引頁
A4: 選擇商機 → | C4: OPP-24 醫院IDC機房與院區網路建置 | F4: 對應CAP數 | G4: ○缺口 | H4: 群晶主導 | I4: 平均準備分 | J4: 金額級距 | K4: 越南現況
F5: =IFERROR(INDEX(15_商機字典_OppLibrary!$H$5:$H$94,MATCH($C$4,15_商機字典_OppLibrary!$U$5:$U$94,0)),"") -> 3 | G5: =IFERROR(INDEX(15_商機字典_OppLibrary!$K$5:$K$94,MATCH($C$4,15_商機字典_OppLibrary!$U$5:$U$94,0)),"") -> 0 | H5: =IFERROR(INDEX(15_商機字典_OppLibrary!$X$5:$X$94,MATCH($C$4,15_商機字典_OppLibrary!$U$5:$U$94,0)),"") -> 3 | I5: =IFERROR(INDEX(15_商機字典_OppLibrary!$J$5:$J$94,MATCH($C$4,15_商機字典_OppLibrary!$U$5:$U$94,0)),"") -> 3.4 | J5: =IFERROR(INDEX(15_商機字典_OppLibrary!$P$5:$P$94,MATCH($C$4,15_商機字典_OppLibrary!$U$5:$U$94,0)),"") -> 2M-10M USD | K5: =IFERROR(INDEX(15_商機字典_OppLibrary!$F$5:$F$94,MATCH($C$4,15_商機字典_OppLibrary!$U$5:$U$94,0)),"") -> ② 起步中：剛開始有人做
A6: =IFERROR("主要競爭者／在地玩家："&INDEX(15_商機字典_OppLibrary!$V$5:$V$94,MATCH($C$4,15_商機字典_OppLibrary!$U$5:$U$94,0)),"") -> 主要競爭者／在地玩家：Viettel IDC/VNPT/FPT 自有機房（通用型）
A7: =IFERROR("我們的切入角度："&INDEX(15_商機字典_OppLibrary!$W$5:$W$94,MATCH($C$4,15_商機字典_OppLibrary!$U$5:$U$94,0)),"") -> 我們的切入角度：醫院級機房（IEC 80001＋隔離電源整合），非通用機房
A8: =IFERROR("越南在地重點："&INDEX(15_商機字典_OppLibrary!$S$5:$S$94,MATCH($C$4,15_商機字典_OppLibrary!$U$5:$U$94,0)),"") -> 越南在地重點：★群晶核心強項。越南資料在地化(Decree 53)與資安法要求機房落地，機房選址須與OPP-10供電一起談
A10: # | B10: CAP ID | C10: 需要的能力 | D10: 拼圖狀態 | E10: 主責 | F10: 候選夥伴 | G10: 準備分 | H10: 缺什麼/下一步 | I10: 關鍵門檻 | J10: 商業判斷 | K10: 所屬商機(全部)
A11: =IF($B11="","",1) -> 1 | B11: =IFERROR(INDEX(03_能力總表_Master!$A$5:$A$154,MATCH(1,_計算_Calc!$CC$5:$CC$154,0)),"") -> CAP-020 | C11: =IFERROR(INDEX(03_能力總表_Master!$E$5:$E$154,MATCH(1,_計算_Calc!$CC$5:$CC$154,0)),"") -> IDC與邊緣運算底座 | D11: =IFERROR(INDEX(03_能力總表_Master!$H$5:$H$154,MATCH(1,_計算_Calc!$CC$5:$CC$154,0)),"") -> 群晶主導 | E11: =IFERROR(INDEX(03_能力總表_Master!$I$5:$I$154,MATCH(1,_計算_Calc!$CC$5:$CC$154,0)),"") -> Digital Infrastructure Lead | F11: =IFERROR(INDEX(03_能力總表_Master!$J$5:$J$154,MATCH(1,_計算_Calc!$CC$5:$CC$154,0)),"") -> P-001 群晶科技 | G11: =IFERROR(INDEX(03_能力總表_Master!$U$5:$U$154,MATCH(1,_計算_Calc!$CC$5:$CC$154,0)),"") -> 3.4 | H11: =IFERROR(INDEX(03_能力總表_Master!$K$5:$K$154,MATCH(1,_計算_Calc!$CC$5:$CC$154,0)),"") -> 群晶提出方案書與實績 | I11: =IFERROR(INDEX(03_能力總表_Master!$L$5:$L$154,MATCH(1,_計算_Calc!$CC$5:$CC$154,0)),"") -> HIMSS-INFRAM; ISO-27001 | J11: =IFERROR(INDEX(03_能力總表_Master!$W$5:$W$154,MATCH(1,_計算_Calc!$CC$5:$CC$154,0)),"") -> 立即推進 Go | K11: =IFERROR(INDEX(03_能力總表_Master!$AF$5:$AF$154,MATCH(1,_計算_Calc!$CC$5:$CC$154,0)),"") -> OPP-24; OPP-25; OPP-40; OPP-57
A12: =IF($B12="","",2) -> 2 | B12: =IFERROR(INDEX(03_能力總表_Master!$A$5:$A$154,MATCH(2,_計算_Calc!$CC$5:$CC$154,0)),"") -> CAP-021 | C12: =IFERROR(INDEX(03_能力總表_Master!$E$5:$E$154,MATCH(2,_計算_Calc!$CC$5:$CC$154,0)),"") -> 有線無線網路與分區 | D12: =IFERROR(INDEX(03_能力總表_Master!$H$5:$H$154,MATCH(2,_計算_Calc!$CC$5:$CC$154,0)),"") -> 群晶主導 | E12: =IFERROR(INDEX(03_能力總表_Master!$I$5:$I$154,MATCH(2,_計算_Calc!$CC$5:$CC$154,0)),"") -> Network Lead | F12: =IFERROR(INDEX(03_能力總表_Master!$J$5:$J$154,MATCH(2,_計算_Calc!$CC$5:$CC$154,0)),"") -> P-001 群晶科技 | G12: =IFERROR(INDEX(03_能力總表_Master!$U$5:$U$154,MATCH(2,_計算_Calc!$CC$5:$CC$154,0)),"") -> 3.4 | H12: =IFERROR(INDEX(03_能力總表_Master!$K$5:$K$154,MATCH(2,_計算_Calc!$CC$5:$CC$154,0)),"") -> 群晶提出方案書與實績 | I12: =IFERROR(INDEX(03_能力總表_Master!$L$5:$L$154,MATCH(2,_計算_Calc!$CC$5:$CC$154,0)),"") -> HIMSS-INFRAM; ISO-27001 | J12: =IFERROR(INDEX(03_能力總表_Master!$W$5:$W$154,MATCH(2,_計算_Calc!$CC$5:$CC$154,0)),"") -> 快速小案 Quick-win | K12: =IFERROR(INDEX(03_能力總表_Master!$AF$5:$AF$154,MATCH(2,_計算_Calc!$CC$5:$CC$154,0)),"") -> OPP-24
A13: =IF($B13="","",3) -> 3 | B13: =IFERROR(INDEX(03_能力總表_Master!$A$5:$A$154,MATCH(3,_計算_Calc!$CC$5:$CC$154,0)),"") -> CAP-026 | C13: =IFERROR(INDEX(03_能力總表_Master!$E$5:$E$154,MATCH(3,_計算_Calc!$CC$5:$CC$154,0)),"") -> 災難復原與營運持續 | D13: =IFERROR(INDEX(03_能力總表_Master!$H$5:$H$154,MATCH(3,_計算_Calc!$CC$5:$CC$154,0)),"") -> 群晶主導 | E13: =IFERROR(INDEX(03_能力總表_Master!$I$5:$I$154,MATCH(3,_計算_Calc!$CC$5:$CC$154,0)),"") -> BCM Lead | F13: =IFERROR(INDEX(03_能力總表_Master!$J$5:$J$154,MATCH(3,_計算_Calc!$CC$5:$CC$154,0)),"") -> P-001 群晶科技 | G13: =IFERROR(INDEX(03_能力總表_Master!$U$5:$U$154,MATCH(3,_計算_Calc!$CC$5:$CC$154,0)),"") -> 3.4 | H13: =IFERROR(INDEX(03_能力總表_Master!$K$5:$K$154,MATCH(3,_計算_Calc!$CC$5:$CC$154,0)),"") -> 群晶提出方案書與實績 | I13: =IFERROR(INDEX(03_能力總表_Master!$L$5:$L$154,MATCH(3,_計算_Calc!$CC$5:$CC$154,0)),"") -> ISO-22301; ISO-27001 | J13: =IFERROR(INDEX(03_能力總表_Master!$W$5:$W$154,MATCH(3,_計算_Calc!$CC$5:$CC$154,0)),"") -> 立即推進 Go | K13: =IFERROR(INDEX(03_能力總表_Master!$AF$5:$AF$154,MATCH(3,_計算_Calc!$CC$5:$CC$154,0)),"") -> OPP-24; OPP-25; OPP-27; OPP-29; OPP-39; OPP-59
A14: =IF($B14="","",4) | B14: =IFERROR(INDEX(03_能力總表_Master!$A$5:$A$154,MATCH(4,_計算_Calc!$CC$5:$CC$154,0)),"") | C14: =IFERROR(INDEX(03_能力總表_Master!$E$5:$E$154,MATCH(4,_計算_Calc!$CC$5:$CC$154,0)),"") | D14: =IFERROR(INDEX(03_能力總表_Master!$H$5:$H$154,MATCH(4,_計算_Calc!$CC$5:$CC$154,0)),"") | E14: =IFERROR(INDEX(03_能力總表_Master!$I$5:$I$154,MATCH(4,_計算_Calc!$CC$5:$CC$154,0)),"") | F14: =IFERROR(INDEX(03_能力總表_Master!$J$5:$J$154,MATCH(4,_計算_Calc!$CC$5:$CC$154,0)),"") | G14: =IFERROR(INDEX(03_能力總表_Master!$U$5:$U$154,MATCH(4,_計算_Calc!$CC$5:$CC$154,0)),"") | H14: =IFERROR(INDEX(03_能力總表_Master!$K$5:$K$154,MATCH(4,_計算_Calc!$CC$5:$CC$154,0)),"") | I14: =IFERROR(INDEX(03_能力總表_Master!$L$5:$L$154,MATCH(4,_計算_Calc!$CC$5:$CC$154,0)),"") | J14: =IFERROR(INDEX(03_能力總表_Master!$W$5:$W$154,MATCH(4,_計算_Calc!$CC$5:$CC$154,0)),"") | K14: =IFERROR(INDEX(03_能力總表_Master!$AF$5:$AF$154,MATCH(4,_計算_Calc!$CC$5:$CC$154,0)),"")
