Workbook

Sheet 00_使用說明_Howto
A1: VMH-EcoMap-2 專案商模試算器 v1.0｜Project Business Case Calculator
A2: 搭配主工具「VMH-EcoMap-1_主工具_越南醫院生態盤點」使用。主工具回答「做不做、誰做、何時做」；本檔回答「這一個子專案划不划算」。本檔的六個設計重點：投資類別框架（不同類別用不同評估尺規）、三幣別一鍵切換、BOQ 級成本明細、折舊攤提與越南稅務優惠、WACC 推算與 FCFF 現金流、使能型投資專用評估。
A4: 一、本檔最重要的一個觀念：不同類型的投資，要用不同的尺
B5: 把「機房」「網路」「資料平台」這類基礎建設，拿去跟「CT 影像中心」用同一套 NPV 標準比較，結論一定是基礎建設不值得投——但那是尺用錯了，不是案子不好。 MIT Sloan（Weill & Aral）的實證指出：基礎建設是企業 IT 支出中佔比最高的一類（平均 46%），也是「事前最難做成本正當化（most difficult to cost-justify in advance）」的一類——因為效益歸屬於建在它上面的其他專案，成本卻留在自己身上。同一份研究還顯示：★ 績效前段班公司把 55% 的 IT 支出放在基礎建設，後段班只有 37%。 因此本檔在 01 分頁要求先選「投資類別」，10 決策摘要會依類別套用不同的判讀規則，使能型投資另有 09 分頁專用的「自建 vs 外租 TCO」評估。
A10: 二、六種投資類別與各自該用的評估指標
B11: 類別 | C11: 定義 | D11: 通過條件 | E11: 主要指標 | F11: 典型案例
B12: A 營收型投資 Revenue-generating | C12: 本身直接向外部付款者收費，自己就能產生現金流。對應 Weill 四分類的 Transactional／Strategic。 | D12: NPV ＞ 0、IRR ≥ WACC、折現回收期在合約年限內 | E12: NPV／IRR／PI | F12: 例：CT 影像中心、檢驗中心、健檢中心——有給付碼或自費市場，「做一件收一件」。
B13: B 使能型投資 Enabling / Infrastructure | C13: 本身不直接收費，而是讓其他專案得以成立、或降低整體營運成本。Weill 四分類佔比最高（46%）、也是 MIT Sloan 明指「事前最難做成本正當化」的一類。 | D13: ΔTCO（不做 vs 做）現值 ＞ 0；服務單位成本低於外購市價；承載專案數 ≥ 2 | E13: ΔTCO 現值／單位服務成本／選擇權價值 | F13: 例：院內 IDC 機房、院區網路、資料平台、整合中介層。★ 用單獨 NPV 評估必然為負——那是尺用錯了，不是案子不好。
B14: C 法規強制型 Mandatory / Compliance | C14: 法規或評鑑要求，不做就不能營業。CFA 資本預算明列此類「通常不產生營收、繞過傳統成本效益分析」。 | D14: 在合規前提下的最低總成本；並列出「不做的代價」（罰則、停業、失去投標資格） | E14: 最低合規成本／不做的代價 | F14: 例：電子病歷分級驗收、個資法 PDPL 91/2025 合規、資安等級保護、輻射安全許可。
B15: D 降本型投資 Cost-reduction | C15: 不增加收入，但減少既有支出。效益＝被避免掉的成本。 | D15: 成本節省現值 ＞ 投資額；回收期 ≤ 設備壽命的一半 | E15: 成本節省 NPV／回收期 | F15: 例：無片化（省底片）、能源優化、流程自動化、以租代購取代自購。
B16: E 汰換維持型 Replacement / Maintenance | C16: 維持既有營運不中斷。CFA 分類指出此類「通常不做詳細分析」，因為不做就停擺。 | D16: 與「不汰換的停機風險成本」比較；同規格中取最低生命週期成本 | E16: 生命週期成本／停機風險 | F16: 例：UPS 電池更換、伺服器汰換、球管更換、到期授權續約。
B17: F 策略布局型 Strategic / Option | C17: 為了取得未來機會、參考案例或市場位置。現金流高度不確定，CFA 指出需「超越傳統資本預算」的方法。 | D17: 分階段關卡（stage-gate）：每階段設可量測的續投條件，而非一次核定全額 | E17: 選擇權價值／階段關卡達成率 | F17: 例：第一家旗艦醫院（取得 reference site）、新國家市場試點、AI 產品共同開發。
A19: 三、分頁導覽（黃底＝要填，藍字＝公式自動算）
B20: 順序 | C20: 分頁 | D20: 性質 | E20: 內容
B21: ① | C21: 01 專案設定 | D21: 填 | E21: 專案識別、★投資類別、幣別與匯率（預設新台幣，可一鍵切換 USD／VND）、稅務優惠、營運資金、終值假設。
B22: ①B | C22: 01B 類別判斷精靈 | D22: 填 | E22: ★ 不確定該選哪一種投資類別時用。回答四題 → 推薦一類＋說明理由＋列出下一步，並與 01 分頁目前的選擇比對。
B23: ② | C23: 02 投資成本 CAPEX | D23: 填 | E23: BOQ 級明細：分項工程名稱、單位、數量、單價、進口／在地、關稅與 VAT、折舊類別與年限、置換年、殘值率。
B24: ③ | C24: 03 營運成本 OPEX | D24: 填 | E24: 人力、維保、耗材、電力、授權、保險；可設年成長率，並標示「隨服務量變動」或「固定」。
B25: ④ | C25: 04 收入與產能 | D25: 填 | E25: 服務量、健保價與自費價、自費比例、成長率、開辦爬坡。使能型投資可留白（收入為 0）。
B26: ⑤ | C26: 05 折舊攤提 | D26: 算 | E26: 依 02 每一列的折舊類別與年限，逐年計算折舊；置換資產於置換年重新起算。依越南 Circular 45/2013/TT-BTC。
B27: ⑥ | C27: 06 現金流 | D27: 算 | E27: 營收→EBITDA→折舊→EBIT→所得稅（含免稅期與虧損扣抵）→NOPAT→＋折舊−資本支出−營運資金＝自由現金流 FCFF。
B28: ⑦ | C28: 07 折現率 WACC | D28: 填/算 | E28: CAPM：無風險利率＋β×成熟市場風險溢酬＋越南國家風險溢酬，再與債務成本加權。可切換為手動輸入。
B29: ⑧ | C29: 08 敏感度 | D29: 算 | E29: 三情境（保守／基準／樂觀）、量價 ±30% 矩陣、龍捲風圖（哪個變數最致命）、損益兩平點。
B30: ⑨ | C30: 09 使能型評估 | D30: 填/算 | E30: ★ 僅使能型投資需要：自建 vs 外租十年 TCO 比較、承載專案成本分攤、單位服務成本、選擇權價值。
B31: ⑩ | C31: 10 決策摘要 | D31: 算 | E31: 一頁結論。★ 判讀規則依 01 選定的投資類別自動切換。
B32: ⑪ | C32: 11 假設來源 | D32: 填 | E32: 每一筆金額與比率的出處、狀態（實績／報價／法規／推測）、日期、負責人。
A34: 四、本檔的六個設計重點
B35: ▍三幣別一鍵切換 | C35: 01 分頁選「輸入幣別」與「顯示幣別」，全檔金額自動換算。預設輸入新台幣。另可切換顯示單位（元／千元／百萬元），避免越南盾位數過長。
B36: ▍BOQ 級成本明細 | C36: 02、03 用工程界正式的分項名稱與「數量×單價」結構，並區分進口／在地。★ 越南醫療服務免 VAT，代表進項 VAT 不可扣抵、必須計入成本——本檔已內建此欄位，這是越南醫院財務模型最常見的重大低估。
B37: ▍折舊與越南稅務優惠 | C37: 折舊依 Circular 45/2013/TT-BTC 的法定年限區間。稅率不再寫死：社會化醫療領域適用 10% 優惠稅率（PwC：整個專案期），並內建免稅 4 年＋減半期，且免稅起算採「首次獲利年 vs 營收第 4 年孰早」的法定規則。虧損可扣抵 5 年。
B38: ▍營運資金 | C38: 越南健保給付延遲是真實風險——2025 年胡志明市各醫院被懸置的健保結算近 2,500 十億越盾。本檔把健保應收天數與自費應收天數分開設定，並計入現金流。
B39: ▍WACC 與 FCFF | C39: 折現率不再是隨手填的數字：07 分頁用 CAPM 推算（越南 10 年期公債殖利率＋β×成熟市場 ERP＋越南國家風險溢酬）。現金流改用業界標準的無槓桿自由現金流 FCFF。
B40: ▍MIRR、PI、ROIC、龍捲風 | C40: IRR 對「中途有大額置換投資」的現金流可能出現多重解，且隱含以 IRR 本身再投資的不合理假設——本檔改以 MIRR 為主要報酬指標。另加 PI（資本受限時的排序指標）、ROIC（與 WACC 比較）、龍捲風圖（找出最致命的變數）。
B42: 重要聲明：本檔內建的金額為「規劃用示意值」，用來讓模型立即跑出結果與示範用法，不是越南市場報價。正式評估前，每一筆金額都必須以廠商報價、越南在地工程估算或合約條件取代，並在 11 分頁登錄出處。稅務優惠的實際適用（特別是社會化醫療 10% 稅率的資格認定）須由越南在地稅務顧問就個案出具確認。

Sheet 01_專案設定_Setup
A1: 01 專案設定｜Project Setup
A2: 黃底＝請填寫或用下拉選擇；藍字＝公式自動算，請勿覆蓋。本頁的設定會驅動後面所有分頁。
J3: （類別查表區，可隱藏）
A4: A. 專案識別 | J4: A 營收型投資 Revenue-generating | K4: 本身直接向外部付款者收費，自己就能產生現金流。對應 Weill 四分類的 Transactional／Strategic。 | L4: NPV ＞ 0、IRR ≥ WACC、折現回收期在合約年限內 | M4: NPV／IRR／PI | N4: 例：CT 影像中心、檢驗中心、健檢中心——有給付碼或自費市場，「做一件收一件」。 | O4: NPV
A5: 專案名稱 Project name | B5: B醫院 500床 HIS／EMR 以租代購 一期（模擬案） | D5: 建議格式：醫院＋標的＋期別，例「A醫院 128排CT影像中心 一期」 | J5: B 使能型投資 Enabling / Infrastructure | K5: 本身不直接收費，而是讓其他專案得以成立、或降低整體營運成本。Weill 四分類佔比最高（46%）、也是 MIT Sloan 明指「事前最難做成本正當化」的一類。 | L5: ΔTCO（不做 vs 做）現值 ＞ 0；服務單位成本低於外購市價；承載專案數 ≥ 2 | M5: ΔTCO 現值／單位服務成本／選擇權價值 | N5: 例：院內 IDC 機房、院區網路、資料平台、整合中介層。★ 用單獨 NPV 評估必然為負——那是尺用錯了，不是案子不好。 | O5: DTCO
A6: 對應能力 CAP ID | B6: CAP-033 HIS／EMR核心平台 | D6: 對應主工具 03 能力總表的編號，讓本案接得回盤點結果 | J6: C 法規強制型 Mandatory / Compliance | K6: 法規或評鑑要求，不做就不能營業。CFA 資本預算明列此類「通常不產生營收、繞過傳統成本效益分析」。 | L6: 在合規前提下的最低總成本；並列出「不做的代價」（罰則、停業、失去投標資格） | M6: 最低合規成本／不做的代價 | N6: 例：電子病歷分級驗收、個資法 PDPL 91/2025 合規、資安等級保護、輻射安全許可。 | O6: MINCOST
A7: 主責夥伴 Lead partner | B7: P-007 醫療資訊整合商（＋群晶科技：承載環境） | D7: 對應主工具 04 夥伴拼圖 | J7: D 降本型投資 Cost-reduction | K7: 不增加收入，但減少既有支出。效益＝被避免掉的成本。 | L7: 成本節省現值 ＞ 投資額；回收期 ≤ 設備壽命的一半 | M7: 成本節省 NPV／回收期 | N7: 例：無片化（省底片）、能源優化、流程自動化、以租代購取代自購。 | O7: SAVING
A8: 情境範本 Template | B8: HIS 醫療資訊系統 | D8: CT 影像設備／IDC 機房／HIS 醫療資訊系統／自訂 | J8: E 汰換維持型 Replacement / Maintenance | K8: 維持既有營運不中斷。CFA 分類指出此類「通常不做詳細分析」，因為不做就停擺。 | L8: 與「不汰換的停機風險成本」比較；同規格中取最低生命週期成本 | M8: 生命週期成本／停機風險 | N8: 例：UPS 電池更換、伺服器汰換、球管更換、到期授權續約。 | O8: LCC
A9: ★ 投資類別 Investment category | B9: F 策略布局型 Strategic / Option | D9: ★ 最重要的一格。不同類別在 10 決策摘要會套用不同的判讀規則——用錯尺就會做出錯的決定。 | J9: F 策略布局型 Strategic / Option | K9: 為了取得未來機會、參考案例或市場位置。現金流高度不確定，CFA 指出需「超越傳統資本預算」的方法。 | L9: 分階段關卡（stage-gate）：每階段設可量測的續投條件，而非一次核定全額 | M9: 選擇權價值／階段關卡達成率 | N9: 例：第一家旗艦醫院（取得 reference site）、新國家市場試點、AI 產品共同開發。 | O9: OPTION
A10: └ 類別定義 | B10: =IFERROR(INDEX(_CatDef,MATCH($B$9,_CatName,0)),"") -> 為了取得未來機會、參考案例或市場位置。現金流高度不確定，CFA 指出需「超越傳統資本預算」的方法。
A11: └ 通過條件 | B11: =IFERROR(INDEX(_CatCond,MATCH($B$9,_CatName,0)),"") -> 分階段關卡（stage-gate）：每階段設可量測的續投條件，而非一次核定全額
A12: └ 主要評估指標 | B12: =IFERROR(INDEX(_CatMetric,MATCH($B$9,_CatName,0)),"") -> 選擇權價值／階段關卡達成率
A13: └ 判斷精靈比對 | B13: =IF(LEFT('01B_類別判斷_Wizard'!$C$22,1)="▶","▶ 不確定要選哪一類？請到 01B 判斷精靈分頁回答四題，它會推薦一類並說明理由。",IF('01B_類別判斷_Wizard'!$C$22=$B$9,"✓ 與 01B 判斷精靈的建議一致。","⚠ 與 01B 判斷精靈的建議不一致——精靈建議：「"&'01B_類別判斷_Wizard'!$C$22&"」。若你有充分理由維持目前的選擇，請在 11 假設來源分頁記錄原因。")) -> ✓ 與 01B 判斷精靈的建議一致。
A15: B. 幣別與匯率（預設輸入新台幣；顯示幣別可一鍵切換）
A16: 輸入幣別 Input currency | B16: TWD 新台幣 | D16: ★ 02、03、04 分頁「單價」欄位是用這個幣別填寫的。改這一格不會換算既有數字，只改變你打算用什麼幣別填。
A17: 顯示幣別 Display currency | B17: TWD 新台幣 | D17: ★ 一鍵切換：改這一格，全檔的金額顯示會自動換算。輸入的數字不動。
A18: 顯示單位 Display unit | B18: 千元 Thousand | D18: 越南盾位數很長，建議切到「百萬 Million」；新台幣建議「千元」。
A20: 匯率表（以越南盾為基準） | D20: ★ 財務模型慣例：3–10 年的長期預測不應直接用即期匯率。Damodaran 明述「Never use the current spot rate for long-term projections」，正確作法是用兩國通膨差（購買力平價）推算逐年匯率，或全程用單一幣別建模、最後才換算。本檔採後者（較穩健），並在 11 分頁登錄匯率假設與日期。
A21: 幣別 | B21: 1 單位 ＝ ? 越南盾 | C21: 代碼
A22: TWD 新台幣 | B22: 810 | C22: TWD
A23: USD 美元 | B23: 26082 | C23: USD
A24: VND 越南盾 | B24: 1 | C24: VND
A26: 輸入幣別對 VND 匯率 | B26: =INDEX($B$22:$B$24,MATCH($B$16,$A$22:$A$24,0)) -> 810 | D26: 自動由上表帶出
A27: 顯示幣別對 VND 匯率 | B27: =INDEX($B$22:$B$24,MATCH($B$17,$A$22:$A$24,0)) -> 810 | D27: 自動由上表帶出
A28: 幣別換算倍率 FX multiplier | B28: =$B$26/$B$27 -> 1 | D28: ＝輸入幣別匯率 ÷ 顯示幣別匯率。輸入幣別的金額 × 這個倍率 ＝ 顯示幣別的金額。
A29: 顯示單位除數 | B29: =IF($B$18="元 Unit",1,IF($B$18="千元 Thousand",1000,1000000)) -> 1000 | D29: 自動由「顯示單位」帶出
A30: ★ 顯示係數 Display factor | B30: =$B$28/$B$29 -> 0.001 | D30: 全檔所有「顯示幣別」欄位都乘這個係數。
A31: 金額標示 Money label | B31: =LEFT($B$17,3)&" "&IF($B$29=1,"元",IF($B$29=1000,"千",""&"百萬")) -> TWD 千 | D31: 出現在各分頁的欄位標題，例「TWD 千」
A33: C. 時間與稅務（越南）
A34: 模型年數 Model years | B34: 10 | C34: 年 | D34: 建議 8–12 年，須涵蓋主要設備壽命。本檔欄位配置上限為 10 年。
A35: 建置期 Build months | B35: 12 | C35: 月 | D35: 第 0 年＝建置期，不產生收入
A36: 起始年 Start year | B36: 2027 | C36: 年 | D36: 第 1 個營運年的西元年
A37: 標準企業所得稅率 | B37: 0.2 | D37: 越南標準 CIT 稅率 20%（Law 67/2025/QH15 自 2025/10/1 生效）
A38: 適用優惠稅率 | B38: 0.1 | D38: ★ PwC 越南 Pocket Tax Book 明載：教育、醫療等社會化領域享有「整個專案存續期間」的 10% 稅率。若本案不符資格請改回 20%。資格認定須由越南稅務顧問確認。
A39: 免稅年數 Tax holiday | B39: 4 | C39: 年 | D39: 社會化專案：位於社經困難地區者免稅 4 年＋減半 9 年；一般地區免稅 4 年＋減半 5 年。
A40: 減半年數 50% reduction | B40: 5 | C40: 年 | D40: 接續免稅期之後，稅率減半（10%→5%）
A41: 免稅起算規則：營收後最多遞延 | B41: 3 | C41: 年 | D41: ★ 法定規則（PwC）：免稅期自「首次從受優惠活動獲利」起算；但若產生營收後 3 年內仍未獲利，則自營運第 4 年起強制起算。本檔已內建此邏輯。
A42: 虧損可扣抵年限 | B42: 5 | C42: 年 | D42: 越南：虧損可全額連續向後扣抵最長 5 年，不得向前扣抵。逾期未用即永久失效。
A43: ★ 進項 VAT 可否扣抵 | B43: 否 — 醫療服務免 VAT | D43: ★ 越南醫療檢查治療服務屬 VAT「免稅（exempt）」而非零稅率（VAT Law 48/2024/QH15 第 5 條第 10 款）。免稅代表進項 VAT 不可扣抵、必須計入成本。這是越南醫院財務模型最常見的重大低估（CAPEX 會少估 5–10%）。
A45: D. 折現率
A46: 折現率來源 | B46: 由 07 分頁 WACC 推算 | D46: 「由 07 分頁 WACC 推算」或「手動輸入」
A47: 手動折現率 | B47: 0.12 | D47: 僅當上一格選「手動輸入」時採用
A48: ★ 採用折現率 Discount rate | B48: =IF($B$46="手動輸入",$B$47,'07_折現率_WACC'!$B$28) -> 0.11994697 | D48: 本模型實際使用的折現率
A49: MIRR 再投資報酬率 | B49: 0.08 | D49: ★ MIRR 相對 IRR 的關鍵改良：IRR 隱含假設所有期中現金流都以 IRR 本身再投資（對高 IRR 專案極不現實）。MIRR 讓你明確指定一個合理的再投資率。建議設為公司實際的資金報酬率或略低於 WACC。
A51: E. 營運資金（Working capital）
A52: ★ 越南醫療業特有風險 | D52: 2025 年 8 月報導：胡志明市各醫院被健保「懸置未結算」的費用近 2,500 十億越盾（約 9,600 萬美元），橫跨 2023–2024 兩年，醫院須依《健保法》第 32 條請求社保先行墊付。因此健保應收天數不應套用一般假設。
A54: 健保應收天數 DSO (BHYT) | B54: 90 | C54: 天 | D54: 越南社保按季結算且常有延遲與超支懸置，建議 120–180 天
A55: 自費應收天數 DSO (self-pay) | B55: 90 | C55: 天 | D55: 自費多為當場收款
A56: 耗材存貨天數 DIO | B56: 0 | C56: 天 | D56: 顯影劑、針具等耗材的安全庫存；進口耗材建議 45–90 天
A57: 應付帳款天數 DPO | B57: 45 | C57: 天 | D57: 向供應商的付款條件
A59: F. 終值與殘值（Terminal value）
A60: 終值方法 | B60: 殘值法 Salvage（有限年期資產） | D60: ★ 基礎建設與特許經營型專案的業界作法：不用永續成長法。Wall Street Prep 明述「終值法假設無限期營運，對有預定終止日的有限年期資產需採替代評價方法」。本檔預設殘值法。
A61: 永續成長率 g（僅永續法用） | B61: 0.025 | D61: 若改用永續成長法：g 應介於 2–4%，超過 5% 等於假設本案最終超越全球經濟成長。
A63: 填完本頁後，請依序檢查 02 → 03 → 04，然後直接看 10 決策摘要。05、06、08 是自動算的，不需編輯；07 折現率建議與投資方確認後再定案；09 只有使能型投資需要填。

Sheet 01B_類別判斷_Wizard
A1: 01B 投資類別判斷精靈｜Which yardstick should this project be measured with?
A2: 不確定 01 分頁該選哪一種投資類別時，回答下面四題（不適用的題目留白即可），本頁會推薦一類並說明理由。★ 這是輔助工具，不是替你決定——推薦出來之後請自己確認合理，再回到 01 分頁 B 欄選擇。
A4: ★ 回答之前先確認一件事：本試算器一律站在「群晶／聯盟」的投資角度，不是醫院的角度。 同一個案子，對醫院可能是「法規強制型」（不做不能營業），對群晶卻是「營收型」或「策略布局型」。搞錯立場，後面四題都會答錯。
A7: A. 依序回答（不適用的題留白）
A8: 題號 | B8: 問題 | C8: 你的回答（下拉選擇） | D8: 怎麼想這一題
A9: Q1 | B9: 這個案子有沒有錢從「聯盟外部」進來？ | C9: 有，但金額還算不準（要等市場成熟，或要等第 2、3 個客戶） | D9: ★ 關鍵在「外部」兩個字。外部＝聯盟以外的付款者（醫院、健保 BHYT、病人自費、保險公司）。院內或聯盟內的「內部轉付服務費」不算——那是左手換右手，不是新的錢進來。「算得準」的意思是：有公告給付碼、有正式報價，或有可比的市場行情。
A12: Q2 | B12: 不做這個案子，會發生什麼？（Q1 選「沒有」才需要答） | D12: 這一題在問「效益的形式」。它不產生收入，那它到底幫你避免了什麼？是別的專案做不成、是被罰、是某筆支出繼續花、還是營運中斷——四種答案對應四種不同的評估方法。
A15: Q3 | B15: 這個案子承載（服務）幾個其他專案？ | D15: ★ 使能型投資的硬門檻：必須 ≥ 2。只服務單一專案的「平台」，本質上是那個專案的成本，不是平台，應該把成本併進那個專案一起評估。填之前可以先去 09 分頁 F 區塊把承載清單列出來數一數。
A18: Q4 | B18: 不做的話，現有營運會不會停擺？（Q2 選「某一筆既有支出」才需要答） | D18: 用來分辨 D 降本型與 E 汰換維持型。判準是「你有沒有真的選擇」：不做就停擺 ⇒ E（沒得選，不必細算，同規格取最低生命週期成本即可）；還能撐一段時間 ⇒ D（有得選，要細算，因為你可以選擇不做）。
A21: B. 判斷結果
A22: ★ 建議投資類別 | C22: =IF($C$9="","▶ 請先回答 Q1",IF(ISNUMBER(SEARCH("算得準",$C$9)),"A 營收型投資 Revenue-generating",IF(ISNUMBER(SEARCH("算不準",$C$9)),"F 策略布局型 Strategic / Option",IF($C$12="","▶ 請回答 Q2",IF(ISNUMBER(SEARCH("別的專案",$C$12)),IF($C$15="","▶ 請回答 Q3",IF($C$15>=2,"B 使能型投資 Enabling / Infrastructure","⚠ 不應獨立立案（承載專案數不足 2）")),IF(ISNUMBER(SEARCH("罰",$C$12)),"C 法規強制型 Mandatory / Compliance",IF(ISNUMBER(SEARCH("既有支出",$C$12)),IF($C$18="","▶ 請回答 Q4",IF(ISNUMBER(SEARCH("會停擺",$C$18)),"E 汰換維持型 Replacement / Maintenance","D 降本型投資 Cost-reduction")),IF(ISNUMBER(SEARCH("營運會中斷",$C$12)),"E 汰換維持型 Replacement / Maintenance","▶ 請回答 Q2")))))))) -> F 策略布局型 Strategic / Option
A23: 判斷理由 | C23: =IF(LEFT($C$22,1)="▶","",IF(LEFT($C$22,1)="A","效益是外部客戶付進來的錢，而且金額算得準 ⇒ 用 NPV／MIRR／PI 這把尺，本案適合走標準資本預算流程。",IF(LEFT($C$22,1)="B","它不對外收費，但別的專案要靠它才能做，且承載 "&$C$15&" 個專案（≥2）⇒ 用 ΔTCO 差異法（做 vs 不做），不是絕對 NPV。",IF(LEFT($C$22,1)="C","不做就不能營業，屬強制投資 ⇒ 比的是「合規前提下的最低總成本」與「不做的代價」。NPV 為負屬正常，不構成否決理由。",IF(LEFT($C$22,1)="D","收入不變，但某筆既有支出會消失，而且你還有得選 ⇒ 效益＝被避免掉的成本，要細算。",IF(LEFT($C$22,1)="E","不做就停擺，沒得選 ⇒ 不必用 NPV 論斷，同規格中取最低生命週期成本、並確認停機風險成本即可。",IF(LEFT($C$22,1)="F","錢會進來，但現在算不準（要等市場成熟或第 2、3 個客戶）⇒ 不要一次核定全額，改用分階段關卡。","承載專案數不足 2 ⇒ 這不是平台，是它所服務的那一個專案的成本。建議把本案的建置成本併入該專案一起評估，不要獨立立案。"))))))) -> 錢會進來，但現在算不準（要等市場成熟或第 2、3 個客戶）⇒ 不要一次核定全額，改用分階段關卡。
A24: 建議下一步 | C24: =IF(LEFT($C$22,1)="▶","",IF(LEFT($C$22,1)="B","▶ 到 09 使能型評估分頁：F 區塊填承載專案清單、C 區塊填外租比較報價，ΔTCO 才算得出來。",IF(LEFT($C$22,1)="F","▶ 把 02 分頁的 CAPEX 拆成 2–3 期，每期在 11 假設來源分頁寫下可量測的續投條件（不要一次核定全額）。",IF(LEFT($C$22,1)="C","▶ 到 11 假設來源分頁登錄：法源、期限、不做的罰則或停業風險，並附至少三家供應商的比價。",IF(LEFT($C$22,1)="E","▶ 到 11 假設來源分頁登錄：現有資產的剩餘壽命、故障率，以及不汰換的停機風險成本。",IF(LEFT($C$22,1)="⚠","▶ 不要獨立立案。把本案成本併入它所服務的那個專案，或先確認第 2 個承載專案再回來。","▶ 把 02 分頁的示意值換成廠商正式報價，並確認 07 分頁的折現率已與投資方書面談定。")))))) -> ▶ 把 02 分頁的 CAPEX 拆成 2–3 期，每期在 11 假設來源分頁寫下可量測的續投條件（不要一次核定全額）。
A25: 與 01 分頁比對 | C25: =IF(LEFT($C$22,1)="▶","",IF($C$22='01_專案設定_Setup'!$B$9,"✓ 與 01 分頁目前的選擇一致，可以繼續。","⚠ 01 分頁目前選的是「"&'01_專案設定_Setup'!$B$9&"」，與本頁建議不同。若要採用建議，請到 01 分頁 B9 改選；若你有充分理由維持原選擇（例如本案同時具備兩種屬性），請在 11 假設來源分頁記錄理由。")) -> ✓ 與 01 分頁目前的選擇一致，可以繼續。
A28: C. 四個最常卡住的地方
A29: ① 立場沒講清楚 | C29: 同一個案子，對醫院是「法規強制型」（2025 年 10 月前必須完成電子病歷），對群晶卻是「策略布局型」。本表一律站在群晶／聯盟的投資角度。填之前先確認你在算誰的帳。
A30: ② 內部轉付被當成營收 | C30: 機房向院內其他專案收「內部服務費」，看起來像收入，但那是左手換右手。判準：這筆錢有沒有從聯盟外部進來？沒有就是 B 使能型，不是 A 營收型。
A31: ③ D 和 E 分不開 | C31: 汰換舊伺服器同時也省電費，算哪一種？看你有沒有真的選擇：不換就停擺 ⇒ E（不必細算）；還能撐但換了更省 ⇒ D（要細算）。這就是 Q4 在問的事。
A32: ④ 一個案子同時符合兩三類 | C32: 很常見。IDC 案其實同時是 B（承載別的專案）和 D（比外租省錢）。規則：選效益佔比最大的那一類，其餘寫進 11 假設來源分頁備註，不要為了數字好看挑一個。
A34: 如果四題怎麼答都答不出來，通常不是分類法不夠用，而是「專案範圍畫錯了」——把兩件性質不同的事綁在同一個案子裡。這時候該做的是拆案，不是硬選一個類別。（本工具的 IDC 個案刻意把院區網路排除在機房案之外，就是這個理由。）

Sheet 02_投資成本_CAPEX
A1: 02 投資成本 CAPEX｜工程分項明細（BOQ）
A2: 黃底＝要填。每一列請用工程界正式的分項名稱，並以「數量 × 單價」結構表達，這樣才能拿去跟廠商報價逐項核對。★ 關稅與 VAT：越南醫療服務屬 VAT 免稅，代表進項 VAT 不可扣抵、必須計入成本並資本化——K 欄已內建此計算。★ 折舊年限依 Circular 45/2013/TT-BTC：建物 25–50 年、醫療設備 6–15 年、電腦設備 3–8 年、軟體 3–8 年。
A4: ★ 進口項目會被課關稅與進口 VAT，且關稅計價基礎是 CIF（含運費保險）；在地施工項目只有 VAT。CT 主機 HS 9022.12.00 的 MFN 稅率為 0%、FTA 亦為 0%（須附有效 C/O），但 UPS／發電機／空調類非 ITA 涵蓋，稅率明顯較高。
A5: 項次 | B5: 分類 | C5: 分項工程名稱 Work item（工程界正式名稱） | D5: 單位 | E5: 數量 | F5: 單價 （輸入幣別） | G5: 未稅小計 （輸入幣別） | H5: 進口／在地 | I5: 關稅率 | J5: VAT率 | K5: 不可扣抵稅費 （輸入幣別） | L5: 含稅總額 （輸入幣別） | M5: 折舊類別 | N5: 折舊 年限 | O5: 置換年 | P5: 殘值率 | Q5: =CONCATENATE("含稅總額",CHAR(10),"（",'01_專案設定_Setup'!$B$31,"）") -> 含稅總額 （TWD 千） | R5: 出處／備註
A6: 1 | B6: 軟體 | C6: HIS／EMR 核心平台授權（500 床規模，含門診、住院、批價、病歷） | D6: 套 | E6: 1 | F6: 9205500 | G6: =IF($C6="",0,$E6*$F6) -> 9205500 | H6: 進口 | I6: 0 | J6: 0.1 | K6: =IF($C6="",0,$G6*$I6+$G6*(1+$I6)*$J6*IF(LEFT('01_專案設定_Setup'!$B$43,1)="否",1,0)) -> 920550 | L6: =IF($C6="",0,$G6+$K6) -> 10126050 | M6: 軟體與無形 Software | N6: 5 | O6: 0 | P6: 0 | Q6: =IF($C6="",0,$L6*'01_專案設定_Setup'!$B$30) -> 10126.05 | R6: tuoitre.vn：越南一級醫院 IT 投資 10.5–40bn VND、占營收 0.57–2.1%。★ 越南無公開每床授權價，廠商不公布價目（ykhoanet.com）
A7: 2 | B7: 軟體 | C7: LIS 檢驗資訊模組與儀器雙向介接 | D7: 套 | E7: 1 | F7: 1453500 | G7: =IF($C7="",0,$E7*$F7) -> 1453500 | H7: 進口 | I7: 0 | J7: 0.1 | K7: =IF($C7="",0,$G7*$I7+$G7*(1+$I7)*$J7*IF(LEFT('01_專案設定_Setup'!$B$43,1)="否",1,0)) -> 145350 | L7: =IF($C7="",0,$G7+$K7) -> 1598850 | M7: 軟體與無形 Software | N7: 5 | O7: 0 | P7: 0 | Q7: =IF($C7="",0,$L7*'01_專案設定_Setup'!$B$30) -> 1598.85 | R7: 電子病歷分級驗收要求檢驗檢查閉環
A8: 3 | B8: 軟體 | C8: RIS／PACS 介接與院內影像調閱 | D8: 套 | E8: 1 | F8: 1065900 | G8: =IF($C8="",0,$E8*$F8) -> 1065900 | H8: 進口 | I8: 0 | J8: 0.1 | K8: =IF($C8="",0,$G8*$I8+$G8*(1+$I8)*$J8*IF(LEFT('01_專案設定_Setup'!$B$43,1)="否",1,0)) -> 106590 | L8: =IF($C8="",0,$G8+$K8) -> 1172490 | M8: 軟體與無形 Software | N8: 5 | O8: 0 | P8: 0 | Q8: =IF($C8="",0,$L8*'01_專案設定_Setup'!$B$30) -> 1172.49 | R8: 與 A 醫院 CT 案的 PACS 採同一套標準，利於日後複製
A9: 4 | B9: 軟體 | C9: 藥事管理與閉環給藥 CPOE／BCMA 模組 | D9: 套 | E9: 1 | F9: 1227400 | G9: =IF($C9="",0,$E9*$F9) -> 1227400 | H9: 進口 | I9: 0 | J9: 0.1 | K9: =IF($C9="",0,$G9*$I9+$G9*(1+$I9)*$J9*IF(LEFT('01_專案設定_Setup'!$B$43,1)="否",1,0)) -> 122740 | L9: =IF($C9="",0,$G9+$K9) -> 1350140 | M9: 軟體與無形 Software | N9: 5 | O9: 0 | P9: 0 | Q9: =IF($C9="",0,$L9*'01_專案設定_Setup'!$B$30) -> 1350.14 | R9: 給藥安全是 EMR 分級驗收的重點項目
A10: 5 | B10: 軟體 | C10: 護理紀錄與電子表單（含行動護理車終端授權） | D10: 套 | E10: 1 | F10: 839800 | G10: =IF($C10="",0,$E10*$F10) -> 839800 | H10: 進口 | I10: 0 | J10: 0.1 | K10: =IF($C10="",0,$G10*$I10+$G10*(1+$I10)*$J10*IF(LEFT('01_專案設定_Setup'!$B$43,1)="否",1,0)) -> 83980 | L10: =IF($C10="",0,$G10+$K10) -> 923780 | M10: 軟體與無形 Software | N10: 5 | O10: 0 | P10: 0 | Q10: =IF($C10="",0,$L10*'01_專案設定_Setup'!$B$30) -> 923.78 | R10: 護理紀錄電子化是無紙化的最大工作量
A11: 6 | B11: 軟體 | C11: FHIR 介接引擎（HL7 FHIR R4＋DICOM） | D11: 套 | E11: 1 | F11: 1550400 | G11: =IF($C11="",0,$E11*$F11) -> 1550400 | H11: 進口 | I11: 0 | J11: 0.1 | K11: =IF($C11="",0,$G11*$I11+$G11*(1+$I11)*$J11*IF(LEFT('01_專案設定_Setup'!$B$43,1)="否",1,0)) -> 155040 | L11: =IF($C11="",0,$G11+$K11) -> 1705440 | M11: 軟體與無形 Software | N11: 5 | O11: 0 | P11: 0 | Q11: =IF($C11="",0,$L11*'01_專案設定_Setup'!$B$30) -> 1705.44 | R11: Decision 2146/QĐ-BYT 指定 HL7 FHIR R4＋DICOM 為國家標準；★ 越南本地 IG 仍為試用版，規格會變
A12: 7 | B12: 軟體 | C12: VNeID／VSS 健保申報與身分核驗介接 | D12: 套 | E12: 1 | F12: 1421200 | G12: =IF($C12="",0,$E12*$F12) -> 1421200 | H12: 進口 | I12: 0 | J12: 0.1 | K12: =IF($C12="",0,$G12*$I12+$G12*(1+$I12)*$J12*IF(LEFT('01_專案設定_Setup'!$B$43,1)="否",1,0)) -> 142120 | L12: =IF($C12="",0,$G12+$K12) -> 1563320 | M12: 軟體與無形 Software | N12: 5 | O12: 0 | P12: 0 | Q12: =IF($C12="",0,$L12*'01_專案設定_Setup'!$B$30) -> 1563.32 | R12: ★ 越南社保正在修訂申報資料閘道規則，介接規格變更風險高，OPEX 已編列維護費
A13: 8 | B13: 服務 | C13: 越南在地化：病歷範本、衛生部報表格式、越文介面與術語對應 | D13: 式 | E13: 1 | F13: 3714500 | G13: =IF($C13="",0,$E13*$F13) -> 3714500 | H13: 在地 | I13: 0 | J13: 0.08 | K13: =IF($C13="",0,$G13*$I13+$G13*(1+$I13)*$J13*IF(LEFT('01_專案設定_Setup'!$B$43,1)="否",1,0)) -> 297160 | L13: =IF($C13="",0,$G13+$K13) -> 4011660 | M13: 軟體與無形 Software | N13: 5 | O13: 0 | P13: 0 | Q13: =IF($C13="",0,$L13*'01_專案設定_Setup'!$B$30) -> 4011.66 | R13: ★ 一次性投入。複製到第 2、3 家醫院時可攤薄六成以上——這是本案的核心商業論點
A14: 9 | B14: 服務 | C14: 資料移轉與病人主檔 MPI 清理去重（與 CCCD／VNeID 比對） | D14: 式 | E14: 1 | F14: 2196400 | G14: =IF($C14="",0,$E14*$F14) -> 2196400 | H14: 在地 | I14: 0 | J14: 0.08 | K14: =IF($C14="",0,$G14*$I14+$G14*(1+$I14)*$J14*IF(LEFT('01_專案設定_Setup'!$B$43,1)="否",1,0)) -> 175712 | L14: =IF($C14="",0,$G14+$K14) -> 2372112 | M14: 費用化 Expensed | N14: 0 | O14: 0 | P14: 0 | Q14: =IF($C14="",0,$L14*'01_專案設定_Setup'!$B$30) -> 2372.112 | R14: pacscribe.com：資料移轉 US$0.05–0.50/study。★ 一次性投入
A15: 10 | B15: 服務 | C15: 導入服務：流程重整、平行測試、12 個月上線輔導 | D15: 式 | E15: 1 | F15: 4360500 | G15: =IF($C15="",0,$E15*$F15) -> 4360500 | H15: 在地 | I15: 0 | J15: 0.08 | K15: =IF($C15="",0,$G15*$I15+$G15*(1+$I15)*$J15*IF(LEFT('01_專案設定_Setup'!$B$43,1)="否",1,0)) -> 348840 | L15: =IF($C15="",0,$G15+$K15) -> 4709340 | M15: 費用化 Expensed | N15: 0 | O15: 0 | P15: 0 | Q15: =IF($C15="",0,$L15*'01_專案設定_Setup'!$B$30) -> 4709.34 | R15: bvdkthaibinh.vn：越南 EMR 租賃 RFQ 多為 36 個月、按季付款無預付。★ 一次性投入
A16: 11 | B16: 服務 | C16: 醫師與護理教育訓練（含種子講師制度） | D16: 人 | E16: 600 | F16: 2261 | G16: =IF($C16="",0,$E16*$F16) -> 1356600 | H16: 在地 | I16: 0 | J16: 0.08 | K16: =IF($C16="",0,$G16*$I16+$G16*(1+$I16)*$J16*IF(LEFT('01_專案設定_Setup'!$B$43,1)="否",1,0)) -> 108528 | L16: =IF($C16="",0,$G16+$K16) -> 1465128 | M16: 費用化 Expensed | N16: 0 | O16: 0 | P16: 0 | Q16: =IF($C16="",0,$L16*'01_專案設定_Setup'!$B$30) -> 1465.128 | R16: pacscribe.com：訓練 US$200–700/人。500 床醫院約 600 名需訓人員。★ 一次性投入
A17: 12 | B17: 設備 | C17: 承載環境：伺服器、儲存、備份（可承載於 A醫院 IDC，或商用雲） | D17: 式 | E17: 1 | F17: 2842400 | G17: =IF($C17="",0,$E17*$F17) -> 2842400 | H17: 進口 | I17: 0 | J17: 0.1 | K17: =IF($C17="",0,$G17*$I17+$G17*(1+$I17)*$J17*IF(LEFT('01_專案設定_Setup'!$B$43,1)="否",1,0)) -> 284240 | L17: =IF($C17="",0,$G17+$K17) -> 3126640 | M17: 電腦與網通 IT | N17: 5 | O17: 6 | P17: 0.05 | Q17: =IF($C17="",0,$L17*'01_專案設定_Setup'!$B$30) -> 3126.64 | R17: ★ 若承載於 A醫院 IDC，本項即為聯盟內部轉付，並構成該機房「承載專案數 ≥2」的證據
... A21: 16 | B21: 預備 | C21: 不可預見費 Contingency | D21: 式 | E21: 1 | F21: 2100000 | G21: =IF($C21="",0,$E21*$F21) -> 2100000 | H21: 在地 | I21: 0 | J21: 0.08 | K21: =IF($C21="",0,$G21*$I21+$G21*(1+$I21)*$J21*IF(LEFT('01_專案設定_Setup'!$B$43,1)="否",1,0)) -> 168000 | L21: =IF($C21="",0,$G21+$K21) -> 2268000 | M21: 費用化 Expensed | N21: 0 | O21: 0 | P21: 0 | Q21: =IF($C21="",0,$L21*'01_專案設定_Setup'!$B$30) -> 2268 | R21: 約未稅總額 6%。醫院流程重整的變更風險高
A22: 17 | G22: =IF($C22="",0,$E22*$F22) -> 0 | K22: =IF($C22="",0,$G22*$I22+$G22*(1+$I22)*$J22*IF(LEFT('01_專案設定_Setup'!$B$43,1)="否",1,0)) -> 0 | L22: =IF($C22="",0,$G22+$K22) -> 0 | Q22: =IF($C22="",0,$L22*'01_專案設定_Setup'!$B$30) -> 0
A23: 18 | G23: =IF($C23="",0,$E23*$F23) -> 0 | K23: =IF($C23="",0,$G23*$I23+$G23*(1+$I23)*$J23*IF(LEFT('01_專案設定_Setup'!$B$43,1)="否",1,0)) -> 0 | L23: =IF($C23="",0,$G23+$K23) -> 0 | Q23: =IF($C23="",0,$L23*'01_專案設定_Setup'!$B$30) -> 0
A24: 19 | G24: =IF($C24="",0,$E24*$F24) -> 0 | K24: =IF($C24="",0,$G24*$I24+$G24*(1+$I24)*$J24*IF(LEFT('01_專案設定_Setup'!$B$43,1)="否",1,0)) -> 0 | L24: =IF($C24="",0,$G24+$K24) -> 0 | Q24: =IF($C24="",0,$L24*'01_專案設定_Setup'!$B$30) -> 0
A25: 20 | G25: =IF($C25="",0,$E25*$F25) -> 0 | K25: =IF($C25="",0,$G25*$I25+$G25*(1+$I25)*$J25*IF(LEFT('01_專案設定_Setup'!$B$43,1)="否",1,0)) -> 0 | L25: =IF($C25="",0,$G25+$K25) -> 0 | Q25: =IF($C25="",0,$L25*'01_專案設定_Setup'!$B$30) -> 0
A26: 21 | G26: =IF($C26="",0,$E26*$F26) -> 0 | K26: =IF($C26="",0,$G26*$I26+$G26*(1+$I26)*$J26*IF(LEFT('01_專案設定_Setup'!$B$43,1)="否",1,0)) -> 0 | L26: =IF($C26="",0,$G26+$K26) -> 0 | Q26: =IF($C26="",0,$L26*'01_專案設定_Setup'!$B$30) -> 0
A27: 22 | G27: =IF($C27="",0,$E27*$F27) -> 0 | K27: =IF($C27="",0,$G27*$I27+$G27*(1+$I27)*$J27*IF(LEFT('01_專案設定_Setup'!$B$43,1)="否",1,0)) -> 0 | L27: =IF($C27="",0,$G27+$K27) -> 0 | Q27: =IF($C27="",0,$L27*'01_專案設定_Setup'!$B$30) -> 0
A28: 23 | G28: =IF($C28="",0,$E28*$F28) -> 0 | K28: =IF($C28="",0,$G28*$I28+$G28*(1+$I28)*$J28*IF(LEFT('01_專案設定_Setup'!$B$43,1)="否",1,0)) -> 0 | L28: =IF($C28="",0,$G28+$K28) -> 0 | Q28: =IF($C28="",0,$L28*'01_專案設定_Setup'!$B$30) -> 0
A29: 24 | G29: =IF($C29="",0,$E29*$F29) -> 0 | K29: =IF($C29="",0,$G29*$I29+$G29*(1+$I29)*$J29*IF(LEFT('01_專案設定_Setup'!$B$43,1)="否",1,0)) -> 0 | L29: =IF($C29="",0,$G29+$K29) -> 0 | Q29: =IF($C29="",0,$L29*'01_專案設定_Setup'!$B$30) -> 0
A30: 25 | G30: =IF($C30="",0,$E30*$F30) -> 0 | K30: =IF($C30="",0,$G30*$I30+$G30*(1+$I30)*$J30*IF(LEFT('01_專案設定_Setup'!$B$43,1)="否",1,0)) -> 0 | L30: =IF($C30="",0,$G30+$K30) -> 0 | Q30: =IF($C30="",0,$L30*'01_專案設定_Setup'!$B$30) -> 0
A31: 26 | G31: =IF($C31="",0,$E31*$F31) -> 0 | K31: =IF($C31="",0,$G31*$I31+$G31*(1+$I31)*$J31*IF(LEFT('01_專案設定_Setup'!$B$43,1)="否",1,0)) -> 0 | L31: =IF($C31="",0,$G31+$K31) -> 0 | Q31: =IF($C31="",0,$L31*'01_專案設定_Setup'!$B$30) -> 0
A32: 27 | G32: =IF($C32="",0,$E32*$F32) -> 0 | K32: =IF($C32="",0,$G32*$I32+$G32*(1+$I32)*$J32*IF(LEFT('01_專案設定_Setup'!$B$43,1)="否",1,0)) -> 0 | L32: =IF($C32="",0,$G32+$K32) -> 0 | Q32: =IF($C32="",0,$L32*'01_專案設定_Setup'!$B$30) -> 0
A33: 28 | G33: =IF($C33="",0,$E33*$F33) -> 0 | K33: =IF($C33="",0,$G33*$I33+$G33*(1+$I33)*$J33*IF(LEFT('01_專案設定_Setup'!$B$43,1)="否",1,0)) -> 0 | L33: =IF($C33="",0,$G33+$K33) -> 0 | Q33: =IF($C33="",0,$L33*'01_專案設定_Setup'!$B$30) -> 0
... A63: 58 | G63: =IF($C63="",0,$E63*$F63) -> 0 | K63: =IF($C63="",0,$G63*$I63+$G63*(1+$I63)*$J63*IF(LEFT('01_專案設定_Setup'!$B$43,1)="否",1,0)) -> 0 | L63: =IF($C63="",0,$G63+$K63) -> 0 | Q63: =IF($C63="",0,$L63*'01_專案設定_Setup'!$B$30) -> 0
C64: 合計 Total CAPEX（含不可扣抵稅費） | G64: =SUM($G$6:$G$63) -> 37597700 | K64: =SUM($K$6:$K$63) -> 3421902 | L64: =SUM($L$6:$L$63) -> 41019602 | Q64: =SUM($Q$6:$Q$63) -> 41019.602
A66: 分類小計與結構檢查
A67: 分類 | B67: 未稅金額 | C67: 佔比 | E67: 折舊類別 | F67: 含稅金額 | G67: 折舊年限（加權） | I67: 進口／在地 | J67: 含稅金額 | K67: 佔比
A68: 設備 | B68: =SUMIF($B$6:$B$63,$A68,$G$6:$G$63) -> 2842400 | C68: =IFERROR($B68/$G$64,0) -> 0.075600369 | E68: 建物與裝修 Building | F68: =SUMIF($M$6:$M$63,$E68,$L$6:$L$63) -> 0 | G68: =IFERROR(SUMPRODUCT(($M$6:$M$63=$E68)*$L$6:$L$63*$N$6:$N$63)/$F68,0) -> 0 | I68: 進口 | J68: =SUMIF($H$6:$H$63,$I68,$L$6:$L$63) -> 22774730 | K68: =IFERROR($J68/$L$64,0) -> 0.55521577
A69: 工程 | B69: =SUMIF($B$6:$B$63,$A69,$G$6:$G$63) -> 0 | C69: =IFERROR($B69/$G$64,0) -> 0 | E69: 醫療設備 Medical equip | F69: =SUMIF($M$6:$M$63,$E69,$L$6:$L$63) -> 0 | G69: =IFERROR(SUMPRODUCT(($M$6:$M$63=$E69)*$L$6:$L$63*$N$6:$N$63)/$F69,0) -> 0 | I69: 在地 | J69: =SUMIF($H$6:$H$63,$I69,$L$6:$L$63) -> 18244872 | K69: =IFERROR($J69/$L$64,0) -> 0.44478423
A70: 軟體 | B70: =SUMIF($B$6:$B$63,$A70,$G$6:$G$63) -> 17861900 | C70: =IFERROR($B70/$G$64,0) -> 0.47507959 | E70: 機電設備 M&E | F70: =SUMIF($M$6:$M$63,$E70,$L$6:$L$63) -> 0 | G70: =IFERROR(SUMPRODUCT(($M$6:$M$63=$E70)*$L$6:$L$63*$N$6:$N$63)/$F70,0) -> 0 | I70: 混合 | J70: =SUMIF($H$6:$H$63,$I70,$L$6:$L$63) -> 0 | K70: =IFERROR($J70/$L$64,0) -> 0
A71: 服務 | B71: =SUMIF($B$6:$B$63,$A71,$G$6:$G$63) -> 14793400 | C71: =IFERROR($B71/$G$64,0) -> 0.39346556 | E71: 電腦與網通 IT | F71: =SUMIF($M$6:$M$63,$E71,$L$6:$L$63) -> 3126640 | G71: =IFERROR(SUMPRODUCT(($M$6:$M$63=$E71)*$L$6:$L$63*$N$6:$N$63)/$F71,0) -> 5
A72: 預備 | B72: =SUMIF($B$6:$B$63,$A72,$G$6:$G$63) -> 2100000 | C72: =IFERROR($B72/$G$64,0) -> 0.05585448 | E72: 軟體與無形 Software | F72: =SUMIF($M$6:$M$63,$E72,$L$6:$L$63) -> 23659750 | G72: =IFERROR(SUMPRODUCT(($M$6:$M$63=$E72)*$L$6:$L$63*$N$6:$N$63)/$F72,0) -> 5
E73: 費用化 Expensed | F73: =SUMIF($M$6:$M$63,$E73,$L$6:$L$63) -> 14233212 | G73: =IFERROR(SUMPRODUCT(($M$6:$M$63=$E73)*$L$6:$L$63*$N$6:$N$63)/$F73,0) -> 0
A75: ★ 檢查點：不可扣抵稅費佔未稅金額的比例 | D75: =IFERROR($K$64/$G$64,0) -> 0.091013599 | F75: 若這個數字低於 4%，表示你可能把進項 VAT 當成可退稅處理了。越南醫療服務免 VAT ⇒ 進項不可扣抵 ⇒ 這一筆是實實在在的成本。

Sheet 03_營運成本_OPEX
A1: 03 營運成本 OPEX｜年度營運成本明細
A2: 黃底＝要填。「成本性質」欄很重要：標為「變動」的項目會隨 04 分頁的服務量爬坡而等比例縮放（例如顯影劑、耗材）；標為「固定」的項目不隨量變動（例如維保合約、人力、保險）。這一欄填錯，開辦頭幾年的現金流會嚴重失真。
A4: 項次 | B4: 分類 | C4: 成本項目 Cost item | D4: 單位 | E4: 數量 | F4: 單價／年費 （輸入幣別） | G4: 首年金額 （輸入幣別） | H4: 年成長率 | I4: 成本性質 | J4: =CONCATENATE("首年金額",CHAR(10),"（",'01_專案設定_Setup'!$B$31,"）") -> 首年金額 （TWD 千） | K4: 負責角色 | L4: 出處／備註
A5: 1 | B5: 人力 | C5: 產品維護與版本升級團隊（3 人） | D5: 人 | E5: 3 | F5: 468000 | G5: =IF($C5="",0,$E5*$F5) -> 1404000 | H5: 0.08 | I5: 固定 | J5: =IF($C5="",0,$G5*'01_專案設定_Setup'!$B$30) -> 1404 | K5: 醫療資訊 | L5: manpower.com.vn：越南資深開發／DevOps 37–75m VND/月。★ 成長率 8% 反映越南 IT 薪資漲幅
A6: 2 | B6: 人力 | C6: 現場駐點支援工程師（2 人） | D6: 人 | E6: 2 | F6: 316500 | G6: =IF($C6="",0,$E6*$F6) -> 633000 | H6: 0.08 | I6: 固定 | J6: =IF($C6="",0,$G6*'01_專案設定_Setup'!$B$30) -> 633 | K6: 醫療資訊 | L6: ykhoanet.com：越南醫院 IT 10–20m VND/月，駐點取高段
A7: 3 | B7: 公用 | C7: 承載環境代管費（機房／雲端） | D7: 年 | E7: 1 | F7: 1033600 | G7: =IF($C7="",0,$E7*$F7) -> 1033600 | H7: 0.03 | I7: 固定 | J7: =IF($C7="",0,$G7*'01_專案設定_Setup'!$B$30) -> 1033.6 | K7: 數位基建 | L7: ★ 若承載於 A醫院 IDC 即為聯盟內部轉付；市價見 IDC 案 09 分頁的外租單價
A8: 4 | B8: 軟體 | C8: 第三方軟體授權（資料庫、中介軟體、報表引擎） | D8: 年 | E8: 1 | F8: 904400 | G8: =IF($C8="",0,$E8*$F8) -> 904400 | H8: 0.05 | I8: 固定 | J8: =IF($C8="",0,$G8*'01_專案設定_Setup'!$B$30) -> 904.4 | K8: 醫療資訊 | L8: 原廠年費
A9: 5 | B9: 維保 | C9: 資安維運與弱點修補（SOC 訂閱） | D9: 年 | E9: 1 | F9: 678300 | G9: =IF($C9="",0,$E9*$F9) -> 678300 | H9: 0.06 | I9: 固定 | J9: =IF($C9="",0,$G9*'01_專案設定_Setup'!$B$30) -> 678.3 | K9: CISO | L9: PDPL 91/2025 的 72 小時通報義務需有偵測與應變量能
A10: 6 | B10: 服務 | C10: FHIR／VSS 介接規格變更維護 | D10: 年 | E10: 1 | F10: 516800 | G10: =IF($C10="",0,$E10*$F10) -> 516800 | H10: 0.05 | I10: 固定 | J10: =IF($C10="",0,$G10*'01_專案設定_Setup'!$B$30) -> 516.8 | K10: 醫療資訊 | L10: ★ 越南社保正在修訂申報資料閘道規則，介接規格會變。這是越南醫療 IT 特有的持續性成本
A11: 7 | B11: 法規 | C11: 年度稽核與合規（EMR 分級年度覆核、個資稽核） | D11: 年 | E11: 1 | F11: 387600 | G11: =IF($C11="",0,$E11*$F11) -> 387600 | H11: 0.04 | I11: 固定 | J11: =IF($C11="",0,$G11*'01_專案設定_Setup'!$B$30) -> 387.6 | K11: 法務 | L11: 含衛生部電子病歷分級年度覆核
A12: 8 | B12: 公用 | C12: 機房電力與對外頻寬分攤 | D12: 年 | E12: 1 | F12: 258400 | G12: =IF($C12="",0,$E12*$F12) -> 258400 | H12: 0.05 | I12: 固定 | J12: =IF($C12="",0,$G12*'01_專案設定_Setup'!$B$30) -> 258.4 | K12: 數位基建 | L12: 承載環境的水電與頻寬
A13: 9 | B13: 服務 | C13: 客服專線與持續教育訓練支援 | D13: 年 | E13: 1 | F13: 323000 | G13: =IF($C13="",0,$E13*$F13) -> 323000 | H13: 0.05 | I13: 變動 | J13: =IF($C13="",0,$G13*'01_專案設定_Setup'!$B$30) -> 323 | K13: 營運 | L13: 人員異動後的補訓需求持續存在
A14: 10 | B14: 管理 | C14: 間接管理費分攤 Overhead | D14: 年 | E14: 1 | F14: 581400 | G14: =IF($C14="",0,$E14*$F14) -> 581400 | H14: 0.05 | I14: 固定 | J14: =IF($C14="",0,$G14*'01_專案設定_Setup'!$B$30) -> 581.4 | K14: 財務 | L14: 分攤聯盟管理成本
A15: 11 | G15: =IF($C15="",0,$E15*$F15) -> 0 | J15: =IF($C15="",0,$G15*'01_專案設定_Setup'!$B$30) -> 0
A16: 12 | G16: =IF($C16="",0,$E16*$F16) -> 0 | J16: =IF($C16="",0,$G16*'01_專案設定_Setup'!$B$30) -> 0
A17: 13 | G17: =IF($C17="",0,$E17*$F17) -> 0 | J17: =IF($C17="",0,$G17*'01_專案設定_Setup'!$B$30) -> 0
A18: 14 | G18: =IF($C18="",0,$E18*$F18) -> 0 | J18: =IF($C18="",0,$G18*'01_專案設定_Setup'!$B$30) -> 0
A19: 15 | G19: =IF($C19="",0,$E19*$F19) -> 0 | J19: =IF($C19="",0,$G19*'01_專案設定_Setup'!$B$30) -> 0
A20: 16 | G20: =IF($C20="",0,$E20*$F20) -> 0 | J20: =IF($C20="",0,$G20*'01_專案設定_Setup'!$B$30) -> 0
A21: 17 | G21: =IF($C21="",0,$E21*$F21) -> 0 | J21: =IF($C21="",0,$G21*'01_專案設定_Setup'!$B$30) -> 0
A22: 18 | G22: =IF($C22="",0,$E22*$F22) -> 0 | J22: =IF($C22="",0,$G22*'01_專案設定_Setup'!$B$30) -> 0
A23: 19 | G23: =IF($C23="",0,$E23*$F23) -> 0 | J23: =IF($C23="",0,$G23*'01_專案設定_Setup'!$B$30) -> 0
A24: 20 | G24: =IF($C24="",0,$E24*$F24) -> 0 | J24: =IF($C24="",0,$G24*'01_專案設定_Setup'!$B$30) -> 0
A25: 21 | G25: =IF($C25="",0,$E25*$F25) -> 0 | J25: =IF($C25="",0,$G25*'01_專案設定_Setup'!$B$30) -> 0
A26: 22 | G26: =IF($C26="",0,$E26*$F26) -> 0 | J26: =IF($C26="",0,$G26*'01_專案設定_Setup'!$B$30) -> 0
... A34: 30 | G34: =IF($C34="",0,$E34*$F34) -> 0 | J34: =IF($C34="",0,$G34*'01_專案設定_Setup'!$B$30) -> 0
C35: 合計 首年 OPEX | G35: =SUM($G$5:$G$34) -> 6720500 | J35: =SUM($J$5:$J$34) -> 6720.5
C36: 其中：變動成本 Variable | G36: =SUMIF($I$5:$I$34,"變動",$G$5:$G$34) -> 323000 | J36: =$G36*'01_專案設定_Setup'!$B$30 -> 323
C37: 其中：固定成本 Fixed | G37: =SUMIF($I$5:$I$34,"固定",$G$5:$G$34) -> 6397500 | J37: =$G37*'01_專案設定_Setup'!$B$30 -> 6397.5
C38: 加權平均年成長率（依金額加權） | G38: =IFERROR(SUMPRODUCT($G$5:$G$34,$H$5:$H$34)/$G$35,0) -> 0.056449669
A40: ★ 越南在地成本的三個常見低估：①「原廠維保」影像設備的業界行情是設備價的 8–15%／年，十年就是另一台機器的錢；② 薪資年成長率不要填 0——越南薪資漲幅明顯高於服務單價漲幅，這個剪刀差是長期模型裡最容易被忽略的殺手；③ 進口耗材要計入不可扣抵的進項 VAT。

Sheet 04_收入產能_Revenue
A1: 04 收入與產能｜Revenue & Capacity
A2: 黃底＝要填。收入 ＝ 服務量 × 計費期數 × 加權單價 × 爬坡率。健保與自費分開設定，因為兩者的「單價」與「收現速度」完全不同——收現速度會在 06 分頁的營運資金計算中用到。★ 使能型投資（如機房）若不直接對外收費，本頁服務量可填 0，改到 09 分頁做評估。
A4: A. 產能與服務量
A5: 服務床數 Beds | B5: 500 | C5: 床 | D5: B 醫院核定床數。★ 若實際規模為 700–800 床，請直接改這一格重算——床數是本案最直接的槓桿。
A6: 計費期數 Billing periods | B6: 12 | C6: 月／年 | D6: 以租代購年費按月計，一年 12 期
A7: 設計產能利用率 Capacity utilisation | B7: 0.85 | D7: 滿載服務量相對於設備設計最大產能的比例，用來檢查「量」的假設是否物理上可行
A9: B. 單價（健保 vs 自費）
A10: 基本服務費 Base fee | B10: 1680 | C10: TWD／床／月 | D10: 含 HIS／EMR／LIS／RIS、承載環境與維運。500 床 × 1,680 × 12 ＝ 1,008 萬 TWD／年 ≒ 8.2bn VND／年；五年約 41bn VND，已落在越南一級醫院 IT 投資區間（10.5–40bn VND）的上緣。
A11: 加值模組費 Add-on fee | B11: 2420 | C11: TWD／床／月 | D11: AI 判讀介接、病人 App、BI 營運指揮、行動護理等加值模組
A12: 加值模組採用比例 | B12: 0.2 | D12: 初期僅部分科別導入加值模組
A13: 加權平均單價 Weighted price | B13: =$B$10*(1-$B$12)+$B$11*$B$12 -> 1828 | C13: TWD／床／月 | D13: 自動計算
A15: C. 成長率
A16: 服務量年成長率 | B16: 0.02 | D16: 床數成長有限，主要來自服務範圍擴大
A17: 單價年成長率 | B17: 0.03 | D17: 合約每 3 年檢討一次。★ 越南尚無醫院軟體的公開定價基準（ykhoanet.com），廠商不公布價目
A19: D. 開辦爬坡 Ramp-up（第 1–10 年，滿載＝100%）
A20: 年度 | B20: 第 1 年 | C20: 第 2 年 | D20: 第 3 年 | E20: 第 4 年 | F20: 第 5 年 | G20: 第 6 年 | H20: 第 7 年 | I20: 第 8 年 | J20: 第 9 年 | K20: 第 10 年
A21: 爬坡率 Ramp | B21: 0.4 | C21: 0.75 | D21: 1 | E21: 1 | F21: 1 | G21: 1 | H21: 1 | I21: 1 | J21: 1 | K21: 1
A23: E. 逐年營收（自動計算，顯示幣別）
A24: 項目 | B24: =CONCATENATE("第 1 年",CHAR(10),"(",'01_專案設定_Setup'!$B$36+0,")") -> 第 1 年 (2027) | C24: =CONCATENATE("第 2 年",CHAR(10),"(",'01_專案設定_Setup'!$B$36+1,")") -> 第 2 年 (2028) | D24: =CONCATENATE("第 3 年",CHAR(10),"(",'01_專案設定_Setup'!$B$36+2,")") -> 第 3 年 (2029) | E24: =CONCATENATE("第 4 年",CHAR(10),"(",'01_專案設定_Setup'!$B$36+3,")") -> 第 4 年 (2030) | F24: =CONCATENATE("第 5 年",CHAR(10),"(",'01_專案設定_Setup'!$B$36+4,")") -> 第 5 年 (2031) | G24: =CONCATENATE("第 6 年",CHAR(10),"(",'01_專案設定_Setup'!$B$36+5,")") -> 第 6 年 (2032) | H24: =CONCATENATE("第 7 年",CHAR(10),"(",'01_專案設定_Setup'!$B$36+6,")") -> 第 7 年 (2033) | I24: =CONCATENATE("第 8 年",CHAR(10),"(",'01_專案設定_Setup'!$B$36+7,")") -> 第 8 年 (2034) | J24: =CONCATENATE("第 9 年",CHAR(10),"(",'01_專案設定_Setup'!$B$36+8,")") -> 第 9 年 (2035) | K24: =CONCATENATE("第 10 年",CHAR(10),"(",'01_專案設定_Setup'!$B$36+9,")") -> 第 10 年 (2036)
A25: 服務量（爬坡後） | B25: =$B$5*$B$6*(1+$B$16)^0*B$21 -> 2400 | C25: =$B$5*$B$6*(1+$B$16)^1*C$21 -> 4590 | D25: =$B$5*$B$6*(1+$B$16)^2*D$21 -> 6242.4 | E25: =$B$5*$B$6*(1+$B$16)^3*E$21 -> 6367.248 | F25: =$B$5*$B$6*(1+$B$16)^4*F$21 -> 6494.593 | G25: =$B$5*$B$6*(1+$B$16)^5*G$21 -> 6624.4848 | H25: =$B$5*$B$6*(1+$B$16)^6*H$21 -> 6756.9745 | I25: =$B$5*$B$6*(1+$B$16)^7*I$21 -> 6892.114 | J25: =$B$5*$B$6*(1+$B$16)^8*J$21 -> 7029.9563 | K25: =$B$5*$B$6*(1+$B$16)^9*K$21 -> 7170.5554
A26: 加權單價（成長後・輸入幣別） | B26: =$B$13*(1+$B$17)^0 -> 1828 | C26: =$B$13*(1+$B$17)^1 -> 1882.84 | D26: =$B$13*(1+$B$17)^2 -> 1939.3252 | E26: =$B$13*(1+$B$17)^3 -> 1997.505 | F26: =$B$13*(1+$B$17)^4 -> 2057.4301 | G26: =$B$13*(1+$B$17)^5 -> 2119.153 | H26: =$B$13*(1+$B$17)^6 -> 2182.7276 | I26: =$B$13*(1+$B$17)^7 -> 2248.2094 | J26: =$B$13*(1+$B$17)^8 -> 2315.6557 | K26: =$B$13*(1+$B$17)^9 -> 2385.1254
A27: 健保營收 BHYT（顯示幣別） | B27: =IF($B$5=0,0,B$25*(1-$B$12)*$B$10*(1+$B$17)^0*'01_專案設定_Setup'!$B$30) -> 3225.6 | C27: =IF($B$5=0,0,C$25*(1-$B$12)*$B$10*(1+$B$17)^1*'01_專案設定_Setup'!$B$30) -> 6354.0288 | D27: =IF($B$5=0,0,D$25*(1-$B$12)*$B$10*(1+$B$17)^2*'01_專案設定_Setup'!$B$30) -> 8900.7235 | E27: =IF($B$5=0,0,E$25*(1-$B$12)*$B$10*(1+$B$17)^3*'01_專案設定_Setup'!$B$30) -> 9351.1002 | F27: =IF($B$5=0,0,F$25*(1-$B$12)*$B$10*(1+$B$17)^4*'01_專案設定_Setup'!$B$30) -> 9824.2658 | G27: =IF($B$5=0,0,G$25*(1-$B$12)*$B$10*(1+$B$17)^5*'01_專案設定_Setup'!$B$30) -> 10321.374 | H27: =IF($B$5=0,0,H$25*(1-$B$12)*$B$10*(1+$B$17)^6*'01_專案設定_Setup'!$B$30) -> 10843.635 | I27: =IF($B$5=0,0,I$25*(1-$B$12)*$B$10*(1+$B$17)^7*'01_專案設定_Setup'!$B$30) -> 11392.323 | J27: =IF($B$5=0,0,J$25*(1-$B$12)*$B$10*(1+$B$17)^8*'01_專案設定_Setup'!$B$30) -> 11968.775 | K27: =IF($B$5=0,0,K$25*(1-$B$12)*$B$10*(1+$B$17)^9*'01_專案設定_Setup'!$B$30) -> 12574.395
A28: 自費營收 Self-pay（顯示幣別） | B28: =IF($B$5=0,0,B$25*$B$12*$B$11*(1+$B$17)^0*'01_專案設定_Setup'!$B$30) -> 1161.6 | C28: =IF($B$5=0,0,C$25*$B$12*$B$11*(1+$B$17)^1*'01_專案設定_Setup'!$B$30) -> 2288.2068 | D28: =IF($B$5=0,0,D$25*$B$12*$B$11*(1+$B$17)^2*'01_專案設定_Setup'!$B$30) -> 3205.3201 | E28: =IF($B$5=0,0,E$25*$B$12*$B$11*(1+$B$17)^3*'01_專案設定_Setup'!$B$30) -> 3367.5093 | F28: =IF($B$5=0,0,F$25*$B$12*$B$11*(1+$B$17)^4*'01_專案設定_Setup'!$B$30) -> 3537.9053 | G28: =IF($B$5=0,0,G$25*$B$12*$B$11*(1+$B$17)^5*'01_專案設定_Setup'!$B$30) -> 3716.9233 | H28: =IF($B$5=0,0,H$25*$B$12*$B$11*(1+$B$17)^6*'01_專案設定_Setup'!$B$30) -> 3904.9996 | I28: =IF($B$5=0,0,I$25*$B$12*$B$11*(1+$B$17)^7*'01_專案設定_Setup'!$B$30) -> 4102.5926 | J28: =IF($B$5=0,0,J$25*$B$12*$B$11*(1+$B$17)^8*'01_專案設定_Setup'!$B$30) -> 4310.1837 | K28: =IF($B$5=0,0,K$25*$B$12*$B$11*(1+$B$17)^9*'01_專案設定_Setup'!$B$30) -> 4528.279
A29: 營收合計 Total revenue（顯示幣別） | B29: =B$27+B$28 -> 4387.2 | C29: =C$27+C$28 -> 8642.2356 | D29: =D$27+D$28 -> 12106.044 | E29: =E$27+E$28 -> 12718.609 | F29: =F$27+F$28 -> 13362.171 | G29: =G$27+G$28 -> 14038.297 | H29: =H$27+H$28 -> 14748.635 | I29: =I$27+I$28 -> 15494.916 | ... K29: =K$27+K$28 -> 17102.674
A31: 滿載年營收 Full-capacity revenue（顯示幣別） | B31: =$B$5*$B$6*$B$13*'01_專案設定_Setup'!$B$30 -> 10968 | D31: ＝服務量 × 計費期數 × 加權單價，不含爬坡與成長。用來檢查量級是否合理。
A33: 收入＝床數 × 月數 × 服務費（以租代購年費）。爬坡代表分階段上線：第 1 年 40%（門診）、第 2 年 75%（住院＋檢驗）、第 3 年起 100%（全院無紙化）。★ 本案投資類別選「F 策略布局型」而非「A 營收型」，原因見 10 分頁的解讀。

Sheet 05_折舊攤提_Depreciation
A1: 05 折舊攤提｜Depreciation & Amortisation Schedule
A2: 全公式，不需編輯。逐列對應 02 分頁的每一個 CAPEX 分項，依其折舊類別與年限採直線法計提；設有「置換年」的資產（如 UPS 電池、球管、伺服器）會在置換年重新起算一段折舊。★ 折舊年限依越南 Circular 45/2013/TT-BTC 附錄一的法定區間：建物 25–50 年、醫療設備 6–15 年、電腦設備 3–8 年、軟體 3–8 年。★ 稅務提醒：本案若適用長期免稅或 10% 優惠稅率，加速折舊反而會浪費稅盾——折舊年限宜取法定區間的上限。
A4: 項次 | B4: 分項名稱 | C4: 折舊類別 | D4: 年限 | E4: 置換年 | F4: 折舊基數 | G4: 第 1 年 | H4: 第 2 年 | I4: 第 3 年 | J4: 第 4 年 | K4: 第 5 年 | L4: 第 6 年 | M4: 第 7 年 | N4: 第 8 年 | O4: 第 9 年 | P4: 第 10 年
A5: =IF('02_投資成本_CAPEX'!$C6="","",'02_投資成本_CAPEX'!$A6) -> 1 | B5: =IF('02_投資成本_CAPEX'!$C6="","",'02_投資成本_CAPEX'!$C6) -> HIS／EMR 核心平台授權（500 床規模，含門診、住院、批價、病歷） | C5: =IF('02_投資成本_CAPEX'!$C6="","",'02_投資成本_CAPEX'!$M6) -> 軟體與無形 Software | D5: =IF('02_投資成本_CAPEX'!$C6="","",'02_投資成本_CAPEX'!$N6) -> 5 | E5: =IF('02_投資成本_CAPEX'!$C6="","",'02_投資成本_CAPEX'!$O6) -> 0 | F5: =IF('02_投資成本_CAPEX'!$C6="",0,'02_投資成本_CAPEX'!$L6*(1-'02_投資成本_CAPEX'!$P6)*'01_專案設定_Setup'!$B$30) -> 10126.05 | G5: =IF(OR('02_投資成本_CAPEX'!$C6="",'02_投資成本_CAPEX'!$N6=0),0,IF(AND(1>=1,1<='02_投資成本_CAPEX'!$N6),$F5/'02_投資成本_CAPEX'!$N6,0)+IF(AND('02_投資成本_CAPEX'!$O6>0,1>='02_投資成本_CAPEX'!$O6,1<='02_投資成本_CAPEX'!$O6+'02_投資成本_CAPEX'!$N6-1),$F5/'02_投資成本_CAPEX'!$N6,0)) -> 2025.21 | H5: =IF(OR('02_投資成本_CAPEX'!$C6="",'02_投資成本_CAPEX'!$N6=0),0,IF(AND(2>=1,2<='02_投資成本_CAPEX'!$N6),$F5/'02_投資成本_CAPEX'!$N6,0)+IF(AND('02_投資成本_CAPEX'!$O6>0,2>='02_投資成本_CAPEX'!$O6,2<='02_投資成本_CAPEX'!$O6+'02_投資成本_CAPEX'!$N6-1),$F5/'02_投資成本_CAPEX'!$N6,0)) -> 2025.21 | I5: =IF(OR('02_投資成本_CAPEX'!$C6="",'02_投資成本_CAPEX'!$N6=0),0,IF(AND(3>=1,3<='02_投資成本_CAPEX'!$N6),$F5/'02_投資成本_CAPEX'!$N6,0)+IF(AND('02_投資成本_CAPEX'!$O6>0,3>='02_投資成本_CAPEX'!$O6,3<='02_投資成本_CAPEX'!$O6+'02_投資成本_CAPEX'!$N6-1),$F5/'02_投資成本_CAPEX'!$N6,0)) -> 2025.21 | J5: =IF(OR('02_投資成本_CAPEX'!$C6="",'02_投資成本_CAPEX'!$N6=0),0,IF(AND(4>=1,4<='02_投資成本_CAPEX'!$N6),$F5/'02_投資成本_CAPEX'!$N6,0)+IF(AND('02_投資成本_CAPEX'!$O6>0,4>='02_投資成本_CAPEX'!$O6,4<='02_投資成本_CAPEX'!$O6+'02_投資成本_CAPEX'!$N6-1),$F5/'02_投資成本_CAPEX'!$N6,0)) -> 2025.21 | K5: =IF(OR('02_投資成本_CAPEX'!$C6="",'02_投資成本_CAPEX'!$N6=0),0,IF(AND(5>=1,5<='02_投資成本_CAPEX'!$N6),$F5/'02_投資成本_CAPEX'!$N6,0)+IF(AND('02_投資成本_CAPEX'!$O6>0,5>='02_投資成本_CAPEX'!$O6,5<='02_投資成本_CAPEX'!$O6+'02_投資成本_CAPEX'!$N6-1),$F5/'02_投資成本_CAPEX'!$N6,0)) -> 2025.21 | L5: =IF(OR('02_投資成本_CAPEX'!$C6="",'02_投資成本_CAPEX'!$N6=0),0,IF(AND(6>=1,6<='02_投資成本_CAPEX'!$N6),$F5/'02_投資成本_CAPEX'!$N6,0)+IF(AND('02_投資成本_CAPEX'!$O6>0,6>='02_投資成本_CAPEX'!$O6,6<='02_投資成本_CAPEX'!$O6+'02_投資成本_CAPEX'!$N6-1),$F5/'02_投資成本_CAPEX'!$N6,0)) -> 0 | M5: =IF(OR('02_投資成本_CAPEX'!$C6="",'02_投資成本_CAPEX'!$N6=0),0,IF(AND(7>=1,7<='02_投資成本_CAPEX'!$N6),$F5/'02_投資成本_CAPEX'!$N6,0)+IF(AND('02_投資成本_CAPEX'!$O6>0,7>='02_投資成本_CAPEX'!$O6,7<='02_投資成本_CAPEX'!$O6+'02_投資成本_CAPEX'!$N6-1),$F5/'02_投資成本_CAPEX'!$N6,0)) -> 0 | N5: =IF(OR('02_投資成本_CAPEX'!$C6="",'02_投資成本_CAPEX'!$N6=0),0,IF(AND(8>=1,8<='02_投資成本_CAPEX'!$N6),$F5/'02_投資成本_CAPEX'!$N6,0)+IF(AND('02_投資成本_CAPEX'!$O6>0,8>='02_投資成本_CAPEX'!$O6,8<='02_投資成本_CAPEX'!$O6+'02_投資成本_CAPEX'!$N6-1),$F5/'02_投資成本_CAPEX'!$N6,0)) -> 0 | O5: =IF(OR('02_投資成本_CAPEX'!$C6="",'02_投資成本_CAPEX'!$N6=0),0,IF(AND(9>=1,9<='02_投資成本_CAPEX'!$N6),$F5/'02_投資成本_CAPEX'!$N6,0)+IF(AND('02_投資成本_CAPEX'!$O6>0,9>='02_投資成本_CAPEX'!$O6,9<='02_投資成本_CAPEX'!$O6+'02_投資成本_CAPEX'!$N6-1),$F5/'02_投資成本_CAPEX'!$N6,0)) -> 0 | P5: =IF(OR('02_投資成本_CAPEX'!$C6="",'02_投資成本_CAPEX'!$N6=0),0,IF(AND(10>=1,10<='02_投資成本_CAPEX'!$N6),$F5/'02_投資成本_CAPEX'!$N6,0)+IF(AND('02_投資成本_CAPEX'!$O6>0,10>='02_投資成本_CAPEX'!$O6,10<='02_投資成本_CAPEX'!$O6+'02_投資成本_CAPEX'!$N6-1),$F5/'02_投資成本_CAPEX'!$N6,0)) -> 0
A6: =IF('02_投資成本_CAPEX'!$C7="","",'02_投資成本_CAPEX'!$A7) -> 2 | B6: =IF('02_投資成本_CAPEX'!$C7="","",'02_投資成本_CAPEX'!$C7) -> LIS 檢驗資訊模組與儀器雙向介接 | C6: =IF('02_投資成本_CAPEX'!$C7="","",'02_投資成本_CAPEX'!$M7) -> 軟體與無形 Software | D6: =IF('02_投資成本_CAPEX'!$C7="","",'02_投資成本_CAPEX'!$N7) -> 5 | E6: =IF('02_投資成本_CAPEX'!$C7="","",'02_投資成本_CAPEX'!$O7) -> 0 | F6: =IF('02_投資成本_CAPEX'!$C7="",0,'02_投資成本_CAPEX'!$L7*(1-'02_投資成本_CAPEX'!$P7)*'01_專案設定_Setup'!$B$30) -> 1598.85 | G6: =IF(OR('02_投資成本_CAPEX'!$C7="",'02_投資成本_CAPEX'!$N7=0),0,IF(AND(1>=1,1<='02_投資成本_CAPEX'!$N7),$F6/'02_投資成本_CAPEX'!$N7,0)+IF(AND('02_投資成本_CAPEX'!$O7>0,1>='02_投資成本_CAPEX'!$O7,1<='02_投資成本_CAPEX'!$O7+'02_投資成本_CAPEX'!$N7-1),$F6/'02_投資成本_CAPEX'!$N7,0)) -> 319.77 | H6: =IF(OR('02_投資成本_CAPEX'!$C7="",'02_投資成本_CAPEX'!$N7=0),0,IF(AND(2>=1,2<='02_投資成本_CAPEX'!$N7),$F6/'02_投資成本_CAPEX'!$N7,0)+IF(AND('02_投資成本_CAPEX'!$O7>0,2>='02_投資成本_CAPEX'!$O7,2<='02_投資成本_CAPEX'!$O7+'02_投資成本_CAPEX'!$N7-1),$F6/'02_投資成本_CAPEX'!$N7,0)) -> 319.77 | I6: =IF(OR('02_投資成本_CAPEX'!$C7="",'02_投資成本_CAPEX'!$N7=0),0,IF(AND(3>=1,3<='02_投資成本_CAPEX'!$N7),$F6/'02_投資成本_CAPEX'!$N7,0)+IF(AND('02_投資成本_CAPEX'!$O7>0,3>='02_投資成本_CAPEX'!$O7,3<='02_投資成本_CAPEX'!$O7+'02_投資成本_CAPEX'!$N7-1),$F6/'02_投資成本_CAPEX'!$N7,0)) -> 319.77 | J6: =IF(OR('02_投資成本_CAPEX'!$C7="",'02_投資成本_CAPEX'!$N7=0),0,IF(AND(4>=1,4<='02_投資成本_CAPEX'!$N7),$F6/'02_投資成本_CAPEX'!$N7,0)+IF(AND('02_投資成本_CAPEX'!$O7>0,4>='02_投資成本_CAPEX'!$O7,4<='02_投資成本_CAPEX'!$O7+'02_投資成本_CAPEX'!$N7-1),$F6/'02_投資成本_CAPEX'!$N7,0)) -> 319.77 | K6: =IF(OR('02_投資成本_CAPEX'!$C7="",'02_投資成本_CAPEX'!$N7=0),0,IF(AND(5>=1,5<='02_投資成本_CAPEX'!$N7),$F6/'02_投資成本_CAPEX'!$N7,0)+IF(AND('02_投資成本_CAPEX'!$O7>0,5>='02_投資成本_CAPEX'!$O7,5<='02_投資成本_CAPEX'!$O7+'02_投資成本_CAPEX'!$N7-1),$F6/'02_投資成本_CAPEX'!$N7,0)) -> 319.77 | L6: =IF(OR('02_投資成本_CAPEX'!$C7="",'02_投資成本_CAPEX'!$N7=0),0,IF(AND(6>=1,6<='02_投資成本_CAPEX'!$N7),$F6/'02_投資成本_CAPEX'!$N7,0)+IF(AND('02_投資成本_CAPEX'!$O7>0,6>='02_投資成本_CAPEX'!$O7,6<='02_投資成本_CAPEX'!$O7+'02_投資成本_CAPEX'!$N7-1),$F6/'02_投資成本_CAPEX'!$N7,0)) -> 0 | M6: =IF(OR('02_投資成本_CAPEX'!$C7="",'02_投資成本_CAPEX'!$N7=0),0,IF(AND(7>=1,7<='02_投資成本_CAPEX'!$N7),$F6/'02_投資成本_CAPEX'!$N7,0)+IF(AND('02_投資成本_CAPEX'!$O7>0,7>='02_投資成本_CAPEX'!$O7,7<='02_投資成本_CAPEX'!$O7+'02_投資成本_CAPEX'!$N7-1),$F6/'02_投資成本_CAPEX'!$N7,0)) -> 0 | N6: =IF(OR('02_投資成本_CAPEX'!$C7="",'02_投資成本_CAPEX'!$N7=0),0,IF(AND(8>=1,8<='02_投資成本_CAPEX'!$N7),$F6/'02_投資成本_CAPEX'!$N7,0)+IF(AND('02_投資成本_CAPEX'!$O7>0,8>='02_投資成本_CAPEX'!$O7,8<='02_投資成本_CAPEX'!$O7+'02_投資成本_CAPEX'!$N7-1),$F6/'02_投資成本_CAPEX'!$N7,0)) -> 0 | O6: =IF(OR('02_投資成本_CAPEX'!$C7="",'02_投資成本_CAPEX'!$N7=0),0,IF(AND(9>=1,9<='02_投資成本_CAPEX'!$N7),$F6/'02_投資成本_CAPEX'!$N7,0)+IF(AND('02_投資成本_CAPEX'!$O7>0,9>='02_投資成本_CAPEX'!$O7,9<='02_投資成本_CAPEX'!$O7+'02_投資成本_CAPEX'!$N7-1),$F6/'02_投資成本_CAPEX'!$N7,0)) -> 0 | P6: =IF(OR('02_投資成本_CAPEX'!$C7="",'02_投資成本_CAPEX'!$N7=0),0,IF(AND(10>=1,10<='02_投資成本_CAPEX'!$N7),$F6/'02_投資成本_CAPEX'!$N7,0)+IF(AND('02_投資成本_CAPEX'!$O7>0,10>='02_投資成本_CAPEX'!$O7,10<='02_投資成本_CAPEX'!$O7+'02_投資成本_CAPEX'!$N7-1),$F6/'02_投資成本_CAPEX'!$N7,0)) -> 0
A7: =IF('02_投資成本_CAPEX'!$C8="","",'02_投資成本_CAPEX'!$A8) -> 3 | B7: =IF('02_投資成本_CAPEX'!$C8="","",'02_投資成本_CAPEX'!$C8) -> RIS／PACS 介接與院內影像調閱 | C7: =IF('02_投資成本_CAPEX'!$C8="","",'02_投資成本_CAPEX'!$M8) -> 軟體與無形 Software | D7: =IF('02_投資成本_CAPEX'!$C8="","",'02_投資成本_CAPEX'!$N8) -> 5 | E7: =IF('02_投資成本_CAPEX'!$C8="","",'02_投資成本_CAPEX'!$O8) -> 0 | F7: =IF('02_投資成本_CAPEX'!$C8="",0,'02_投資成本_CAPEX'!$L8*(1-'02_投資成本_CAPEX'!$P8)*'01_專案設定_Setup'!$B$30) -> 1172.49 | G7: =IF(OR('02_投資成本_CAPEX'!$C8="",'02_投資成本_CAPEX'!$N8=0),0,IF(AND(1>=1,1<='02_投資成本_CAPEX'!$N8),$F7/'02_投資成本_CAPEX'!$N8,0)+IF(AND('02_投資成本_CAPEX'!$O8>0,1>='02_投資成本_CAPEX'!$O8,1<='02_投資成本_CAPEX'!$O8+'02_投資成本_CAPEX'!$N8-1),$F7/'02_投資成本_CAPEX'!$N8,0)) -> 234.498 | H7: =IF(OR('02_投資成本_CAPEX'!$C8="",'02_投資成本_CAPEX'!$N8=0),0,IF(AND(2>=1,2<='02_投資成本_CAPEX'!$N8),$F7/'02_投資成本_CAPEX'!$N8,0)+IF(AND('02_投資成本_CAPEX'!$O8>0,2>='02_投資成本_CAPEX'!$O8,2<='02_投資成本_CAPEX'!$O8+'02_投資成本_CAPEX'!$N8-1),$F7/'02_投資成本_CAPEX'!$N8,0)) -> 234.498 | I7: =IF(OR('02_投資成本_CAPEX'!$C8="",'02_投資成本_CAPEX'!$N8=0),0,IF(AND(3>=1,3<='02_投資成本_CAPEX'!$N8),$F7/'02_投資成本_CAPEX'!$N8,0)+IF(AND('02_投資成本_CAPEX'!$O8>0,3>='02_投資成本_CAPEX'!$O8,3<='02_投資成本_CAPEX'!$O8+'02_投資成本_CAPEX'!$N8-1),$F7/'02_投資成本_CAPEX'!$N8,0)) -> 234.498 | J7: =IF(OR('02_投資成本_CAPEX'!$C8="",'02_投資成本_CAPEX'!$N8=0),0,IF(AND(4>=1,4<='02_投資成本_CAPEX'!$N8),$F7/'02_投資成本_CAPEX'!$N8,0)+IF(AND('02_投資成本_CAPEX'!$O8>0,4>='02_投資成本_CAPEX'!$O8,4<='02_投資成本_CAPEX'!$O8+'02_投資成本_CAPEX'!$N8-1),$F7/'02_投資成本_CAPEX'!$N8,0)) -> 234.498 | K7: =IF(OR('02_投資成本_CAPEX'!$C8="",'02_投資成本_CAPEX'!$N8=0),0,IF(AND(5>=1,5<='02_投資成本_CAPEX'!$N8),$F7/'02_投資成本_CAPEX'!$N8,0)+IF(AND('02_投資成本_CAPEX'!$O8>0,5>='02_投資成本_CAPEX'!$O8,5<='02_投資成本_CAPEX'!$O8+'02_投資成本_CAPEX'!$N8-1),$F7/'02_投資成本_CAPEX'!$N8,0)) -> 234.498 | L7: =IF(OR('02_投資成本_CAPEX'!$C8="",'02_投資成本_CAPEX'!$N8=0),0,IF(AND(6>=1,6<='02_投資成本_CAPEX'!$N8),$F7/'02_投資成本_CAPEX'!$N8,0)+IF(AND('02_投資成本_CAPEX'!$O8>0,6>='02_投資成本_CAPEX'!$O8,6<='02_投資成本_CAPEX'!$O8+'02_投資成本_CAPEX'!$N8-1),$F7/'02_投資成本_CAPEX'!$N8,0)) -> 0 | M7: =IF(OR('02_投資成本_CAPEX'!$C8="",'02_投資成本_CAPEX'!$N8=0),0,IF(AND(7>=1,7<='02_投資成本_CAPEX'!$N8),$F7/'02_投資成本_CAPEX'!$N8,0)+IF(AND('02_投資成本_CAPEX'!$O8>0,7>='02_投資成本_CAPEX'!$O8,7<='02_投資成本_CAPEX'!$O8+'02_投資成本_CAPEX'!$N8-1),$F7/'02_投資成本_CAPEX'!$N8,0)) -> 0 | N7: =IF(OR('02_投資成本_CAPEX'!$C8="",'02_投資成本_CAPEX'!$N8=0),0,IF(AND(8>=1,8<='02_投資成本_CAPEX'!$N8),$F7/'02_投資成本_CAPEX'!$N8,0)+IF(AND('02_投資成本_CAPEX'!$O8>0,8>='02_投資成本_CAPEX'!$O8,8<='02_投資成本_CAPEX'!$O8+'02_投資成本_CAPEX'!$N8-1),$F7/'02_投資成本_CAPEX'!$N8,0)) -> 0 | O7: =IF(OR('02_投資成本_CAPEX'!$C8="",'02_投資成本_CAPEX'!$N8=0),0,IF(AND(9>=1,9<='02_投資成本_CAPEX'!$N8),$F7/'02_投資成本_CAPEX'!$N8,0)+IF(AND('02_投資成本_CAPEX'!$O8>0,9>='02_投資成本_CAPEX'!$O8,9<='02_投資成本_CAPEX'!$O8+'02_投資成本_CAPEX'!$N8-1),$F7/'02_投資成本_CAPEX'!$N8,0)) -> 0 | P7: =IF(OR('02_投資成本_CAPEX'!$C8="",'02_投資成本_CAPEX'!$N8=0),0,IF(AND(10>=1,10<='02_投資成本_CAPEX'!$N8),$F7/'02_投資成本_CAPEX'!$N8,0)+IF(AND('02_投資成本_CAPEX'!$O8>0,10>='02_投資成本_CAPEX'!$O8,10<='02_投資成本_CAPEX'!$O8+'02_投資成本_CAPEX'!$N8-1),$F7/'02_投資成本_CAPEX'!$N8,0)) -> 0
A8: =IF('02_投資成本_CAPEX'!$C9="","",'02_投資成本_CAPEX'!$A9) -> 4 | B8: =IF('02_投資成本_CAPEX'!$C9="","",'02_投資成本_CAPEX'!$C9) -> 藥事管理與閉環給藥 CPOE／BCMA 模組 | C8: =IF('02_投資成本_CAPEX'!$C9="","",'02_投資成本_CAPEX'!$M9) -> 軟體與無形 Software | D8: =IF('02_投資成本_CAPEX'!$C9="","",'02_投資成本_CAPEX'!$N9) -> 5 | E8: =IF('02_投資成本_CAPEX'!$C9="","",'02_投資成本_CAPEX'!$O9) -> 0 | F8: =IF('02_投資成本_CAPEX'!$C9="",0,'02_投資成本_CAPEX'!$L9*(1-'02_投資成本_CAPEX'!$P9)*'01_專案設定_Setup'!$B$30) -> 1350.14 | G8: =IF(OR('02_投資成本_CAPEX'!$C9="",'02_投資成本_CAPEX'!$N9=0),0,IF(AND(1>=1,1<='02_投資成本_CAPEX'!$N9),$F8/'02_投資成本_CAPEX'!$N9,0)+IF(AND('02_投資成本_CAPEX'!$O9>0,1>='02_投資成本_CAPEX'!$O9,1<='02_投資成本_CAPEX'!$O9+'02_投資成本_CAPEX'!$N9-1),$F8/'02_投資成本_CAPEX'!$N9,0)) -> 270.028 | H8: =IF(OR('02_投資成本_CAPEX'!$C9="",'02_投資成本_CAPEX'!$N9=0),0,IF(AND(2>=1,2<='02_投資成本_CAPEX'!$N9),$F8/'02_投資成本_CAPEX'!$N9,0)+IF(AND('02_投資成本_CAPEX'!$O9>0,2>='02_投資成本_CAPEX'!$O9,2<='02_投資成本_CAPEX'!$O9+'02_投資成本_CAPEX'!$N9-1),$F8/'02_投資成本_CAPEX'!$N9,0)) -> 270.028 | I8: =IF(OR('02_投資成本_CAPEX'!$C9="",'02_投資成本_CAPEX'!$N9=0),0,IF(AND(3>=1,3<='02_投資成本_CAPEX'!$N9),$F8/'02_投資成本_CAPEX'!$N9,0)+IF(AND('02_投資成本_CAPEX'!$O9>0,3>='02_投資成本_CAPEX'!$O9,3<='02_投資成本_CAPEX'!$O9+'02_投資成本_CAPEX'!$N9-1),$F8/'02_投資成本_CAPEX'!$N9,0)) -> 270.028 | J8: =IF(OR('02_投資成本_CAPEX'!$C9="",'02_投資成本_CAPEX'!$N9=0),0,IF(AND(4>=1,4<='02_投資成本_CAPEX'!$N9),$F8/'02_投資成本_CAPEX'!$N9,0)+IF(AND('02_投資成本_CAPEX'!$O9>0,4>='02_投資成本_CAPEX'!$O9,4<='02_投資成本_CAPEX'!$O9+'02_投資成本_CAPEX'!$N9-1),$F8/'02_投資成本_CAPEX'!$N9,0)) -> 270.028 | K8: =IF(OR('02_投資成本_CAPEX'!$C9="",'02_投資成本_CAPEX'!$N9=0),0,IF(AND(5>=1,5<='02_投資成本_CAPEX'!$N9),$F8/'02_投資成本_CAPEX'!$N9,0)+IF(AND('02_投資成本_CAPEX'!$O9>0,5>='02_投資成本_CAPEX'!$O9,5<='02_投資成本_CAPEX'!$O9+'02_投資成本_CAPEX'!$N9-1),$F8/'02_投資成本_CAPEX'!$N9,0)) -> 270.028 | L8: =IF(OR('02_投資成本_CAPEX'!$C9="",'02_投資成本_CAPEX'!$N9=0),0,IF(AND(6>=1,6<='02_投資成本_CAPEX'!$N9),$F8/'02_投資成本_CAPEX'!$N9,0)+IF(AND('02_投資成本_CAPEX'!$O9>0,6>='02_投資成本_CAPEX'!$O9,6<='02_投資成本_CAPEX'!$O9+'02_投資成本_CAPEX'!$N9-1),$F8/'02_投資成本_CAPEX'!$N9,0)) -> 0 | M8: =IF(OR('02_投資成本_CAPEX'!$C9="",'02_投資成本_CAPEX'!$N9=0),0,IF(AND(7>=1,7<='02_投資成本_CAPEX'!$N9),$F8/'02_投資成本_CAPEX'!$N9,0)+IF(AND('02_投資成本_CAPEX'!$O9>0,7>='02_投資成本_CAPEX'!$O9,7<='02_投資成本_CAPEX'!$O9+'02_投資成本_CAPEX'!$N9-1),$F8/'02_投資成本_CAPEX'!$N9,0)) -> 0 | N8: =IF(OR('02_投資成本_CAPEX'!$C9="",'02_投資成本_CAPEX'!$N9=0),0,IF(AND(8>=1,8<='02_投資成本_CAPEX'!$N9),$F8/'02_投資成本_CAPEX'!$N9,0)+IF(AND('02_投資成本_CAPEX'!$O9>0,8>='02_投資成本_CAPEX'!$O9,8<='02_投資成本_CAPEX'!$O9+'02_投資成本_CAPEX'!$N9-1),$F8/'02_投資成本_CAPEX'!$N9,0)) -> 0 | O8: =IF(OR('02_投資成本_CAPEX'!$C9="",'02_投資成本_CAPEX'!$N9=0),0,IF(AND(9>=1,9<='02_投資成本_CAPEX'!$N9),$F8/'02_投資成本_CAPEX'!$N9,0)+IF(AND('02_投資成本_CAPEX'!$O9>0,9>='02_投資成本_CAPEX'!$O9,9<='02_投資成本_CAPEX'!$O9+'02_投資成本_CAPEX'!$N9-1),$F8/'02_投資成本_CAPEX'!$N9,0)) -> 0 | P8: =IF(OR('02_投資成本_CAPEX'!$C9="",'02_投資成本_CAPEX'!$N9=0),0,IF(AND(10>=1,10<='02_投資成本_CAPEX'!$N9),$F8/'02_投資成本_CAPEX'!$N9,0)+IF(AND('02_投資成本_CAPEX'!$O9>0,10>='02_投資成本_CAPEX'!$O9,10<='02_投資成本_CAPEX'!$O9+'02_投資成本_CAPEX'!$N9-1),$F8/'02_投資成本_CAPEX'!$N9,0)) -> 0
A9: =IF('02_投資成本_CAPEX'!$C10="","",'02_投資成本_CAPEX'!$A10) -> 5 | B9: =IF('02_投資成本_CAPEX'!$C10="","",'02_投資成本_CAPEX'!$C10) -> 護理紀錄與電子表單（含行動護理車終端授權） | C9: =IF('02_投資成本_CAPEX'!$C10="","",'02_投資成本_CAPEX'!$M10) -> 軟體與無形 Software | D9: =IF('02_投資成本_CAPEX'!$C10="","",'02_投資成本_CAPEX'!$N10) -> 5 | E9: =IF('02_投資成本_CAPEX'!$C10="","",'02_投資成本_CAPEX'!$O10) -> 0 | F9: =IF('02_投資成本_CAPEX'!$C10="",0,'02_投資成本_CAPEX'!$L10*(1-'02_投資成本_CAPEX'!$P10)*'01_專案設定_Setup'!$B$30) -> 923.78 | G9: =IF(OR('02_投資成本_CAPEX'!$C10="",'02_投資成本_CAPEX'!$N10=0),0,IF(AND(1>=1,1<='02_投資成本_CAPEX'!$N10),$F9/'02_投資成本_CAPEX'!$N10,0)+IF(AND('02_投資成本_CAPEX'!$O10>0,1>='02_投資成本_CAPEX'!$O10,1<='02_投資成本_CAPEX'!$O10+'02_投資成本_CAPEX'!$N10-1),$F9/'02_投資成本_CAPEX'!$N10,0)) -> 184.756 | H9: =IF(OR('02_投資成本_CAPEX'!$C10="",'02_投資成本_CAPEX'!$N10=0),0,IF(AND(2>=1,2<='02_投資成本_CAPEX'!$N10),$F9/'02_投資成本_CAPEX'!$N10,0)+IF(AND('02_投資成本_CAPEX'!$O10>0,2>='02_投資成本_CAPEX'!$O10,2<='02_投資成本_CAPEX'!$O10+'02_投資成本_CAPEX'!$N10-1),$F9/'02_投資成本_CAPEX'!$N10,0)) -> 184.756 | I9: =IF(OR('02_投資成本_CAPEX'!$C10="",'02_投資成本_CAPEX'!$N10=0),0,IF(AND(3>=1,3<='02_投資成本_CAPEX'!$N10),$F9/'02_投資成本_CAPEX'!$N10,0)+IF(AND('02_投資成本_CAPEX'!$O10>0,3>='02_投資成本_CAPEX'!$O10,3<='02_投資成本_CAPEX'!$O10+'02_投資成本_CAPEX'!$N10-1),$F9/'02_投資成本_CAPEX'!$N10,0)) -> 184.756 | J9: =IF(OR('02_投資成本_CAPEX'!$C10="",'02_投資成本_CAPEX'!$N10=0),0,IF(AND(4>=1,4<='02_投資成本_CAPEX'!$N10),$F9/'02_投資成本_CAPEX'!$N10,0)+IF(AND('02_投資成本_CAPEX'!$O10>0,4>='02_投資成本_CAPEX'!$O10,4<='02_投資成本_CAPEX'!$O10+'02_投資成本_CAPEX'!$N10-1),$F9/'02_投資成本_CAPEX'!$N10,0)) -> 184.756 | K9: =IF(OR('02_投資成本_CAPEX'!$C10="",'02_投資成本_CAPEX'!$N10=0),0,IF(AND(5>=1,5<='02_投資成本_CAPEX'!$N10),$F9/'02_投資成本_CAPEX'!$N10,0)+IF(AND('02_投資成本_CAPEX'!$O10>0,5>='02_投資成本_CAPEX'!$O10,5<='02_投資成本_CAPEX'!$O10+'02_投資成本_CAPEX'!$N10-1),$F9/'02_投資成本_CAPEX'!$N10,0)) -> 184.756 | L9: =IF(OR('02_投資成本_CAPEX'!$C10="",'02_投資成本_CAPEX'!$N10=0),0,IF(AND(6>=1,6<='02_投資成本_CAPEX'!$N10),$F9/'02_投資成本_CAPEX'!$N10,0)+IF(AND('02_投資成本_CAPEX'!$O10>0,6>='02_投資成本_CAPEX'!$O10,6<='02_投資成本_CAPEX'!$O10+'02_投資成本_CAPEX'!$N10-1),$F9/'02_投資成本_CAPEX'!$N10,0)) -> 0 | M9: =IF(OR('02_投資成本_CAPEX'!$C10="",'02_投資成本_CAPEX'!$N10=0),0,IF(AND(7>=1,7<='02_投資成本_CAPEX'!$N10),$F9/'02_投資成本_CAPEX'!$N10,0)+IF(AND('02_投資成本_CAPEX'!$O10>0,7>='02_投資成本_CAPEX'!$O10,7<='02_投資成本_CAPEX'!$O10+'02_投資成本_CAPEX'!$N10-1),$F9/'02_投資成本_CAPEX'!$N10,0)) -> 0 | N9: =IF(OR('02_投資成本_CAPEX'!$C10="",'02_投資成本_CAPEX'!$N10=0),0,IF(AND(8>=1,8<='02_投資成本_CAPEX'!$N10),$F9/'02_投資成本_CAPEX'!$N10,0)+IF(AND('02_投資成本_CAPEX'!$O10>0,8>='02_投資成本_CAPEX'!$O10,8<='02_投資成本_CAPEX'!$O10+'02_投資成本_CAPEX'!$N10-1),$F9/'02_投資成本_CAPEX'!$N10,0)) -> 0 | O9: =IF(OR('02_投資成本_CAPEX'!$C10="",'02_投資成本_CAPEX'!$N10=0),0,IF(AND(9>=1,9<='02_投資成本_CAPEX'!$N10),$F9/'02_投資成本_CAPEX'!$N10,0)+IF(AND('02_投資成本_CAPEX'!$O10>0,9>='02_投資成本_CAPEX'!$O10,9<='02_投資成本_CAPEX'!$O10+'02_投資成本_CAPEX'!$N10-1),$F9/'02_投資成本_CAPEX'!$N10,0)) -> 0 | P9: =IF(OR('02_投資成本_CAPEX'!$C10="",'02_投資成本_CAPEX'!$N10=0),0,IF(AND(10>=1,10<='02_投資成本_CAPEX'!$N10),$F9/'02_投資成本_CAPEX'!$N10,0)+IF(AND('02_投資成本_CAPEX'!$O10>0,10>='02_投資成本_CAPEX'!$O10,10<='02_投資成本_CAPEX'!$O10+'02_投資成本_CAPEX'!$N10-1),$F9/'02_投資成本_CAPEX'!$N10,0)) -> 0
A10: =IF('02_投資成本_CAPEX'!$C11="","",'02_投資成本_CAPEX'!$A11) -> 6 | B10: =IF('02_投資成本_CAPEX'!$C11="","",'02_投資成本_CAPEX'!$C11) -> FHIR 介接引擎（HL7 FHIR R4＋DICOM） | C10: =IF('02_投資成本_CAPEX'!$C11="","",'02_投資成本_CAPEX'!$M11) -> 軟體與無形 Software | D10: =IF('02_投資成本_CAPEX'!$C11="","",'02_投資成本_CAPEX'!$N11) -> 5 | E10: =IF('02_投資成本_CAPEX'!$C11="","",'02_投資成本_CAPEX'!$O11) -> 0 | F10: =IF('02_投資成本_CAPEX'!$C11="",0,'02_投資成本_CAPEX'!$L11*(1-'02_投資成本_CAPEX'!$P11)*'01_專案設定_Setup'!$B$30) -> 1705.44 | G10: =IF(OR('02_投資成本_CAPEX'!$C11="",'02_投資成本_CAPEX'!$N11=0),0,IF(AND(1>=1,1<='02_投資成本_CAPEX'!$N11),$F10/'02_投資成本_CAPEX'!$N11,0)+IF(AND('02_投資成本_CAPEX'!$O11>0,1>='02_投資成本_CAPEX'!$O11,1<='02_投資成本_CAPEX'!$O11+'02_投資成本_CAPEX'!$N11-1),$F10/'02_投資成本_CAPEX'!$N11,0)) -> 341.088 | H10: =IF(OR('02_投資成本_CAPEX'!$C11="",'02_投資成本_CAPEX'!$N11=0),0,IF(AND(2>=1,2<='02_投資成本_CAPEX'!$N11),$F10/'02_投資成本_CAPEX'!$N11,0)+IF(AND('02_投資成本_CAPEX'!$O11>0,2>='02_投資成本_CAPEX'!$O11,2<='02_投資成本_CAPEX'!$O11+'02_投資成本_CAPEX'!$N11-1),$F10/'02_投資成本_CAPEX'!$N11,0)) -> 341.088 | I10: =IF(OR('02_投資成本_CAPEX'!$C11="",'02_投資成本_CAPEX'!$N11=0),0,IF(AND(3>=1,3<='02_投資成本_CAPEX'!$N11),$F10/'02_投資成本_CAPEX'!$N11,0)+IF(AND('02_投資成本_CAPEX'!$O11>0,3>='02_投資成本_CAPEX'!$O11,3<='02_投資成本_CAPEX'!$O11+'02_投資成本_CAPEX'!$N11-1),$F10/'02_投資成本_CAPEX'!$N11,0)) -> 341.088 | J10: =IF(OR('02_投資成本_CAPEX'!$C11="",'02_投資成本_CAPEX'!$N11=0),0,IF(AND(4>=1,4<='02_投資成本_CAPEX'!$N11),$F10/'02_投資成本_CAPEX'!$N11,0)+IF(AND('02_投資成本_CAPEX'!$O11>0,4>='02_投資成本_CAPEX'!$O11,4<='02_投資成本_CAPEX'!$O11+'02_投資成本_CAPEX'!$N11-1),$F10/'02_投資成本_CAPEX'!$N11,0)) -> 341.088 | K10: =IF(OR('02_投資成本_CAPEX'!$C11="",'02_投資成本_CAPEX'!$N11=0),0,IF(AND(5>=1,5<='02_投資成本_CAPEX'!$N11),$F10/'02_投資成本_CAPEX'!$N11,0)+IF(AND('02_投資成本_CAPEX'!$O11>0,5>='02_投資成本_CAPEX'!$O11,5<='02_投資成本_CAPEX'!$O11+'02_投資成本_CAPEX'!$N11-1),$F10/'02_投資成本_CAPEX'!$N11,0)) -> 341.088 | L10: =IF(OR('02_投資成本_CAPEX'!$C11="",'02_投資成本_CAPEX'!$N11=0),0,IF(AND(6>=1,6<='02_投資成本_CAPEX'!$N11),$F10/'02_投資成本_CAPEX'!$N11,0)+IF(AND('02_投資成本_CAPEX'!$O11>0,6>='02_投資成本_CAPEX'!$O11,6<='02_投資成本_CAPEX'!$O11+'02_投資成本_CAPEX'!$N11-1),$F10/'02_投資成本_CAPEX'!$N11,0)) -> 0 | M10: =IF(OR('02_投資成本_CAPEX'!$C11="",'02_投資成本_CAPEX'!$N11=0),0,IF(AND(7>=1,7<='02_投資成本_CAPEX'!$N11),$F10/'02_投資成本_CAPEX'!$N11,0)+IF(AND('02_投資成本_CAPEX'!$O11>0,7>='02_投資成本_CAPEX'!$O11,7<='02_投資成本_CAPEX'!$O11+'02_投資成本_CAPEX'!$N11-1),$F10/'02_投資成本_CAPEX'!$N11,0)) -> 0 | N10: =IF(OR('02_投資成本_CAPEX'!$C11="",'02_投資成本_CAPEX'!$N11=0),0,IF(AND(8>=1,8<='02_投資成本_CAPEX'!$N11),$F10/'02_投資成本_CAPEX'!$N11,0)+IF(AND('02_投資成本_CAPEX'!$O11>0,8>='02_投資成本_CAPEX'!$O11,8<='02_投資成本_CAPEX'!$O11+'02_投資成本_CAPEX'!$N11-1),$F10/'02_投資成本_CAPEX'!$N11,0)) -> 0 | O10: =IF(OR('02_投資成本_CAPEX'!$C11="",'02_投資成本_CAPEX'!$N11=0),0,IF(AND(9>=1,9<='02_投資成本_CAPEX'!$N11),$F10/'02_投資成本_CAPEX'!$N11,0)+IF(AND('02_投資成本_CAPEX'!$O11>0,9>='02_投資成本_CAPEX'!$O11,9<='02_投資成本_CAPEX'!$O11+'02_投資成本_CAPEX'!$N11-1),$F10/'02_投資成本_CAPEX'!$N11,0)) -> 0 | P10: =IF(OR('02_投資成本_CAPEX'!$C11="",'02_投資成本_CAPEX'!$N11=0),0,IF(AND(10>=1,10<='02_投資成本_CAPEX'!$N11),$F10/'02_投資成本_CAPEX'!$N11,0)+IF(AND('02_投資成本_CAPEX'!$O11>0,10>='02_投資成本_CAPEX'!$O11,10<='02_投資成本_CAPEX'!$O11+'02_投資成本_CAPEX'!$N11-1),$F10/'02_投資成本_CAPEX'!$N11,0)) -> 0
A11: =IF('02_投資成本_CAPEX'!$C12="","",'02_投資成本_CAPEX'!$A12) -> 7 | B11: =IF('02_投資成本_CAPEX'!$C12="","",'02_投資成本_CAPEX'!$C12) -> VNeID／VSS 健保申報與身分核驗介接 | C11: =IF('02_投資成本_CAPEX'!$C12="","",'02_投資成本_CAPEX'!$M12) -> 軟體與無形 Software | D11: =IF('02_投資成本_CAPEX'!$C12="","",'02_投資成本_CAPEX'!$N12) -> 5 | E11: =IF('02_投資成本_CAPEX'!$C12="","",'02_投資成本_CAPEX'!$O12) -> 0 | F11: =IF('02_投資成本_CAPEX'!$C12="",0,'02_投資成本_CAPEX'!$L12*(1-'02_投資成本_CAPEX'!$P12)*'01_專案設定_Setup'!$B$30) -> 1563.32 | G11: =IF(OR('02_投資成本_CAPEX'!$C12="",'02_投資成本_CAPEX'!$N12=0),0,IF(AND(1>=1,1<='02_投資成本_CAPEX'!$N12),$F11/'02_投資成本_CAPEX'!$N12,0)+IF(AND('02_投資成本_CAPEX'!$O12>0,1>='02_投資成本_CAPEX'!$O12,1<='02_投資成本_CAPEX'!$O12+'02_投資成本_CAPEX'!$N12-1),$F11/'02_投資成本_CAPEX'!$N12,0)) -> 312.664 | H11: =IF(OR('02_投資成本_CAPEX'!$C12="",'02_投資成本_CAPEX'!$N12=0),0,IF(AND(2>=1,2<='02_投資成本_CAPEX'!$N12),$F11/'02_投資成本_CAPEX'!$N12,0)+IF(AND('02_投資成本_CAPEX'!$O12>0,2>='02_投資成本_CAPEX'!$O12,2<='02_投資成本_CAPEX'!$O12+'02_投資成本_CAPEX'!$N12-1),$F11/'02_投資成本_CAPEX'!$N12,0)) -> 312.664 | I11: =IF(OR('02_投資成本_CAPEX'!$C12="",'02_投資成本_CAPEX'!$N12=0),0,IF(AND(3>=1,3<='02_投資成本_CAPEX'!$N12),$F11/'02_投資成本_CAPEX'!$N12,0)+IF(AND('02_投資成本_CAPEX'!$O12>0,3>='02_投資成本_CAPEX'!$O12,3<='02_投資成本_CAPEX'!$O12+'02_投資成本_CAPEX'!$N12-1),$F11/'02_投資成本_CAPEX'!$N12,0)) -> 312.664 | J11: =IF(OR('02_投資成本_CAPEX'!$C12="",'02_投資成本_CAPEX'!$N12=0),0,IF(AND(4>=1,4<='02_投資成本_CAPEX'!$N12),$F11/'02_投資成本_CAPEX'!$N12,0)+IF(AND('02_投資成本_CAPEX'!$O12>0,4>='02_投資成本_CAPEX'!$O12,4<='02_投資成本_CAPEX'!$O12+'02_投資成本_CAPEX'!$N12-1),$F11/'02_投資成本_CAPEX'!$N12,0)) -> 312.664 | K11: =IF(OR('02_投資成本_CAPEX'!$C12="",'02_投資成本_CAPEX'!$N12=0),0,IF(AND(5>=1,5<='02_投資成本_CAPEX'!$N12),$F11/'02_投資成本_CAPEX'!$N12,0)+IF(AND('02_投資成本_CAPEX'!$O12>0,5>='02_投資成本_CAPEX'!$O12,5<='02_投資成本_CAPEX'!$O12+'02_投資成本_CAPEX'!$N12-1),$F11/'02_投資成本_CAPEX'!$N12,0)) -> 312.664 | L11: =IF(OR('02_投資成本_CAPEX'!$C12="",'02_投資成本_CAPEX'!$N12=0),0,IF(AND(6>=1,6<='02_投資成本_CAPEX'!$N12),$F11/'02_投資成本_CAPEX'!$N12,0)+IF(AND('02_投資成本_CAPEX'!$O12>0,6>='02_投資成本_CAPEX'!$O12,6<='02_投資成本_CAPEX'!$O12+'02_投資成本_CAPEX'!$N12-1),$F11/'02_投資成本_CAPEX'!$N12,0)) -> 0 | M11: =IF(OR('02_投資成本_CAPEX'!$C12="",'02_投資成本_CAPEX'!$N12=0),0,IF(AND(7>=1,7<='02_投資成本_CAPEX'!$N12),$F11/'02_投資成本_CAPEX'!$N12,0)+IF(AND('02_投資成本_CAPEX'!$O12>0,7>='02_投資成本_CAPEX'!$O12,7<='02_投資成本_CAPEX'!$O12+'02_投資成本_CAPEX'!$N12-1),$F11/'02_投資成本_CAPEX'!$N12,0)) -> 0 | N11: =IF(OR('02_投資成本_CAPEX'!$C12="",'02_投資成本_CAPEX'!$N12=0),0,IF(AND(8>=1,8<='02_投資成本_CAPEX'!$N12),$F11/'02_投資成本_CAPEX'!$N12,0)+IF(AND('02_投資成本_CAPEX'!$O12>0,8>='02_投資成本_CAPEX'!$O12,8<='02_投資成本_CAPEX'!$O12+'02_投資成本_CAPEX'!$N12-1),$F11/'02_投資成本_CAPEX'!$N12,0)) -> 0 | O11: =IF(OR('02_投資成本_CAPEX'!$C12="",'02_投資成本_CAPEX'!$N12=0),0,IF(AND(9>=1,9<='02_投資成本_CAPEX'!$N12),$F11/'02_投資成本_CAPEX'!$N12,0)+IF(AND('02_投資成本_CAPEX'!$O12>0,9>='02_投資成本_CAPEX'!$O12,9<='02_投資成本_CAPEX'!$O12+'02_投資成本_CAPEX'!$N12-1),$F11/'02_投資成本_CAPEX'!$N12,0)) -> 0 | P11: =IF(OR('02_投資成本_CAPEX'!$C12="",'02_投資成本_CAPEX'!$N12=0),0,IF(AND(10>=1,10<='02_投資成本_CAPEX'!$N12),$F11/'02_投資成本_CAPEX'!$N12,0)+IF(AND('02_投資成本_CAPEX'!$O12>0,10>='02_投資成本_CAPEX'!$O12,10<='02_投資成本_CAPEX'!$O12+'02_投資成本_CAPEX'!$N12-1),$F11/'02_投資成本_CAPEX'!$N12,0)) -> 0
A12: =IF('02_投資成本_CAPEX'!$C13="","",'02_投資成本_CAPEX'!$A13) -> 8 | B12: =IF('02_投資成本_CAPEX'!$C13="","",'02_投資成本_CAPEX'!$C13) -> 越南在地化：病歷範本、衛生部報表格式、越文介面與術語對應 | C12: =IF('02_投資成本_CAPEX'!$C13="","",'02_投資成本_CAPEX'!$M13) -> 軟體與無形 Software | D12: =IF('02_投資成本_CAPEX'!$C13="","",'02_投資成本_CAPEX'!$N13) -> 5 | E12: =IF('02_投資成本_CAPEX'!$C13="","",'02_投資成本_CAPEX'!$O13) -> 0 | F12: =IF('02_投資成本_CAPEX'!$C13="",0,'02_投資成本_CAPEX'!$L13*(1-'02_投資成本_CAPEX'!$P13)*'01_專案設定_Setup'!$B$30) -> 4011.66 | G12: =IF(OR('02_投資成本_CAPEX'!$C13="",'02_投資成本_CAPEX'!$N13=0),0,IF(AND(1>=1,1<='02_投資成本_CAPEX'!$N13),$F12/'02_投資成本_CAPEX'!$N13,0)+IF(AND('02_投資成本_CAPEX'!$O13>0,1>='02_投資成本_CAPEX'!$O13,1<='02_投資成本_CAPEX'!$O13+'02_投資成本_CAPEX'!$N13-1),$F12/'02_投資成本_CAPEX'!$N13,0)) -> 802.332 | H12: =IF(OR('02_投資成本_CAPEX'!$C13="",'02_投資成本_CAPEX'!$N13=0),0,IF(AND(2>=1,2<='02_投資成本_CAPEX'!$N13),$F12/'02_投資成本_CAPEX'!$N13,0)+IF(AND('02_投資成本_CAPEX'!$O13>0,2>='02_投資成本_CAPEX'!$O13,2<='02_投資成本_CAPEX'!$O13+'02_投資成本_CAPEX'!$N13-1),$F12/'02_投資成本_CAPEX'!$N13,0)) -> 802.332 | I12: =IF(OR('02_投資成本_CAPEX'!$C13="",'02_投資成本_CAPEX'!$N13=0),0,IF(AND(3>=1,3<='02_投資成本_CAPEX'!$N13),$F12/'02_投資成本_CAPEX'!$N13,0)+IF(AND('02_投資成本_CAPEX'!$O13>0,3>='02_投資成本_CAPEX'!$O13,3<='02_投資成本_CAPEX'!$O13+'02_投資成本_CAPEX'!$N13-1),$F12/'02_投資成本_CAPEX'!$N13,0)) -> 802.332 | J12: =IF(OR('02_投資成本_CAPEX'!$C13="",'02_投資成本_CAPEX'!$N13=0),0,IF(AND(4>=1,4<='02_投資成本_CAPEX'!$N13),$F12/'02_投資成本_CAPEX'!$N13,0)+IF(AND('02_投資成本_CAPEX'!$O13>0,4>='02_投資成本_CAPEX'!$O13,4<='02_投資成本_CAPEX'!$O13+'02_投資成本_CAPEX'!$N13-1),$F12/'02_投資成本_CAPEX'!$N13,0)) -> 802.332 | K12: =IF(OR('02_投資成本_CAPEX'!$C13="",'02_投資成本_CAPEX'!$N13=0),0,IF(AND(5>=1,5<='02_投資成本_CAPEX'!$N13),$F12/'02_投資成本_CAPEX'!$N13,0)+IF(AND('02_投資成本_CAPEX'!$O13>0,5>='02_投資成本_CAPEX'!$O13,5<='02_投資成本_CAPEX'!$O13+'02_投資成本_CAPEX'!$N13-1),$F12/'02_投資成本_CAPEX'!$N13,0)) -> 802.332 | L12: =IF(OR('02_投資成本_CAPEX'!$C13="",'02_投資成本_CAPEX'!$N13=0),0,IF(AND(6>=1,6<='02_投資成本_CAPEX'!$N13),$F12/'02_投資成本_CAPEX'!$N13,0)+IF(AND('02_投資成本_CAPEX'!$O13>0,6>='02_投資成本_CAPEX'!$O13,6<='02_投資成本_CAPEX'!$O13+'02_投資成本_CAPEX'!$N13-1),$F12/'02_投資成本_CAPEX'!$N13,0)) -> 0 | M12: =IF(OR('02_投資成本_CAPEX'!$C13="",'02_投資成本_CAPEX'!$N13=0),0,IF(AND(7>=1,7<='02_投資成本_CAPEX'!$N13),$F12/'02_投資成本_CAPEX'!$N13,0)+IF(AND('02_投資成本_CAPEX'!$O13>0,7>='02_投資成本_CAPEX'!$O13,7<='02_投資成本_CAPEX'!$O13+'02_投資成本_CAPEX'!$N13-1),$F12/'02_投資成本_CAPEX'!$N13,0)) -> 0 | N12: =IF(OR('02_投資成本_CAPEX'!$C13="",'02_投資成本_CAPEX'!$N13=0),0,IF(AND(8>=1,8<='02_投資成本_CAPEX'!$N13),$F12/'02_投資成本_CAPEX'!$N13,0)+IF(AND('02_投資成本_CAPEX'!$O13>0,8>='02_投資成本_CAPEX'!$O13,8<='02_投資成本_CAPEX'!$O13+'02_投資成本_CAPEX'!$N13-1),$F12/'02_投資成本_CAPEX'!$N13,0)) -> 0 | O12: =IF(OR('02_投資成本_CAPEX'!$C13="",'02_投資成本_CAPEX'!$N13=0),0,IF(AND(9>=1,9<='02_投資成本_CAPEX'!$N13),$F12/'02_投資成本_CAPEX'!$N13,0)+IF(AND('02_投資成本_CAPEX'!$O13>0,9>='02_投資成本_CAPEX'!$O13,9<='02_投資成本_CAPEX'!$O13+'02_投資成本_CAPEX'!$N13-1),$F12/'02_投資成本_CAPEX'!$N13,0)) -> 0 | P12: =IF(OR('02_投資成本_CAPEX'!$C13="",'02_投資成本_CAPEX'!$N13=0),0,IF(AND(10>=1,10<='02_投資成本_CAPEX'!$N13),$F12/'02_投資成本_CAPEX'!$N13,0)+IF(AND('02_投資成本_CAPEX'!$O13>0,10>='02_投資成本_CAPEX'!$O13,10<='02_投資成本_CAPEX'!$O13+'02_投資成本_CAPEX'!$N13-1),$F12/'02_投資成本_CAPEX'!$N13,0)) -> 0
A13: =IF('02_投資成本_CAPEX'!$C14="","",'02_投資成本_CAPEX'!$A14) -> 9 | B13: =IF('02_投資成本_CAPEX'!$C14="","",'02_投資成本_CAPEX'!$C14) -> 資料移轉與病人主檔 MPI 清理去重（與 CCCD／VNeID 比對） | C13: =IF('02_投資成本_CAPEX'!$C14="","",'02_投資成本_CAPEX'!$M14) -> 費用化 Expensed | D13: =IF('02_投資成本_CAPEX'!$C14="","",'02_投資成本_CAPEX'!$N14) -> 0 | E13: =IF('02_投資成本_CAPEX'!$C14="","",'02_投資成本_CAPEX'!$O14) -> 0 | F13: =IF('02_投資成本_CAPEX'!$C14="",0,'02_投資成本_CAPEX'!$L14*(1-'02_投資成本_CAPEX'!$P14)*'01_專案設定_Setup'!$B$30) -> 2372.112 | G13: =IF(OR('02_投資成本_CAPEX'!$C14="",'02_投資成本_CAPEX'!$N14=0),0,IF(AND(1>=1,1<='02_投資成本_CAPEX'!$N14),$F13/'02_投資成本_CAPEX'!$N14,0)+IF(AND('02_投資成本_CAPEX'!$O14>0,1>='02_投資成本_CAPEX'!$O14,1<='02_投資成本_CAPEX'!$O14+'02_投資成本_CAPEX'!$N14-1),$F13/'02_投資成本_CAPEX'!$N14,0)) -> 0 | H13: =IF(OR('02_投資成本_CAPEX'!$C14="",'02_投資成本_CAPEX'!$N14=0),0,IF(AND(2>=1,2<='02_投資成本_CAPEX'!$N14),$F13/'02_投資成本_CAPEX'!$N14,0)+IF(AND('02_投資成本_CAPEX'!$O14>0,2>='02_投資成本_CAPEX'!$O14,2<='02_投資成本_CAPEX'!$O14+'02_投資成本_CAPEX'!$N14-1),$F13/'02_投資成本_CAPEX'!$N14,0)) -> 0 | I13: =IF(OR('02_投資成本_CAPEX'!$C14="",'02_投資成本_CAPEX'!$N14=0),0,IF(AND(3>=1,3<='02_投資成本_CAPEX'!$N14),$F13/'02_投資成本_CAPEX'!$N14,0)+IF(AND('02_投資成本_CAPEX'!$O14>0,3>='02_投資成本_CAPEX'!$O14,3<='02_投資成本_CAPEX'!$O14+'02_投資成本_CAPEX'!$N14-1),$F13/'02_投資成本_CAPEX'!$N14,0)) -> 0 | J13: =IF(OR('02_投資成本_CAPEX'!$C14="",'02_投資成本_CAPEX'!$N14=0),0,IF(AND(4>=1,4<='02_投資成本_CAPEX'!$N14),$F13/'02_投資成本_CAPEX'!$N14,0)+IF(AND('02_投資成本_CAPEX'!$O14>0,4>='02_投資成本_CAPEX'!$O14,4<='02_投資成本_CAPEX'!$O14+'02_投資成本_CAPEX'!$N14-1),$F13/'02_投資成本_CAPEX'!$N14,0)) -> 0 | K13: =IF(OR('02_投資成本_CAPEX'!$C14="",'02_投資成本_CAPEX'!$N14=0),0,IF(AND(5>=1,5<='02_投資成本_CAPEX'!$N14),$F13/'02_投資成本_CAPEX'!$N14,0)+IF(AND('02_投資成本_CAPEX'!$O14>0,5>='02_投資成本_CAPEX'!$O14,5<='02_投資成本_CAPEX'!$O14+'02_投資成本_CAPEX'!$N14-1),$F13/'02_投資成本_CAPEX'!$N14,0)) -> 0 | L13: =IF(OR('02_投資成本_CAPEX'!$C14="",'02_投資成本_CAPEX'!$N14=0),0,IF(AND(6>=1,6<='02_投資成本_CAPEX'!$N14),$F13/'02_投資成本_CAPEX'!$N14,0)+IF(AND('02_投資成本_CAPEX'!$O14>0,6>='02_投資成本_CAPEX'!$O14,6<='02_投資成本_CAPEX'!$O14+'02_投資成本_CAPEX'!$N14-1),$F13/'02_投資成本_CAPEX'!$N14,0)) -> 0 | M13: =IF(OR('02_投資成本_CAPEX'!$C14="",'02_投資成本_CAPEX'!$N14=0),0,IF(AND(7>=1,7<='02_投資成本_CAPEX'!$N14),$F13/'02_投資成本_CAPEX'!$N14,0)+IF(AND('02_投資成本_CAPEX'!$O14>0,7>='02_投資成本_CAPEX'!$O14,7<='02_投資成本_CAPEX'!$O14+'02_投資成本_CAPEX'!$N14-1),$F13/'02_投資成本_CAPEX'!$N14,0)) -> 0 | N13: =IF(OR('02_投資成本_CAPEX'!$C14="",'02_投資成本_CAPEX'!$N14=0),0,IF(AND(8>=1,8<='02_投資成本_CAPEX'!$N14),$F13/'02_投資成本_CAPEX'!$N14,0)+IF(AND('02_投資成本_CAPEX'!$O14>0,8>='02_投資成本_CAPEX'!$O14,8<='02_投資成本_CAPEX'!$O14+'02_投資成本_CAPEX'!$N14-1),$F13/'02_投資成本_CAPEX'!$N14,0)) -> 0 | O13: =IF(OR('02_投資成本_CAPEX'!$C14="",'02_投資成本_CAPEX'!$N14=0),0,IF(AND(9>=1,9<='02_投資成本_CAPEX'!$N14),$F13/'02_投資成本_CAPEX'!$N14,0)+IF(AND('02_投資成本_CAPEX'!$O14>0,9>='02_投資成本_CAPEX'!$O14,9<='02_投資成本_CAPEX'!$O14+'02_投資成本_CAPEX'!$N14-1),$F13/'02_投資成本_CAPEX'!$N14,0)) -> 0 | P13: =IF(OR('02_投資成本_CAPEX'!$C14="",'02_投資成本_CAPEX'!$N14=0),0,IF(AND(10>=1,10<='02_投資成本_CAPEX'!$N14),$F13/'02_投資成本_CAPEX'!$N14,0)+IF(AND('02_投資成本_CAPEX'!$O14>0,10>='02_投資成本_CAPEX'!$O14,10<='02_投資成本_CAPEX'!$O14+'02_投資成本_CAPEX'!$N14-1),$F13/'02_投資成本_CAPEX'!$N14,0)) -> 0
A14: =IF('02_投資成本_CAPEX'!$C15="","",'02_投資成本_CAPEX'!$A15) -> 10 | B14: =IF('02_投資成本_CAPEX'!$C15="","",'02_投資成本_CAPEX'!$C15) -> 導入服務：流程重整、平行測試、12 個月上線輔導 | C14: =IF('02_投資成本_CAPEX'!$C15="","",'02_投資成本_CAPEX'!$M15) -> 費用化 Expensed | D14: =IF('02_投資成本_CAPEX'!$C15="","",'02_投資成本_CAPEX'!$N15) -> 0 | E14: =IF('02_投資成本_CAPEX'!$C15="","",'02_投資成本_CAPEX'!$O15) -> 0 | F14: =IF('02_投資成本_CAPEX'!$C15="",0,'02_投資成本_CAPEX'!$L15*(1-'02_投資成本_CAPEX'!$P15)*'01_專案設定_Setup'!$B$30) -> 4709.34 | G14: =IF(OR('02_投資成本_CAPEX'!$C15="",'02_投資成本_CAPEX'!$N15=0),0,IF(AND(1>=1,1<='02_投資成本_CAPEX'!$N15),$F14/'02_投資成本_CAPEX'!$N15,0)+IF(AND('02_投資成本_CAPEX'!$O15>0,1>='02_投資成本_CAPEX'!$O15,1<='02_投資成本_CAPEX'!$O15+'02_投資成本_CAPEX'!$N15-1),$F14/'02_投資成本_CAPEX'!$N15,0)) -> 0 | H14: =IF(OR('02_投資成本_CAPEX'!$C15="",'02_投資成本_CAPEX'!$N15=0),0,IF(AND(2>=1,2<='02_投資成本_CAPEX'!$N15),$F14/'02_投資成本_CAPEX'!$N15,0)+IF(AND('02_投資成本_CAPEX'!$O15>0,2>='02_投資成本_CAPEX'!$O15,2<='02_投資成本_CAPEX'!$O15+'02_投資成本_CAPEX'!$N15-1),$F14/'02_投資成本_CAPEX'!$N15,0)) -> 0 | I14: =IF(OR('02_投資成本_CAPEX'!$C15="",'02_投資成本_CAPEX'!$N15=0),0,IF(AND(3>=1,3<='02_投資成本_CAPEX'!$N15),$F14/'02_投資成本_CAPEX'!$N15,0)+IF(AND('02_投資成本_CAPEX'!$O15>0,3>='02_投資成本_CAPEX'!$O15,3<='02_投資成本_CAPEX'!$O15+'02_投資成本_CAPEX'!$N15-1),$F14/'02_投資成本_CAPEX'!$N15,0)) -> 0 | J14: =IF(OR('02_投資成本_CAPEX'!$C15="",'02_投資成本_CAPEX'!$N15=0),0,IF(AND(4>=1,4<='02_投資成本_CAPEX'!$N15),$F14/'02_投資成本_CAPEX'!$N15,0)+IF(AND('02_投資成本_CAPEX'!$O15>0,4>='02_投資成本_CAPEX'!$O15,4<='02_投資成本_CAPEX'!$O15+'02_投資成本_CAPEX'!$N15-1),$F14/'02_投資成本_CAPEX'!$N15,0)) -> 0 | K14: =IF(OR('02_投資成本_CAPEX'!$C15="",'02_投資成本_CAPEX'!$N15=0),0,IF(AND(5>=1,5<='02_投資成本_CAPEX'!$N15),$F14/'02_投資成本_CAPEX'!$N15,0)+IF(AND('02_投資成本_CAPEX'!$O15>0,5>='02_投資成本_CAPEX'!$O15,5<='02_投資成本_CAPEX'!$O15+'02_投資成本_CAPEX'!$N15-1),$F14/'02_投資成本_CAPEX'!$N15,0)) -> 0 | L14: =IF(OR('02_投資成本_CAPEX'!$C15="",'02_投資成本_CAPEX'!$N15=0),0,IF(AND(6>=1,6<='02_投資成本_CAPEX'!$N15),$F14/'02_投資成本_CAPEX'!$N15,0)+IF(AND('02_投資成本_CAPEX'!$O15>0,6>='02_投資成本_CAPEX'!$O15,6<='02_投資成本_CAPEX'!$O15+'02_投資成本_CAPEX'!$N15-1),$F14/'02_投資成本_CAPEX'!$N15,0)) -> 0 | M14: =IF(OR('02_投資成本_CAPEX'!$C15="",'02_投資成本_CAPEX'!$N15=0),0,IF(AND(7>=1,7<='02_投資成本_CAPEX'!$N15),$F14/'02_投資成本_CAPEX'!$N15,0)+IF(AND('02_投資成本_CAPEX'!$O15>0,7>='02_投資成本_CAPEX'!$O15,7<='02_投資成本_CAPEX'!$O15+'02_投資成本_CAPEX'!$N15-1),$F14/'02_投資成本_CAPEX'!$N15,0)) -> 0 | N14: =IF(OR('02_投資成本_CAPEX'!$C15="",'02_投資成本_CAPEX'!$N15=0),0,IF(AND(8>=1,8<='02_投資成本_CAPEX'!$N15),$F14/'02_投資成本_CAPEX'!$N15,0)+IF(AND('02_投資成本_CAPEX'!$O15>0,8>='02_投資成本_CAPEX'!$O15,8<='02_投資成本_CAPEX'!$O15+'02_投資成本_CAPEX'!$N15-1),$F14/'02_投資成本_CAPEX'!$N15,0)) -> 0 | O14: =IF(OR('02_投資成本_CAPEX'!$C15="",'02_投資成本_CAPEX'!$N15=0),0,IF(AND(9>=1,9<='02_投資成本_CAPEX'!$N15),$F14/'02_投資成本_CAPEX'!$N15,0)+IF(AND('02_投資成本_CAPEX'!$O15>0,9>='02_投資成本_CAPEX'!$O15,9<='02_投資成本_CAPEX'!$O15+'02_投資成本_CAPEX'!$N15-1),$F14/'02_投資成本_CAPEX'!$N15,0)) -> 0 | P14: =IF(OR('02_投資成本_CAPEX'!$C15="",'02_投資成本_CAPEX'!$N15=0),0,IF(AND(10>=1,10<='02_投資成本_CAPEX'!$N15),$F14/'02_投資成本_CAPEX'!$N15,0)+IF(AND('02_投資成本_CAPEX'!$O15>0,10>='02_投資成本_CAPEX'!$O15,10<='02_投資成本_CAPEX'!$O15+'02_投資成本_CAPEX'!$N15-1),$F14/'02_投資成本_CAPEX'!$N15,0)) -> 0
A15: =IF('02_投資成本_CAPEX'!$C16="","",'02_投資成本_CAPEX'!$A16) -> 11 | B15: =IF('02_投資成本_CAPEX'!$C16="","",'02_投資成本_CAPEX'!$C16) -> 醫師與護理教育訓練（含種子講師制度） | C15: =IF('02_投資成本_CAPEX'!$C16="","",'02_投資成本_CAPEX'!$M16) -> 費用化 Expensed | D15: =IF('02_投資成本_CAPEX'!$C16="","",'02_投資成本_CAPEX'!$N16) -> 0 | E15: =IF('02_投資成本_CAPEX'!$C16="","",'02_投資成本_CAPEX'!$O16) -> 0 | F15: =IF('02_投資成本_CAPEX'!$C16="",0,'02_投資成本_CAPEX'!$L16*(1-'02_投資成本_CAPEX'!$P16)*'01_專案設定_Setup'!$B$30) -> 1465.128 | G15: =IF(OR('02_投資成本_CAPEX'!$C16="",'02_投資成本_CAPEX'!$N16=0),0,IF(AND(1>=1,1<='02_投資成本_CAPEX'!$N16),$F15/'02_投資成本_CAPEX'!$N16,0)+IF(AND('02_投資成本_CAPEX'!$O16>0,1>='02_投資成本_CAPEX'!$O16,1<='02_投資成本_CAPEX'!$O16+'02_投資成本_CAPEX'!$N16-1),$F15/'02_投資成本_CAPEX'!$N16,0)) -> 0 | H15: =IF(OR('02_投資成本_CAPEX'!$C16="",'02_投資成本_CAPEX'!$N16=0),0,IF(AND(2>=1,2<='02_投資成本_CAPEX'!$N16),$F15/'02_投資成本_CAPEX'!$N16,0)+IF(AND('02_投資成本_CAPEX'!$O16>0,2>='02_投資成本_CAPEX'!$O16,2<='02_投資成本_CAPEX'!$O16+'02_投資成本_CAPEX'!$N16-1),$F15/'02_投資成本_CAPEX'!$N16,0)) -> 0 | I15: =IF(OR('02_投資成本_CAPEX'!$C16="",'02_投資成本_CAPEX'!$N16=0),0,IF(AND(3>=1,3<='02_投資成本_CAPEX'!$N16),$F15/'02_投資成本_CAPEX'!$N16,0)+IF(AND('02_投資成本_CAPEX'!$O16>0,3>='02_投資成本_CAPEX'!$O16,3<='02_投資成本_CAPEX'!$O16+'02_投資成本_CAPEX'!$N16-1),$F15/'02_投資成本_CAPEX'!$N16,0)) -> 0 | J15: =IF(OR('02_投資成本_CAPEX'!$C16="",'02_投資成本_CAPEX'!$N16=0),0,IF(AND(4>=1,4<='02_投資成本_CAPEX'!$N16),$F15/'02_投資成本_CAPEX'!$N16,0)+IF(AND('02_投資成本_CAPEX'!$O16>0,4>='02_投資成本_CAPEX'!$O16,4<='02_投資成本_CAPEX'!$O16+'02_投資成本_CAPEX'!$N16-1),$F15/'02_投資成本_CAPEX'!$N16,0)) -> 0 | K15: =IF(OR('02_投資成本_CAPEX'!$C16="",'02_投資成本_CAPEX'!$N16=0),0,IF(AND(5>=1,5<='02_投資成本_CAPEX'!$N16),$F15/'02_投資成本_CAPEX'!$N16,0)+IF(AND('02_投資成本_CAPEX'!$O16>0,5>='02_投資成本_CAPEX'!$O16,5<='02_投資成本_CAPEX'!$O16+'02_投資成本_CAPEX'!$N16-1),$F15/'02_投資成本_CAPEX'!$N16,0)) -> 0 | L15: =IF(OR('02_投資成本_CAPEX'!$C16="",'02_投資成本_CAPEX'!$N16=0),0,IF(AND(6>=1,6<='02_投資成本_CAPEX'!$N16),$F15/'02_投資成本_CAPEX'!$N16,0)+IF(AND('02_投資成本_CAPEX'!$O16>0,6>='02_投資成本_CAPEX'!$O16,6<='02_投資成本_CAPEX'!$O16+'02_投資成本_CAPEX'!$N16-1),$F15/'02_投資成本_CAPEX'!$N16,0)) -> 0 | M15: =IF(OR('02_投資成本_CAPEX'!$C16="",'02_投資成本_CAPEX'!$N16=0),0,IF(AND(7>=1,7<='02_投資成本_CAPEX'!$N16),$F15/'02_投資成本_CAPEX'!$N16,0)+IF(AND('02_投資成本_CAPEX'!$O16>0,7>='02_投資成本_CAPEX'!$O16,7<='02_投資成本_CAPEX'!$O16+'02_投資成本_CAPEX'!$N16-1),$F15/'02_投資成本_CAPEX'!$N16,0)) -> 0 | N15: =IF(OR('02_投資成本_CAPEX'!$C16="",'02_投資成本_CAPEX'!$N16=0),0,IF(AND(8>=1,8<='02_投資成本_CAPEX'!$N16),$F15/'02_投資成本_CAPEX'!$N16,0)+IF(AND('02_投資成本_CAPEX'!$O16>0,8>='02_投資成本_CAPEX'!$O16,8<='02_投資成本_CAPEX'!$O16+'02_投資成本_CAPEX'!$N16-1),$F15/'02_投資成本_CAPEX'!$N16,0)) -> 0 | O15: =IF(OR('02_投資成本_CAPEX'!$C16="",'02_投資成本_CAPEX'!$N16=0),0,IF(AND(9>=1,9<='02_投資成本_CAPEX'!$N16),$F15/'02_投資成本_CAPEX'!$N16,0)+IF(AND('02_投資成本_CAPEX'!$O16>0,9>='02_投資成本_CAPEX'!$O16,9<='02_投資成本_CAPEX'!$O16+'02_投資成本_CAPEX'!$N16-1),$F15/'02_投資成本_CAPEX'!$N16,0)) -> 0 | P15: =IF(OR('02_投資成本_CAPEX'!$C16="",'02_投資成本_CAPEX'!$N16=0),0,IF(AND(10>=1,10<='02_投資成本_CAPEX'!$N16),$F15/'02_投資成本_CAPEX'!$N16,0)+IF(AND('02_投資成本_CAPEX'!$O16>0,10>='02_投資成本_CAPEX'!$O16,10<='02_投資成本_CAPEX'!$O16+'02_投資成本_CAPEX'!$N16-1),$F15/'02_投資成本_CAPEX'!$N16,0)) -> 0
A16: =IF('02_投資成本_CAPEX'!$C17="","",'02_投資成本_CAPEX'!$A17) -> 12 | B16: =IF('02_投資成本_CAPEX'!$C17="","",'02_投資成本_CAPEX'!$C17) -> 承載環境：伺服器、儲存、備份（可承載於 A醫院 IDC，或商用雲） | C16: =IF('02_投資成本_CAPEX'!$C17="","",'02_投資成本_CAPEX'!$M17) -> 電腦與網通 IT | D16: =IF('02_投資成本_CAPEX'!$C17="","",'02_投資成本_CAPEX'!$N17) -> 5 | E16: =IF('02_投資成本_CAPEX'!$C17="","",'02_投資成本_CAPEX'!$O17) -> 6 | F16: =IF('02_投資成本_CAPEX'!$C17="",0,'02_投資成本_CAPEX'!$L17*(1-'02_投資成本_CAPEX'!$P17)*'01_專案設定_Setup'!$B$30) -> 2970.308 | G16: =IF(OR('02_投資成本_CAPEX'!$C17="",'02_投資成本_CAPEX'!$N17=0),0,IF(AND(1>=1,1<='02_投資成本_CAPEX'!$N17),$F16/'02_投資成本_CAPEX'!$N17,0)+IF(AND('02_投資成本_CAPEX'!$O17>0,1>='02_投資成本_CAPEX'!$O17,1<='02_投資成本_CAPEX'!$O17+'02_投資成本_CAPEX'!$N17-1),$F16/'02_投資成本_CAPEX'!$N17,0)) -> 594.0616 | H16: =IF(OR('02_投資成本_CAPEX'!$C17="",'02_投資成本_CAPEX'!$N17=0),0,IF(AND(2>=1,2<='02_投資成本_CAPEX'!$N17),$F16/'02_投資成本_CAPEX'!$N17,0)+IF(AND('02_投資成本_CAPEX'!$O17>0,2>='02_投資成本_CAPEX'!$O17,2<='02_投資成本_CAPEX'!$O17+'02_投資成本_CAPEX'!$N17-1),$F16/'02_投資成本_CAPEX'!$N17,0)) -> 594.0616 | I16: =IF(OR('02_投資成本_CAPEX'!$C17="",'02_投資成本_CAPEX'!$N17=0),0,IF(AND(3>=1,3<='02_投資成本_CAPEX'!$N17),$F16/'02_投資成本_CAPEX'!$N17,0)+IF(AND('02_投資成本_CAPEX'!$O17>0,3>='02_投資成本_CAPEX'!$O17,3<='02_投資成本_CAPEX'!$O17+'02_投資成本_CAPEX'!$N17-1),$F16/'02_投資成本_CAPEX'!$N17,0)) -> 594.0616 | J16: =IF(OR('02_投資成本_CAPEX'!$C17="",'02_投資成本_CAPEX'!$N17=0),0,IF(AND(4>=1,4<='02_投資成本_CAPEX'!$N17),$F16/'02_投資成本_CAPEX'!$N17,0)+IF(AND('02_投資成本_CAPEX'!$O17>0,4>='02_投資成本_CAPEX'!$O17,4<='02_投資成本_CAPEX'!$O17+'02_投資成本_CAPEX'!$N17-1),$F16/'02_投資成本_CAPEX'!$N17,0)) -> 594.0616 | K16: =IF(OR('02_投資成本_CAPEX'!$C17="",'02_投資成本_CAPEX'!$N17=0),0,IF(AND(5>=1,5<='02_投資成本_CAPEX'!$N17),$F16/'02_投資成本_CAPEX'!$N17,0)+IF(AND('02_投資成本_CAPEX'!$O17>0,5>='02_投資成本_CAPEX'!$O17,5<='02_投資成本_CAPEX'!$O17+'02_投資成本_CAPEX'!$N17-1),$F16/'02_投資成本_CAPEX'!$N17,0)) -> 594.0616 | L16: =IF(OR('02_投資成本_CAPEX'!$C17="",'02_投資成本_CAPEX'!$N17=0),0,IF(AND(6>=1,6<='02_投資成本_CAPEX'!$N17),$F16/'02_投資成本_CAPEX'!$N17,0)+IF(AND('02_投資成本_CAPEX'!$O17>0,6>='02_投資成本_CAPEX'!$O17,6<='02_投資成本_CAPEX'!$O17+'02_投資成本_CAPEX'!$N17-1),$F16/'02_投資成本_CAPEX'!$N17,0)) -> 594.0616 | M16: =IF(OR('02_投資成本_CAPEX'!$C17="",'02_投資成本_CAPEX'!$N17=0),0,IF(AND(7>=1,7<='02_投資成本_CAPEX'!$N17),$F16/'02_投資成本_CAPEX'!$N17,0)+IF(AND('02_投資成本_CAPEX'!$O17>0,7>='02_投資成本_CAPEX'!$O17,7<='02_投資成本_CAPEX'!$O17+'02_投資成本_CAPEX'!$N17-1),$F16/'02_投資成本_CAPEX'!$N17,0)) -> 594.0616 | N16: =IF(OR('02_投資成本_CAPEX'!$C17="",'02_投資成本_CAPEX'!$N17=0),0,IF(AND(8>=1,8<='02_投資成本_CAPEX'!$N17),$F16/'02_投資成本_CAPEX'!$N17,0)+IF(AND('02_投資成本_CAPEX'!$O17>0,8>='02_投資成本_CAPEX'!$O17,8<='02_投資成本_CAPEX'!$O17+'02_投資成本_CAPEX'!$N17-1),$F16/'02_投資成本_CAPEX'!$N17,0)) -> 594.0616 | O16: =IF(OR('02_投資成本_CAPEX'!$C17="",'02_投資成本_CAPEX'!$N17=0),0,IF(AND(9>=1,9<='02_投資成本_CAPEX'!$N17),$F16/'02_投資成本_CAPEX'!$N17,0)+IF(AND('02_投資成本_CAPEX'!$O17>0,9>='02_投資成本_CAPEX'!$O17,9<='02_投資成本_CAPEX'!$O17+'02_投資成本_CAPEX'!$N17-1),$F16/'02_投資成本_CAPEX'!$N17,0)) -> 594.0616 | P16: =IF(OR('02_投資成本_CAPEX'!$C17="",'02_投資成本_CAPEX'!$N17=0),0,IF(AND(10>=1,10<='02_投資成本_CAPEX'!$N17),$F16/'02_投資成本_CAPEX'!$N17,0)+IF(AND('02_投資成本_CAPEX'!$O17>0,10>='02_投資成本_CAPEX'!$O17,10<='02_投資成本_CAPEX'!$O17+'02_投資成本_CAPEX'!$N17-1),$F16/'02_投資成本_CAPEX'!$N17,0)) -> 594.0616
... A62: =IF('02_投資成本_CAPEX'!$C63="","",'02_投資成本_CAPEX'!$A63) | B62: =IF('02_投資成本_CAPEX'!$C63="","",'02_投資成本_CAPEX'!$C63) | C62: =IF('02_投資成本_CAPEX'!$C63="","",'02_投資成本_CAPEX'!$M63) | D62: =IF('02_投資成本_CAPEX'!$C63="","",'02_投資成本_CAPEX'!$N63) | E62: =IF('02_投資成本_CAPEX'!$C63="","",'02_投資成本_CAPEX'!$O63) | F62: =IF('02_投資成本_CAPEX'!$C63="",0,'02_投資成本_CAPEX'!$L63*(1-'02_投資成本_CAPEX'!$P63)*'01_專案設定_Setup'!$B$30) -> 0 | G62: =IF(OR('02_投資成本_CAPEX'!$C63="",'02_投資成本_CAPEX'!$N63=0),0,IF(AND(1>=1,1<='02_投資成本_CAPEX'!$N63),$F62/'02_投資成本_CAPEX'!$N63,0)+IF(AND('02_投資成本_CAPEX'!$O63>0,1>='02_投資成本_CAPEX'!$O63,1<='02_投資成本_CAPEX'!$O63+'02_投資成本_CAPEX'!$N63-1),$F62/'02_投資成本_CAPEX'!$N63,0)) -> 0 | H62: =IF(OR('02_投資成本_CAPEX'!$C63="",'02_投資成本_CAPEX'!$N63=0),0,IF(AND(2>=1,2<='02_投資成本_CAPEX'!$N63),$F62/'02_投資成本_CAPEX'!$N63,0)+IF(AND('02_投資成本_CAPEX'!$O63>0,2>='02_投資成本_CAPEX'!$O63,2<='02_投資成本_CAPEX'!$O63+'02_投資成本_CAPEX'!$N63-1),$F62/'02_投資成本_CAPEX'!$N63,0)) -> 0 | I62: =IF(OR('02_投資成本_CAPEX'!$C63="",'02_投資成本_CAPEX'!$N63=0),0,IF(AND(3>=1,3<='02_投資成本_CAPEX'!$N63),$F62/'02_投資成本_CAPEX'!$N63,0)+IF(AND('02_投資成本_CAPEX'!$O63>0,3>='02_投資成本_CAPEX'!$O63,3<='02_投資成本_CAPEX'!$O63+'02_投資成本_CAPEX'!$N63-1),$F62/'02_投資成本_CAPEX'!$N63,0)) -> 0 | J62: =IF(OR('02_投資成本_CAPEX'!$C63="",'02_投資成本_CAPEX'!$N63=0),0,IF(AND(4>=1,4<='02_投資成本_CAPEX'!$N63),$F62/'02_投資成本_CAPEX'!$N63,0)+IF(AND('02_投資成本_CAPEX'!$O63>0,4>='02_投資成本_CAPEX'!$O63,4<='02_投資成本_CAPEX'!$O63+'02_投資成本_CAPEX'!$N63-1),$F62/'02_投資成本_CAPEX'!$N63,0)) -> 0 | K62: =IF(OR('02_投資成本_CAPEX'!$C63="",'02_投資成本_CAPEX'!$N63=0),0,IF(AND(5>=1,5<='02_投資成本_CAPEX'!$N63),$F62/'02_投資成本_CAPEX'!$N63,0)+IF(AND('02_投資成本_CAPEX'!$O63>0,5>='02_投資成本_CAPEX'!$O63,5<='02_投資成本_CAPEX'!$O63+'02_投資成本_CAPEX'!$N63-1),$F62/'02_投資成本_CAPEX'!$N63,0)) -> 0 | L62: =IF(OR('02_投資成本_CAPEX'!$C63="",'02_投資成本_CAPEX'!$N63=0),0,IF(AND(6>=1,6<='02_投資成本_CAPEX'!$N63),$F62/'02_投資成本_CAPEX'!$N63,0)+IF(AND('02_投資成本_CAPEX'!$O63>0,6>='02_投資成本_CAPEX'!$O63,6<='02_投資成本_CAPEX'!$O63+'02_投資成本_CAPEX'!$N63-1),$F62/'02_投資成本_CAPEX'!$N63,0)) -> 0 | M62: =IF(OR('02_投資成本_CAPEX'!$C63="",'02_投資成本_CAPEX'!$N63=0),0,IF(AND(7>=1,7<='02_投資成本_CAPEX'!$N63),$F62/'02_投資成本_CAPEX'!$N63,0)+IF(AND('02_投資成本_CAPEX'!$O63>0,7>='02_投資成本_CAPEX'!$O63,7<='02_投資成本_CAPEX'!$O63+'02_投資成本_CAPEX'!$N63-1),$F62/'02_投資成本_CAPEX'!$N63,0)) -> 0 | N62: =IF(OR('02_投資成本_CAPEX'!$C63="",'02_投資成本_CAPEX'!$N63=0),0,IF(AND(8>=1,8<='02_投資成本_CAPEX'!$N63),$F62/'02_投資成本_CAPEX'!$N63,0)+IF(AND('02_投資成本_CAPEX'!$O63>0,8>='02_投資成本_CAPEX'!$O63,8<='02_投資成本_CAPEX'!$O63+'02_投資成本_CAPEX'!$N63-1),$F62/'02_投資成本_CAPEX'!$N63,0)) -> 0 | O62: =IF(OR('02_投資成本_CAPEX'!$C63="",'02_投資成本_CAPEX'!$N63=0),0,IF(AND(9>=1,9<='02_投資成本_CAPEX'!$N63),$F62/'02_投資成本_CAPEX'!$N63,0)+IF(AND('02_投資成本_CAPEX'!$O63>0,9>='02_投資成本_CAPEX'!$O63,9<='02_投資成本_CAPEX'!$O63+'02_投資成本_CAPEX'!$N63-1),$F62/'02_投資成本_CAPEX'!$N63,0)) -> 0 | P62: =IF(OR('02_投資成本_CAPEX'!$C63="",'02_投資成本_CAPEX'!$N63=0),0,IF(AND(10>=1,10<='02_投資成本_CAPEX'!$N63),$F62/'02_投資成本_CAPEX'!$N63,0)+IF(AND('02_投資成本_CAPEX'!$O63>0,10>='02_投資成本_CAPEX'!$O63,10<='02_投資成本_CAPEX'!$O63+'02_投資成本_CAPEX'!$N63-1),$F62/'02_投資成本_CAPEX'!$N63,0)) -> 0
B63: 折舊攤提合計 Total D&A | G63: =SUM(G5:G62) -> 5326.0116 | H63: =SUM(H5:H62) -> 5326.0116 | I63: =SUM(I5:I62) -> 5326.0116 | J63: =SUM(J5:J62) -> 5326.0116 | K63: =SUM(K5:K62) -> 5567.6156 | L63: =SUM(L5:L62) -> 835.6656 | M63: =SUM(M5:M62) -> 835.6656 | N63: =SUM(N5:N62) -> 835.6656 | ... P63: =SUM(P5:P62) -> 594.0616
A65: 資本支出時程（Capital expenditure schedule，顯示幣別）
A66: 項目 | F66: 第 0 年 建置期 | G66: 第 1 年 | H66: 第 2 年 | I66: 第 3 年 | J66: 第 4 年 | K66: 第 5 年 | L66: 第 6 年 | M66: 第 7 年 | N66: 第 8 年 | O66: 第 9 年 | P66: 第 10 年
A67: 初始投資 Initial CAPEX | F67: =SUM('02_投資成本_CAPEX'!$Q$6:$Q$63) -> 41019.602 | G67: 0 | H67: 0 | I67: 0 | J67: 0 | K67: 0 | L67: 0 | M67: 0 | N67: 0 | O67: 0 | P67: 0
A68: 置換投資 Replacement CAPEX | F68: 0 | G68: =SUMIF('02_投資成本_CAPEX'!$O$6:$O$63,1,'02_投資成本_CAPEX'!$Q$6:$Q$63) -> 0 | H68: =SUMIF('02_投資成本_CAPEX'!$O$6:$O$63,2,'02_投資成本_CAPEX'!$Q$6:$Q$63) -> 0 | I68: =SUMIF('02_投資成本_CAPEX'!$O$6:$O$63,3,'02_投資成本_CAPEX'!$Q$6:$Q$63) -> 0 | J68: =SUMIF('02_投資成本_CAPEX'!$O$6:$O$63,4,'02_投資成本_CAPEX'!$Q$6:$Q$63) -> 0 | K68: =SUMIF('02_投資成本_CAPEX'!$O$6:$O$63,5,'02_投資成本_CAPEX'!$Q$6:$Q$63) -> 1208.02 | L68: =SUMIF('02_投資成本_CAPEX'!$O$6:$O$63,6,'02_投資成本_CAPEX'!$Q$6:$Q$63) -> 3126.64 | M68: =SUMIF('02_投資成本_CAPEX'!$O$6:$O$63,7,'02_投資成本_CAPEX'!$Q$6:$Q$63) -> 0 | N68: =SUMIF('02_投資成本_CAPEX'!$O$6:$O$63,8,'02_投資成本_CAPEX'!$Q$6:$Q$63) -> 0 | O68: =SUMIF('02_投資成本_CAPEX'!$O$6:$O$63,9,'02_投資成本_CAPEX'!$Q$6:$Q$63) -> 0 | P68: =SUMIF('02_投資成本_CAPEX'!$O$6:$O$63,10,'02_投資成本_CAPEX'!$Q$6:$Q$63) -> 0
A69: 資本支出合計 | F69: =$F67+$F68 -> 41019.602 | G69: =G67+G68 -> 0 | H69: =H67+H68 -> 0 | I69: =I67+I68 -> 0 | J69: =J67+J68 -> 0 | K69: =K67+K68 -> 1208.02 | L69: =L67+L68 -> 3126.64 | M69: =M67+M68 -> 0 | N69: =N67+N68 -> 0 | ... P69: =P67+P68 -> 0
A71: 期末殘值回收 Salvage value（第 10 年一次認列） | F71: =SUMPRODUCT('02_投資成本_CAPEX'!$L$6:$L$63,'02_投資成本_CAPEX'!$P$6:$P$63)*'01_專案設定_Setup'!$B$30 -> 156.332
A73: ★ 建模說明：本表採直線法。若資產設有置換年，模型讓「原資產按原年限攤完」與「置換資產自置換年重新起算」並存，在置換年到原年限之間會有短暫重疊——這是為了讓公式保持透明可讀所做的簡化，對現金流無影響（折舊只影響稅），且方向保守（折舊多、稅少估）。若本案的置換金額重大，建議在 11 分頁登錄此簡化並請會計師確認。

Sheet 06_現金流_Cashflow
A1: 06 現金流｜Free Cash Flow to Firm（無槓桿自由現金流）
A2: 全公式，不需編輯。採業界標準推導：營收 → EBITDA → 折舊攤提 → EBIT → 所得稅 → NOPAT → ＋折舊 −資本支出 −營運資金變動 ＝ FCFF。★ 稅採「EBIT × 稅率」（未槓桿稅負），不用損益表實際稅額——因為利息稅盾已含在 WACC 的 Kd×(1−t) 裡，重複計會高估價值。★ 所得稅已內建越南免稅期起算規則與 5 年虧損扣抵。全部金額為 01 分頁設定的顯示幣別。
A4: 項目 Item | B4: 第 0 年 建置期 | C4: =CONCATENATE("第 1 年",CHAR(10),"(",'01_專案設定_Setup'!$B$36+0,")") -> 第 1 年 (2027) | D4: =CONCATENATE("第 2 年",CHAR(10),"(",'01_專案設定_Setup'!$B$36+1,")") -> 第 2 年 (2028) | E4: =CONCATENATE("第 3 年",CHAR(10),"(",'01_專案設定_Setup'!$B$36+2,")") -> 第 3 年 (2029) | F4: =CONCATENATE("第 4 年",CHAR(10),"(",'01_專案設定_Setup'!$B$36+3,")") -> 第 4 年 (2030) | G4: =CONCATENATE("第 5 年",CHAR(10),"(",'01_專案設定_Setup'!$B$36+4,")") -> 第 5 年 (2031) | H4: =CONCATENATE("第 6 年",CHAR(10),"(",'01_專案設定_Setup'!$B$36+5,")") -> 第 6 年 (2032) | I4: =CONCATENATE("第 7 年",CHAR(10),"(",'01_專案設定_Setup'!$B$36+6,")") -> 第 7 年 (2033) | J4: =CONCATENATE("第 8 年",CHAR(10),"(",'01_專案設定_Setup'!$B$36+7,")") -> 第 8 年 (2034) | K4: =CONCATENATE("第 9 年",CHAR(10),"(",'01_專案設定_Setup'!$B$36+8,")") -> 第 9 年 (2035) | L4: =CONCATENATE("第 10 年",CHAR(10),"(",'01_專案設定_Setup'!$B$36+9,")") -> 第 10 年 (2036)
A5: A. 營業損益 Profit & Loss
A6: 健保營收 BHYT revenue | B6: 0 | C6: ='04_收入產能_Revenue'!B$27 -> 3225.6 | D6: ='04_收入產能_Revenue'!C$27 -> 6354.0288 | E6: ='04_收入產能_Revenue'!D$27 -> 8900.7235 | F6: ='04_收入產能_Revenue'!E$27 -> 9351.1002 | G6: ='04_收入產能_Revenue'!F$27 -> 9824.2658 | H6: ='04_收入產能_Revenue'!G$27 -> 10321.374 | I6: ='04_收入產能_Revenue'!H$27 -> 10843.635 | J6: ='04_收入產能_Revenue'!I$27 -> 11392.323 | ... L6: ='04_收入產能_Revenue'!K$27 -> 12574.395
A7: 自費營收 Self-pay revenue | B7: 0 | C7: ='04_收入產能_Revenue'!B$28 -> 1161.6 | D7: ='04_收入產能_Revenue'!C$28 -> 2288.2068 | E7: ='04_收入產能_Revenue'!D$28 -> 3205.3201 | F7: ='04_收入產能_Revenue'!E$28 -> 3367.5093 | G7: ='04_收入產能_Revenue'!F$28 -> 3537.9053 | H7: ='04_收入產能_Revenue'!G$28 -> 3716.9233 | I7: ='04_收入產能_Revenue'!H$28 -> 3904.9996 | J7: ='04_收入產能_Revenue'!I$28 -> 4102.5926 | ... L7: ='04_收入產能_Revenue'!K$28 -> 4528.279
A8: 營收合計 Total revenue | B8: 0 | C8: =C6+C7 -> 4387.2 | D8: =D6+D7 -> 8642.2356 | E8: =E6+E7 -> 12106.044 | F8: =F6+F7 -> 12718.609 | G8: =G6+G7 -> 13362.171 | H8: =H6+H7 -> 14038.297 | I8: =I6+I7 -> 14748.635 | J8: =J6+J7 -> 15494.916 | ... L8: =L6+L7 -> 17102.674
A9: 變動營運成本 Variable OPEX | B9: 0 | C9: =-SUMPRODUCT(('03_營運成本_OPEX'!$I$5:$I$34="變動")*'03_營運成本_OPEX'!$G$5:$G$34*(1+'03_營運成本_OPEX'!$H$5:$H$34)^0)*'01_專案設定_Setup'!$B$30*'04_收入產能_Revenue'!B$21*(1+'04_收入產能_Revenue'!$B$16)^0 -> -129.2 | D9: =-SUMPRODUCT(('03_營運成本_OPEX'!$I$5:$I$34="變動")*'03_營運成本_OPEX'!$G$5:$G$34*(1+'03_營運成本_OPEX'!$H$5:$H$34)^1)*'01_專案設定_Setup'!$B$30*'04_收入產能_Revenue'!C$21*(1+'04_收入產能_Revenue'!$B$16)^1 -> -259.44975 | E9: =-SUMPRODUCT(('03_營運成本_OPEX'!$I$5:$I$34="變動")*'03_營運成本_OPEX'!$G$5:$G$34*(1+'03_營運成本_OPEX'!$H$5:$H$34)^2)*'01_專案設定_Setup'!$B$30*'04_收入產能_Revenue'!D$21*(1+'04_收入產能_Revenue'!$B$16)^2 -> -370.49424 | F9: =-SUMPRODUCT(('03_營運成本_OPEX'!$I$5:$I$34="變動")*'03_營運成本_OPEX'!$G$5:$G$34*(1+'03_營運成本_OPEX'!$H$5:$H$34)^3)*'01_專案設定_Setup'!$B$30*'04_收入產能_Revenue'!E$21*(1+'04_收入產能_Revenue'!$B$16)^3 -> -396.79933 | G9: =-SUMPRODUCT(('03_營運成本_OPEX'!$I$5:$I$34="變動")*'03_營運成本_OPEX'!$G$5:$G$34*(1+'03_營運成本_OPEX'!$H$5:$H$34)^4)*'01_專案設定_Setup'!$B$30*'04_收入產能_Revenue'!F$21*(1+'04_收入產能_Revenue'!$B$16)^4 -> -424.97209 | H9: =-SUMPRODUCT(('03_營運成本_OPEX'!$I$5:$I$34="變動")*'03_營運成本_OPEX'!$G$5:$G$34*(1+'03_營運成本_OPEX'!$H$5:$H$34)^5)*'01_專案設定_Setup'!$B$30*'04_收入產能_Revenue'!G$21*(1+'04_收入產能_Revenue'!$B$16)^5 -> -455.14511 | I9: =-SUMPRODUCT(('03_營運成本_OPEX'!$I$5:$I$34="變動")*'03_營運成本_OPEX'!$G$5:$G$34*(1+'03_營運成本_OPEX'!$H$5:$H$34)^6)*'01_專案設定_Setup'!$B$30*'04_收入產能_Revenue'!H$21*(1+'04_收入產能_Revenue'!$B$16)^6 -> -487.46041 | J9: =-SUMPRODUCT(('03_營運成本_OPEX'!$I$5:$I$34="變動")*'03_營運成本_OPEX'!$G$5:$G$34*(1+'03_營運成本_OPEX'!$H$5:$H$34)^7)*'01_專案設定_Setup'!$B$30*'04_收入產能_Revenue'!I$21*(1+'04_收入產能_Revenue'!$B$16)^7 -> -522.0701 | K9: =-SUMPRODUCT(('03_營運成本_OPEX'!$I$5:$I$34="變動")*'03_營運成本_OPEX'!$G$5:$G$34*(1+'03_營運成本_OPEX'!$H$5:$H$34)^8)*'01_專案設定_Setup'!$B$30*'04_收入產能_Revenue'!J$21*(1+'04_收入產能_Revenue'!$B$16)^8 -> -559.13707 | L9: =-SUMPRODUCT(('03_營運成本_OPEX'!$I$5:$I$34="變動")*'03_營運成本_OPEX'!$G$5:$G$34*(1+'03_營運成本_OPEX'!$H$5:$H$34)^9)*'01_專案設定_Setup'!$B$30*'04_收入產能_Revenue'!K$21*(1+'04_收入產能_Revenue'!$B$16)^9 -> -598.83581
A10: 固定營運成本 Fixed OPEX | B10: 0 | C10: =-SUMPRODUCT(('03_營運成本_OPEX'!$I$5:$I$34="固定")*'03_營運成本_OPEX'!$G$5:$G$34*(1+'03_營運成本_OPEX'!$H$5:$H$34)^0)*'01_專案設定_Setup'!$B$30 -> -6397.5 | D10: =-SUMPRODUCT(('03_營運成本_OPEX'!$I$5:$I$34="固定")*'03_營運成本_OPEX'!$G$5:$G$34*(1+'03_營運成本_OPEX'!$H$5:$H$34)^1)*'01_專案設定_Setup'!$B$30 -> -6760.72 | E10: =-SUMPRODUCT(('03_營運成本_OPEX'!$I$5:$I$34="固定")*'03_營運成本_OPEX'!$G$5:$G$34*(1+'03_營運成本_OPEX'!$H$5:$H$34)^2)*'01_專案設定_Setup'!$B$30 -> -7146.6216 | F10: =-SUMPRODUCT(('03_營運成本_OPEX'!$I$5:$I$34="固定")*'03_營運成本_OPEX'!$G$5:$G$34*(1+'03_營運成本_OPEX'!$H$5:$H$34)^3)*'01_專案設定_Setup'!$B$30 -> -7556.7295 | G10: =-SUMPRODUCT(('03_營運成本_OPEX'!$I$5:$I$34="固定")*'03_營運成本_OPEX'!$G$5:$G$34*(1+'03_營運成本_OPEX'!$H$5:$H$34)^4)*'01_專案設定_Setup'!$B$30 -> -7992.6768 | H10: =-SUMPRODUCT(('03_營運成本_OPEX'!$I$5:$I$34="固定")*'03_營運成本_OPEX'!$G$5:$G$34*(1+'03_營運成本_OPEX'!$H$5:$H$34)^5)*'01_專案設定_Setup'!$B$30 -> -8456.2127 | I10: =-SUMPRODUCT(('03_營運成本_OPEX'!$I$5:$I$34="固定")*'03_營運成本_OPEX'!$G$5:$G$34*(1+'03_營運成本_OPEX'!$H$5:$H$34)^6)*'01_專案設定_Setup'!$B$30 -> -8949.2109 | J10: =-SUMPRODUCT(('03_營運成本_OPEX'!$I$5:$I$34="固定")*'03_營運成本_OPEX'!$G$5:$G$34*(1+'03_營運成本_OPEX'!$H$5:$H$34)^7)*'01_專案設定_Setup'!$B$30 -> -9473.6793 | K10: =-SUMPRODUCT(('03_營運成本_OPEX'!$I$5:$I$34="固定")*'03_營運成本_OPEX'!$G$5:$G$34*(1+'03_營運成本_OPEX'!$H$5:$H$34)^8)*'01_專案設定_Setup'!$B$30 -> -10031.77 | L10: =-SUMPRODUCT(('03_營運成本_OPEX'!$I$5:$I$34="固定")*'03_營運成本_OPEX'!$G$5:$G$34*(1+'03_營運成本_OPEX'!$H$5:$H$34)^9)*'01_專案設定_Setup'!$B$30 -> -10625.788
A11: 營運成本合計 Total OPEX | B11: 0 | C11: =C9+C10 -> -6526.7 | D11: =D9+D10 -> -7020.1698 | E11: =E9+E10 -> -7517.1158 | F11: =F9+F10 -> -7953.5289 | G11: =G9+G10 -> -8417.6489 | H11: =H9+H10 -> -8911.3578 | I11: =I9+I10 -> -9436.6713 | J11: =J9+J10 -> -9995.7494 | ... L11: =L9+L10 -> -11224.624
A12: EBITDA | B12: 0 | C12: =C8+C11 -> -2139.5 | D12: =D8+D11 -> 1622.0658 | E12: =E8+E11 -> 4588.9278 | F12: =F8+F11 -> 4765.0806 | G12: =G8+G11 -> 4944.5221 | H12: =H8+H11 -> 5126.9392 | I12: =I8+I11 -> 5311.9635 | J12: =J8+J11 -> 5499.1663 | ... L12: =L8+L11 -> 5878.0496
A13: EBITDA 利潤率 | C13: =IFERROR(C12/C8,"") -> -0.48766867 | D13: =IFERROR(D12/D8,"") -> 0.18769054 | E13: =IFERROR(E12/E8,"") -> 0.3790609 | F13: =IFERROR(F12/F8,"") -> 0.37465421 | G13: =IFERROR(G12/G8,"") -> 0.37003883 | H13: =IFERROR(H12/H8,"") -> 0.36521091 | I13: =IFERROR(I12/I8,"") -> 0.36016645 | J13: =IFERROR(J12/J8,"") -> 0.35490134 | ... L13: =IFERROR(L12/L8,"") -> 0.34369185
A14: 折舊攤提 D&A | B14: 0 | C14: =-'05_折舊攤提_Depreciation'!G$63 -> -5326.0116 | D14: =-'05_折舊攤提_Depreciation'!H$63 -> -5326.0116 | E14: =-'05_折舊攤提_Depreciation'!I$63 -> -5326.0116 | F14: =-'05_折舊攤提_Depreciation'!J$63 -> -5326.0116 | G14: =-'05_折舊攤提_Depreciation'!K$63 -> -5567.6156 | H14: =-'05_折舊攤提_Depreciation'!L$63 -> -835.6656 | I14: =-'05_折舊攤提_Depreciation'!M$63 -> -835.6656 | J14: =-'05_折舊攤提_Depreciation'!N$63 -> -835.6656 | ... L14: =-'05_折舊攤提_Depreciation'!P$63 -> -594.0616
A15: EBIT 營業利益 | B15: 0 | C15: =C12+C14 -> -7465.5116 | D15: =D12+D14 -> -3703.9457 | E15: =E12+E14 -> -737.08379 | F15: =F12+F14 -> -560.93103 | G15: =G12+G14 -> -623.09346 | H15: =H12+H14 -> 4291.2736 | I15: =I12+I14 -> 4476.2979 | J15: =J12+J14 -> 4663.5007 | ... L15: =L12+L14 -> 5283.988
A17: B. 所得稅 Income tax（含越南免稅期與虧損扣抵）
A18: 本期虧損產生 Loss generated | B18: 0 | C18: =MAX(0,-C15) -> 7465.5116 | D18: =MAX(0,-D15) -> 3703.9457 | E18: =MAX(0,-E15) -> 737.08379 | F18: =MAX(0,-F15) -> 560.93103 | G18: =MAX(0,-G15) -> 623.09346 | H18: =MAX(0,-H15) -> 0 | I18: =MAX(0,-I15) -> 0 | J18: =MAX(0,-J15) -> 0 | ... L18: =MAX(0,-L15) -> 0
A19: 可用虧損扣抵餘額（5 年內） | B19: 0 | C19: =0 -> 0 | D19: =MAX(0,SUM(C18:C18)-SUM(C20:C20)) -> 7465.5116 | E19: =MAX(0,SUM(C18:D18)-SUM(C20:D20)) -> 11169.457 | F19: =MAX(0,SUM(C18:E18)-SUM(C20:E20)) -> 11906.541 | G19: =MAX(0,SUM(C18:F18)-SUM(C20:F20)) -> 12467.472 | H19: =MAX(0,SUM(C18:G18)-SUM(C20:G20)) -> 13090.566 | I19: =MAX(0,SUM(D18:H18)-SUM(D20:H20)) -> 5625.054 | J19: =MAX(0,SUM(E18:I18)-SUM(E20:I20)) -> 1921.1083 | K19: =MAX(0,SUM(F18:J18)-SUM(F20:J20)) -> 0 | L19: =MAX(0,SUM(G18:K18)-SUM(G20:K20)) -> 0
A20: 本期使用虧損扣抵 Loss utilised | B20: 0 | C20: =IF(C24=0,0,MIN(C19,MAX(0,C15))) -> 0 | D20: =IF(D24=0,0,MIN(D19,MAX(0,D15))) -> 0 | E20: =IF(E24=0,0,MIN(E19,MAX(0,E15))) -> 0 | F20: =IF(F24=0,0,MIN(F19,MAX(0,F15))) -> 0 | G20: =IF(G24=0,0,MIN(G19,MAX(0,G15))) -> 0 | H20: =IF(H24=0,0,MIN(H19,MAX(0,H15))) -> 0 | I20: =IF(I24=0,0,MIN(I19,MAX(0,I15))) -> 0 | J20: =IF(J24=0,0,MIN(J19,MAX(0,J15))) -> 1921.1083 | ... L20: =IF(L24=0,0,MIN(L19,MAX(0,L15))) -> 0
A21: 課稅所得 Taxable income | B21: 0 | C21: =MAX(0,C15-C20) -> 0 | D21: =MAX(0,D15-D20) -> 0 | E21: =MAX(0,E15-E20) -> 0 | F21: =MAX(0,F15-F20) -> 0 | G21: =MAX(0,G15-G20) -> 0 | H21: =MAX(0,H15-H20) -> 4291.2736 | I21: =MAX(0,I15-I20) -> 4476.2979 | J21: =MAX(0,J15-J20) -> 2742.3924 | ... L21: =MAX(0,L15-L20) -> 5283.988
A22: 首次獲利年 First profitable year | B22: =IFERROR(MATCH(TRUE(),INDEX(C15:L15>0,0),0),99) -> 6 | D22: 免稅期自「首次從受優惠活動獲利」起算；但若產生營收後 3 年內未獲利，則自營運第 4 年起強制起算（PwC）。
A23: 免稅起算年 Holiday start year | B23: =MIN($B$22,1+'01_專案設定_Setup'!$B$41) -> 4
A24: 適用稅率 Effective tax rate | B24: 0 | C24: =IF(1<$B$23,0,IF(1<=$B$23+'01_專案設定_Setup'!$B$39-1,0,IF(1<=$B$23+'01_專案設定_Setup'!$B$39+'01_專案設定_Setup'!$B$40-1,'01_專案設定_Setup'!$B$38*0.5,'01_專案設定_Setup'!$B$38))) -> 0 | D24: =IF(2<$B$23,0,IF(2<=$B$23+'01_專案設定_Setup'!$B$39-1,0,IF(2<=$B$23+'01_專案設定_Setup'!$B$39+'01_專案設定_Setup'!$B$40-1,'01_專案設定_Setup'!$B$38*0.5,'01_專案設定_Setup'!$B$38))) -> 0 | E24: =IF(3<$B$23,0,IF(3<=$B$23+'01_專案設定_Setup'!$B$39-1,0,IF(3<=$B$23+'01_專案設定_Setup'!$B$39+'01_專案設定_Setup'!$B$40-1,'01_專案設定_Setup'!$B$38*0.5,'01_專案設定_Setup'!$B$38))) -> 0 | F24: =IF(4<$B$23,0,IF(4<=$B$23+'01_專案設定_Setup'!$B$39-1,0,IF(4<=$B$23+'01_專案設定_Setup'!$B$39+'01_專案設定_Setup'!$B$40-1,'01_專案設定_Setup'!$B$38*0.5,'01_專案設定_Setup'!$B$38))) -> 0 | G24: =IF(5<$B$23,0,IF(5<=$B$23+'01_專案設定_Setup'!$B$39-1,0,IF(5<=$B$23+'01_專案設定_Setup'!$B$39+'01_專案設定_Setup'!$B$40-1,'01_專案設定_Setup'!$B$38*0.5,'01_專案設定_Setup'!$B$38))) -> 0 | H24: =IF(6<$B$23,0,IF(6<=$B$23+'01_專案設定_Setup'!$B$39-1,0,IF(6<=$B$23+'01_專案設定_Setup'!$B$39+'01_專案設定_Setup'!$B$40-1,'01_專案設定_Setup'!$B$38*0.5,'01_專案設定_Setup'!$B$38))) -> 0 | I24: =IF(7<$B$23,0,IF(7<=$B$23+'01_專案設定_Setup'!$B$39-1,0,IF(7<=$B$23+'01_專案設定_Setup'!$B$39+'01_專案設定_Setup'!$B$40-1,'01_專案設定_Setup'!$B$38*0.5,'01_專案設定_Setup'!$B$38))) -> 0 | J24: =IF(8<$B$23,0,IF(8<=$B$23+'01_專案設定_Setup'!$B$39-1,0,IF(8<=$B$23+'01_專案設定_Setup'!$B$39+'01_專案設定_Setup'!$B$40-1,'01_專案設定_Setup'!$B$38*0.5,'01_專案設定_Setup'!$B$38))) -> 0.05 | K24: =IF(9<$B$23,0,IF(9<=$B$23+'01_專案設定_Setup'!$B$39-1,0,IF(9<=$B$23+'01_專案設定_Setup'!$B$39+'01_專案設定_Setup'!$B$40-1,'01_專案設定_Setup'!$B$38*0.5,'01_專案設定_Setup'!$B$38))) -> 0.05 | L24: =IF(10<$B$23,0,IF(10<=$B$23+'01_專案設定_Setup'!$B$39-1,0,IF(10<=$B$23+'01_專案設定_Setup'!$B$39+'01_專案設定_Setup'!$B$40-1,'01_專案設定_Setup'!$B$38*0.5,'01_專案設定_Setup'!$B$38))) -> 0.05
A25: 所得稅 Income tax | B25: 0 | C25: =-C21*C24 -> 0 | D25: =-D21*D24 -> 0 | E25: =-E21*E24 -> 0 | F25: =-F21*F24 -> 0 | G25: =-G21*G24 -> 0 | H25: =-H21*H24 -> 0 | I25: =-I21*I24 -> 0 | J25: =-J21*J24 -> -137.11962 | ... L25: =-L21*L24 -> -264.1994
A26: NOPAT 稅後營業淨利 | B26: 0 | C26: =C15+C25 -> -7465.5116 | D26: =D15+D25 -> -3703.9457 | E26: =E15+E25 -> -737.08379 | F26: =F15+F25 -> -560.93103 | G26: =G15+G25 -> -623.09346 | H26: =H15+H25 -> 4291.2736 | I26: =I15+I25 -> 4476.2979 | J26: =J15+J25 -> 4526.3811 | ... L26: =L15+L25 -> 5019.7886
A28: C. 營運資金 Working capital
A29: 應收帳款 AR（健保／自費分開） | B29: 0 | C29: =C6*'01_專案設定_Setup'!$B$54/365+C7*'01_專案設定_Setup'!$B$55/365 -> 1081.7753 | D29: =D6*'01_專案設定_Setup'!$B$54/365+D7*'01_專案設定_Setup'!$B$55/365 -> 2130.9622 | E29: =E6*'01_專案設定_Setup'!$B$54/365+E7*'01_專案設定_Setup'!$B$55/365 -> 2985.0519 | F29: =F6*'01_專案設定_Setup'!$B$54/365+F7*'01_專案設定_Setup'!$B$55/365 -> 3136.0955 | G29: =G6*'01_專案設定_Setup'!$B$54/365+G7*'01_專案設定_Setup'!$B$55/365 -> 3294.7819 | H29: =H6*'01_專案設定_Setup'!$B$54/365+H7*'01_專案設定_Setup'!$B$55/365 -> 3461.4979 | I29: =I6*'01_專案設定_Setup'!$B$54/365+I7*'01_專案設定_Setup'!$B$55/365 -> 3636.6497 | J29: =J6*'01_專案設定_Setup'!$B$54/365+J7*'01_專案設定_Setup'!$B$55/365 -> 3820.6641 | ... L29: =L6*'01_專案設定_Setup'!$B$54/365+L7*'01_專案設定_Setup'!$B$55/365 -> 4217.0976
A30: 耗材存貨 Inventory | B30: 0 | C30: =-C9*'01_專案設定_Setup'!$B$56/365 -> 0 | D30: =-D9*'01_專案設定_Setup'!$B$56/365 -> 0 | E30: =-E9*'01_專案設定_Setup'!$B$56/365 -> 0 | F30: =-F9*'01_專案設定_Setup'!$B$56/365 -> 0 | G30: =-G9*'01_專案設定_Setup'!$B$56/365 -> 0 | H30: =-H9*'01_專案設定_Setup'!$B$56/365 -> 0 | I30: =-I9*'01_專案設定_Setup'!$B$56/365 -> 0 | J30: =-J9*'01_專案設定_Setup'!$B$56/365 -> 0 | ... L30: =-L9*'01_專案設定_Setup'!$B$56/365 -> 0
A31: 應付帳款 AP | B31: 0 | C31: =C11*'01_專案設定_Setup'!$B$57/365 -> -804.66164 | D31: =D11*'01_專案設定_Setup'!$B$57/365 -> -865.50038 | E31: =E11*'01_專案設定_Setup'!$B$57/365 -> -926.7677 | F31: =F11*'01_專案設定_Setup'!$B$57/365 -> -980.57205 | G31: =G11*'01_專案設定_Setup'!$B$57/365 -> -1037.7923 | H31: =H11*'01_專案設定_Setup'!$B$57/365 -> -1098.6605 | I31: =I11*'01_專案設定_Setup'!$B$57/365 -> -1163.4252 | J31: =J11*'01_專案設定_Setup'!$B$57/365 -> -1232.3527 | ... L31: =L11*'01_專案設定_Setup'!$B$57/365 -> -1383.8578
A32: 營運資金淨額 NWC | B32: 0 | C32: =C29+C30+C31 -> 277.1137 | D32: =D29+D30+D31 -> 1265.4618 | E32: =E29+E30+E31 -> 2058.2841 | F32: =F29+F30+F31 -> 2155.5234 | G32: =G29+G30+G31 -> 2256.9896 | H32: =H29+H30+H31 -> 2362.8373 | I32: =I29+I30+I31 -> 2473.2244 | J32: =J29+J30+J31 -> 2588.3115 | ... L32: =L29+L30+L31 -> 2833.2399
A33: 營運資金變動 ΔNWC | B33: 0 | C33: =C32-$B$32 -> 277.1137 | D33: =D32-C32 -> 988.34812 | E33: =E32-D32 -> 792.82233 | F33: =F32-E32 -> 97.239276 | G33: =G32-F32 -> 101.46615 | H33: =H32-G32 -> 105.84775 | I33: =I32-H32 -> 110.38711 | J33: =J32-I32 -> 115.08703 | K33: =K32-J32 -> 119.95004 | L33: =L32-K32 -> 124.97834
A35: D. 自由現金流 Free Cash Flow to Firm
A36: ＋ 折舊攤提（非現金加回） | B36: 0 | C36: =-C14 -> 5326.0116 | D36: =-D14 -> 5326.0116 | E36: =-E14 -> 5326.0116 | F36: =-F14 -> 5326.0116 | G36: =-G14 -> 5567.6156 | H36: =-H14 -> 835.6656 | I36: =-I14 -> 835.6656 | J36: =-J14 -> 835.6656 | ... L36: =-L14 -> 594.0616
A37: − 資本支出 CapEx | B37: =-'05_折舊攤提_Depreciation'!$F$69 -> -41019.602 | C37: =-'05_折舊攤提_Depreciation'!G$69 -> 0 | D37: =-'05_折舊攤提_Depreciation'!H$69 -> 0 | E37: =-'05_折舊攤提_Depreciation'!I$69 -> 0 | F37: =-'05_折舊攤提_Depreciation'!J$69 -> 0 | G37: =-'05_折舊攤提_Depreciation'!K$69 -> -1208.02 | H37: =-'05_折舊攤提_Depreciation'!L$69 -> -3126.64 | I37: =-'05_折舊攤提_Depreciation'!M$69 -> 0 | J37: =-'05_折舊攤提_Depreciation'!N$69 -> 0 | ... L37: =-'05_折舊攤提_Depreciation'!P$69 -> 0
A38: − 營運資金變動 | B38: 0 | C38: =-C33 -> -277.1137 | D38: =-D33 -> -988.34812 | E38: =-E33 -> -792.82233 | F38: =-F33 -> -97.239276 | G38: =-G33 -> -101.46615 | H38: =-H33 -> -105.84775 | I38: =-I33 -> -110.38711 | J38: =-J33 -> -115.08703 | ... L38: =-L33 -> -124.97834
A39: ＋ 期末殘值回收 Salvage | B39: 0 | C39: =0 -> 0 | D39: =0 -> 0 | E39: =0 -> 0 | F39: =0 -> 0 | G39: =0 -> 0 | H39: =0 -> 0 | I39: =0 -> 0 | J39: =0 -> 0 | K39: =0 -> 0 | L39: ='05_折舊攤提_Depreciation'!$F$71 -> 156.332
A40: 自由現金流 FCFF | B40: =$B$37 -> -41019.602 | C40: =C26+C36+C37+C38+C39 -> -2416.6137 | D40: =D26+D36+D37+D38+D39 -> 633.71773 | E40: =E26+E36+E37+E38+E39 -> 3796.1055 | F40: =F26+F36+F37+F38+F39 -> 4667.8413 | G40: =G26+G36+G37+G38+G39 -> 3635.036 | H40: =H26+H36+H37+H38+H39 -> 1894.4514 | I40: =I26+I36+I37+I38+I39 -> 5201.5764 | J40: =J26+J36+J37+J38+J39 -> 5246.9596 | ... L40: =L26+L36+L37+L38+L39 -> 5645.2038
A41: 折現因子 Discount factor | B41: 1 | C41: =1/(1+'01_專案設定_Setup'!$B$48)^1 -> 0.89289942 | D41: =1/(1+'01_專案設定_Setup'!$B$48)^2 -> 0.79726937 | E41: =1/(1+'01_專案設定_Setup'!$B$48)^3 -> 0.71188136 | F41: =1/(1+'01_專案設定_Setup'!$B$48)^4 -> 0.63563845 | G41: =1/(1+'01_專案設定_Setup'!$B$48)^5 -> 0.5675612 | H41: =1/(1+'01_專案設定_Setup'!$B$48)^6 -> 0.50677507 | I41: =1/(1+'01_專案設定_Setup'!$B$48)^7 -> 0.45249917 | J41: =1/(1+'01_專案設定_Setup'!$B$48)^8 -> 0.40403624 | K41: =1/(1+'01_專案設定_Setup'!$B$48)^9 -> 0.36076373 | L41: =1/(1+'01_專案設定_Setup'!$B$48)^10 -> 0.32212572
A42: 折現現金流 Discounted FCF | B42: =$B$40*$B$41 -> -41019.602 | C42: =C40*C41 -> -2157.793 | D42: =D40*D41 -> 505.24373 | E42: =E40*E41 -> 2702.3767 | F42: =F40*F41 -> 2967.0594 | G42: =G40*G41 -> 2063.1054 | H42: =H40*H41 -> 960.06075 | I42: =I40*I41 -> 2353.709 | J42: =J40*J41 -> 2119.9619 | ... L42: =L40*L41 -> 1818.4654
A43: 累計折現現金流 Cumulative | B43: =$B$42 -> -41019.602 | C43: =$B$43+C42 -> -43177.395 | D43: =C43+D42 -> -42672.151 | E43: =D43+E42 -> -39969.775 | F43: =E43+F42 -> -37002.715 | G43: =F43+G42 -> -34939.61 | H43: =G43+H42 -> -33979.549 | I43: =H43+I42 -> -31625.84 | J43: =I43+J42 -> -29505.878 | K43: =J43+K42 -> -27584.637 | L43: =K43+L42 -> -25766.172
A45: E. 投資指標 Investment metrics
A46: NPV 淨現值 | B46: =SUM($B$42:L$42) -> -25766.172 | C46: 所有年度折現現金流的總和。＞0 代表在此折現率下創造價值。
A47: IRR 內部報酬率 | B47: =IFERROR(IRR($B$40:L$40),"n/a") -> -0.027121388 | C47: 使 NPV＝0 的折現率。★ 當現金流正負交替（例如中途有大額置換投資）時 IRR 可能有多重解，請以 MIRR 為準。
A48: ★ MIRR 修正內部報酬率 | B48: =IFERROR(MIRR($B$40:L$40,'01_專案設定_Setup'!$B$48,'01_專案設定_Setup'!$B$49),"n/a") -> 0.008677402 | C48: ★ 主要報酬指標。IRR 隱含假設期中現金流以 IRR 本身再投資（不現實）；MIRR 改用你在 01 指定的再投資率，且對任何現金流序列都只有單一解。
A49: PI 獲利指數 | B49: =IFERROR(SUM(C$42:L$42)/-$B$40,"n/a") -> 0.3718571 | C49: ＝營運期折現現金流現值 ÷ 初始投資。＞1 即可接受。資本受限、要在多案之間排序時用這個指標。
A50: 折現回收期（年） | B50: =IFERROR(MATCH(TRUE(),INDEX(C$43:L$43>=0,0),0)-1+(-INDEX(C$43:L$43,MATCH(TRUE(),INDEX(C$43:L$43>=0,0),0)-1))/INDEX(C$42:L$42,MATCH(TRUE(),INDEX(C$43:L$43>=0,0),0)),"未回收") -> 未回收 | C50: 折現後的累計現金流轉正所需年數。
A51: 簡單回收期（年） | B51: =IFERROR(MATCH(TRUE(),INDEX(C$40:L$40>0,0),0),"n/a") -> 2 | C51: 不折現的粗略參考值。
A52: ROIC 投入資本報酬率 | B52: =IFERROR(AVERAGE(C$26:L$26)/'02_投資成本_CAPEX'!$Q$64,"n/a") -> 0.023971325 | C52: ＝平均 NOPAT ÷ 投入資本。★ 判讀方式：與 WACC 比較——高於 WACC 才是真正在創造價值。
A53: 滿載年 EBITDA 利潤率 | B53: =IFERROR(L$12/L$8,"n/a") -> 0.34369185 | C53: 第 10 年的 EBITDA ÷ 營收。
A54: 十年累計 FCFF | B54: =SUM($B$40:L$40) -> -7389.8416 | C54: 不折現的十年淨現金流總額。
A56: ★ 為什麼本檔以 MIRR 為主要報酬指標：本模型允許每一個 CAPEX 分項設定「置換年」——UPS 電池第 6 年、伺服器第 6 年、球管第 5 年——這使得現金流序列在正負之間交替，正是會讓 IRR 出現多重解的型態。Corporate Finance Institute 明述：「MIRR 對任何現金流序列都得到單一解，而 IRR 對正負交替的序列可能有兩個解。」

Sheet 07_折現率_WACC
A1: 07 折現率｜WACC（加權平均資金成本）
A2: 折現率是整個模型影響最大的單一假設，不該隨手填。本頁用 CAPM 推算：股權成本 ＝ 無風險利率 ＋ β×成熟市場風險溢酬 ＋ 國家風險溢酬，再與稅後債務成本加權。★ 若要改用手動輸入，請到 01 分頁把「折現率來源」改成「手動輸入」。
A4: A. 無風險利率與風險溢酬（Damodaran, 2026 年 1 月）
A5: 無風險利率 Rf | B5: 0.0454 | D5: 越南 10 年期公債殖利率（tradingeconomics.com，2026-08-12）。以越南公債為基準代表本模型是「越盾名目」計價。
A6: 成熟市場風險溢酬 ERP | B6: 0.0423 | D6: Damodaran 2026-01-01：由 S&P 500 隱含 ERP 扣除美國自身違約價差 0.23% 後得出（pages.stern.nyu.edu）。
A7: 越南國家風險溢酬 CRP | B7: 0.039 | D7: Damodaran 2026-01-05：越南評等 Ba2、調整後違約價差 2.56%，再依股票相對債券的波動度放大約 1.52 倍得出（pages.stern.nyu.edu）。
A8: （參考）越南主權評等 | B8: Ba2 (Moody's) | D8: 越南股權風險溢酬合計 ＝ 4.23% ＋ 3.90% ＝ 8.13%（Damodaran 資料表）
A9: （參考）越南調整後違約價差 | B9: 0.0256
A11: B. 產業 Beta（Damodaran 產業資料，2026 年 1 月）
A12: 產業別 Industry | B12: Computer Services (βu 0.92) | D12: ★ 資料中心無獨立產業分類。實務上以 R.E.I.T.（βu 0.39，反映長約穩定現金流）與 Computer Services（βu 0.92，反映營運型服務）為區間上下界，依「長約 vs 零售」比重內插。
A13: 無槓桿 Beta βu | B13: 0.92 | D13: 醫院／醫療機構 0.55（D/E 59.92%）；醫材產品 0.83；資訊服務 0.74；電腦服務 0.92；REIT 0.39。★ 為 Damodaran 美國樣本；用於越南專案時建議另取新興市場版校正。
A14: 目標負債／權益 D/E | B14: 0.4 | D14: 本專案的目標資本結構。
A15: 適用稅率 t | B15: ='01_專案設定_Setup'!$B$38 -> 0.1 | D15: 由 01 分頁帶入（社會化醫療優惠稅率）
A16: 有槓桿 Beta βL | B16: =$B$13*(1+(1-$B$15)*$B$14) -> 1.2512 | D16: Hamada 公式：βL ＝ βu × [1 ＋ (1−t) × D/E]
A18: C. 資本成本
A19: 股權成本 Ke | B19: =$B$5+$B$16*$B$6+$B$7 -> 0.13732576 | D19: CAPM ＋ 國家風險溢酬（Damodaran 2026 採「加法」而非 lambda 乘數法）
A20: 債務成本 Kd（稅前） | B20: 0.085 | D20: 越南本地企業借款利率，或無風險利率＋本案信用價差。須以實際 term sheet 為準。
A21: 稅後債務成本 Kd×(1−t) | B21: =$B$20*(1-$B$15) -> 0.0765 | D21: 利息可抵稅，故實際成本較低。★ 這也是為何 FCFF 的稅要用 EBIT×t，否則稅盾會被重複計算。
A22: 權益比重 E/(D+E) | B22: =1/(1+$B$14) -> 0.71428571 | D22: 由 D/E 推得
A23: 負債比重 D/(D+E) | B23: =$B$14/(1+$B$14) -> 0.28571429 | D23: 由 D/E 推得
A25: D. 加權平均資金成本
A26: WACC（越盾名目） | B26: =$B$22*$B$19+$B$23*$B$21 -> 0.11994697 | D26: ＝ E權重×Ke ＋ D權重×稅後Kd。本模型的營收成長率是越盾名目成長，故對應的折現率也應為越盾名目。
A27: （參考）美元等值 WACC | B27: =(1+$B$26)*(1+0.025)/(1+0.04)-1 -> 0.10379389 | D27: 依 Damodaran 的一致性原則換算：(1+r_USD) ＝ (1+r_VND) × (1+美國通膨) ÷ (1+越南通膨)。假設越南長期通膨 4.0%、美國 2.5%。★ 僅供對照——若要改用美元建模，現金流的成長率也必須同步改為美元名目，否則就犯了「現金流與折現率通膨假設不一致」的錯誤。
A28: ★ 本模型採用的折現率 | B28: =$B$26 -> 0.11994697 | D28: 01 分頁的「採用折現率」會抓這一格（除非你在 01 選了「手動輸入」）。★ 送投資決策前，這個數字必須與投資方書面確認——它比任何一筆成本估算都更能左右結論。
A30: E. 敏感度：WACC 每變動 1 個百分點，NPV 變動多少
A31: 折現率 | B31: −2pp | C31: −1pp | D31: 基準 | E31: ＋1pp | F31: ＋2pp
A32: 折現率值 | B32: ='01_專案設定_Setup'!$B$48+-0.02 -> 0.099946971 | C32: ='01_專案設定_Setup'!$B$48+-0.01 -> 0.10994697 | D32: ='01_專案設定_Setup'!$B$48+0 -> 0.11994697 | E32: ='01_專案設定_Setup'!$B$48+0.01 -> 0.12994697 | F32: ='01_專案設定_Setup'!$B$48+0.02 -> 0.13994697
A33: 對應 NPV | B33: =NPV('01_專案設定_Setup'!$B$48+-0.02,'06_現金流_Cashflow'!C$40:L$40)+'06_現金流_Cashflow'!$B$40 -> -23768.41 | C33: =NPV('01_專案設定_Setup'!$B$48+-0.01,'06_現金流_Cashflow'!C$40:L$40)+'06_現金流_Cashflow'!$B$40 -> -24804.309 | D33: =NPV('01_專案設定_Setup'!$B$48+0,'06_現金流_Cashflow'!C$40:L$40)+'06_現金流_Cashflow'!$B$40 -> -25766.172 | E33: =NPV('01_專案設定_Setup'!$B$48+0.01,'06_現金流_Cashflow'!C$40:L$40)+'06_現金流_Cashflow'!$B$40 -> -26660.211 | F33: =NPV('01_專案設定_Setup'!$B$48+0.02,'06_現金流_Cashflow'!C$40:L$40)+'06_現金流_Cashflow'!$B$40 -> -27492.048
A35: ★ 判讀：如果「＋1pp」那一格就讓 NPV 轉負，代表本案對折現率極度敏感，在跟投資方談之前務必先把折現率的口徑談定，否則同一份模型會得到相反的結論。

Sheet 08_敏感度_Sensitivity
A1: 08 敏感度分析｜Scenarios, Tornado & Breakeven
A2: 全公式。三個區塊回答三個不同的問題：情境分析＝「如果整個世界比預期差，會怎樣」；龍捲風圖＝「哪一個變數最致命，該優先去查證或談判」；損益兩平＝「至少要做到多少才不虧」。★ 龍捲風圖應在跑任何複雜模擬之前先做——它告訴你該把查證力氣花在哪裡。
A4: A. 計算基礎（自動由 06 現金流彙總）
A5: 基準 NPV | B5: ='06_現金流_Cashflow'!$B$46 -> -25766.172
A6: 基準 MIRR | B6: ='06_現金流_Cashflow'!$B$48 -> 0.008677402
A7: 基準 PI | B7: ='06_現金流_Cashflow'!$B$49 -> 0.3718571
A8: 折現後營收現值 | B8: =SUMPRODUCT('06_現金流_Cashflow'!C$8:L$8,'06_現金流_Cashflow'!C$41:L$41) -> 66524.452
A9: 折現後變動成本現值 | B9: =-SUMPRODUCT('06_現金流_Cashflow'!C$9:L$9,'06_現金流_Cashflow'!C$41:L$41) -> 2136.1641
A10: 折現後固定成本現值 | B10: =-SUMPRODUCT('06_現金流_Cashflow'!C$10:L$10,'06_現金流_Cashflow'!C$41:L$41) -> 44734.223
A11: 資本支出現值 | B11: ='02_投資成本_CAPEX'!$Q$64 -> 41019.602
A12: 平均適用稅率 | B12: =AVERAGE('06_現金流_Cashflow'!C$24:L$24) -> 0.015
A14: B. 情境分析 Scenario analysis
A15: 情境 | B15: 服務量 | C15: 單價 | D15: 營運成本 | E15: 資本支出 | F15: 折現率 | G15: NPV | H15: 相對基準 | I15: 說明
A16: 保守 Downside | B16: -0.15 | C16: -0.1 | D16: 0.1 | E16: 0.1 | F16: 0.01 | G16: =$B$5+$B$8*((1+$B16)*(1+$C16)-1)*(1-$B$12)-$B$9*$B16*(1-$B$12)-($B$9+$B$10)*$D16*(1-$B$12)-$B$11*$E16+(NPV('01_專案設定_Setup'!$B$48+$F16,'06_現金流_Cashflow'!C$40:L$40)+'06_現金流_Cashflow'!$B$40-$B$5) -> -50462.034 | H16: =$G16-$B$5 -> -24695.862 | I16: 量少一成半、價低一成、成本高一成、折現率高 1pp
A17: 基準 Base | B17: 0 | C17: 0 | D17: 0 | E17: 0 | F17: 0 | G17: =$B$5+$B$8*((1+$B17)*(1+$C17)-1)*(1-$B$12)-$B$9*$B17*(1-$B$12)-($B$9+$B$10)*$D17*(1-$B$12)-$B$11*$E17+(NPV('01_專案設定_Setup'!$B$48+$F17,'06_現金流_Cashflow'!C$40:L$40)+'06_現金流_Cashflow'!$B$40-$B$5) -> -25766.172 | H17: =$G17-$B$5 -> 0 | I17: 01–04 分頁目前的假設
A18: 樂觀 Upside | B18: 0.15 | C18: 0.05 | D18: -0.05 | E18: -0.05 | F18: -0.01 | G18: =$B$5+$B$8*((1+$B18)*(1+$C18)-1)*(1-$B$12)-$B$9*$B18*(1-$B$12)-($B$9+$B$10)*$D18*(1-$B$12)-$B$11*$E18+(NPV('01_專案設定_Setup'!$B$48+$F18,'06_現金流_Cashflow'!C$40:L$40)+'06_現金流_Cashflow'!$B$40-$B$5) -> -7163.8137 | H18: =$G18-$B$5 -> 18602.358 | I18: 量多一成半、價高 5%、成本低 5%、折現率低 1pp
A20: C. 龍捲風圖 Tornado — 哪一個變數最致命
A21: 每次只變動一個變數（±15%，折現率為 ±1pp），其餘不變，看 NPV 的變動幅度，由大到小排序。長條最長的那一個，就是你該優先去查證、談判、或在合約裡設保護條款的變數。
A22: 變數 | B22: −15% 時的 NPV | C22: ＋15% 時的 NPV | D22: 影響幅度（絕對值） | E22: 排序 | F22: 判讀
A23: 服務量 Volume | B23: =$B$5+$B$8*(-0.15)*(1-$B$12)-$B$9*(-0.15)*(1-$B$12) -> -35279.541 | C23: =$B$5+$B$8*(0.15)*(1-$B$12)-$B$9*(0.15)*(1-$B$12) -> -16252.802 | D23: =ABS($C23-$B23) -> 19026.739 | E23: =RANK($D23,$D$23:$D$28,0) -> 2 | F23: 量的風險應該用合約保底量或收入分成下限來管理
A24: 單價 Price | B24: =$B$5+$B$8*(-0.15)*(1-$B$12) -> -35595.16 | C24: =$B$5+$B$8*(0.15)*(1-$B$12) -> -15937.184 | D24: =ABS($C24-$B24) -> 19657.976 | E24: =RANK($D24,$D$23:$D$28,0) -> 1 | F24: 價的風險來自公告費率調整與自費客層——查證健保費率與市場行情
A25: 營運成本 OPEX | B25: =$B$5+($B$9+$B$10)*(0.15)*(1-$B$12) -> -18841.072 | C25: =$B$5+-($B$9+$B$10)*(0.15)*(1-$B$12) -> -32691.272 | D25: =ABS($C25-$B25) -> 13850.199 | E25: =RANK($D25,$D$23:$D$28,0) -> 3 | F25: 用長約鎖定維保費率與人力成本，並注意越南薪資漲幅
A26: 資本支出 CAPEX | B26: =$B$5+$B$11*0.15 -> -19613.232 | C26: =$B$5+-$B$11*0.15 -> -31919.112 | D26: =ABS($C26-$B26) -> 12305.881 | E26: =RANK($D26,$D$23:$D$28,0) -> 4 | F26: 把示意值換成廠商正式報價就能大幅收斂這一項
A27: 折現率 WACC | B27: =$B$5+NPV('01_專案設定_Setup'!$B$48-0.01,'06_現金流_Cashflow'!C$40:L$40)+'06_現金流_Cashflow'!$B$40-$B$5 -> -24804.309 | C27: =$B$5+NPV('01_專案設定_Setup'!$B$48+0.01,'06_現金流_Cashflow'!C$40:L$40)+'06_現金流_Cashflow'!$B$40-$B$5 -> -26660.211 | D27: =ABS($C27-$B27) -> 1855.9026 | E27: =RANK($D27,$D$23:$D$28,0) -> 6 | F27: ★ 若這一項排在前段，代表結論高度依賴折現率口徑，務必先與投資方談定
A28: 自費比例 Mix | B28: =$B$5+$B$8*(-0.15)*(1-$B$12)*0.5 -> -30680.666 | C28: =$B$5+$B$8*(0.15)*(1-$B$12)*0.5 -> -20851.678 | D28: =ABS($C28-$B28) -> 9828.9878 | E28: =RANK($D28,$D$23:$D$28,0) -> 5 | F28: 自費占比往往比服務量更能決定獲利
A30: D. NPV 矩陣：服務量 × 單價（各 ±30%）
A31: 服務量＼單價 | B31: -30% | C31: -15% | D31: +0% | E31: +15% | F31: +30%
A32: -30% | B32: =$B$5+$B$8*((1+-0.3)*(1+-0.3)-1)*(1-$B$12)-$B$9*-0.3*(1-$B$12) -> -58553.494 | C32: =$B$5+$B$8*((1+-0.3)*(1+-0.15)-1)*(1-$B$12)-$B$9*-0.3*(1-$B$12) -> -51673.202 | D32: =$B$5+$B$8*((1+-0.3)*(1+0)-1)*(1-$B$12)-$B$9*-0.3*(1-$B$12) -> -44792.911 | E32: =$B$5+$B$8*((1+-0.3)*(1+0.15)-1)*(1-$B$12)-$B$9*-0.3*(1-$B$12) -> -37912.62 | F32: =$B$5+$B$8*((1+-0.3)*(1+0.3)-1)*(1-$B$12)-$B$9*-0.3*(1-$B$12) -> -31032.328
A33: -15% | B33: =$B$5+$B$8*((1+-0.15)*(1+-0.3)-1)*(1-$B$12)-$B$9*-0.15*(1-$B$12) -> -51988.821 | C33: =$B$5+$B$8*((1+-0.15)*(1+-0.15)-1)*(1-$B$12)-$B$9*-0.15*(1-$B$12) -> -43634.181 | D33: =$B$5+$B$8*((1+-0.15)*(1+0)-1)*(1-$B$12)-$B$9*-0.15*(1-$B$12) -> -35279.541 | E33: =$B$5+$B$8*((1+-0.15)*(1+0.15)-1)*(1-$B$12)-$B$9*-0.15*(1-$B$12) -> -26924.902 | F33: =$B$5+$B$8*((1+-0.15)*(1+0.3)-1)*(1-$B$12)-$B$9*-0.15*(1-$B$12) -> -18570.262
A34: +0% | B34: =$B$5+$B$8*((1+0)*(1+-0.3)-1)*(1-$B$12)-$B$9*0*(1-$B$12) -> -45424.148 | C34: =$B$5+$B$8*((1+0)*(1+-0.15)-1)*(1-$B$12)-$B$9*0*(1-$B$12) -> -35595.16 | D34: =$B$5+$B$8*((1+0)*(1+0)-1)*(1-$B$12)-$B$9*0*(1-$B$12) -> -25766.172 | E34: =$B$5+$B$8*((1+0)*(1+0.15)-1)*(1-$B$12)-$B$9*0*(1-$B$12) -> -15937.184 | F34: =$B$5+$B$8*((1+0)*(1+0.3)-1)*(1-$B$12)-$B$9*0*(1-$B$12) -> -6108.1963
A35: +15% | B35: =$B$5+$B$8*((1+0.15)*(1+-0.3)-1)*(1-$B$12)-$B$9*0.15*(1-$B$12) -> -38859.474 | C35: =$B$5+$B$8*((1+0.15)*(1+-0.15)-1)*(1-$B$12)-$B$9*0.15*(1-$B$12) -> -27556.138 | D35: =$B$5+$B$8*((1+0.15)*(1+0)-1)*(1-$B$12)-$B$9*0.15*(1-$B$12) -> -16252.802 | E35: =$B$5+$B$8*((1+0.15)*(1+0.15)-1)*(1-$B$12)-$B$9*0.15*(1-$B$12) -> -4949.4664 | F35: =$B$5+$B$8*((1+0.15)*(1+0.3)-1)*(1-$B$12)-$B$9*0.15*(1-$B$12) -> 6353.8695
A36: +30% | B36: =$B$5+$B$8*((1+0.3)*(1+-0.3)-1)*(1-$B$12)-$B$9*0.3*(1-$B$12) -> -32294.801 | C36: =$B$5+$B$8*((1+0.3)*(1+-0.15)-1)*(1-$B$12)-$B$9*0.3*(1-$B$12) -> -19517.117 | D36: =$B$5+$B$8*((1+0.3)*(1+0)-1)*(1-$B$12)-$B$9*0.3*(1-$B$12) -> -6739.4328 | E36: =$B$5+$B$8*((1+0.3)*(1+0.15)-1)*(1-$B$12)-$B$9*0.3*(1-$B$12) -> 6038.2513 | F36: =$B$5+$B$8*((1+0.3)*(1+0.3)-1)*(1-$B$12)-$B$9*0.3*(1-$B$12) -> 18815.935
A38: E. 損益兩平 Breakeven
A39: NPV＝0 所需的單價調整幅度 | B39: =IFERROR(-$B$5/($B$8*(1-$B$12)),"n/a") -> 0.39321707 | C39: 負值代表現在的單價已有這麼多的下跌空間；正值代表單價必須再漲這麼多本案才成立。
A40: NPV＝0 所需的服務量調整幅度 | B40: =IFERROR(-$B$5/(($B$8-$B$9)*(1-$B$12)),"n/a") -> 0.40626255 | C40: 負值代表量還有這麼多下跌空間；正值代表量必須再增加這麼多。
A41: EBITDA 損益兩平年服務量 | B41: =IFERROR('03_營運成本_OPEX'!$G$37*'01_專案設定_Setup'!$B$28/('04_收入產能_Revenue'!$B$13*'01_專案設定_Setup'!$B$28-'03_營運成本_OPEX'!$G$36*'01_專案設定_Setup'!$B$28/('04_收入產能_Revenue'!$B$5*'04_收入產能_Revenue'!$B$6)),"n/a") -> 3605.9183 | C41: ＝固定成本 ÷（加權單價 − 單位變動成本）。低於這個量，連折舊前的營運都是虧的。
A42: 相對於規劃滿載量的比例 | B42: =IFERROR($B41/('04_收入產能_Revenue'!$B$5*'04_收入產能_Revenue'!$B$6),"n/a") -> 0.60098638 | C42: ★ 這個比例若高於 70%，代表本案幾乎沒有容錯空間，開辦爬坡期會非常辛苦。

Sheet 09_使能型評估_EnablingCase
A1: 09 使能型投資評估｜Enabling Investment Case（自建 vs 外租 TCO・成本分攤・選擇權價值）
A2: ★ 只有 01 分頁的投資類別選「B 使能型投資」時才需要填這一頁。機房、網路、資料平台這類投資本身不對外收費，用單獨 NPV 評估必然為負——正確的評估方式是三件事：①「不做的話要花多少錢」（自建 vs 外租的十年 TCO 差額）；② 單位服務成本是否低於市場外購價；③ 它讓哪些後續專案得以成立（選擇權價值）。依據：Gartner TCO 差異法、TBM Council 成本分攤、Amram & Kulatilaka 實質選擇權。
A3: =IF(INDEX(_CatCode,MATCH('01_專案設定_Setup'!$B$9,_CatName,0))="DTCO","✔ 本案投資類別為「B 使能型投資」，本頁適用——10 決策摘要會以本頁的 ΔTCO 作為主要判讀依據。","⚠ 本案投資類別為「"&'01_專案設定_Setup'!$B$9&"」，本頁不適用，可略過。（若要改用使能型的評估方式，請到 01 分頁把投資類別改成「B 使能型投資」。）") -> ⚠ 本案投資類別為「F 策略布局型 Strategic / Option」，本頁不適用，可略過。（若要改用使能型的評估方式，請到 01 分頁把投資類別改成「B 使能型投資」。）
A4: A. 比較前提（兩個方案必須是同一個服務範圍，否則比較無效）
A5: 比較範圍 Scope | B5: （請填：兩方案共同涵蓋的服務範圍） | C5: ★ 最容易出錯的一格。兩個方案必須涵蓋完全相同的服務——如果自建方案含了院區網路而外租方案沒有，比較就沒有意義。
A6: 服務單位 Service unit | B6: 機櫃 | C6: 計價與分攤的單位。資料中心業界已從「空間計價」轉向「功率計價（kW）」，若對外議價建議同時列出 kW。
A7: 服務數量 Quantity | B7: 0 | C7: 例：24 機櫃、120 kW
A8: 折現率 | B8: ='01_專案設定_Setup'!$B$48 -> 0.11994697 | C8: 由 01 分頁帶入
A10: B. 方案一：自建（本案）— 十年總持有成本 TCO
A11: 項目 | B11: 第 1 年 | C11: 第 2 年 | D11: 第 3 年 | E11: 第 4 年 | F11: 第 5 年 | G11: 第 6 年 | H11: 第 7 年 | I11: 第 8 年 | J11: 第 9 年 | K11: 第 10 年 | L11: 十年現值 PV
A12: 建置與置換資本支出 CapEx | B12: ='05_折舊攤提_Depreciation'!G$68 -> 0 | C12: ='05_折舊攤提_Depreciation'!H$68 -> 0 | D12: ='05_折舊攤提_Depreciation'!I$68 -> 0 | E12: ='05_折舊攤提_Depreciation'!J$68 -> 0 | F12: ='05_折舊攤提_Depreciation'!K$68 -> 1208.02 | G12: ='05_折舊攤提_Depreciation'!L$68 -> 3126.64 | H12: ='05_折舊攤提_Depreciation'!M$68 -> 0 | I12: ='05_折舊攤提_Depreciation'!N$68 -> 0 | ... K12: ='05_折舊攤提_Depreciation'!P$68 -> 0 | L12: ='02_投資成本_CAPEX'!$Q$64+SUMPRODUCT(B12:K12,'06_現金流_Cashflow'!C$41:L$41) -> 43289.73
A13: 年度營運成本 OpEx | B13: =-'06_現金流_Cashflow'!C$11 -> 6526.7 | C13: =-'06_現金流_Cashflow'!D$11 -> 7020.1698 | D13: =-'06_現金流_Cashflow'!E$11 -> 7517.1158 | E13: =-'06_現金流_Cashflow'!F$11 -> 7953.5289 | F13: =-'06_現金流_Cashflow'!G$11 -> 8417.6489 | G13: =-'06_現金流_Cashflow'!H$11 -> 8911.3578 | H13: =-'06_現金流_Cashflow'!I$11 -> 9436.6713 | I13: =-'06_現金流_Cashflow'!J$11 -> 9995.7494 | ... K13: =-'06_現金流_Cashflow'!L$11 -> 11224.624 | L13: =SUMPRODUCT(B13:K13,'06_現金流_Cashflow'!C$41:L$41) -> 46870.387
A14: 自建十年 TCO（現值） | B14: =B12+B13 -> 6526.7 | C14: =C12+C13 -> 7020.1698 | D14: =D12+D13 -> 7517.1158 | E14: =E12+E13 -> 7953.5289 | F14: =F12+F13 -> 9625.6689 | G14: =G12+G13 -> 12037.998 | H14: =H12+H13 -> 9436.6713 | I14: =I12+I13 -> 9995.7494 | ... L14: =L12+L13 -> 90160.118
A16: C. 方案二：外租／委外 — 同範圍的十年總持有成本
A17: 外租單價（每單位每月・輸入幣別） | B17: 0 | C17: 市場行情。2026 年標準企業級 colocation 整櫃（42U，3–5kW，Tier 3）約 US$900–2,500／櫃／月；批發型（250–500kW）約 US$196／kW／月。越南在地：FPT 胡志明 42U 約 24.5m VND／月、Viettel 21U 約 16–18m VND／月。
A18: 外租單價年成長率 | B18: 0.03 | C18: 合約通常每 2–3 年檢討一次
A19: 一次性遷移／接續成本 | B19: 0 | C19: 搬遷、專線建置、資料移轉、平行運行期的雙重成本
A20: 外租方案的額外年成本 | B20: 0 | C20: ★ 常被漏掉：到外租機房的專線與備援線路、跨站延遲造成的效能損失、資料落地與稽核的額外合規成本、以及失去現場處置能力所需的到場服務合約。
A22: 項目 | B22: 第 1 年 | C22: 第 2 年 | D22: 第 3 年 | E22: 第 4 年 | F22: 第 5 年 | G22: 第 6 年 | H22: 第 7 年 | I22: 第 8 年 | J22: 第 9 年 | K22: 第 10 年 | L22: 十年現值 PV
A23: 外租租金 | B23: =$B$7*$B$17*12*(1+$B$18)^0*'01_專案設定_Setup'!$B$30 -> 0 | C23: =$B$7*$B$17*12*(1+$B$18)^1*'01_專案設定_Setup'!$B$30 -> 0 | D23: =$B$7*$B$17*12*(1+$B$18)^2*'01_專案設定_Setup'!$B$30 -> 0 | E23: =$B$7*$B$17*12*(1+$B$18)^3*'01_專案設定_Setup'!$B$30 -> 0 | F23: =$B$7*$B$17*12*(1+$B$18)^4*'01_專案設定_Setup'!$B$30 -> 0 | G23: =$B$7*$B$17*12*(1+$B$18)^5*'01_專案設定_Setup'!$B$30 -> 0 | H23: =$B$7*$B$17*12*(1+$B$18)^6*'01_專案設定_Setup'!$B$30 -> 0 | I23: =$B$7*$B$17*12*(1+$B$18)^7*'01_專案設定_Setup'!$B$30 -> 0 | J23: =$B$7*$B$17*12*(1+$B$18)^8*'01_專案設定_Setup'!$B$30 -> 0 | K23: =$B$7*$B$17*12*(1+$B$18)^9*'01_專案設定_Setup'!$B$30 -> 0 | L23: =SUMPRODUCT(B23:K23,'06_現金流_Cashflow'!C$41:L$41) -> 0
A24: 額外年成本（專線、合規、到場服務） | B24: =$B$20*(1+$B$18)^0*'01_專案設定_Setup'!$B$30 -> 0 | C24: =$B$20*(1+$B$18)^1*'01_專案設定_Setup'!$B$30 -> 0 | D24: =$B$20*(1+$B$18)^2*'01_專案設定_Setup'!$B$30 -> 0 | E24: =$B$20*(1+$B$18)^3*'01_專案設定_Setup'!$B$30 -> 0 | F24: =$B$20*(1+$B$18)^4*'01_專案設定_Setup'!$B$30 -> 0 | G24: =$B$20*(1+$B$18)^5*'01_專案設定_Setup'!$B$30 -> 0 | H24: =$B$20*(1+$B$18)^6*'01_專案設定_Setup'!$B$30 -> 0 | I24: =$B$20*(1+$B$18)^7*'01_專案設定_Setup'!$B$30 -> 0 | J24: =$B$20*(1+$B$18)^8*'01_專案設定_Setup'!$B$30 -> 0 | K24: =$B$20*(1+$B$18)^9*'01_專案設定_Setup'!$B$30 -> 0 | L24: =SUMPRODUCT(B24:K24,'06_現金流_Cashflow'!C$41:L$41) -> 0
A25: 外租十年 TCO（現值，含一次性遷移成本） | B25: =B23+B24+$B$19*'01_專案設定_Setup'!$B$30 -> 0 | C25: =C23+C24 -> 0 | D25: =D23+D24 -> 0 | E25: =E23+E24 -> 0 | F25: =F23+F24 -> 0 | G25: =G23+G24 -> 0 | H25: =H23+H24 -> 0 | I25: =I23+I24 -> 0 | J25: =J23+J24 -> 0 | K25: =K23+K24 -> 0 | L25: =L23+L24+$B$19*'01_專案設定_Setup'!$B$30 -> 0
A27: D. ΔTCO — 使能型投資的真正「淨現值」
A28: ★ ΔTCO 現值 ＝ 外租 − 自建 | B28: =L25-L14 -> -90160.118 | E28: ★ 正值＝自建比外租便宜，這個數字就是本案作為使能型投資的淨現值；負值＝不該自建，應該外租。這才是 Gartner TCO 框架所說的「比較基準情境與替代情境」——重點不在絕對金額，而在兩個方案的差額。
A29: ΔTCO 簡單回收期（年） | B29: =IFERROR('02_投資成本_CAPEX'!$Q$64/(B25-B13-B12),"未回收") -> -6.2848916 | E29: ＝自建的建置成本 ÷ 每年因自建而省下的現金。這是向業主說明使能型投資最直接的一句話：「這座機房幾年就把自己付掉了」。
A31: E. 單位服務成本（Chargeback rate — 內部轉撥計價的基礎）
A32: 自建：每單位每月成本 | B32: =IFERROR((L14/10/12)/$B$7,"n/a") -> n/a | E32: 把十年現值攤回每單位每月，這是你對院內或對其他專案「內部轉撥計價」的成本底線
A33: 外租：每單位每月價格 | B33: =IFERROR(($B$17*'01_專案設定_Setup'!$B$30)+(($B$20*'01_專案設定_Setup'!$B$30)/12/$B$7),"n/a") -> n/a | E33: 市場外購價（含額外成本分攤）
A34: 差額（外租 − 自建） | B34: =IFERROR($B$33-$B$32,"n/a") -> n/a | E34: ★ 正值代表自建的單位成本低於市場價——這是使能型投資最有說服力的一句話
A35: 自建成本相對市價 | B35: =IFERROR($B$32/$B$33,"n/a") -> n/a | E35: 低於 100% 即代表自建具成本優勢
A37: F. 承載專案與成本分攤（TBM Council：先 Showback 建立信任，再 Chargeback 實際入帳）
A38: 承載的專案／服務 | B38: 佔用容量 | C38: 分攤比例 | D38: 年分攤金額 | E38: 分攤方式 | F38: 說明
A39: （請填：本平台承載哪些專案） | B39: 0 | C39: =IFERROR($B39/SUM($B$39:$B$46),"") | D39: =IFERROR($C39*(L14/10),"") | E39: 直接分攤 Direct
C40: =IFERROR($B40/SUM($B$39:$B$46),"") | D40: =IFERROR($C40*(L14/10),"")
C41: =IFERROR($B41/SUM($B$39:$B$46),"") | D41: =IFERROR($C41*(L14/10),"")
C42: =IFERROR($B42/SUM($B$39:$B$46),"") | D42: =IFERROR($C42*(L14/10),"")
C43: =IFERROR($B43/SUM($B$39:$B$46),"") | D43: =IFERROR($C43*(L14/10),"")
C44: =IFERROR($B44/SUM($B$39:$B$46),"") | D44: =IFERROR($C44*(L14/10),"")
C45: =IFERROR($B45/SUM($B$39:$B$46),"") | D45: =IFERROR($C45*(L14/10),"")
C46: =IFERROR($B46/SUM($B$39:$B$46),"") | D46: =IFERROR($C46*(L14/10),"")
A47: 合計 | B47: =SUM($B$39:$B$46) -> 0 | C47: =SUM($C$39:$C$46) -> 0 | D47: =SUM($D$39:$D$46) -> 0
A48: ★ 承載專案數 | B48: =COUNTA($A$39:$A$46) -> 1 | C48: 使能型投資的通過條件之一是承載專案數 ≥ 2。只服務一個專案的「平台」，本質上是那個專案的成本，不是平台。
A50: G. 選擇權價值（Real option — 這個平台讓哪些未來的事情變得可能）
A51: Amram & Kulatilaka 指出平台投資內嵌四種選擇權：延後、分階段、放棄、★擴張。下表估算「擴張選擇權」：因為已經有這個平台，未來每一個新專案可以省下多少原本必須自己蓋的建置成本。★ 此欄位不計入 ΔTCO，也不應加進 NPV——它是決策時的補充證據，不是可入帳的效益。
A53: 未來可承載的專案 | B53: 若無此平台的 增量建置成本 | C53: 實現機率 | D53: 期望值 | E53: 說明
A54: （請填：因為有這個平台，未來哪些專案可以省下自建成本） | B54: 0 | C54: 0.5 | D54: =IFERROR($B54*$C54*'01_專案設定_Setup'!$B$30,"") -> 0
D55: =IFERROR($B55*$C55*'01_專案設定_Setup'!$B$30,"") -> 0
D56: =IFERROR($B56*$C56*'01_專案設定_Setup'!$B$30,"") -> 0
D57: =IFERROR($B57*$C57*'01_專案設定_Setup'!$B$30,"") -> 0
D58: =IFERROR($B58*$C58*'01_專案設定_Setup'!$B$30,"") -> 0
A59: 選擇權價值合計（期望值） | D59: =SUM($D$54:$D$58) -> 0
A61: H. 使能型投資結論
A62: =IF(L25=0,"⚠ 尚未填寫外租方案的比較資料——請先填 C 區塊，否則本頁無法給出結論。",IF($B$28<=0,"✕ 不建議自建：外租的十年總持有成本低於自建。應改採外租，把資本留給能直接產生收入的專案。",IF($B$48<2,"△ 條件不足：ΔTCO 為正，但目前只承載 "&$B$48&" 個專案。只服務單一專案的平台本質上是該專案的成本——建議先確認第 2 個承載專案，或把本案的建置成本併入該專案一起評估。","○ 建議自建：自建的十年總持有成本低於外租（ΔTCO 為正），單位服務成本低於市場外購價，且承載專案數已達 "&$B$48&" 個。★ 送投資決策時請以本頁的 ΔTCO 為主要指標，並在主工具 10 決策紀錄中把本案登記為「使能型投資 Enabling investment」——它的價值在於讓其他專案得以成立，不在於自己賺錢。"))) -> ⚠ 尚未填寫外租方案的比較資料——請先填 C 區塊，否則本頁無法給出結論。

Sheet 10_決策摘要_Summary
A1: 10 決策摘要｜Investment Decision Summary（可直接貼進投資決策文件）
A2: 全公式，不需編輯。★ 本頁的判讀規則會依 01 分頁選定的「投資類別」自動切換——營收型看 NPV／MIRR，使能型看 ΔTCO，法規強制型看最低合規成本，各有各的尺。
A4: 專案名稱 | B4: ='01_專案設定_Setup'!$B$5 -> B醫院 500床 HIS／EMR 以租代購 一期（模擬案）
A5: 對應能力 CAP ID | B5: ='01_專案設定_Setup'!$B$6 -> CAP-033 HIS／EMR核心平台
A6: 主責夥伴 | B6: ='01_專案設定_Setup'!$B$7 -> P-007 醫療資訊整合商（＋群晶科技：承載環境）
A7: ★ 投資類別 | B7: ='01_專案設定_Setup'!$B$9 -> F 策略布局型 Strategic / Option | C7: 下面的判讀規則依這一格自動切換。
A8: └ 主要評估指標 | B8: =IFERROR(INDEX(_CatMetric,MATCH('01_專案設定_Setup'!$B$9,_CatName,0)),"") -> 選擇權價值／階段關卡達成率
A9: 幣別 / 單位 / 年數 | B9: ='01_專案設定_Setup'!$B$31&" / "&'01_專案設定_Setup'!$B$34&" 年" -> TWD 千 / 10 年
A10: 折現率 WACC | B10: ='01_專案設定_Setup'!$B$48 -> 0.11994697 | C10: 見 07 分頁的推算過程。這個數字比任何一筆成本估算都更能左右結論。
A12: 一、共通財務結果（所有類別都會算，但不是每一類都以此為準）
A13: 投資總額 CAPEX（含不可扣抵稅費） | B13: ='02_投資成本_CAPEX'!$Q$64 -> 41019.602 | C13: 含關稅與不可扣抵的進項 VAT。越南醫療服務免 VAT ⇒ 進項不可扣抵 ⇒ 這是實實在在的成本。
A14: 首年 OPEX | B14: ='03_營運成本_OPEX'!$J$35 -> 6720.5
A15: 滿載年營收 | B15: ='04_收入產能_Revenue'!$B$31 -> 10968 | C15: 使能型投資若不對外收費，此欄為 0 屬正常，請看第二段的 ΔTCO。
A16: NPV 淨現值 | B16: ='06_現金流_Cashflow'!$B$46 -> -25766.172
A17: ★ MIRR 修正內部報酬率 | B17: ='06_現金流_Cashflow'!$B$48 -> 0.008677402 | C17: 本檔的主要報酬指標。因為模型含中途置換投資（現金流正負交替），IRR 可能有多重解，MIRR 只有單一解。
A18: （參考）IRR | B18: ='06_現金流_Cashflow'!$B$47 -> -0.027121388
A19: PI 獲利指數 | B19: ='06_現金流_Cashflow'!$B$49 -> 0.3718571 | C19: ＞1 即可接受。多案排序、資本受限時用這個。
A20: 折現回收期（年） | B20: ='06_現金流_Cashflow'!$B$50 -> 未回收
A21: ROIC 投入資本報酬率 | B21: ='06_現金流_Cashflow'!$B$52 -> 0.023971325 | C21: 與上方的折現率 WACC 比較：高於 WACC 才是真正在創造價值。
A23: 二、使能型投資專用指標（投資類別選 B 時以此為準）
A24: ★ ΔTCO 現值（外租 − 自建） | B24: =IF(INDEX(_CatCode,MATCH('01_專案設定_Setup'!$B$9,_CatName,0))<>"DTCO","— 本案投資類別非「B 使能型」，本段不適用",'09_使能型評估_EnablingCase'!$B$28) -> — 本案投資類別非「B 使能型」，本段不適用 | C24: 正值＝自建比外租便宜，這才是使能型投資的「淨現值」。見 09 分頁。
A25: ΔTCO 簡單回收期（年） | B25: =IF(INDEX(_CatCode,MATCH('01_專案設定_Setup'!$B$9,_CatName,0))<>"DTCO","— 本案投資類別非「B 使能型」，本段不適用",'09_使能型評估_EnablingCase'!$B$29) -> — 本案投資類別非「B 使能型」，本段不適用
A26: 承載專案數 | B26: =IF(INDEX(_CatCode,MATCH('01_專案設定_Setup'!$B$9,_CatName,0))<>"DTCO","— 本案投資類別非「B 使能型」，本段不適用",'09_使能型評估_EnablingCase'!$B$48) -> — 本案投資類別非「B 使能型」，本段不適用 | C26: 使能型投資的通過條件之一：≥ 2。只服務單一專案的平台，本質上是那個專案的成本。
A27: 選擇權價值（期望值・參考） | B27: =IF(INDEX(_CatCode,MATCH('01_專案設定_Setup'!$B$9,_CatName,0))<>"DTCO","— 本案投資類別非「B 使能型」，本段不適用",'09_使能型評估_EnablingCase'!$D$59) -> — 本案投資類別非「B 使能型」，本段不適用 | C27: ★ 不計入 NPV，也不可入帳。是決策時的補充證據。
A29: 三、自動判讀 Verdict（依投資類別切換規則）
A30: =IF(INDEX(_CatCode,MATCH('01_專案設定_Setup'!$B$9,_CatName,0))="DTCO",'09_使能型評估_EnablingCase'!$A$62,IF(INDEX(_CatCode,MATCH('01_專案設定_Setup'!$B$9,_CatName,0))="MINCOST","【法規強制型】本案的問題不是「划不划算」而是「不做的代價是什麼」。投資額 "&TEXT($B$13,"#,##0")&"。請在 11 分頁明確登錄：①法源與期限 ②不做的罰則或停業風險 ③至少三家供應商的比價，並確認本方案是在合規前提下的最低總成本。NPV 為負屬正常，不構成否決理由。",IF(INDEX(_CatCode,MATCH('01_專案設定_Setup'!$B$9,_CatName,0))="LCC","【汰換維持型】本案是維持營運不中斷的必要支出，不應以 NPV 論斷。請確認：①現有資產的剩餘壽命與故障率 ②不汰換的停機風險成本 ③同規格中已取得最低生命週期成本。投資額 "&TEXT($B$13,"#,##0")&"，折現回收期 "&TEXT($B$20,"0.0")&" 年。",IF(INDEX(_CatCode,MATCH('01_專案設定_Setup'!$B$9,_CatName,0))="OPTION","【策略布局型】本案的價值在於取得未來機會與參考案例，現金流本來就高度不確定。★ 不要一次核定全額——請改用分階段關卡：把 "&TEXT($B$13,"#,##0")&" 拆成 2–3 期，每期設定可量測的續投條件（例如：第一期只做到取得醫院簽署的意向書與試點驗收）。目前 NPV "&TEXT($B$16,"#,##0")&"。",IF($B$16<=0,"✕ 不建議：NPV 為負，在目前折現率下無法回收。請看 08 分頁的龍捲風圖找出最致命的變數，並確認投資類別是否選對——若本案其實是使能型或法規強制型，就不該用 NPV 這把尺。",IF(IFERROR($B$17,0)<'01_專案設定_Setup'!$B$48,"△ 條件不足：MIRR 低於折現率，報酬未超過機會成本。同一筆錢投別的案子更划算，除非有策略價值。",IF($B$19<1,"△ 條件不足：獲利指數低於 1。",IF(IFERROR($B$20,99)>7,"△ 可行但偏慢：NPV 為正、MIRR 高於門檻，但折現回收期超過 7 年。務必確認合約年限涵蓋回收期，否則合約到期時錢還沒收回來。","○ 建議推進：NPV 為正、MIRR 高於折現率、獲利指數大於 1、回收期在合理範圍。下一步進入主工具 WP-09 投資決策。")))))))) -> 【策略布局型】本案的價值在於取得未來機會與參考案例，現金流本來就高度不確定。★ 不要一次核定全額——請改用分階段關卡：把 41,020 拆成 2–3 期，每期設定可量測的續投條件（例如：第一期只做到取得醫院簽署的意向書與試點驗收）。目前 NPV -25,766。
A35: 四、本案解讀｜這個數字代表什麼、可以動哪些槓桿
A36: ① 本案的投資類別刻意選「F 策略布局型」而不是「A 營收型」，這不是為了迴避難看的數字，而是分類本身就該如此：單一家醫院的 HIS 合約，收入天花板被越南的付款結構鎖死——★ 越南醫療服務價格至今只含人工與直接成本、未含 IT（tuoitre.vn），而第一個把 IT 納入給付的案例（Decision 313/QĐ-BYT 白梅醫院 PACS 無片化）公告價反而低 5.9%。需求是被法規逼出來的（衛生部要求 2025 年 10 月前完成電子病歷），付款來源卻還沒建立。
A37: ② 收入端已經頂到天花板，不是還沒努力。基準每床每月 1,680 TWD，500 床五年合約總額約 41bn VND——已落在越南一級醫院 IT 投資區間（10.5–40bn VND）的上緣。換句話說，把價格再往上調並不是可行解，那會直接談不成。
A38: ③ 真正的解在「複製」，而且金額很具體：02 分頁中的在地化（371 萬）、資料移轉（220 萬）、導入服務（436 萬）、教育訓練（136 萬）合計約 1,053 萬 TWD 屬一次性投入，複製到第 2、第 3 家醫院時可攤薄六成以上。★ 所以不要用一家醫院的合約去論證這門生意，要用「三年內拿下 3–5 家、共用同一平台」的路線去論證（對應主工具 OPP-85 複製藍圖）。第一家醫院應被視為取得參考案例（reference site）的成本。
A39: ④ 因為是策略布局型，決策方式也要跟著改：★ 不要一次核定全額。建議拆成三期並設定可量測的續投條件——第一期（約 30%）：完成門診上線與院方書面滿意度驗收，且取得可對外引用的案例授權；第二期（約 40%）：完成住院與檢驗上線，且已有第 2 家醫院進入正式議約；第三期（約 30%）：全院無紙化驗收，且第 2 家合約簽訂。任一關卡未達成即停止投入。這正是 CFA 資本預算對高不確定性專案建議的 stage-gate 作法。
A40: ⑤ 提案論述必須換一個講法。不要說「請為 IT 多付費」，要說「幫你省下這些成本」——白梅醫院無紙化年省約 100bn VND、底片月省約 1bn VND，這是越南衛生部自己認可過的邏輯（Decision 313/QĐ-BYT 的定價機制就是回收底片節省）。這是能不能成交的分水嶺。
A41: ⑥ 兩個容易被忽略的現金流壓力：（a）以租代購代表聯盟先墊資本、醫院分 36 個月按季付款（bvdkthaibinh.vn），平均應收約 90 天，是一般軟體業的兩倍——請看 06 分頁的營運資金列；（b）有累積虧損時不得匯出利潤（Circular 186/2010＋Decree 252/2026），本案前幾年帳上虧損會直接卡住資金回台。這兩點請一併納入資金規劃。
A42: ⑦ 最後一個好消息：若取得社會化醫療資格，適用 10% 優惠稅率＋免稅 4 年，而免稅期是「自首次獲利年起算」——本案前幾年虧損反而讓免稅期往後遞延到真正賺錢的年份，不會被浪費掉。這一點在 06 分頁的稅務區塊已內建計算。
A44: 五、送交投資決策前的必備檢查
A45: ☐ | B45: 02 分頁每一筆 CAPEX 都已用廠商正式報價或工程估算取代示意值，並在 11 分頁登錄來源與日期
A46: ☐ | B46: ★ 關稅與進項 VAT 已確認：醫材 HS 9022 適用 MFN 0%（須附有效 C/O），但 UPS／發電機／空調類非 ITA 涵蓋、稅率較高；且醫療服務免 VAT ⇒ 進項不可扣抵、必須資本化
A47: ☐ | B47: ★ 稅務優惠資格已由越南在地稅務顧問書面確認（社會化醫療 10% 稅率、免稅期起算年、虧損扣抵 5 年）
A48: ☐ | B48: ★ 折現率（07 分頁 WACC）已與投資方書面談定——同一份模型用不同折現率會得到相反的結論
A49: ☐ | B49: 越南醫材／軟體註冊路徑與時程已由法規顧問確認（對應主工具 05 法規門檻）
A50: ☐ | B50: OPEX 已含在地人力、維保合約、耗材與電力，維保費率以合約報價為準，且薪資年成長率不為 0
A51: ☐ | B51: 收入單價已核對越南健保公告費率與自費市場行情；★ 注意 PACS 無片化給付價反而低於有片價
A52: ☐ | B52: 健保應收天數已依實際結算經驗設定（越南社保按季結算且常有超支懸置），並在 08 下檔情境測試過
A53: ☐ | B53: 08 分頁龍捲風圖排序第一的變數，已有對應的合約條款或查證計畫
A54: ☐ | B54: 獨立驗證單位已複核本模型（對應主工具 04 的獨立臨床與成本驗證）

Sheet 11_假設來源_Assumptions
A1: 11 假設與來源｜Assumptions & Sources
A2: 每一筆重要金額與比率都要在這裡登錄出處。「狀態」欄是給投資決策看的：★ 只要還有任何一列是「推測」，這份模型就不能直接送投資決策。
A4: 編號 | B4: 假設項目 | C4: 採用值 | D4: 狀態 | E4: 來源／依據 | F4: 更新日期 | G4: 負責人
A5: X-01 | B5: 匯率 1 TWD = 810 VND、1 USD = 26,082 VND | C5: 810 / 26,082 | D5: 實績資料 | E5: xe.com 中間匯率，2026-08-13。★ 3–10 年模型不應直接用即期匯率外推（Damodaran）；本檔採單一幣別建模、最後換算的穩健作法。 | F5: 2026-08-13 | G5: Financial Model Lead
A6: X-02 | B6: 折現率 WACC | C6: 見 07 分頁 | D6: 規劃假設 | E6: CAPM＋國家風險溢酬。Rf＝越南 10Y 公債 4.54%（tradingeconomics.com，2026-08-12）；成熟市場 ERP 4.23%、越南 CRP 3.90%（Damodaran，pages.stern.nyu.edu，2026-01）。 | F6: 2026-08-13 | G6: Financial Model Lead
A7: X-03 | B7: 企業所得稅優惠稅率 10% | C7: 10% | D7: 法規公告 | E7: PwC 越南 Pocket Tax Book：「Certain social sectors (e.g. education, health) enjoy the 10% rate for the entire life of the project.」★ 惟 lntpartners.com 對 Law 67/2025 的解讀較保守，認為須符合第 12 條其他資格條件。務必由在地稅務顧問就個案確認；下檔情境應改用 20%。 | F7: 2026-08-13 | G7: Tax Advisor
A8: X-04 | B8: 免稅 4 年＋減半期 | C8: 4＋5 或 4＋9 年 | D8: 法規公告 | E8: 社會化專案位於社經困難地區者免稅 4 年＋減半 9 年；一般地區免稅 4 年＋減半 5 年。免稅期自「首次從受優惠活動獲利」起算，但若產生營收後 3 年內未獲利則自營運第 4 年起強制起算（PwC）。 | F8: 2026-08-13 | G8: Tax Advisor
A9: X-05 | B9: ★ 醫療服務 VAT 免稅 ⇒ 進項不可扣抵 | C9: 進項 VAT 全額計入成本 | D9: 法規公告 | E9: VAT Law 48/2024/QH15 第 5 條第 10 款(a)：人的醫療檢查、治療與疾病預防服務屬「不課徵 VAT 對象」。★ 免稅（exempt）≠ 零稅率（0%）——免稅代表進項 VAT 不可退還，必須資本化或計入費用。醫材與藥品進項適用 5%、IT 設備 10%。 | F9: 2026-08-13 | G9: Tax Advisor
A10: X-06 | B10: 折舊年限 | C10: 依 Circular 45/2013/TT-BTC | D10: 法規公告 | E10: 附錄一法定區間：堅固建物 25–50 年、醫療設備 6–15 年、電腦與電子設備 3–8 年、軟體 3–8 年、一般機械 5–15 年。★ 本案若適用長期免稅或 10% 優惠稅率，宜取區間上限拉長折舊，把稅盾延後到稅率較高的期間。 | F10: 2026-08-13 | G10: 會計師
A11: X-07 | B11: 虧損扣抵 5 年 | C11: 5 年 | D11: 法規公告 | E11: 越南：虧損可全額連續向後扣抵最長 5 年，不得向前扣抵，逾期永久失效。本檔以 5 年滾動窗口近似 FIFO 到期邏輯。 | F11: 2026-08-13 | G11: Tax Advisor
A12: X-08 | B12: 健保應收天數 | C12: 見 01 分頁 | D12: 實績資料 | E12: ★ 2025-08 報導：胡志明市各醫院被健保懸置未結算的費用近 2,500 十億越盾（2023 年超支 5,575 億、2024 年約 1 兆 9,500 億），醫院須依《健保法》第 32 條請求社保墊付（vietnam.vn）。VSS 結算的確切法定天數查無明文，須由在地法律顧問確認。 | F12: 2026-08-13 | G12: Revenue Cycle Lead
A13: X-09 | B13: 利潤匯回限制 | C13: 有累積虧損不得匯出 | D13: 法規公告 | E13: Circular 186/2010/TT-BTC＋Decree 252/2026/ND-CP：須完成財務義務、提交查核財報與 CIT 決算表，匯出前 7 個工作天通知稅務機關。★ 有累積虧損的企業不得匯出利潤，即使當年度獲利。外國法人股東 0% 扣繳、個人股東 5%。 | F13: 2026-08-13 | G13: Legal Lead
A14: X-10 | B14: 投資類別分類法 | C14: 見 01 分頁 | D14: 實績資料 | E14: Weill & Aral（MIT Sloan）IT 投資組合四分類：Infrastructure 46%／Transactional 26%／Informational 17%／Strategic 11%；★ 績效前段班公司把 55% 的 IT 支出放在基礎建設，後段班只有 37%（MIT CISR 2016）。另參考 CFA 資本預算分類、Gartner Run/Grow/Transform、TBM Council 成本分攤方法。 | F14: 2026-08-13 | G14: PI Office
A15: C-01 | B15: HIS/EMR 總建置（含不可扣抵稅費） | C15: 見 02 分頁 | D15: 規劃假設 | E15: tuoitre.vn：越南一級醫院 IT 投資 10.5–40bn VND、占營收 0.57–2.1%。越南無公開每床授權價（ykhoanet.com） | F15: 2026-08-13 | G15: Health IT Lead
... A26: C-12 | B26: 爬坡率 40/75/100% | C26: — | D26: 規劃假設 | E26: 分階段上線：門診 → 住院與檢驗 → 全院無紙化。須與院方變革管理計畫對齊 | F26: 2026-08-13 | G26: Change Lead
A36: 狀態統計
B37: 實績資料 | C37: =COUNTIF($D$5:$D$34,$B37) -> 3
B38: 報價 | C38: =COUNTIF($D$5:$D$34,$B38) -> 0
B39: 合約條款 | C39: =COUNTIF($D$5:$D$34,$B39) -> 2
B40: 法規公告 | C40: =COUNTIF($D$5:$D$34,$B40) -> 11
B41: 規劃假設 | C41: =COUNTIF($D$5:$D$34,$B41) -> 6
B42: 推測 | C42: =COUNTIF($D$5:$D$34,$B42) -> 0
B43: ★ 只要「推測」的數量不是 0，這份模型就不能直接送投資決策。

Sheet _Lists
A1: L_Cur | B1: L_Unit | C1: L_DiscSrc | D1: L_VatC | E1: L_TV | F1: L_CapCat | G1: L_Origin | H1: L_Dep | I1: L_OpCat | J1: L_CostType | K1: L_Status | L1: L_Alloc | M1: L_Industry | N1: L_W1 | O1: L_W2 | P1: L_W4 | Q1: L_Role
A2: TWD 新台幣 | B2: 元 Unit | C2: 由 07 分頁 WACC 推算 | D2: 否 — 醫療服務免 VAT | E2: 殘值法 Salvage（有限年期資產） | F2: 設備 | G2: 進口 | H2: 建物與裝修 Building | I2: 人力 | J2: 變動 | K2: 實績資料 | L2: 直接分攤 Direct | M2: Hospitals / Healthcare Facilities (βu 0.55) | N2: 有，而且金額算得準（有給付碼、正式報價或可比市場） | O2: 別的專案做不成，或成本會大增 | P2: 會停擺——沒得選，一定要做 | Q2: 專案總監
A3: USD 美元 | B3: 千元 Thousand | C3: 手動輸入 | D3: 是 — 可扣抵 | E3: 永續成長法 Gordon growth | F3: 工程 | G3: 在地 | H3: 醫療設備 Medical equip | I3: 維保 | J3: 固定 | K3: 報價 | L3: 作業基礎 ABC | M3: Healthcare Support Services (βu 0.69) | N3: 有，但金額還算不準（要等市場成熟，或要等第 2、3 個客戶） | O3: 會被罰、被要求停業，或失去投標資格 | P3: 不會，還能撐一段時間——有得選 | Q3: 財務
A4: VND 越南盾 | B4: 百萬 Million | E4: 退出倍數法 Exit multiple | F4: 軟體 | G4: 混合 | H4: 機電設備 M&E | I4: 耗材 | K4: 合約條款 | L4: 固定分攤 Fixed | M4: Healthcare Products (βu 0.83) | N4: 沒有（不對外收費，或只有聯盟內部轉付） | O4: 某一筆既有支出會繼續花下去 | Q4: 醫療資訊
E5: 不計終值 | F5: 服務 | H5: 電腦與網通 IT | I5: 公用 | K5: 法規公告 | L5: 共用服務 Shared | M5: Information Services (βu 0.74) | O5: 現有營運會中斷 | Q5: 數位基建
F6: 預備 | H6: 軟體與無形 Software | I6: 軟體 | K6: 規劃假設 | L6: 加權分攤 Weighted | M6: Computer Services (βu 0.92) | Q6: 設施維運
H7: 費用化 Expensed | I7: 服務 | K7: 推測 | M7: Telecom Equipment (βu 0.86) | Q7: 網路
I8: 法規 | M8: R.E.I.T. — 資料中心參考下界 (βu 0.39) | Q8: CISO
I9: 保險 | M9: 自訂 Custom | Q9: 法務
I10: 管理 | Q10: HR
Q11: 採購
Q12: 營運
Q13: 放射科
Q14: 品保
